Workbook

Sheet Cost Margin
A1: Cost margin sheet
A2: Yellow = inputs (blue text). Grey = calculated. * = required. Pick the engagement type first — it decides how revenue is counted.
S3: Project summary
A4: Engagement type * (pick first) | B4: Assessment | C4: Fixed cost / Assessment → fill Total project price. MSP → fill Monthly fee. Time & materials → bill rates on each row are used. Fields not needed for the chosen type turn grey. | S4: Engagement type | T4: =IF(B4="","",B4) -> Assessment
A5: Project name | B5: AI Assessment | S5: Duration (months) | T5: =B10 -> 0.96129032
A6: Client | B6: Peppermill | S6: Project revenue | T6: =IF(B4="","",IF(B4="MSP",IF(OR(B12="",B10=""),"",B12*B10),IF(B4="Time & materials",M37,IF(B11="","",B11)))) -> 50000
A7: Currency | B7: USD | S7: Pass-through expenses billed to client | T7: =H53 -> 0
A8: Project start * | B8: 46272 | S8: Total revenue | T8: =IF(T6="","",T6+T7) -> 50000
A9: Project end * | B9: 46300 | S9: Labour cost | T9: =N37 -> 27416.122
A10: Duration (months, partial months by days) | B10: =IF(OR(B8="",B9=""),"",SUM(Monthly!$C$4:$Z$4)) -> 0.96129032 | C10: =IF(OR(B8="",B9=""),"",IF(B9<B8,"End is before start",DATEDIF(B8,B9+1,"M")&" month(s) "&DATEDIF(B8,B9+1,"MD")&" day(s) — "&(B9-B8+1)&" calendar days inclusive")) -> 0 month(s) 29 day(s) — 29 calendar days inclusive | S10: Burden cost | T10: =O37 -> 3143.0838
A11: Total project price * (Fixed cost / Assessment) | B11: 50000 | C11: =IF(OR(B4="Fixed cost",B4="Assessment"),IF(B11="","← required for this engagement type",""),IF(B11="","","Not used for this engagement type")) | S11: Additional costs | T11: =G53 -> 3000
A12: Monthly fee * (MSP) | C12: =IF(B4="MSP",IF(B12="","← required for MSP",""),IF(B12="","","Not used for this engagement type")) | S12: Total cost | T12: =T9+T10+T11 -> 33559.205
A13: Additional costs on this project? * (Y/N) | B13: Y | C13: =IF(B13="","← required: Y if there are travel, licences, subcontractor or other costs; N if none","") | S13: Gross margin $ | T13: =IF(T8="","",T8-T12) -> 16440.795
S14: Gross margin % | T14: =IF(OR(T8="",T8=0),"",T13/T8) -> 0.32881589
A15: Staffing — one row per person. To remove a person, select that row's yellow cells and press Delete; a row with no Role is ignored. (Rows can't be deleted — the Monthly tab maps to them.) | S15: Target GM % (blended floor) | T15: =IF(N37=0,"",SUMPRODUCT(N17:N36,Q17:Q36)/N37) -> 0.35
A16: Role * | B16: Seniority * | C16: Location * | D16: Utilization % | E16: Hours (auto type in Hours override to change) | F16: Bill rate (what we CHARGE the client per hour — T&M only) | G16: Our cost / hour * (what the person COSTS us per hour, before burden, pre-filled from the Settings rate card; overwrite if known) | H16: Start (pre-filled from project start, change if the person joins later) | I16: End (pre-filled from project end, change if they leave earlier) | J16: Working days | K16: Hours override (optional) | L16: Burden % | M16: Labour at bill rate (T&M revenue) | N16: Labour cost (hours × cost/hr) | O16: Burden cost | P16: Loaded cost (labour + burden) | Q16: GM floor % | S16: Status | T16: =IF(T18<>"","INCOMPLETE — see below",IF(OR(T14="",T15=""),"",IF(T14>=T15,"PASS","BELOW FLOOR"))) -> BELOW FLOOR
A17: Vikrin | B17: Senior | C17: US | D17: 1 | E17: =IF(K17<>"",K17,IF(J17="","",J17*Settings!$B$3*IF(D17="",1,D17))) -> 168 | G17: 143 | H17: =IF(OR(A17="",$B$8=""),"",$B$8) -> 46272 | I17: =IF(OR(A17="",$B$9=""),"",$B$9) -> 46300 | J17: =IF(OR(A17="",IF(H17="",$B$8,H17)="",IF(I17="",$B$9,I17)=""),"",IFERROR(NETWORKDAYS(IF(H17="",$B$8,H17),IF(I17="",$B$9,I17),INDEX(Settings!$J$7:$M$60,0,MATCH(C17,Settings!$J$6:$M$6,0))),NETWORKDAYS(IF(H17="",$B$8,H17),IF(I17="",$B$9,I17)))) -> 21 | L17: 0.08 | M17: =IF(OR(E17="",F17=""),0,E17*F17) -> 0 | N17: =IF(OR(E17="",G17=""),0,E17*G17) -> 24024 | O17: =N17*L17 -> 1921.92 | P17: =N17+O17 -> 25945.92 | Q17: =IF(C17="",0,IFERROR(INDEX(Settings!$C$6:$C$9,MATCH(C17,Settings!$A$6:$A$9,0)),0)) -> 0.35
A18: srikanth | B18: Senior | C18: US | D18: 0.24 | E18: =IF(K18<>"",K18,IF(J18="","",J18*Settings!$B$3*IF(D18="",1,D18))) -> 40.32 | G18: 84.13 | H18: =IF(OR(A18="",$B$8=""),"",$B$8) -> 46272 | I18: =IF(OR(A18="",$B$9=""),"",$B$9) -> 46300 | J18: =IF(OR(A18="",IF(H18="",$B$8,H18)="",IF(I18="",$B$9,I18)=""),"",IFERROR(NETWORKDAYS(IF(H18="",$B$8,H18),IF(I18="",$B$9,I18),INDEX(Settings!$J$7:$M$60,0,MATCH(C18,Settings!$J$6:$M$6,0))),NETWORKDAYS(IF(H18="",$B$8,H18),IF(I18="",$B$9,I18)))) -> 21 | L18: 0.36 | M18: =IF(OR(E18="",F18=""),0,E18*F18) -> 0 | N18: =IF(OR(E18="",G18=""),0,E18*G18) -> 3392.1216 | O18: =N18*L18 -> 1221.1638 | P18: =N18+O18 -> 4613.2854 | Q18: =IF(C18="",0,IFERROR(INDEX(Settings!$C$6:$C$9,MATCH(C18,Settings!$A$6:$A$9,0)),0)) -> 0.35 | S18: Missing inputs | T18: =TRIM(IF(B4="","Engagement type. ","")&IF(OR(B8="",B9=""),"Project dates. ","")&IF(AND(OR(B4="Fixed cost",B4="Assessment"),B11=""),"Total project price. ","")&IF(AND(B4="MSP",B12=""),"Monthly fee. ","")&IF(B13="","Additional costs Y/N. ","")&IF(COUNTIF(I41:I52,"Pick*")>0,"Billed to client Y/N (column F) on additional cost rows. ","")&IF(COUNTIFS(A17:A36,"<>",G17:G36,"")>0,"Our cost/hour (column G) on staffing rows — pick Seniority + Location or type it. ","")&IF(AND(B4="Time & materials",COUNTIFS(A17:A36,"<>",F17:F36,"")>0),"Bill rate on T&M rows. ",""))
E19: =IF(K19<>"",K19,IF(J19="","",J19*Settings!$B$3*IF(D19="",1,D19))) | G19: =IFERROR(INDEX(Settings!$Q$7:$T$10,MATCH(B19,Settings!$P$7:$P$10,0),MATCH(C19,Settings!$Q$6:$T$6,0)),"") | H19: =IF(OR(A19="",$B$8=""),"",$B$8) | I19: =IF(OR(A19="",$B$9=""),"",$B$9) | J19: =IF(OR(A19="",IF(H19="",$B$8,H19)="",IF(I19="",$B$9,I19)=""),"",IFERROR(NETWORKDAYS(IF(H19="",$B$8,H19),IF(I19="",$B$9,I19),INDEX(Settings!$J$7:$M$60,0,MATCH(C19,Settings!$J$6:$M$6,0))),NETWORKDAYS(IF(H19="",$B$8,H19),IF(I19="",$B$9,I19)))) | L19: =IF(C19="",0,IFERROR(INDEX(Settings!$B$6:$B$9,MATCH(C19,Settings!$A$6:$A$9,0)),0)) -> 0 | M19: =IF(OR(E19="",F19=""),0,E19*F19) -> 0 | N19: =IF(OR(E19="",G19=""),0,E19*G19) -> 0 | O19: =N19*L19 -> 0 | P19: =N19+O19 -> 0 | Q19: =IF(C19="",0,IFERROR(INDEX(Settings!$C$6:$C$9,MATCH(C19,Settings!$A$6:$A$9,0)),0)) -> 0
E20: =IF(K20<>"",K20,IF(J20="","",J20*Settings!$B$3*IF(D20="",1,D20))) | G20: =IFERROR(INDEX(Settings!$Q$7:$T$10,MATCH(B20,Settings!$P$7:$P$10,0),MATCH(C20,Settings!$Q$6:$T$6,0)),"") | H20: =IF(OR(A20="",$B$8=""),"",$B$8) | I20: =IF(OR(A20="",$B$9=""),"",$B$9) | J20: =IF(OR(A20="",IF(H20="",$B$8,H20)="",IF(I20="",$B$9,I20)=""),"",IFERROR(NETWORKDAYS(IF(H20="",$B$8,H20),IF(I20="",$B$9,I20),INDEX(Settings!$J$7:$M$60,0,MATCH(C20,Settings!$J$6:$M$6,0))),NETWORKDAYS(IF(H20="",$B$8,H20),IF(I20="",$B$9,I20)))) | L20: =IF(C20="",0,IFERROR(INDEX(Settings!$B$6:$B$9,MATCH(C20,Settings!$A$6:$A$9,0)),0)) -> 0 | M20: =IF(OR(E20="",F20=""),0,E20*F20) -> 0 | N20: =IF(OR(E20="",G20=""),0,E20*G20) -> 0 | O20: =N20*L20 -> 0 | P20: =N20+O20 -> 0 | Q20: =IF(C20="",0,IFERROR(INDEX(Settings!$C$6:$C$9,MATCH(C20,Settings!$A$6:$A$9,0)),0)) -> 0 | S20: Monthly view | T20: =IF(B10="","",IF(B10>2,"Required — see Monthly tab","Not needed (≤ 2 months)")) -> Not needed (≤ 2 months)
E21: =IF(K21<>"",K21,IF(J21="","",J21*Settings!$B$3*IF(D21="",1,D21))) | G21: =IFERROR(INDEX(Settings!$Q$7:$T$10,MATCH(B21,Settings!$P$7:$P$10,0),MATCH(C21,Settings!$Q$6:$T$6,0)),"") | H21: =IF(OR(A21="",$B$8=""),"",$B$8) | I21: =IF(OR(A21="",$B$9=""),"",$B$9) | J21: =IF(OR(A21="",IF(H21="",$B$8,H21)="",IF(I21="",$B$9,I21)=""),"",IFERROR(NETWORKDAYS(IF(H21="",$B$8,H21),IF(I21="",$B$9,I21),INDEX(Settings!$J$7:$M$60,0,MATCH(C21,Settings!$J$6:$M$6,0))),NETWORKDAYS(IF(H21="",$B$8,H21),IF(I21="",$B$9,I21)))) | L21: =IF(C21="",0,IFERROR(INDEX(Settings!$B$6:$B$9,MATCH(C21,Settings!$A$6:$A$9,0)),0)) -> 0 | M21: =IF(OR(E21="",F21=""),0,E21*F21) -> 0 | N21: =IF(OR(E21="",G21=""),0,E21*G21) -> 0 | O21: =N21*L21 -> 0 | P21: =N21+O21 -> 0 | Q21: =IF(C21="",0,IFERROR(INDEX(Settings!$C$6:$C$9,MATCH(C21,Settings!$A$6:$A$9,0)),0)) -> 0
E22: =IF(K22<>"",K22,IF(J22="","",J22*Settings!$B$3*IF(D22="",1,D22))) | G22: =IFERROR(INDEX(Settings!$Q$7:$T$10,MATCH(B22,Settings!$P$7:$P$10,0),MATCH(C22,Settings!$Q$6:$T$6,0)),"") | H22: =IF(OR(A22="",$B$8=""),"",$B$8) | I22: =IF(OR(A22="",$B$9=""),"",$B$9) | J22: =IF(OR(A22="",IF(H22="",$B$8,H22)="",IF(I22="",$B$9,I22)=""),"",IFERROR(NETWORKDAYS(IF(H22="",$B$8,H22),IF(I22="",$B$9,I22),INDEX(Settings!$J$7:$M$60,0,MATCH(C22,Settings!$J$6:$M$6,0))),NETWORKDAYS(IF(H22="",$B$8,H22),IF(I22="",$B$9,I22)))) | L22: =IF(C22="",0,IFERROR(INDEX(Settings!$B$6:$B$9,MATCH(C22,Settings!$A$6:$A$9,0)),0)) -> 0 | M22: =IF(OR(E22="",F22=""),0,E22*F22) -> 0 | N22: =IF(OR(E22="",G22=""),0,E22*G22) -> 0 | O22: =N22*L22 -> 0 | P22: =N22+O22 -> 0 | Q22: =IF(C22="",0,IFERROR(INDEX(Settings!$C$6:$C$9,MATCH(C22,Settings!$A$6:$A$9,0)),0)) -> 0 | S22: Labour by location
E23: =IF(K23<>"",K23,IF(J23="","",J23*Settings!$B$3*IF(D23="",1,D23))) | G23: =IFERROR(INDEX(Settings!$Q$7:$T$10,MATCH(B23,Settings!$P$7:$P$10,0),MATCH(C23,Settings!$Q$6:$T$6,0)),"") | H23: =IF(OR(A23="",$B$8=""),"",$B$8) | I23: =IF(OR(A23="",$B$9=""),"",$B$9) | J23: =IF(OR(A23="",IF(H23="",$B$8,H23)="",IF(I23="",$B$9,I23)=""),"",IFERROR(NETWORKDAYS(IF(H23="",$B$8,H23),IF(I23="",$B$9,I23),INDEX(Settings!$J$7:$M$60,0,MATCH(C23,Settings!$J$6:$M$6,0))),NETWORKDAYS(IF(H23="",$B$8,H23),IF(I23="",$B$9,I23)))) | L23: =IF(C23="",0,IFERROR(INDEX(Settings!$B$6:$B$9,MATCH(C23,Settings!$A$6:$A$9,0)),0)) -> 0 | M23: =IF(OR(E23="",F23=""),0,E23*F23) -> 0 | N23: =IF(OR(E23="",G23=""),0,E23*G23) -> 0 | O23: =N23*L23 -> 0 | P23: =N23+O23 -> 0 | Q23: =IF(C23="",0,IFERROR(INDEX(Settings!$C$6:$C$9,MATCH(C23,Settings!$A$6:$A$9,0)),0)) -> 0 | S23: Location | T23: Loaded cost | U23: Share of labour | V23: Floor
E24: =IF(K24<>"",K24,IF(J24="","",J24*Settings!$B$3*IF(D24="",1,D24))) | G24: =IFERROR(INDEX(Settings!$Q$7:$T$10,MATCH(B24,Settings!$P$7:$P$10,0),MATCH(C24,Settings!$Q$6:$T$6,0)),"") | H24: =IF(OR(A24="",$B$8=""),"",$B$8) | I24: =IF(OR(A24="",$B$9=""),"",$B$9) | J24: =IF(OR(A24="",IF(H24="",$B$8,H24)="",IF(I24="",$B$9,I24)=""),"",IFERROR(NETWORKDAYS(IF(H24="",$B$8,H24),IF(I24="",$B$9,I24),INDEX(Settings!$J$7:$M$60,0,MATCH(C24,Settings!$J$6:$M$6,0))),NETWORKDAYS(IF(H24="",$B$8,H24),IF(I24="",$B$9,I24)))) | L24: =IF(C24="",0,IFERROR(INDEX(Settings!$B$6:$B$9,MATCH(C24,Settings!$A$6:$A$9,0)),0)) -> 0 | M24: =IF(OR(E24="",F24=""),0,E24*F24) -> 0 | N24: =IF(OR(E24="",G24=""),0,E24*G24) -> 0 | O24: =N24*L24 -> 0 | P24: =N24+O24 -> 0 | Q24: =IF(C24="",0,IFERROR(INDEX(Settings!$C$6:$C$9,MATCH(C24,Settings!$A$6:$A$9,0)),0)) -> 0 | S24: =IF(Settings!A6="","",Settings!A6) -> US | T24: =IF(S24="","",SUMIF($C$17:$C$36,S24,$P$17:$P$36)) -> 30559.205 | U24: =IF(OR(S24="",$P$37=0),"",T24/$P$37) -> 1 | V24: =IF(S24="","",Settings!C6) -> 0.35
E25: =IF(K25<>"",K25,IF(J25="","",J25*Settings!$B$3*IF(D25="",1,D25))) | G25: =IFERROR(INDEX(Settings!$Q$7:$T$10,MATCH(B25,Settings!$P$7:$P$10,0),MATCH(C25,Settings!$Q$6:$T$6,0)),"") | H25: =IF(OR(A25="",$B$8=""),"",$B$8) | I25: =IF(OR(A25="",$B$9=""),"",$B$9) | J25: =IF(OR(A25="",IF(H25="",$B$8,H25)="",IF(I25="",$B$9,I25)=""),"",IFERROR(NETWORKDAYS(IF(H25="",$B$8,H25),IF(I25="",$B$9,I25),INDEX(Settings!$J$7:$M$60,0,MATCH(C25,Settings!$J$6:$M$6,0))),NETWORKDAYS(IF(H25="",$B$8,H25),IF(I25="",$B$9,I25)))) | L25: =IF(C25="",0,IFERROR(INDEX(Settings!$B$6:$B$9,MATCH(C25,Settings!$A$6:$A$9,0)),0)) -> 0 | M25: =IF(OR(E25="",F25=""),0,E25*F25) -> 0 | N25: =IF(OR(E25="",G25=""),0,E25*G25) -> 0 | O25: =N25*L25 -> 0 | P25: =N25+O25 -> 0 | Q25: =IF(C25="",0,IFERROR(INDEX(Settings!$C$6:$C$9,MATCH(C25,Settings!$A$6:$A$9,0)),0)) -> 0 | S25: =IF(Settings!A7="","",Settings!A7) -> India | T25: =IF(S25="","",SUMIF($C$17:$C$36,S25,$P$17:$P$36)) -> 0 | U25: =IF(OR(S25="",$P$37=0),"",T25/$P$37) -> 0 | V25: =IF(S25="","",Settings!C7) -> 0.5
E26: =IF(K26<>"",K26,IF(J26="","",J26*Settings!$B$3*IF(D26="",1,D26))) | G26: =IFERROR(INDEX(Settings!$Q$7:$T$10,MATCH(B26,Settings!$P$7:$P$10,0),MATCH(C26,Settings!$Q$6:$T$6,0)),"") | H26: =IF(OR(A26="",$B$8=""),"",$B$8) | I26: =IF(OR(A26="",$B$9=""),"",$B$9) | J26: =IF(OR(A26="",IF(H26="",$B$8,H26)="",IF(I26="",$B$9,I26)=""),"",IFERROR(NETWORKDAYS(IF(H26="",$B$8,H26),IF(I26="",$B$9,I26),INDEX(Settings!$J$7:$M$60,0,MATCH(C26,Settings!$J$6:$M$6,0))),NETWORKDAYS(IF(H26="",$B$8,H26),IF(I26="",$B$9,I26)))) | L26: =IF(C26="",0,IFERROR(INDEX(Settings!$B$6:$B$9,MATCH(C26,Settings!$A$6:$A$9,0)),0)) -> 0 | M26: =IF(OR(E26="",F26=""),0,E26*F26) -> 0 | N26: =IF(OR(E26="",G26=""),0,E26*G26) -> 0 | O26: =N26*L26 -> 0 | P26: =N26+O26 -> 0 | Q26: =IF(C26="",0,IFERROR(INDEX(Settings!$C$6:$C$9,MATCH(C26,Settings!$A$6:$A$9,0)),0)) -> 0 | S26: =IF(Settings!A8="","",Settings!A8) | T26: =IF(S26="","",SUMIF($C$17:$C$36,S26,$P$17:$P$36)) | U26: =IF(OR(S26="",$P$37=0),"",T26/$P$37) | V26: =IF(S26="","",Settings!C8)
E27: =IF(K27<>"",K27,IF(J27="","",J27*Settings!$B$3*IF(D27="",1,D27))) | G27: =IFERROR(INDEX(Settings!$Q$7:$T$10,MATCH(B27,Settings!$P$7:$P$10,0),MATCH(C27,Settings!$Q$6:$T$6,0)),"") | H27: =IF(OR(A27="",$B$8=""),"",$B$8) | I27: =IF(OR(A27="",$B$9=""),"",$B$9) | J27: =IF(OR(A27="",IF(H27="",$B$8,H27)="",IF(I27="",$B$9,I27)=""),"",IFERROR(NETWORKDAYS(IF(H27="",$B$8,H27),IF(I27="",$B$9,I27),INDEX(Settings!$J$7:$M$60,0,MATCH(C27,Settings!$J$6:$M$6,0))),NETWORKDAYS(IF(H27="",$B$8,H27),IF(I27="",$B$9,I27)))) | L27: =IF(C27="",0,IFERROR(INDEX(Settings!$B$6:$B$9,MATCH(C27,Settings!$A$6:$A$9,0)),0)) -> 0 | M27: =IF(OR(E27="",F27=""),0,E27*F27) -> 0 | N27: =IF(OR(E27="",G27=""),0,E27*G27) -> 0 | O27: =N27*L27 -> 0 | P27: =N27+O27 -> 0 | Q27: =IF(C27="",0,IFERROR(INDEX(Settings!$C$6:$C$9,MATCH(C27,Settings!$A$6:$A$9,0)),0)) -> 0 | S27: =IF(Settings!A9="","",Settings!A9) | T27: =IF(S27="","",SUMIF($C$17:$C$36,S27,$P$17:$P$36)) | U27: =IF(OR(S27="",$P$37=0),"",T27/$P$37) | V27: =IF(S27="","",Settings!C9)
E28: =IF(K28<>"",K28,IF(J28="","",J28*Settings!$B$3*IF(D28="",1,D28))) | G28: =IFERROR(INDEX(Settings!$Q$7:$T$10,MATCH(B28,Settings!$P$7:$P$10,0),MATCH(C28,Settings!$Q$6:$T$6,0)),"") | H28: =IF(OR(A28="",$B$8=""),"",$B$8) | I28: =IF(OR(A28="",$B$9=""),"",$B$9) | J28: =IF(OR(A28="",IF(H28="",$B$8,H28)="",IF(I28="",$B$9,I28)=""),"",IFERROR(NETWORKDAYS(IF(H28="",$B$8,H28),IF(I28="",$B$9,I28),INDEX(Settings!$J$7:$M$60,0,MATCH(C28,Settings!$J$6:$M$6,0))),NETWORKDAYS(IF(H28="",$B$8,H28),IF(I28="",$B$9,I28)))) | L28: =IF(C28="",0,IFERROR(INDEX(Settings!$B$6:$B$9,MATCH(C28,Settings!$A$6:$A$9,0)),0)) -> 0 | M28: =IF(OR(E28="",F28=""),0,E28*F28) -> 0 | N28: =IF(OR(E28="",G28=""),0,E28*G28) -> 0 | O28: =N28*L28 -> 0 | P28: =N28+O28 -> 0 | Q28: =IF(C28="",0,IFERROR(INDEX(Settings!$C$6:$C$9,MATCH(C28,Settings!$A$6:$A$9,0)),0)) -> 0
E29: =IF(K29<>"",K29,IF(J29="","",J29*Settings!$B$3*IF(D29="",1,D29))) | G29: =IFERROR(INDEX(Settings!$Q$7:$T$10,MATCH(B29,Settings!$P$7:$P$10,0),MATCH(C29,Settings!$Q$6:$T$6,0)),"") | H29: =IF(OR(A29="",$B$8=""),"",$B$8) | I29: =IF(OR(A29="",$B$9=""),"",$B$9) | J29: =IF(OR(A29="",IF(H29="",$B$8,H29)="",IF(I29="",$B$9,I29)=""),"",IFERROR(NETWORKDAYS(IF(H29="",$B$8,H29),IF(I29="",$B$9,I29),INDEX(Settings!$J$7:$M$60,0,MATCH(C29,Settings!$J$6:$M$6,0))),NETWORKDAYS(IF(H29="",$B$8,H29),IF(I29="",$B$9,I29)))) | L29: =IF(C29="",0,IFERROR(INDEX(Settings!$B$6:$B$9,MATCH(C29,Settings!$A$6:$A$9,0)),0)) -> 0 | M29: =IF(OR(E29="",F29=""),0,E29*F29) -> 0 | N29: =IF(OR(E29="",G29=""),0,E29*G29) -> 0 | O29: =N29*L29 -> 0 | P29: =N29+O29 -> 0 | Q29: =IF(C29="",0,IFERROR(INDEX(Settings!$C$6:$C$9,MATCH(C29,Settings!$A$6:$A$9,0)),0)) -> 0
E30: =IF(K30<>"",K30,IF(J30="","",J30*Settings!$B$3*IF(D30="",1,D30))) | G30: =IFERROR(INDEX(Settings!$Q$7:$T$10,MATCH(B30,Settings!$P$7:$P$10,0),MATCH(C30,Settings!$Q$6:$T$6,0)),"") | H30: =IF(OR(A30="",$B$8=""),"",$B$8) | I30: =IF(OR(A30="",$B$9=""),"",$B$9) | J30: =IF(OR(A30="",IF(H30="",$B$8,H30)="",IF(I30="",$B$9,I30)=""),"",IFERROR(NETWORKDAYS(IF(H30="",$B$8,H30),IF(I30="",$B$9,I30),INDEX(Settings!$J$7:$M$60,0,MATCH(C30,Settings!$J$6:$M$6,0))),NETWORKDAYS(IF(H30="",$B$8,H30),IF(I30="",$B$9,I30)))) | L30: =IF(C30="",0,IFERROR(INDEX(Settings!$B$6:$B$9,MATCH(C30,Settings!$A$6:$A$9,0)),0)) -> 0 | M30: =IF(OR(E30="",F30=""),0,E30*F30) -> 0 | N30: =IF(OR(E30="",G30=""),0,E30*G30) -> 0 | O30: =N30*L30 -> 0 | P30: =N30+O30 -> 0 | Q30: =IF(C30="",0,IFERROR(INDEX(Settings!$C$6:$C$9,MATCH(C30,Settings!$A$6:$A$9,0)),0)) -> 0 | S30: How to use
E31: =IF(K31<>"",K31,IF(J31="","",J31*Settings!$B$3*IF(D31="",1,D31))) | G31: =IFERROR(INDEX(Settings!$Q$7:$T$10,MATCH(B31,Settings!$P$7:$P$10,0),MATCH(C31,Settings!$Q$6:$T$6,0)),"") | H31: =IF(OR(A31="",$B$8=""),"",$B$8) | I31: =IF(OR(A31="",$B$9=""),"",$B$9) | J31: =IF(OR(A31="",IF(H31="",$B$8,H31)="",IF(I31="",$B$9,I31)=""),"",IFERROR(NETWORKDAYS(IF(H31="",$B$8,H31),IF(I31="",$B$9,I31),INDEX(Settings!$J$7:$M$60,0,MATCH(C31,Settings!$J$6:$M$6,0))),NETWORKDAYS(IF(H31="",$B$8,H31),IF(I31="",$B$9,I31)))) | L31: =IF(C31="",0,IFERROR(INDEX(Settings!$B$6:$B$9,MATCH(C31,Settings!$A$6:$A$9,0)),0)) -> 0 | M31: =IF(OR(E31="",F31=""),0,E31*F31) -> 0 | N31: =IF(OR(E31="",G31=""),0,E31*G31) -> 0 | O31: =N31*L31 -> 0 | P31: =N31+O31 -> 0 | Q31: =IF(C31="",0,IFERROR(INDEX(Settings!$C$6:$C$9,MATCH(C31,Settings!$A$6:$A$9,0)),0)) -> 0 | S31: 1. Fill the project block: engagement type, dates, and the price (Fixed cost / Assessment) or monthly fee (MSP). Duration is exact — Sep 7 to Oct 5 is 0.97 months (0 months 29 days). Partial months count by their days, so MSP fees and monthly costs are prorated.
E32: =IF(K32<>"",K32,IF(J32="","",J32*Settings!$B$3*IF(D32="",1,D32))) | G32: =IFERROR(INDEX(Settings!$Q$7:$T$10,MATCH(B32,Settings!$P$7:$P$10,0),MATCH(C32,Settings!$Q$6:$T$6,0)),"") | H32: =IF(OR(A32="",$B$8=""),"",$B$8) | I32: =IF(OR(A32="",$B$9=""),"",$B$9) | J32: =IF(OR(A32="",IF(H32="",$B$8,H32)="",IF(I32="",$B$9,I32)=""),"",IFERROR(NETWORKDAYS(IF(H32="",$B$8,H32),IF(I32="",$B$9,I32),INDEX(Settings!$J$7:$M$60,0,MATCH(C32,Settings!$J$6:$M$6,0))),NETWORKDAYS(IF(H32="",$B$8,H32),IF(I32="",$B$9,I32)))) | L32: =IF(C32="",0,IFERROR(INDEX(Settings!$B$6:$B$9,MATCH(C32,Settings!$A$6:$A$9,0)),0)) -> 0 | M32: =IF(OR(E32="",F32=""),0,E32*F32) -> 0 | N32: =IF(OR(E32="",G32=""),0,E32*G32) -> 0 | O32: =N32*L32 -> 0 | P32: =N32+O32 -> 0 | Q32: =IF(C32="",0,IFERROR(INDEX(Settings!$C$6:$C$9,MATCH(C32,Settings!$A$6:$A$9,0)),0)) -> 0 | S32: 2. Say Y or N to additional costs. If Y, every cost row needs Frequency and Billed-to-client — the Check column tells you.
E33: =IF(K33<>"",K33,IF(J33="","",J33*Settings!$B$3*IF(D33="",1,D33))) | G33: =IFERROR(INDEX(Settings!$Q$7:$T$10,MATCH(B33,Settings!$P$7:$P$10,0),MATCH(C33,Settings!$Q$6:$T$6,0)),"") | H33: =IF(OR(A33="",$B$8=""),"",$B$8) | I33: =IF(OR(A33="",$B$9=""),"",$B$9) | J33: =IF(OR(A33="",IF(H33="",$B$8,H33)="",IF(I33="",$B$9,I33)=""),"",IFERROR(NETWORKDAYS(IF(H33="",$B$8,H33),IF(I33="",$B$9,I33),INDEX(Settings!$J$7:$M$60,0,MATCH(C33,Settings!$J$6:$M$6,0))),NETWORKDAYS(IF(H33="",$B$8,H33),IF(I33="",$B$9,I33)))) | L33: =IF(C33="",0,IFERROR(INDEX(Settings!$B$6:$B$9,MATCH(C33,Settings!$A$6:$A$9,0)),0)) -> 0 | M33: =IF(OR(E33="",F33=""),0,E33*F33) -> 0 | N33: =IF(OR(E33="",G33=""),0,E33*G33) -> 0 | O33: =N33*L33 -> 0 | P33: =N33+O33 -> 0 | Q33: =IF(C33="",0,IFERROR(INDEX(Settings!$C$6:$C$9,MATCH(C33,Settings!$A$6:$A$9,0)),0)) -> 0 | S33: 3. One staffing row per person. Hours come from the dates (weekends and the location's holidays removed) × hours/day × utilization; type an override if the SOW fixes hours.
E34: =IF(K34<>"",K34,IF(J34="","",J34*Settings!$B$3*IF(D34="",1,D34))) | G34: =IFERROR(INDEX(Settings!$Q$7:$T$10,MATCH(B34,Settings!$P$7:$P$10,0),MATCH(C34,Settings!$Q$6:$T$6,0)),"") | H34: =IF(OR(A34="",$B$8=""),"",$B$8) | I34: =IF(OR(A34="",$B$9=""),"",$B$9) | J34: =IF(OR(A34="",IF(H34="",$B$8,H34)="",IF(I34="",$B$9,I34)=""),"",IFERROR(NETWORKDAYS(IF(H34="",$B$8,H34),IF(I34="",$B$9,I34),INDEX(Settings!$J$7:$M$60,0,MATCH(C34,Settings!$J$6:$M$6,0))),NETWORKDAYS(IF(H34="",$B$8,H34),IF(I34="",$B$9,I34)))) | L34: =IF(C34="",0,IFERROR(INDEX(Settings!$B$6:$B$9,MATCH(C34,Settings!$A$6:$A$9,0)),0)) -> 0 | M34: =IF(OR(E34="",F34=""),0,E34*F34) -> 0 | N34: =IF(OR(E34="",G34=""),0,E34*G34) -> 0 | O34: =N34*L34 -> 0 | P34: =N34+O34 -> 0 | Q34: =IF(C34="",0,IFERROR(INDEX(Settings!$C$6:$C$9,MATCH(C34,Settings!$A$6:$A$9,0)),0)) -> 0 | S34: 4. Bill rate matters only for Time & materials. For Fixed cost, Assessment and MSP the revenue is the price or fee, not the hours.
E35: =IF(K35<>"",K35,IF(J35="","",J35*Settings!$B$3*IF(D35="",1,D35))) | G35: =IFERROR(INDEX(Settings!$Q$7:$T$10,MATCH(B35,Settings!$P$7:$P$10,0),MATCH(C35,Settings!$Q$6:$T$6,0)),"") | H35: =IF(OR(A35="",$B$8=""),"",$B$8) | I35: =IF(OR(A35="",$B$9=""),"",$B$9) | J35: =IF(OR(A35="",IF(H35="",$B$8,H35)="",IF(I35="",$B$9,I35)=""),"",IFERROR(NETWORKDAYS(IF(H35="",$B$8,H35),IF(I35="",$B$9,I35),INDEX(Settings!$J$7:$M$60,0,MATCH(C35,Settings!$J$6:$M$6,0))),NETWORKDAYS(IF(H35="",$B$8,H35),IF(I35="",$B$9,I35)))) | L35: =IF(C35="",0,IFERROR(INDEX(Settings!$B$6:$B$9,MATCH(C35,Settings!$A$6:$A$9,0)),0)) -> 0 | M35: =IF(OR(E35="",F35=""),0,E35*F35) -> 0 | N35: =IF(OR(E35="",G35=""),0,E35*G35) -> 0 | O35: =N35*L35 -> 0 | P35: =N35+O35 -> 0 | Q35: =IF(C35="",0,IFERROR(INDEX(Settings!$C$6:$C$9,MATCH(C35,Settings!$A$6:$A$9,0)),0)) -> 0 | S35: 5. GM % = (revenue − labour − burden − additional costs) ÷ revenue, checked against the floor blended by labour cost share.
E36: =IF(K36<>"",K36,IF(J36="","",J36*Settings!$B$3*IF(D36="",1,D36))) | G36: =IFERROR(INDEX(Settings!$Q$7:$T$10,MATCH(B36,Settings!$P$7:$P$10,0),MATCH(C36,Settings!$Q$6:$T$6,0)),"") | H36: =IF(OR(A36="",$B$8=""),"",$B$8) | I36: =IF(OR(A36="",$B$9=""),"",$B$9) | J36: =IF(OR(A36="",IF(H36="",$B$8,H36)="",IF(I36="",$B$9,I36)=""),"",IFERROR(NETWORKDAYS(IF(H36="",$B$8,H36),IF(I36="",$B$9,I36),INDEX(Settings!$J$7:$M$60,0,MATCH(C36,Settings!$J$6:$M$6,0))),NETWORKDAYS(IF(H36="",$B$8,H36),IF(I36="",$B$9,I36)))) | L36: =IF(C36="",0,IFERROR(INDEX(Settings!$B$6:$B$9,MATCH(C36,Settings!$A$6:$A$9,0)),0)) -> 0 | M36: =IF(OR(E36="",F36=""),0,E36*F36) -> 0 | N36: =IF(OR(E36="",G36=""),0,E36*G36) -> 0 | O36: =N36*L36 -> 0 | P36: =N36+O36 -> 0 | Q36: =IF(C36="",0,IFERROR(INDEX(Settings!$C$6:$C$9,MATCH(C36,Settings!$A$6:$A$9,0)),0)) -> 0 | S36: 6. Monthly tab: people on the project, cost and margin for every month of the tenure — read it for MSP.
A37: Staffing total | E37: =SUM(E17:E36) -> 208.32 | M37: =SUM(M17:M36) -> 0 | N37: =SUM(N17:N36) -> 27416.122 | O37: =SUM(O17:O36) -> 3143.0838 | P37: =SUM(P17:P36) -> 30559.205 | S37: 7. Leave a person's Start/End blank to use the project dates; fill them only if someone joins late or leaves early.
S38: 8. Sheets are unprotected while the form is being stabilised. Don't delete rows inside the staffing table — the Monthly tab maps to them; clear a row's yellow cells instead.
A39: Additional costs — travel, meals, licences, hardware, subcontractors (required when B13 = Y). To remove one, clear its yellow cells. | S39: 9. The sheet starts empty on purpose. Settings has placeholder burden % — set your real values once.
A40: Description * | B40: Category * | C40: Location | D40: Amount * | E40: Frequency (dropdown: One-time or Monthly; blank = One-time) | F40: Billed to client? * (dropdown Y/N — required) | G40: Total cost counted | H40: Revenue counted (pass-through) | I40: Check
A41: Shawnna | B41: Travel | C41: US | D41: 1000 | E41: One-time | F41: N | G41: =IF(OR($B$13<>"Y",D41=""),0,D41*IF(E41="Monthly",IF($B$10="",1,$B$10),1)) -> 1000 | H41: =IF(UPPER(F41)="Y",G41,0) -> 0 | I41: =IF($B$13="N","Not counted (B13 = N)",IF(D41="","",IF($B$13="","Answer B13 first",IF(F41="","Pick Billed to client Y/N","OK")))) -> OK
A42: Chris | B42: Travel | C42: US | D42: 1000 | E42: One-time | F42: N | G42: =IF(OR($B$13<>"Y",D42=""),0,D42*IF(E42="Monthly",IF($B$10="",1,$B$10),1)) -> 1000 | H42: =IF(UPPER(F42)="Y",G42,0) -> 0 | I42: =IF($B$13="N","Not counted (B13 = N)",IF(D42="","",IF($B$13="","Answer B13 first",IF(F42="","Pick Billed to client Y/N","OK")))) -> OK
A43: Srikanth | B43: Travel | C43: US | D43: 1000 | E43: One-time | F43: N | G43: =IF(OR($B$13<>"Y",D43=""),0,D43*IF(E43="Monthly",IF($B$10="",1,$B$10),1)) -> 1000 | H43: =IF(UPPER(F43)="Y",G43,0) -> 0 | I43: =IF($B$13="N","Not counted (B13 = N)",IF(D43="","",IF($B$13="","Answer B13 first",IF(F43="","Pick Billed to client Y/N","OK")))) -> OK
G44: =IF(OR($B$13<>"Y",D44=""),0,D44*IF(E44="Monthly",IF($B$10="",1,$B$10),1)) -> 0 | H44: =IF(UPPER(F44)="Y",G44,0) -> 0 | I44: =IF($B$13="N","Not counted (B13 = N)",IF(D44="","",IF($B$13="","Answer B13 first",IF(F44="","Pick Billed to client Y/N","OK"))))
G45: =IF(OR($B$13<>"Y",D45=""),0,D45*IF(E45="Monthly",IF($B$10="",1,$B$10),1)) -> 0 | H45: =IF(UPPER(F45)="Y",G45,0) -> 0 | I45: =IF($B$13="N","Not counted (B13 = N)",IF(D45="","",IF($B$13="","Answer B13 first",IF(F45="","Pick Billed to client Y/N","OK"))))
G46: =IF(OR($B$13<>"Y",D46=""),0,D46*IF(E46="Monthly",IF($B$10="",1,$B$10),1)) -> 0 | H46: =IF(UPPER(F46)="Y",G46,0) -> 0 | I46: =IF($B$13="N","Not counted (B13 = N)",IF(D46="","",IF($B$13="","Answer B13 first",IF(F46="","Pick Billed to client Y/N","OK"))))
G47: =IF(OR($B$13<>"Y",D47=""),0,D47*IF(E47="Monthly",IF($B$10="",1,$B$10),1)) -> 0 | H47: =IF(UPPER(F47)="Y",G47,0) -> 0 | I47: =IF($B$13="N","Not counted (B13 = N)",IF(D47="","",IF($B$13="","Answer B13 first",IF(F47="","Pick Billed to client Y/N","OK"))))
G48: =IF(OR($B$13<>"Y",D48=""),0,D48*IF(E48="Monthly",IF($B$10="",1,$B$10),1)) -> 0 | H48: =IF(UPPER(F48)="Y",G48,0) -> 0 | I48: =IF($B$13="N","Not counted (B13 = N)",IF(D48="","",IF($B$13="","Answer B13 first",IF(F48="","Pick Billed to client Y/N","OK"))))
G49: =IF(OR($B$13<>"Y",D49=""),0,D49*IF(E49="Monthly",IF($B$10="",1,$B$10),1)) -> 0 | H49: =IF(UPPER(F49)="Y",G49,0) -> 0 | I49: =IF($B$13="N","Not counted (B13 = N)",IF(D49="","",IF($B$13="","Answer B13 first",IF(F49="","Pick Billed to client Y/N","OK"))))
G50: =IF(OR($B$13<>"Y",D50=""),0,D50*IF(E50="Monthly",IF($B$10="",1,$B$10),1)) -> 0 | H50: =IF(UPPER(F50)="Y",G50,0) -> 0 | I50: =IF($B$13="N","Not counted (B13 = N)",IF(D50="","",IF($B$13="","Answer B13 first",IF(F50="","Pick Billed to client Y/N","OK"))))
G51: =IF(OR($B$13<>"Y",D51=""),0,D51*IF(E51="Monthly",IF($B$10="",1,$B$10),1)) -> 0 | H51: =IF(UPPER(F51)="Y",G51,0) -> 0 | I51: =IF($B$13="N","Not counted (B13 = N)",IF(D51="","",IF($B$13="","Answer B13 first",IF(F51="","Pick Billed to client Y/N","OK"))))
G52: =IF(OR($B$13<>"Y",D52=""),0,D52*IF(E52="Monthly",IF($B$10="",1,$B$10),1)) -> 0 | H52: =IF(UPPER(F52)="Y",G52,0) -> 0 | I52: =IF($B$13="N","Not counted (B13 = N)",IF(D52="","",IF($B$13="","Answer B13 first",IF(F52="","Pick Billed to client Y/N","OK"))))
A53: Additional costs total | G53: =SUM(G41:G52) -> 3000 | H53: =SUM(H41:H52) -> 0
A54: Frequency Monthly = the amount repeats every month (× Duration). Blank or One-time = once. Billed to client Y = the client reimburses it (added to revenue and cost, zero margin); N = we absorb it.

Sheet Monthly
A1: Month by month — people, cost and margin
A2: Built from the Cost Margin tab. Up to 24 months. Partial first/last months are prorated by days (row 4). MSP revenue = monthly fee × share of month; Fixed cost / Assessment = price spread by share of month; T&M = that month's hours × bill rate. One-time additional costs land in month 1; monthly ones repeat, prorated.
A3: =IF('Cost Margin'!$B$10="","Fill engagement type and project dates on the Cost Margin tab.",IF('Cost Margin'!$B$10>2,"Monthly view REQUIRED — this engagement runs "&TEXT('Cost Margin'!$B$10,"0.0")&" months.","Not needed — this engagement is "&TEXT('Cost Margin'!$B$10,"0.0")&" month(s). Use the Cost Margin summary; everything below is greyed out.")) -> Not needed — this engagement is 1.0 month(s). Use the Cost Margin summary; everything below is greyed out.
A4: Share of month covered | C4: =IF(C5="","",(C6-C5+1)/DAY(EOMONTH(C5,0))) -> 0.8 | D4: =IF(D5="","",(D6-D5+1)/DAY(EOMONTH(D5,0))) -> 0.16129032 | E4: =IF(E5="","",(E6-E5+1)/DAY(EOMONTH(E5,0))) | F4: =IF(F5="","",(F6-F5+1)/DAY(EOMONTH(F5,0))) | G4: =IF(G5="","",(G6-G5+1)/DAY(EOMONTH(G5,0))) | H4: =IF(H5="","",(H6-H5+1)/DAY(EOMONTH(H5,0))) | I4: =IF(I5="","",(I6-I5+1)/DAY(EOMONTH(I5,0))) | J4: =IF(J5="","",(J6-J5+1)/DAY(EOMONTH(J5,0))) | ... Z4: =IF(Z5="","",(Z6-Z5+1)/DAY(EOMONTH(Z5,0)))
A5: Month start | B5: =IF(OR('Cost Margin'!$B$8="",'Cost Margin'!$B$9=""),"",(YEAR('Cost Margin'!$B$9)-YEAR('Cost Margin'!$B$8))*12+MONTH('Cost Margin'!$B$9)-MONTH('Cost Margin'!$B$8)+1) -> 2 | C5: =IF('Cost Margin'!$B$8="","",'Cost Margin'!$B$8) -> 46272 | D5: =IF(OR($C$5="",$B$5="",1>=$B$5),"",EOMONTH($C$5,0)+1) -> 46296 | E5: =IF(OR($C$5="",$B$5="",2>=$B$5),"",EOMONTH($C$5,1)+1) | F5: =IF(OR($C$5="",$B$5="",3>=$B$5),"",EOMONTH($C$5,2)+1) | G5: =IF(OR($C$5="",$B$5="",4>=$B$5),"",EOMONTH($C$5,3)+1) | H5: =IF(OR($C$5="",$B$5="",5>=$B$5),"",EOMONTH($C$5,4)+1) | I5: =IF(OR($C$5="",$B$5="",6>=$B$5),"",EOMONTH($C$5,5)+1) | J5: =IF(OR($C$5="",$B$5="",7>=$B$5),"",EOMONTH($C$5,6)+1) | K5: =IF(OR($C$5="",$B$5="",8>=$B$5),"",EOMONTH($C$5,7)+1) | L5: =IF(OR($C$5="",$B$5="",9>=$B$5),"",EOMONTH($C$5,8)+1) | M5: =IF(OR($C$5="",$B$5="",10>=$B$5),"",EOMONTH($C$5,9)+1) | N5: =IF(OR($C$5="",$B$5="",11>=$B$5),"",EOMONTH($C$5,10)+1) | O5: =IF(OR($C$5="",$B$5="",12>=$B$5),"",EOMONTH($C$5,11)+1) | P5: =IF(OR($C$5="",$B$5="",13>=$B$5),"",EOMONTH($C$5,12)+1) | Q5: =IF(OR($C$5="",$B$5="",14>=$B$5),"",EOMONTH($C$5,13)+1) | R5: =IF(OR($C$5="",$B$5="",15>=$B$5),"",EOMONTH($C$5,14)+1) | S5: =IF(OR($C$5="",$B$5="",16>=$B$5),"",EOMONTH($C$5,15)+1) | T5: =IF(OR($C$5="",$B$5="",17>=$B$5),"",EOMONTH($C$5,16)+1) | U5: =IF(OR($C$5="",$B$5="",18>=$B$5),"",EOMONTH($C$5,17)+1) | V5: =IF(OR($C$5="",$B$5="",19>=$B$5),"",EOMONTH($C$5,18)+1) | W5: =IF(OR($C$5="",$B$5="",20>=$B$5),"",EOMONTH($C$5,19)+1) | X5: =IF(OR($C$5="",$B$5="",21>=$B$5),"",EOMONTH($C$5,20)+1) | Y5: =IF(OR($C$5="",$B$5="",22>=$B$5),"",EOMONTH($C$5,21)+1) | Z5: =IF(OR($C$5="",$B$5="",23>=$B$5),"",EOMONTH($C$5,22)+1)
A6: Month end | B6: ← calendar months in view | C6: =IF(C5="","",MIN(EOMONTH(C5,0),'Cost Margin'!$B$9)) -> 46295 | D6: =IF(D5="","",MIN(EOMONTH(D5,0),'Cost Margin'!$B$9)) -> 46300 | E6: =IF(E5="","",MIN(EOMONTH(E5,0),'Cost Margin'!$B$9)) | F6: =IF(F5="","",MIN(EOMONTH(F5,0),'Cost Margin'!$B$9)) | G6: =IF(G5="","",MIN(EOMONTH(G5,0),'Cost Margin'!$B$9)) | H6: =IF(H5="","",MIN(EOMONTH(H5,0),'Cost Margin'!$B$9)) | I6: =IF(I5="","",MIN(EOMONTH(I5,0),'Cost Margin'!$B$9)) | J6: =IF(J5="","",MIN(EOMONTH(J5,0),'Cost Margin'!$B$9)) | ... Z6: =IF(Z5="","",MIN(EOMONTH(Z5,0),'Cost Margin'!$B$9))
A7: Row | B7: Person / line | C7: =IF(C5="","",TEXT(C5,"mmm yyyy")) -> Sep 2026 | D7: =IF(D5="","",TEXT(D5,"mmm yyyy")) -> Oct 2026 | E7: =IF(E5="","",TEXT(E5,"mmm yyyy")) | F7: =IF(F5="","",TEXT(F5,"mmm yyyy")) | G7: =IF(G5="","",TEXT(G5,"mmm yyyy")) | H7: =IF(H5="","",TEXT(H5,"mmm yyyy")) | I7: =IF(I5="","",TEXT(I5,"mmm yyyy")) | J7: =IF(J5="","",TEXT(J5,"mmm yyyy")) | ... Z7: =IF(Z5="","",TEXT(Z5,"mmm yyyy")) | AA7: Project total
A8: Working days in month, per person
A9: 1 | B9: =IF('Cost Margin'!A17="","",'Cost Margin'!A17) -> Vikrin | C9: =IF(OR(C$5="",'Cost Margin'!$A17="",IF('Cost Margin'!$H17="",'Cost Margin'!$B$8,'Cost Margin'!$H17)="",IF('Cost Margin'!$I17="",'Cost Margin'!$B$9,'Cost Margin'!$I17)=""),0,IF(MIN(IF('Cost Margin'!$I17="",'Cost Margin'!$B$9,'Cost Margin'!$I17),C$6)<MAX(IF('Cost Margin'!$H17="",'Cost Margin'!$B$8,'Cost Margin'!$H17),C$5),0,IFERROR(NETWORKDAYS(MAX(IF('Cost Margin'!$H17="",'Cost Margin'!$B$8,'Cost Margin'!$H17),C$5),MIN(IF('Cost Margin'!$I17="",'Cost Margin'!$B$9,'Cost Margin'!$I17),C$6),INDEX(Settings!$J$7:$M$60,0,MATCH('Cost Margin'!$C17,Settings!$J$6:$M$6,0))),NETWORKDAYS(MAX(IF('Cost Margin'!$H17="",'Cost Margin'!$B$8,'Cost Margin'!$H17),C$5),MIN(IF('Cost Margin'!$I17="",'Cost Margin'!$B$9,'Cost Margin'!$I17),C$6))))) -> 18 | D9: =IF(OR(D$5="",'Cost Margin'!$A17="",IF('Cost Margin'!$H17="",'Cost Margin'!$B$8,'Cost Margin'!$H17)="",IF('Cost Margin'!$I17="",'Cost Margin'!$B$9,'Cost Margin'!$I17)=""),0,IF(MIN(IF('Cost Margin'!$I17="",'Cost Margin'!$B$9,'Cost Margin'!$I17),D$6)<MAX(IF('Cost Margin'!$H17="",'Cost Margin'!$B$8,'Cost Margin'!$H17),D$5),0,IFERROR(NETWORKDAYS(MAX(IF('Cost Margin'!$H17="",'Cost Margin'!$B$8,'Cost Margin'!$H17),D$5),MIN(IF('Cost Margin'!$I17="",'Cost Margin'!$B$9,'Cost Margin'!$I17),D$6),INDEX(Settings!$J$7:$M$60,0,MATCH('Cost Margin'!$C17,Settings!$J$6:$M$6,0))),NETWORKDAYS(MAX(IF('Cost Margin'!$H17="",'Cost Margin'!$B$8,'Cost Margin'!$H17),D$5),MIN(IF('Cost Margin'!$I17="",'Cost Margin'!$B$9,'Cost Margin'!$I17),D$6))))) -> 3 | E9: =IF(OR(E$5="",'Cost Margin'!$A17="",IF('Cost Margin'!$H17="",'Cost Margin'!$B$8,'Cost Margin'!$H17)="",IF('Cost Margin'!$I17="",'Cost Margin'!$B$9,'Cost Margin'!$I17)=""),0,IF(MIN(IF('Cost Margin'!$I17="",'Cost Margin'!$B$9,'Cost Margin'!$I17),E$6)<MAX(IF('Cost Margin'!$H17="",'Cost Margin'!$B$8,'Cost Margin'!$H17),E$5),0,IFERROR(NETWORKDAYS(MAX(IF('Cost Margin'!$H17="",'Cost Margin'!$B$8,'Cost Margin'!$H17),E$5),MIN(IF('Cost Margin'!$I17="",'Cost Margin'!$B$9,'Cost Margin'!$I17),E$6),INDEX(Settings!$J$7:$M$60,0,MATCH('Cost Margin'!$C17,Settings!$J$6:$M$6,0))),NETWORKDAYS(MAX(IF('Cost Margin'!$H17="",'Cost Margin'!$B$8,'Cost Margin'!$H17),E$5),MIN(IF('Cost Margin'!$I17="",'Cost Margin'!$B$9,'Cost Margin'!$I17),E$6))))) -> 0 | F9: =IF(OR(F$5="",'Cost Margin'!$A17="",IF('Cost Margin'!$H17="",'Cost Margin'!$B$8,'Cost Margin'!$H17)="",IF('Cost Margin'!$I17="",'Cost Margin'!$B$9,'Cost Margin'!$I17)=""),0,IF(MIN(IF('Cost Margin'!$I17="",'Cost Margin'!$B$9,'Cost Margin'!$I17),F$6)<MAX(IF('Cost Margin'!$H17="",'Cost Margin'!$B$8,'Cost Margin'!$H17),F$5),0,IFERROR(NETWORKDAYS(MAX(IF('Cost Margin'!$H17="",'Cost Margin'!$B$8,'Cost Margin'!$H17),F$5),MIN(IF('Cost Margin'!$I17="",'Cost Margin'!$B$9,'Cost Margin'!$I17),F$6),INDEX(Settings!$J$7:$M$60,0,MATCH('Cost Margin'!$C17,Settings!$J$6:$M$6,0))),NETWORKDAYS(MAX(IF('Cost Margin'!$H17="",'Cost Margin'!$B$8,'Cost Margin'!$H17),F$5),MIN(IF('Cost Margin'!$I17="",'Cost Margin'!$B$9,'Cost Margin'!$I17),F$6))))) -> 0 | G9: =IF(OR(G$5="",'Cost Margin'!$A17="",IF('Cost Margin'!$H17="",'Cost Margin'!$B$8,'Cost Margin'!$H17)="",IF('Cost Margin'!$I17="",'Cost Margin'!$B$9,'Cost Margin'!$I17)=""),0,IF(MIN(IF('Cost Margin'!$I17="",'Cost Margin'!$B$9,'Cost Margin'!$I17),G$6)<MAX(IF('Cost Margin'!$H17="",'Cost Margin'!$B$8,'Cost Margin'!$H17),G$5),0,IFERROR(NETWORKDAYS(MAX(IF('Cost Margin'!$H17="",'Cost Margin'!$B$8,'Cost Margin'!$H17),G$5),MIN(IF('Cost Margin'!$I17="",'Cost Margin'!$B$9,'Cost Margin'!$I17),G$6),INDEX(Settings!$J$7:$M$60,0,MATCH('Cost Margin'!$C17,Settings!$J$6:$M$6,0))),NETWORKDAYS(MAX(IF('Cost Margin'!$H17="",'Cost Margin'!$B$8,'Cost Margin'!$H17),G$5),MIN(IF('Cost Margin'!$I17="",'Cost Margin'!$B$9,'Cost Margin'!$I17),G$6))))) -> 0 | H9: =IF(OR(H$5="",'Cost Margin'!$A17="",IF('Cost Margin'!$H17="",'Cost Margin'!$B$8,'Cost Margin'!$H17)="",IF('Cost Margin'!$I17="",'Cost Margin'!$B$9,'Cost Margin'!$I17)=""),0,IF(MIN(IF('Cost Margin'!$I17="",'Cost Margin'!$B$9,'Cost Margin'!$I17),H$6)<MAX(IF('Cost Margin'!$H17="",'Cost Margin'!$B$8,'Cost Margin'!$H17),H$5),0,IFERROR(NETWORKDAYS(MAX(IF('Cost Margin'!$H17="",'Cost Margin'!$B$8,'Cost Margin'!$H17),H$5),MIN(IF('Cost Margin'!$I17="",'Cost Margin'!$B$9,'Cost Margin'!$I17),H$6),INDEX(Settings!$J$7:$M$60,0,MATCH('Cost Margin'!$C17,Settings!$J$6:$M$6,0))),NETWORKDAYS(MAX(IF('Cost Margin'!$H17="",'Cost Margin'!$B$8,'Cost Margin'!$H17),H$5),MIN(IF('Cost Margin'!$I17="",'Cost Margin'!$B$9,'Cost Margin'!$I17),H$6))))) -> 0 | I9: =IF(OR(I$5="",'Cost Margin'!$A17="",IF('Cost Margin'!$H17="",'Cost Margin'!$B$8,'Cost Margin'!$H17)="",IF('Cost Margin'!$I17="",'Cost Margin'!$B$9,'Cost Margin'!$I17)=""),0,IF(MIN(IF('Cost Margin'!$I17="",'Cost Margin'!$B$9,'Cost Margin'!$I17),I$6)<MAX(IF('Cost Margin'!$H17="",'Cost Margin'!$B$8,'Cost Margin'!$H17),I$5),0,IFERROR(NETWORKDAYS(MAX(IF('Cost Margin'!$H17="",'Cost Margin'!$B$8,'Cost Margin'!$H17),I$5),MIN(IF('Cost Margin'!$I17="",'Cost Margin'!$B$9,'Cost Margin'!$I17),I$6),INDEX(Settings!$J$7:$M$60,0,MATCH('Cost Margin'!$C17,Settings!$J$6:$M$6,0))),NETWORKDAYS(MAX(IF('Cost Margin'!$H17="",'Cost Margin'!$B$8,'Cost Margin'!$H17),I$5),MIN(IF('Cost Margin'!$I17="",'Cost Margin'!$B$9,'Cost Margin'!$I17),I$6))))) -> 0 | J9: =IF(OR(J$5="",'Cost Margin'!$A17="",IF('Cost Margin'!$H17="",'Cost Margin'!$B$8,'Cost Margin'!$H17)="",IF('Cost Margin'!$I17="",'Cost Margin'!$B$9,'Cost Margin'!$I17)=""),0,IF(MIN(IF('Cost Margin'!$I17="",'Cost Margin'!$B$9,'Cost Margin'!$I17),J$6)<MAX(IF('Cost Margin'!$H17="",'Cost Margin'!$B$8,'Cost Margin'!$H17),J$5),0,IFERROR(NETWORKDAYS(MAX(IF('Cost Margin'!$H17="",'Cost Margin'!$B$8,'Cost Margin'!$H17),J$5),MIN(IF('Cost Margin'!$I17="",'Cost Margin'!$B$9,'Cost Margin'!$I17),J$6),INDEX(Settings!$J$7:$M$60,0,MATCH('Cost Margin'!$C17,Settings!$J$6:$M$6,0))),NETWORKDAYS(MAX(IF('Cost Margin'!$H17="",'Cost Margin'!$B$8,'Cost Margin'!$H17),J$5),MIN(IF('Cost Margin'!$I17="",'Cost Margin'!$B$9,'Cost Margin'!$I17),J$6))))) -> 0 | ... Z9: =IF(OR(Z$5="",'Cost Margin'!$A17="",IF('Cost Margin'!$H17="",'Cost Margin'!$B$8,'Cost Margin'!$H17)="",IF('Cost Margin'!$I17="",'Cost Margin'!$B$9,'Cost Margin'!$I17)=""),0,IF(MIN(IF('Cost Margin'!$I17="",'Cost Margin'!$B$9,'Cost Margin'!$I17),Z$6)<MAX(IF('Cost Margin'!$H17="",'Cost Margin'!$B$8,'Cost Margin'!$H17),Z$5),0,IFERROR(NETWORKDAYS(MAX(IF('Cost Margin'!$H17="",'Cost Margin'!$B$8,'Cost Margin'!$H17),Z$5),MIN(IF('Cost Margin'!$I17="",'Cost Margin'!$B$9,'Cost Margin'!$I17),Z$6),INDEX(Settings!$J$7:$M$60,0,MATCH('Cost Margin'!$C17,Settings!$J$6:$M$6,0))),NETWORKDAYS(MAX(IF('Cost Margin'!$H17="",'Cost Margin'!$B$8,'Cost Margin'!$H17),Z$5),MIN(IF('Cost Margin'!$I17="",'Cost Margin'!$B$9,'Cost Margin'!$I17),Z$6))))) -> 0
A10: 2 | B10: =IF('Cost Margin'!A18="","",'Cost Margin'!A18) -> srikanth | C10: =IF(OR(C$5="",'Cost Margin'!$A18="",IF('Cost Margin'!$H18="",'Cost Margin'!$B$8,'Cost Margin'!$H18)="",IF('Cost Margin'!$I18="",'Cost Margin'!$B$9,'Cost Margin'!$I18)=""),0,IF(MIN(IF('Cost Margin'!$I18="",'Cost Margin'!$B$9,'Cost Margin'!$I18),C$6)<MAX(IF('Cost Margin'!$H18="",'Cost Margin'!$B$8,'Cost Margin'!$H18),C$5),0,IFERROR(NETWORKDAYS(MAX(IF('Cost Margin'!$H18="",'Cost Margin'!$B$8,'Cost Margin'!$H18),C$5),MIN(IF('Cost Margin'!$I18="",'Cost Margin'!$B$9,'Cost Margin'!$I18),C$6),INDEX(Settings!$J$7:$M$60,0,MATCH('Cost Margin'!$C18,Settings!$J$6:$M$6,0))),NETWORKDAYS(MAX(IF('Cost Margin'!$H18="",'Cost Margin'!$B$8,'Cost Margin'!$H18),C$5),MIN(IF('Cost Margin'!$I18="",'Cost Margin'!$B$9,'Cost Margin'!$I18),C$6))))) -> 18 | D10: =IF(OR(D$5="",'Cost Margin'!$A18="",IF('Cost Margin'!$H18="",'Cost Margin'!$B$8,'Cost Margin'!$H18)="",IF('Cost Margin'!$I18="",'Cost Margin'!$B$9,'Cost Margin'!$I18)=""),0,IF(MIN(IF('Cost Margin'!$I18="",'Cost Margin'!$B$9,'Cost Margin'!$I18),D$6)<MAX(IF('Cost Margin'!$H18="",'Cost Margin'!$B$8,'Cost Margin'!$H18),D$5),0,IFERROR(NETWORKDAYS(MAX(IF('Cost Margin'!$H18="",'Cost Margin'!$B$8,'Cost Margin'!$H18),D$5),MIN(IF('Cost Margin'!$I18="",'Cost Margin'!$B$9,'Cost Margin'!$I18),D$6),INDEX(Settings!$J$7:$M$60,0,MATCH('Cost Margin'!$C18,Settings!$J$6:$M$6,0))),NETWORKDAYS(MAX(IF('Cost Margin'!$H18="",'Cost Margin'!$B$8,'Cost Margin'!$H18),D$5),MIN(IF('Cost Margin'!$I18="",'Cost Margin'!$B$9,'Cost Margin'!$I18),D$6))))) -> 3 | E10: =IF(OR(E$5="",'Cost Margin'!$A18="",IF('Cost Margin'!$H18="",'Cost Margin'!$B$8,'Cost Margin'!$H18)="",IF('Cost Margin'!$I18="",'Cost Margin'!$B$9,'Cost Margin'!$I18)=""),0,IF(MIN(IF('Cost Margin'!$I18="",'Cost Margin'!$B$9,'Cost Margin'!$I18),E$6)<MAX(IF('Cost Margin'!$H18="",'Cost Margin'!$B$8,'Cost Margin'!$H18),E$5),0,IFERROR(NETWORKDAYS(MAX(IF('Cost Margin'!$H18="",'Cost Margin'!$B$8,'Cost Margin'!$H18),E$5),MIN(IF('Cost Margin'!$I18="",'Cost Margin'!$B$9,'Cost Margin'!$I18),E$6),INDEX(Settings!$J$7:$M$60,0,MATCH('Cost Margin'!$C18,Settings!$J$6:$M$6,0))),NETWORKDAYS(MAX(IF('Cost Margin'!$H18="",'Cost Margin'!$B$8,'Cost Margin'!$H18),E$5),MIN(IF('Cost Margin'!$I18="",'Cost Margin'!$B$9,'Cost Margin'!$I18),E$6))))) -> 0 | F10: =IF(OR(F$5="",'Cost Margin'!$A18="",IF('Cost Margin'!$H18="",'Cost Margin'!$B$8,'Cost Margin'!$H18)="",IF('Cost Margin'!$I18="",'Cost Margin'!$B$9,'Cost Margin'!$I18)=""),0,IF(MIN(IF('Cost Margin'!$I18="",'Cost Margin'!$B$9,'Cost Margin'!$I18),F$6)<MAX(IF('Cost Margin'!$H18="",'Cost Margin'!$B$8,'Cost Margin'!$H18),F$5),0,IFERROR(NETWORKDAYS(MAX(IF('Cost Margin'!$H18="",'Cost Margin'!$B$8,'Cost Margin'!$H18),F$5),MIN(IF('Cost Margin'!$I18="",'Cost Margin'!$B$9,'Cost Margin'!$I18),F$6),INDEX(Settings!$J$7:$M$60,0,MATCH('Cost Margin'!$C18,Settings!$J$6:$M$6,0))),NETWORKDAYS(MAX(IF('Cost Margin'!$H18="",'Cost Margin'!$B$8,'Cost Margin'!$H18),F$5),MIN(IF('Cost Margin'!$I18="",'Cost Margin'!$B$9,'Cost Margin'!$I18),F$6))))) -> 0 | G10: =IF(OR(G$5="",'Cost Margin'!$A18="",IF('Cost Margin'!$H18="",'Cost Margin'!$B$8,'Cost Margin'!$H18)="",IF('Cost Margin'!$I18="",'Cost Margin'!$B$9,'Cost Margin'!$I18)=""),0,IF(MIN(IF('Cost Margin'!$I18="",'Cost Margin'!$B$9,'Cost Margin'!$I18),G$6)<MAX(IF('Cost Margin'!$H18="",'Cost Margin'!$B$8,'Cost Margin'!$H18),G$5),0,IFERROR(NETWORKDAYS(MAX(IF('Cost Margin'!$H18="",'Cost Margin'!$B$8,'Cost Margin'!$H18),G$5),MIN(IF('Cost Margin'!$I18="",'Cost Margin'!$B$9,'Cost Margin'!$I18),G$6),INDEX(Settings!$J$7:$M$60,0,MATCH('Cost Margin'!$C18,Settings!$J$6:$M$6,0))),NETWORKDAYS(MAX(IF('Cost Margin'!$H18="",'Cost Margin'!$B$8,'Cost Margin'!$H18),G$5),MIN(IF('Cost Margin'!$I18="",'Cost Margin'!$B$9,'Cost Margin'!$I18),G$6))))) -> 0 | H10: =IF(OR(H$5="",'Cost Margin'!$A18="",IF('Cost Margin'!$H18="",'Cost Margin'!$B$8,'Cost Margin'!$H18)="",IF('Cost Margin'!$I18="",'Cost Margin'!$B$9,'Cost Margin'!$I18)=""),0,IF(MIN(IF('Cost Margin'!$I18="",'Cost Margin'!$B$9,'Cost Margin'!$I18),H$6)<MAX(IF('Cost Margin'!$H18="",'Cost Margin'!$B$8,'Cost Margin'!$H18),H$5),0,IFERROR(NETWORKDAYS(MAX(IF('Cost Margin'!$H18="",'Cost Margin'!$B$8,'Cost Margin'!$H18),H$5),MIN(IF('Cost Margin'!$I18="",'Cost Margin'!$B$9,'Cost Margin'!$I18),H$6),INDEX(Settings!$J$7:$M$60,0,MATCH('Cost Margin'!$C18,Settings!$J$6:$M$6,0))),NETWORKDAYS(MAX(IF('Cost Margin'!$H18="",'Cost Margin'!$B$8,'Cost Margin'!$H18),H$5),MIN(IF('Cost Margin'!$I18="",'Cost Margin'!$B$9,'Cost Margin'!$I18),H$6))))) -> 0 | I10: =IF(OR(I$5="",'Cost Margin'!$A18="",IF('Cost Margin'!$H18="",'Cost Margin'!$B$8,'Cost Margin'!$H18)="",IF('Cost Margin'!$I18="",'Cost Margin'!$B$9,'Cost Margin'!$I18)=""),0,IF(MIN(IF('Cost Margin'!$I18="",'Cost Margin'!$B$9,'Cost Margin'!$I18),I$6)<MAX(IF('Cost Margin'!$H18="",'Cost Margin'!$B$8,'Cost Margin'!$H18),I$5),0,IFERROR(NETWORKDAYS(MAX(IF('Cost Margin'!$H18="",'Cost Margin'!$B$8,'Cost Margin'!$H18),I$5),MIN(IF('Cost Margin'!$I18="",'Cost Margin'!$B$9,'Cost Margin'!$I18),I$6),INDEX(Settings!$J$7:$M$60,0,MATCH('Cost Margin'!$C18,Settings!$J$6:$M$6,0))),NETWORKDAYS(MAX(IF('Cost Margin'!$H18="",'Cost Margin'!$B$8,'Cost Margin'!$H18),I$5),MIN(IF('Cost Margin'!$I18="",'Cost Margin'!$B$9,'Cost Margin'!$I18),I$6))))) -> 0 | J10: =IF(OR(J$5="",'Cost Margin'!$A18="",IF('Cost Margin'!$H18="",'Cost Margin'!$B$8,'Cost Margin'!$H18)="",IF('Cost Margin'!$I18="",'Cost Margin'!$B$9,'Cost Margin'!$I18)=""),0,IF(MIN(IF('Cost Margin'!$I18="",'Cost Margin'!$B$9,'Cost Margin'!$I18),J$6)<MAX(IF('Cost Margin'!$H18="",'Cost Margin'!$B$8,'Cost Margin'!$H18),J$5),0,IFERROR(NETWORKDAYS(MAX(IF('Cost Margin'!$H18="",'Cost Margin'!$B$8,'Cost Margin'!$H18),J$5),MIN(IF('Cost Margin'!$I18="",'Cost Margin'!$B$9,'Cost Margin'!$I18),J$6),INDEX(Settings!$J$7:$M$60,0,MATCH('Cost Margin'!$C18,Settings!$J$6:$M$6,0))),NETWORKDAYS(MAX(IF('Cost Margin'!$H18="",'Cost Margin'!$B$8,'Cost Margin'!$H18),J$5),MIN(IF('Cost Margin'!$I18="",'Cost Margin'!$B$9,'Cost Margin'!$I18),J$6))))) -> 0 | ... Z10: =IF(OR(Z$5="",'Cost Margin'!$A18="",IF('Cost Margin'!$H18="",'Cost Margin'!$B$8,'Cost Margin'!$H18)="",IF('Cost Margin'!$I18="",'Cost Margin'!$B$9,'Cost Margin'!$I18)=""),0,IF(MIN(IF('Cost Margin'!$I18="",'Cost Margin'!$B$9,'Cost Margin'!$I18),Z$6)<MAX(IF('Cost Margin'!$H18="",'Cost Margin'!$B$8,'Cost Margin'!$H18),Z$5),0,IFERROR(NETWORKDAYS(MAX(IF('Cost Margin'!$H18="",'Cost Margin'!$B$8,'Cost Margin'!$H18),Z$5),MIN(IF('Cost Margin'!$I18="",'Cost Margin'!$B$9,'Cost Margin'!$I18),Z$6),INDEX(Settings!$J$7:$M$60,0,MATCH('Cost Margin'!$C18,Settings!$J$6:$M$6,0))),NETWORKDAYS(MAX(IF('Cost Margin'!$H18="",'Cost Margin'!$B$8,'Cost Margin'!$H18),Z$5),MIN(IF('Cost Margin'!$I18="",'Cost Margin'!$B$9,'Cost Margin'!$I18),Z$6))))) -> 0
A11: 3 | B11: =IF('Cost Margin'!A19="","",'Cost Margin'!A19) | C11: =IF(OR(C$5="",'Cost Margin'!$A19="",IF('Cost Margin'!$H19="",'Cost Margin'!$B$8,'Cost Margin'!$H19)="",IF('Cost Margin'!$I19="",'Cost Margin'!$B$9,'Cost Margin'!$I19)=""),0,IF(MIN(IF('Cost Margin'!$I19="",'Cost Margin'!$B$9,'Cost Margin'!$I19),C$6)<MAX(IF('Cost Margin'!$H19="",'Cost Margin'!$B$8,'Cost Margin'!$H19),C$5),0,IFERROR(NETWORKDAYS(MAX(IF('Cost Margin'!$H19="",'Cost Margin'!$B$8,'Cost Margin'!$H19),C$5),MIN(IF('Cost Margin'!$I19="",'Cost Margin'!$B$9,'Cost Margin'!$I19),C$6),INDEX(Settings!$J$7:$M$60,0,MATCH('Cost Margin'!$C19,Settings!$J$6:$M$6,0))),NETWORKDAYS(MAX(IF('Cost Margin'!$H19="",'Cost Margin'!$B$8,'Cost Margin'!$H19),C$5),MIN(IF('Cost Margin'!$I19="",'Cost Margin'!$B$9,'Cost Margin'!$I19),C$6))))) -> 0 | D11: =IF(OR(D$5="",'Cost Margin'!$A19="",IF('Cost Margin'!$H19="",'Cost Margin'!$B$8,'Cost Margin'!$H19)="",IF('Cost Margin'!$I19="",'Cost Margin'!$B$9,'Cost Margin'!$I19)=""),0,IF(MIN(IF('Cost Margin'!$I19="",'Cost Margin'!$B$9,'Cost Margin'!$I19),D$6)<MAX(IF('Cost Margin'!$H19="",'Cost Margin'!$B$8,'Cost Margin'!$H19),D$5),0,IFERROR(NETWORKDAYS(MAX(IF('Cost Margin'!$H19="",'Cost Margin'!$B$8,'Cost Margin'!$H19),D$5),MIN(IF('Cost Margin'!$I19="",'Cost Margin'!$B$9,'Cost Margin'!$I19),D$6),INDEX(Settings!$J$7:$M$60,0,MATCH('Cost Margin'!$C19,Settings!$J$6:$M$6,0))),NETWORKDAYS(MAX(IF('Cost Margin'!$H19="",'Cost Margin'!$B$8,'Cost Margin'!$H19),D$5),MIN(IF('Cost Margin'!$I19="",'Cost Margin'!$B$9,'Cost Margin'!$I19),D$6))))) -> 0 | E11: =IF(OR(E$5="",'Cost Margin'!$A19="",IF('Cost Margin'!$H19="",'Cost Margin'!$B$8,'Cost Margin'!$H19)="",IF('Cost Margin'!$I19="",'Cost Margin'!$B$9,'Cost Margin'!$I19)=""),0,IF(MIN(IF('Cost Margin'!$I19="",'Cost Margin'!$B$9,'Cost Margin'!$I19),E$6)<MAX(IF('Cost Margin'!$H19="",'Cost Margin'!$B$8,'Cost Margin'!$H19),E$5),0,IFERROR(NETWORKDAYS(MAX(IF('Cost Margin'!$H19="",'Cost Margin'!$B$8,'Cost Margin'!$H19),E$5),MIN(IF('Cost Margin'!$I19="",'Cost Margin'!$B$9,'Cost Margin'!$I19),E$6),INDEX(Settings!$J$7:$M$60,0,MATCH('Cost Margin'!$C19,Settings!$J$6:$M$6,0))),NETWORKDAYS(MAX(IF('Cost Margin'!$H19="",'Cost Margin'!$B$8,'Cost Margin'!$H19),E$5),MIN(IF('Cost Margin'!$I19="",'Cost Margin'!$B$9,'Cost Margin'!$I19),E$6))))) -> 0 | F11: =IF(OR(F$5="",'Cost Margin'!$A19="",IF('Cost Margin'!$H19="",'Cost Margin'!$B$8,'Cost Margin'!$H19)="",IF('Cost Margin'!$I19="",'Cost Margin'!$B$9,'Cost Margin'!$I19)=""),0,IF(MIN(IF('Cost Margin'!$I19="",'Cost Margin'!$B$9,'Cost Margin'!$I19),F$6)<MAX(IF('Cost Margin'!$H19="",'Cost Margin'!$B$8,'Cost Margin'!$H19),F$5),0,IFERROR(NETWORKDAYS(MAX(IF('Cost Margin'!$H19="",'Cost Margin'!$B$8,'Cost Margin'!$H19),F$5),MIN(IF('Cost Margin'!$I19="",'Cost Margin'!$B$9,'Cost Margin'!$I19),F$6),INDEX(Settings!$J$7:$M$60,0,MATCH('Cost Margin'!$C19,Settings!$J$6:$M$6,0))),NETWORKDAYS(MAX(IF('Cost Margin'!$H19="",'Cost Margin'!$B$8,'Cost Margin'!$H19),F$5),MIN(IF('Cost Margin'!$I19="",'Cost Margin'!$B$9,'Cost Margin'!$I19),F$6))))) -> 0 | G11: =IF(OR(G$5="",'Cost Margin'!$A19="",IF('Cost Margin'!$H19="",'Cost Margin'!$B$8,'Cost Margin'!$H19)="",IF('Cost Margin'!$I19="",'Cost Margin'!$B$9,'Cost Margin'!$I19)=""),0,IF(MIN(IF('Cost Margin'!$I19="",'Cost Margin'!$B$9,'Cost Margin'!$I19),G$6)<MAX(IF('Cost Margin'!$H19="",'Cost Margin'!$B$8,'Cost Margin'!$H19),G$5),0,IFERROR(NETWORKDAYS(MAX(IF('Cost Margin'!$H19="",'Cost Margin'!$B$8,'Cost Margin'!$H19),G$5),MIN(IF('Cost Margin'!$I19="",'Cost Margin'!$B$9,'Cost Margin'!$I19),G$6),INDEX(Settings!$J$7:$M$60,0,MATCH('Cost Margin'!$C19,Settings!$J$6:$M$6,0))),NETWORKDAYS(MAX(IF('Cost Margin'!$H19="",'Cost Margin'!$B$8,'Cost Margin'!$H19),G$5),MIN(IF('Cost Margin'!$I19="",'Cost Margin'!$B$9,'Cost Margin'!$I19),G$6))))) -> 0 | H11: =IF(OR(H$5="",'Cost Margin'!$A19="",IF('Cost Margin'!$H19="",'Cost Margin'!$B$8,'Cost Margin'!$H19)="",IF('Cost Margin'!$I19="",'Cost Margin'!$B$9,'Cost Margin'!$I19)=""),0,IF(MIN(IF('Cost Margin'!$I19="",'Cost Margin'!$B$9,'Cost Margin'!$I19),H$6)<MAX(IF('Cost Margin'!$H19="",'Cost Margin'!$B$8,'Cost Margin'!$H19),H$5),0,IFERROR(NETWORKDAYS(MAX(IF('Cost Margin'!$H19="",'Cost Margin'!$B$8,'Cost Margin'!$H19),H$5),MIN(IF('Cost Margin'!$I19="",'Cost Margin'!$B$9,'Cost Margin'!$I19),H$6),INDEX(Settings!$J$7:$M$60,0,MATCH('Cost Margin'!$C19,Settings!$J$6:$M$6,0))),NETWORKDAYS(MAX(IF('Cost Margin'!$H19="",'Cost Margin'!$B$8,'Cost Margin'!$H19),H$5),MIN(IF('Cost Margin'!$I19="",'Cost Margin'!$B$9,'Cost Margin'!$I19),H$6))))) -> 0 | I11: =IF(OR(I$5="",'Cost Margin'!$A19="",IF('Cost Margin'!$H19="",'Cost Margin'!$B$8,'Cost Margin'!$H19)="",IF('Cost Margin'!$I19="",'Cost Margin'!$B$9,'Cost Margin'!$I19)=""),0,IF(MIN(IF('Cost Margin'!$I19="",'Cost Margin'!$B$9,'Cost Margin'!$I19),I$6)<MAX(IF('Cost Margin'!$H19="",'Cost Margin'!$B$8,'Cost Margin'!$H19),I$5),0,IFERROR(NETWORKDAYS(MAX(IF('Cost Margin'!$H19="",'Cost Margin'!$B$8,'Cost Margin'!$H19),I$5),MIN(IF('Cost Margin'!$I19="",'Cost Margin'!$B$9,'Cost Margin'!$I19),I$6),INDEX(Settings!$J$7:$M$60,0,MATCH('Cost Margin'!$C19,Settings!$J$6:$M$6,0))),NETWORKDAYS(MAX(IF('Cost Margin'!$H19="",'Cost Margin'!$B$8,'Cost Margin'!$H19),I$5),MIN(IF('Cost Margin'!$I19="",'Cost Margin'!$B$9,'Cost Margin'!$I19),I$6))))) -> 0 | J11: =IF(OR(J$5="",'Cost Margin'!$A19="",IF('Cost Margin'!$H19="",'Cost Margin'!$B$8,'Cost Margin'!$H19)="",IF('Cost Margin'!$I19="",'Cost Margin'!$B$9,'Cost Margin'!$I19)=""),0,IF(MIN(IF('Cost Margin'!$I19="",'Cost Margin'!$B$9,'Cost Margin'!$I19),J$6)<MAX(IF('Cost Margin'!$H19="",'Cost Margin'!$B$8,'Cost Margin'!$H19),J$5),0,IFERROR(NETWORKDAYS(MAX(IF('Cost Margin'!$H19="",'Cost Margin'!$B$8,'Cost Margin'!$H19),J$5),MIN(IF('Cost Margin'!$I19="",'Cost Margin'!$B$9,'Cost Margin'!$I19),J$6),INDEX(Settings!$J$7:$M$60,0,MATCH('Cost Margin'!$C19,Settings!$J$6:$M$6,0))),NETWORKDAYS(MAX(IF('Cost Margin'!$H19="",'Cost Margin'!$B$8,'Cost Margin'!$H19),J$5),MIN(IF('Cost Margin'!$I19="",'Cost Margin'!$B$9,'Cost Margin'!$I19),J$6))))) -> 0 | ... Z11: =IF(OR(Z$5="",'Cost Margin'!$A19="",IF('Cost Margin'!$H19="",'Cost Margin'!$B$8,'Cost Margin'!$H19)="",IF('Cost Margin'!$I19="",'Cost Margin'!$B$9,'Cost Margin'!$I19)=""),0,IF(MIN(IF('Cost Margin'!$I19="",'Cost Margin'!$B$9,'Cost Margin'!$I19),Z$6)<MAX(IF('Cost Margin'!$H19="",'Cost Margin'!$B$8,'Cost Margin'!$H19),Z$5),0,IFERROR(NETWORKDAYS(MAX(IF('Cost Margin'!$H19="",'Cost Margin'!$B$8,'Cost Margin'!$H19),Z$5),MIN(IF('Cost Margin'!$I19="",'Cost Margin'!$B$9,'Cost Margin'!$I19),Z$6),INDEX(Settings!$J$7:$M$60,0,MATCH('Cost Margin'!$C19,Settings!$J$6:$M$6,0))),NETWORKDAYS(MAX(IF('Cost Margin'!$H19="",'Cost Margin'!$B$8,'Cost Margin'!$H19),Z$5),MIN(IF('Cost Margin'!$I19="",'Cost Margin'!$B$9,'Cost Margin'!$I19),Z$6))))) -> 0
A12: 4 | B12: =IF('Cost Margin'!A20="","",'Cost Margin'!A20) | C12: =IF(OR(C$5="",'Cost Margin'!$A20="",IF('Cost Margin'!$H20="",'Cost Margin'!$B$8,'Cost Margin'!$H20)="",IF('Cost Margin'!$I20="",'Cost Margin'!$B$9,'Cost Margin'!$I20)=""),0,IF(MIN(IF('Cost Margin'!$I20="",'Cost Margin'!$B$9,'Cost Margin'!$I20),C$6)<MAX(IF('Cost Margin'!$H20="",'Cost Margin'!$B$8,'Cost Margin'!$H20),C$5),0,IFERROR(NETWORKDAYS(MAX(IF('Cost Margin'!$H20="",'Cost Margin'!$B$8,'Cost Margin'!$H20),C$5),MIN(IF('Cost Margin'!$I20="",'Cost Margin'!$B$9,'Cost Margin'!$I20),C$6),INDEX(Settings!$J$7:$M$60,0,MATCH('Cost Margin'!$C20,Settings!$J$6:$M$6,0))),NETWORKDAYS(MAX(IF('Cost Margin'!$H20="",'Cost Margin'!$B$8,'Cost Margin'!$H20),C$5),MIN(IF('Cost Margin'!$I20="",'Cost Margin'!$B$9,'Cost Margin'!$I20),C$6))))) -> 0 | D12: =IF(OR(D$5="",'Cost Margin'!$A20="",IF('Cost Margin'!$H20="",'Cost Margin'!$B$8,'Cost Margin'!$H20)="",IF('Cost Margin'!$I20="",'Cost Margin'!$B$9,'Cost Margin'!$I20)=""),0,IF(MIN(IF('Cost Margin'!$I20="",'Cost Margin'!$B$9,'Cost Margin'!$I20),D$6)<MAX(IF('Cost Margin'!$H20="",'Cost Margin'!$B$8,'Cost Margin'!$H20),D$5),0,IFERROR(NETWORKDAYS(MAX(IF('Cost Margin'!$H20="",'Cost Margin'!$B$8,'Cost Margin'!$H20),D$5),MIN(IF('Cost Margin'!$I20="",'Cost Margin'!$B$9,'Cost Margin'!$I20),D$6),INDEX(Settings!$J$7:$M$60,0,MATCH('Cost Margin'!$C20,Settings!$J$6:$M$6,0))),NETWORKDAYS(MAX(IF('Cost Margin'!$H20="",'Cost Margin'!$B$8,'Cost Margin'!$H20),D$5),MIN(IF('Cost Margin'!$I20="",'Cost Margin'!$B$9,'Cost Margin'!$I20),D$6))))) -> 0 | E12: =IF(OR(E$5="",'Cost Margin'!$A20="",IF('Cost Margin'!$H20="",'Cost Margin'!$B$8,'Cost Margin'!$H20)="",IF('Cost Margin'!$I20="",'Cost Margin'!$B$9,'Cost Margin'!$I20)=""),0,IF(MIN(IF('Cost Margin'!$I20="",'Cost Margin'!$B$9,'Cost Margin'!$I20),E$6)<MAX(IF('Cost Margin'!$H20="",'Cost Margin'!$B$8,'Cost Margin'!$H20),E$5),0,IFERROR(NETWORKDAYS(MAX(IF('Cost Margin'!$H20="",'Cost Margin'!$B$8,'Cost Margin'!$H20),E$5),MIN(IF('Cost Margin'!$I20="",'Cost Margin'!$B$9,'Cost Margin'!$I20),E$6),INDEX(Settings!$J$7:$M$60,0,MATCH('Cost Margin'!$C20,Settings!$J$6:$M$6,0))),NETWORKDAYS(MAX(IF('Cost Margin'!$H20="",'Cost Margin'!$B$8,'Cost Margin'!$H20),E$5),MIN(IF('Cost Margin'!$I20="",'Cost Margin'!$B$9,'Cost Margin'!$I20),E$6))))) -> 0 | F12: =IF(OR(F$5="",'Cost Margin'!$A20="",IF('Cost Margin'!$H20="",'Cost Margin'!$B$8,'Cost Margin'!$H20)="",IF('Cost Margin'!$I20="",'Cost Margin'!$B$9,'Cost Margin'!$I20)=""),0,IF(MIN(IF('Cost Margin'!$I20="",'Cost Margin'!$B$9,'Cost Margin'!$I20),F$6)<MAX(IF('Cost Margin'!$H20="",'Cost Margin'!$B$8,'Cost Margin'!$H20),F$5),0,IFERROR(NETWORKDAYS(MAX(IF('Cost Margin'!$H20="",'Cost Margin'!$B$8,'Cost Margin'!$H20),F$5),MIN(IF('Cost Margin'!$I20="",'Cost Margin'!$B$9,'Cost Margin'!$I20),F$6),INDEX(Settings!$J$7:$M$60,0,MATCH('Cost Margin'!$C20,Settings!$J$6:$M$6,0))),NETWORKDAYS(MAX(IF('Cost Margin'!$H20="",'Cost Margin'!$B$8,'Cost Margin'!$H20),F$5),MIN(IF('Cost Margin'!$I20="",'Cost Margin'!$B$9,'Cost Margin'!$I20),F$6))))) -> 0 | G12: =IF(OR(G$5="",'Cost Margin'!$A20="",IF('Cost Margin'!$H20="",'Cost Margin'!$B$8,'Cost Margin'!$H20)="",IF('Cost Margin'!$I20="",'Cost Margin'!$B$9,'Cost Margin'!$I20)=""),0,IF(MIN(IF('Cost Margin'!$I20="",'Cost Margin'!$B$9,'Cost Margin'!$I20),G$6)<MAX(IF('Cost Margin'!$H20="",'Cost Margin'!$B$8,'Cost Margin'!$H20),G$5),0,IFERROR(NETWORKDAYS(MAX(IF('Cost Margin'!$H20="",'Cost Margin'!$B$8,'Cost Margin'!$H20),G$5),MIN(IF('Cost Margin'!$I20="",'Cost Margin'!$B$9,'Cost Margin'!$I20),G$6),INDEX(Settings!$J$7:$M$60,0,MATCH('Cost Margin'!$C20,Settings!$J$6:$M$6,0))),NETWORKDAYS(MAX(IF('Cost Margin'!$H20="",'Cost Margin'!$B$8,'Cost Margin'!$H20),G$5),MIN(IF('Cost Margin'!$I20="",'Cost Margin'!$B$9,'Cost Margin'!$I20),G$6))))) -> 0 | H12: =IF(OR(H$5="",'Cost Margin'!$A20="",IF('Cost Margin'!$H20="",'Cost Margin'!$B$8,'Cost Margin'!$H20)="",IF('Cost Margin'!$I20="",'Cost Margin'!$B$9,'Cost Margin'!$I20)=""),0,IF(MIN(IF('Cost Margin'!$I20="",'Cost Margin'!$B$9,'Cost Margin'!$I20),H$6)<MAX(IF('Cost Margin'!$H20="",'Cost Margin'!$B$8,'Cost Margin'!$H20),H$5),0,IFERROR(NETWORKDAYS(MAX(IF('Cost Margin'!$H20="",'Cost Margin'!$B$8,'Cost Margin'!$H20),H$5),MIN(IF('Cost Margin'!$I20="",'Cost Margin'!$B$9,'Cost Margin'!$I20),H$6),INDEX(Settings!$J$7:$M$60,0,MATCH('Cost Margin'!$C20,Settings!$J$6:$M$6,0))),NETWORKDAYS(MAX(IF('Cost Margin'!$H20="",'Cost Margin'!$B$8,'Cost Margin'!$H20),H$5),MIN(IF('Cost Margin'!$I20="",'Cost Margin'!$B$9,'Cost Margin'!$I20),H$6))))) -> 0 | I12: =IF(OR(I$5="",'Cost Margin'!$A20="",IF('Cost Margin'!$H20="",'Cost Margin'!$B$8,'Cost Margin'!$H20)="",IF('Cost Margin'!$I20="",'Cost Margin'!$B$9,'Cost Margin'!$I20)=""),0,IF(MIN(IF('Cost Margin'!$I20="",'Cost Margin'!$B$9,'Cost Margin'!$I20),I$6)<MAX(IF('Cost Margin'!$H20="",'Cost Margin'!$B$8,'Cost Margin'!$H20),I$5),0,IFERROR(NETWORKDAYS(MAX(IF('Cost Margin'!$H20="",'Cost Margin'!$B$8,'Cost Margin'!$H20),I$5),MIN(IF('Cost Margin'!$I20="",'Cost Margin'!$B$9,'Cost Margin'!$I20),I$6),INDEX(Settings!$J$7:$M$60,0,MATCH('Cost Margin'!$C20,Settings!$J$6:$M$6,0))),NETWORKDAYS(MAX(IF('Cost Margin'!$H20="",'Cost Margin'!$B$8,'Cost Margin'!$H20),I$5),MIN(IF('Cost Margin'!$I20="",'Cost Margin'!$B$9,'Cost Margin'!$I20),I$6))))) -> 0 | J12: =IF(OR(J$5="",'Cost Margin'!$A20="",IF('Cost Margin'!$H20="",'Cost Margin'!$B$8,'Cost Margin'!$H20)="",IF('Cost Margin'!$I20="",'Cost Margin'!$B$9,'Cost Margin'!$I20)=""),0,IF(MIN(IF('Cost Margin'!$I20="",'Cost Margin'!$B$9,'Cost Margin'!$I20),J$6)<MAX(IF('Cost Margin'!$H20="",'Cost Margin'!$B$8,'Cost Margin'!$H20),J$5),0,IFERROR(NETWORKDAYS(MAX(IF('Cost Margin'!$H20="",'Cost Margin'!$B$8,'Cost Margin'!$H20),J$5),MIN(IF('Cost Margin'!$I20="",'Cost Margin'!$B$9,'Cost Margin'!$I20),J$6),INDEX(Settings!$J$7:$M$60,0,MATCH('Cost Margin'!$C20,Settings!$J$6:$M$6,0))),NETWORKDAYS(MAX(IF('Cost Margin'!$H20="",'Cost Margin'!$B$8,'Cost Margin'!$H20),J$5),MIN(IF('Cost Margin'!$I20="",'Cost Margin'!$B$9,'Cost Margin'!$I20),J$6))))) -> 0 | ... Z12: =IF(OR(Z$5="",'Cost Margin'!$A20="",IF('Cost Margin'!$H20="",'Cost Margin'!$B$8,'Cost Margin'!$H20)="",IF('Cost Margin'!$I20="",'Cost Margin'!$B$9,'Cost Margin'!$I20)=""),0,IF(MIN(IF('Cost Margin'!$I20="",'Cost Margin'!$B$9,'Cost Margin'!$I20),Z$6)<MAX(IF('Cost Margin'!$H20="",'Cost Margin'!$B$8,'Cost Margin'!$H20),Z$5),0,IFERROR(NETWORKDAYS(MAX(IF('Cost Margin'!$H20="",'Cost Margin'!$B$8,'Cost Margin'!$H20),Z$5),MIN(IF('Cost Margin'!$I20="",'Cost Margin'!$B$9,'Cost Margin'!$I20),Z$6),INDEX(Settings!$J$7:$M$60,0,MATCH('Cost Margin'!$C20,Settings!$J$6:$M$6,0))),NETWORKDAYS(MAX(IF('Cost Margin'!$H20="",'Cost Margin'!$B$8,'Cost Margin'!$H20),Z$5),MIN(IF('Cost Margin'!$I20="",'Cost Margin'!$B$9,'Cost Margin'!$I20),Z$6))))) -> 0
A13: 5 | B13: =IF('Cost Margin'!A21="","",'Cost Margin'!A21) | C13: =IF(OR(C$5="",'Cost Margin'!$A21="",IF('Cost Margin'!$H21="",'Cost Margin'!$B$8,'Cost Margin'!$H21)="",IF('Cost Margin'!$I21="",'Cost Margin'!$B$9,'Cost Margin'!$I21)=""),0,IF(MIN(IF('Cost Margin'!$I21="",'Cost Margin'!$B$9,'Cost Margin'!$I21),C$6)<MAX(IF('Cost Margin'!$H21="",'Cost Margin'!$B$8,'Cost Margin'!$H21),C$5),0,IFERROR(NETWORKDAYS(MAX(IF('Cost Margin'!$H21="",'Cost Margin'!$B$8,'Cost Margin'!$H21),C$5),MIN(IF('Cost Margin'!$I21="",'Cost Margin'!$B$9,'Cost Margin'!$I21),C$6),INDEX(Settings!$J$7:$M$60,0,MATCH('Cost Margin'!$C21,Settings!$J$6:$M$6,0))),NETWORKDAYS(MAX(IF('Cost Margin'!$H21="",'Cost Margin'!$B$8,'Cost Margin'!$H21),C$5),MIN(IF('Cost Margin'!$I21="",'Cost Margin'!$B$9,'Cost Margin'!$I21),C$6))))) -> 0 | D13: =IF(OR(D$5="",'Cost Margin'!$A21="",IF('Cost Margin'!$H21="",'Cost Margin'!$B$8,'Cost Margin'!$H21)="",IF('Cost Margin'!$I21="",'Cost Margin'!$B$9,'Cost Margin'!$I21)=""),0,IF(MIN(IF('Cost Margin'!$I21="",'Cost Margin'!$B$9,'Cost Margin'!$I21),D$6)<MAX(IF('Cost Margin'!$H21="",'Cost Margin'!$B$8,'Cost Margin'!$H21),D$5),0,IFERROR(NETWORKDAYS(MAX(IF('Cost Margin'!$H21="",'Cost Margin'!$B$8,'Cost Margin'!$H21),D$5),MIN(IF('Cost Margin'!$I21="",'Cost Margin'!$B$9,'Cost Margin'!$I21),D$6),INDEX(Settings!$J$7:$M$60,0,MATCH('Cost Margin'!$C21,Settings!$J$6:$M$6,0))),NETWORKDAYS(MAX(IF('Cost Margin'!$H21="",'Cost Margin'!$B$8,'Cost Margin'!$H21),D$5),MIN(IF('Cost Margin'!$I21="",'Cost Margin'!$B$9,'Cost Margin'!$I21),D$6))))) -> 0 | E13: =IF(OR(E$5="",'Cost Margin'!$A21="",IF('Cost Margin'!$H21="",'Cost Margin'!$B$8,'Cost Margin'!$H21)="",IF('Cost Margin'!$I21="",'Cost Margin'!$B$9,'Cost Margin'!$I21)=""),0,IF(MIN(IF('Cost Margin'!$I21="",'Cost Margin'!$B$9,'Cost Margin'!$I21),E$6)<MAX(IF('Cost Margin'!$H21="",'Cost Margin'!$B$8,'Cost Margin'!$H21),E$5),0,IFERROR(NETWORKDAYS(MAX(IF('Cost Margin'!$H21="",'Cost Margin'!$B$8,'Cost Margin'!$H21),E$5),MIN(IF('Cost Margin'!$I21="",'Cost Margin'!$B$9,'Cost Margin'!$I21),E$6),INDEX(Settings!$J$7:$M$60,0,MATCH('Cost Margin'!$C21,Settings!$J$6:$M$6,0))),NETWORKDAYS(MAX(IF('Cost Margin'!$H21="",'Cost Margin'!$B$8,'Cost Margin'!$H21),E$5),MIN(IF('Cost Margin'!$I21="",'Cost Margin'!$B$9,'Cost Margin'!$I21),E$6))))) -> 0 | F13: =IF(OR(F$5="",'Cost Margin'!$A21="",IF('Cost Margin'!$H21="",'Cost Margin'!$B$8,'Cost Margin'!$H21)="",IF('Cost Margin'!$I21="",'Cost Margin'!$B$9,'Cost Margin'!$I21)=""),0,IF(MIN(IF('Cost Margin'!$I21="",'Cost Margin'!$B$9,'Cost Margin'!$I21),F$6)<MAX(IF('Cost Margin'!$H21="",'Cost Margin'!$B$8,'Cost Margin'!$H21),F$5),0,IFERROR(NETWORKDAYS(MAX(IF('Cost Margin'!$H21="",'Cost Margin'!$B$8,'Cost Margin'!$H21),F$5),MIN(IF('Cost Margin'!$I21="",'Cost Margin'!$B$9,'Cost Margin'!$I21),F$6),INDEX(Settings!$J$7:$M$60,0,MATCH('Cost Margin'!$C21,Settings!$J$6:$M$6,0))),NETWORKDAYS(MAX(IF('Cost Margin'!$H21="",'Cost Margin'!$B$8,'Cost Margin'!$H21),F$5),MIN(IF('Cost Margin'!$I21="",'Cost Margin'!$B$9,'Cost Margin'!$I21),F$6))))) -> 0 | G13: =IF(OR(G$5="",'Cost Margin'!$A21="",IF('Cost Margin'!$H21="",'Cost Margin'!$B$8,'Cost Margin'!$H21)="",IF('Cost Margin'!$I21="",'Cost Margin'!$B$9,'Cost Margin'!$I21)=""),0,IF(MIN(IF('Cost Margin'!$I21="",'Cost Margin'!$B$9,'Cost Margin'!$I21),G$6)<MAX(IF('Cost Margin'!$H21="",'Cost Margin'!$B$8,'Cost Margin'!$H21),G$5),0,IFERROR(NETWORKDAYS(MAX(IF('Cost Margin'!$H21="",'Cost Margin'!$B$8,'Cost Margin'!$H21),G$5),MIN(IF('Cost Margin'!$I21="",'Cost Margin'!$B$9,'Cost Margin'!$I21),G$6),INDEX(Settings!$J$7:$M$60,0,MATCH('Cost Margin'!$C21,Settings!$J$6:$M$6,0))),NETWORKDAYS(MAX(IF('Cost Margin'!$H21="",'Cost Margin'!$B$8,'Cost Margin'!$H21),G$5),MIN(IF('Cost Margin'!$I21="",'Cost Margin'!$B$9,'Cost Margin'!$I21),G$6))))) -> 0 | H13: =IF(OR(H$5="",'Cost Margin'!$A21="",IF('Cost Margin'!$H21="",'Cost Margin'!$B$8,'Cost Margin'!$H21)="",IF('Cost Margin'!$I21="",'Cost Margin'!$B$9,'Cost Margin'!$I21)=""),0,IF(MIN(IF('Cost Margin'!$I21="",'Cost Margin'!$B$9,'Cost Margin'!$I21),H$6)<MAX(IF('Cost Margin'!$H21="",'Cost Margin'!$B$8,'Cost Margin'!$H21),H$5),0,IFERROR(NETWORKDAYS(MAX(IF('Cost Margin'!$H21="",'Cost Margin'!$B$8,'Cost Margin'!$H21),H$5),MIN(IF('Cost Margin'!$I21="",'Cost Margin'!$B$9,'Cost Margin'!$I21),H$6),INDEX(Settings!$J$7:$M$60,0,MATCH('Cost Margin'!$C21,Settings!$J$6:$M$6,0))),NETWORKDAYS(MAX(IF('Cost Margin'!$H21="",'Cost Margin'!$B$8,'Cost Margin'!$H21),H$5),MIN(IF('Cost Margin'!$I21="",'Cost Margin'!$B$9,'Cost Margin'!$I21),H$6))))) -> 0 | I13: =IF(OR(I$5="",'Cost Margin'!$A21="",IF('Cost Margin'!$H21="",'Cost Margin'!$B$8,'Cost Margin'!$H21)="",IF('Cost Margin'!$I21="",'Cost Margin'!$B$9,'Cost Margin'!$I21)=""),0,IF(MIN(IF('Cost Margin'!$I21="",'Cost Margin'!$B$9,'Cost Margin'!$I21),I$6)<MAX(IF('Cost Margin'!$H21="",'Cost Margin'!$B$8,'Cost Margin'!$H21),I$5),0,IFERROR(NETWORKDAYS(MAX(IF('Cost Margin'!$H21="",'Cost Margin'!$B$8,'Cost Margin'!$H21),I$5),MIN(IF('Cost Margin'!$I21="",'Cost Margin'!$B$9,'Cost Margin'!$I21),I$6),INDEX(Settings!$J$7:$M$60,0,MATCH('Cost Margin'!$C21,Settings!$J$6:$M$6,0))),NETWORKDAYS(MAX(IF('Cost Margin'!$H21="",'Cost Margin'!$B$8,'Cost Margin'!$H21),I$5),MIN(IF('Cost Margin'!$I21="",'Cost Margin'!$B$9,'Cost Margin'!$I21),I$6))))) -> 0 | J13: =IF(OR(J$5="",'Cost Margin'!$A21="",IF('Cost Margin'!$H21="",'Cost Margin'!$B$8,'Cost Margin'!$H21)="",IF('Cost Margin'!$I21="",'Cost Margin'!$B$9,'Cost Margin'!$I21)=""),0,IF(MIN(IF('Cost Margin'!$I21="",'Cost Margin'!$B$9,'Cost Margin'!$I21),J$6)<MAX(IF('Cost Margin'!$H21="",'Cost Margin'!$B$8,'Cost Margin'!$H21),J$5),0,IFERROR(NETWORKDAYS(MAX(IF('Cost Margin'!$H21="",'Cost Margin'!$B$8,'Cost Margin'!$H21),J$5),MIN(IF('Cost Margin'!$I21="",'Cost Margin'!$B$9,'Cost Margin'!$I21),J$6),INDEX(Settings!$J$7:$M$60,0,MATCH('Cost Margin'!$C21,Settings!$J$6:$M$6,0))),NETWORKDAYS(MAX(IF('Cost Margin'!$H21="",'Cost Margin'!$B$8,'Cost Margin'!$H21),J$5),MIN(IF('Cost Margin'!$I21="",'Cost Margin'!$B$9,'Cost Margin'!$I21),J$6))))) -> 0 | ... Z13: =IF(OR(Z$5="",'Cost Margin'!$A21="",IF('Cost Margin'!$H21="",'Cost Margin'!$B$8,'Cost Margin'!$H21)="",IF('Cost Margin'!$I21="",'Cost Margin'!$B$9,'Cost Margin'!$I21)=""),0,IF(MIN(IF('Cost Margin'!$I21="",'Cost Margin'!$B$9,'Cost Margin'!$I21),Z$6)<MAX(IF('Cost Margin'!$H21="",'Cost Margin'!$B$8,'Cost Margin'!$H21),Z$5),0,IFERROR(NETWORKDAYS(MAX(IF('Cost Margin'!$H21="",'Cost Margin'!$B$8,'Cost Margin'!$H21),Z$5),MIN(IF('Cost Margin'!$I21="",'Cost Margin'!$B$9,'Cost Margin'!$I21),Z$6),INDEX(Settings!$J$7:$M$60,0,MATCH('Cost Margin'!$C21,Settings!$J$6:$M$6,0))),NETWORKDAYS(MAX(IF('Cost Margin'!$H21="",'Cost Margin'!$B$8,'Cost Margin'!$H21),Z$5),MIN(IF('Cost Margin'!$I21="",'Cost Margin'!$B$9,'Cost Margin'!$I21),Z$6))))) -> 0
A14: 6 | B14: =IF('Cost Margin'!A22="","",'Cost Margin'!A22) | C14: =IF(OR(C$5="",'Cost Margin'!$A22="",IF('Cost Margin'!$H22="",'Cost Margin'!$B$8,'Cost Margin'!$H22)="",IF('Cost Margin'!$I22="",'Cost Margin'!$B$9,'Cost Margin'!$I22)=""),0,IF(MIN(IF('Cost Margin'!$I22="",'Cost Margin'!$B$9,'Cost Margin'!$I22),C$6)<MAX(IF('Cost Margin'!$H22="",'Cost Margin'!$B$8,'Cost Margin'!$H22),C$5),0,IFERROR(NETWORKDAYS(MAX(IF('Cost Margin'!$H22="",'Cost Margin'!$B$8,'Cost Margin'!$H22),C$5),MIN(IF('Cost Margin'!$I22="",'Cost Margin'!$B$9,'Cost Margin'!$I22),C$6),INDEX(Settings!$J$7:$M$60,0,MATCH('Cost Margin'!$C22,Settings!$J$6:$M$6,0))),NETWORKDAYS(MAX(IF('Cost Margin'!$H22="",'Cost Margin'!$B$8,'Cost Margin'!$H22),C$5),MIN(IF('Cost Margin'!$I22="",'Cost Margin'!$B$9,'Cost Margin'!$I22),C$6))))) -> 0 | D14: =IF(OR(D$5="",'Cost Margin'!$A22="",IF('Cost Margin'!$H22="",'Cost Margin'!$B$8,'Cost Margin'!$H22)="",IF('Cost Margin'!$I22="",'Cost Margin'!$B$9,'Cost Margin'!$I22)=""),0,IF(MIN(IF('Cost Margin'!$I22="",'Cost Margin'!$B$9,'Cost Margin'!$I22),D$6)<MAX(IF('Cost Margin'!$H22="",'Cost Margin'!$B$8,'Cost Margin'!$H22),D$5),0,IFERROR(NETWORKDAYS(MAX(IF('Cost Margin'!$H22="",'Cost Margin'!$B$8,'Cost Margin'!$H22),D$5),MIN(IF('Cost Margin'!$I22="",'Cost Margin'!$B$9,'Cost Margin'!$I22),D$6),INDEX(Settings!$J$7:$M$60,0,MATCH('Cost Margin'!$C22,Settings!$J$6:$M$6,0))),NETWORKDAYS(MAX(IF('Cost Margin'!$H22="",'Cost Margin'!$B$8,'Cost Margin'!$H22),D$5),MIN(IF('Cost Margin'!$I22="",'Cost Margin'!$B$9,'Cost Margin'!$I22),D$6))))) -> 0 | E14: =IF(OR(E$5="",'Cost Margin'!$A22="",IF('Cost Margin'!$H22="",'Cost Margin'!$B$8,'Cost Margin'!$H22)="",IF('Cost Margin'!$I22="",'Cost Margin'!$B$9,'Cost Margin'!$I22)=""),0,IF(MIN(IF('Cost Margin'!$I22="",'Cost Margin'!$B$9,'Cost Margin'!$I22),E$6)<MAX(IF('Cost Margin'!$H22="",'Cost Margin'!$B$8,'Cost Margin'!$H22),E$5),0,IFERROR(NETWORKDAYS(MAX(IF('Cost Margin'!$H22="",'Cost Margin'!$B$8,'Cost Margin'!$H22),E$5),MIN(IF('Cost Margin'!$I22="",'Cost Margin'!$B$9,'Cost Margin'!$I22),E$6),INDEX(Settings!$J$7:$M$60,0,MATCH('Cost Margin'!$C22,Settings!$J$6:$M$6,0))),NETWORKDAYS(MAX(IF('Cost Margin'!$H22="",'Cost Margin'!$B$8,'Cost Margin'!$H22),E$5),MIN(IF('Cost Margin'!$I22="",'Cost Margin'!$B$9,'Cost Margin'!$I22),E$6))))) -> 0 | F14: =IF(OR(F$5="",'Cost Margin'!$A22="",IF('Cost Margin'!$H22="",'Cost Margin'!$B$8,'Cost Margin'!$H22)="",IF('Cost Margin'!$I22="",'Cost Margin'!$B$9,'Cost Margin'!$I22)=""),0,IF(MIN(IF('Cost Margin'!$I22="",'Cost Margin'!$B$9,'Cost Margin'!$I22),F$6)<MAX(IF('Cost Margin'!$H22="",'Cost Margin'!$B$8,'Cost Margin'!$H22),F$5),0,IFERROR(NETWORKDAYS(MAX(IF('Cost Margin'!$H22="",'Cost Margin'!$B$8,'Cost Margin'!$H22),F$5),MIN(IF('Cost Margin'!$I22="",'Cost Margin'!$B$9,'Cost Margin'!$I22),F$6),INDEX(Settings!$J$7:$M$60,0,MATCH('Cost Margin'!$C22,Settings!$J$6:$M$6,0))),NETWORKDAYS(MAX(IF('Cost Margin'!$H22="",'Cost Margin'!$B$8,'Cost Margin'!$H22),F$5),MIN(IF('Cost Margin'!$I22="",'Cost Margin'!$B$9,'Cost Margin'!$I22),F$6))))) -> 0 | G14: =IF(OR(G$5="",'Cost Margin'!$A22="",IF('Cost Margin'!$H22="",'Cost Margin'!$B$8,'Cost Margin'!$H22)="",IF('Cost Margin'!$I22="",'Cost Margin'!$B$9,'Cost Margin'!$I22)=""),0,IF(MIN(IF('Cost Margin'!$I22="",'Cost Margin'!$B$9,'Cost Margin'!$I22),G$6)<MAX(IF('Cost Margin'!$H22="",'Cost Margin'!$B$8,'Cost Margin'!$H22),G$5),0,IFERROR(NETWORKDAYS(MAX(IF('Cost Margin'!$H22="",'Cost Margin'!$B$8,'Cost Margin'!$H22),G$5),MIN(IF('Cost Margin'!$I22="",'Cost Margin'!$B$9,'Cost Margin'!$I22),G$6),INDEX(Settings!$J$7:$M$60,0,MATCH('Cost Margin'!$C22,Settings!$J$6:$M$6,0))),NETWORKDAYS(MAX(IF('Cost Margin'!$H22="",'Cost Margin'!$B$8,'Cost Margin'!$H22),G$5),MIN(IF('Cost Margin'!$I22="",'Cost Margin'!$B$9,'Cost Margin'!$I22),G$6))))) -> 0 | H14: =IF(OR(H$5="",'Cost Margin'!$A22="",IF('Cost Margin'!$H22="",'Cost Margin'!$B$8,'Cost Margin'!$H22)="",IF('Cost Margin'!$I22="",'Cost Margin'!$B$9,'Cost Margin'!$I22)=""),0,IF(MIN(IF('Cost Margin'!$I22="",'Cost Margin'!$B$9,'Cost Margin'!$I22),H$6)<MAX(IF('Cost Margin'!$H22="",'Cost Margin'!$B$8,'Cost Margin'!$H22),H$5),0,IFERROR(NETWORKDAYS(MAX(IF('Cost Margin'!$H22="",'Cost Margin'!$B$8,'Cost Margin'!$H22),H$5),MIN(IF('Cost Margin'!$I22="",'Cost Margin'!$B$9,'Cost Margin'!$I22),H$6),INDEX(Settings!$J$7:$M$60,0,MATCH('Cost Margin'!$C22,Settings!$J$6:$M$6,0))),NETWORKDAYS(MAX(IF('Cost Margin'!$H22="",'Cost Margin'!$B$8,'Cost Margin'!$H22),H$5),MIN(IF('Cost Margin'!$I22="",'Cost Margin'!$B$9,'Cost Margin'!$I22),H$6))))) -> 0 | I14: =IF(OR(I$5="",'Cost Margin'!$A22="",IF('Cost Margin'!$H22="",'Cost Margin'!$B$8,'Cost Margin'!$H22)="",IF('Cost Margin'!$I22="",'Cost Margin'!$B$9,'Cost Margin'!$I22)=""),0,IF(MIN(IF('Cost Margin'!$I22="",'Cost Margin'!$B$9,'Cost Margin'!$I22),I$6)<MAX(IF('Cost Margin'!$H22="",'Cost Margin'!$B$8,'Cost Margin'!$H22),I$5),0,IFERROR(NETWORKDAYS(MAX(IF('Cost Margin'!$H22="",'Cost Margin'!$B$8,'Cost Margin'!$H22),I$5),MIN(IF('Cost Margin'!$I22="",'Cost Margin'!$B$9,'Cost Margin'!$I22),I$6),INDEX(Settings!$J$7:$M$60,0,MATCH('Cost Margin'!$C22,Settings!$J$6:$M$6,0))),NETWORKDAYS(MAX(IF('Cost Margin'!$H22="",'Cost Margin'!$B$8,'Cost Margin'!$H22),I$5),MIN(IF('Cost Margin'!$I22="",'Cost Margin'!$B$9,'Cost Margin'!$I22),I$6))))) -> 0 | J14: =IF(OR(J$5="",'Cost Margin'!$A22="",IF('Cost Margin'!$H22="",'Cost Margin'!$B$8,'Cost Margin'!$H22)="",IF('Cost Margin'!$I22="",'Cost Margin'!$B$9,'Cost Margin'!$I22)=""),0,IF(MIN(IF('Cost Margin'!$I22="",'Cost Margin'!$B$9,'Cost Margin'!$I22),J$6)<MAX(IF('Cost Margin'!$H22="",'Cost Margin'!$B$8,'Cost Margin'!$H22),J$5),0,IFERROR(NETWORKDAYS(MAX(IF('Cost Margin'!$H22="",'Cost Margin'!$B$8,'Cost Margin'!$H22),J$5),MIN(IF('Cost Margin'!$I22="",'Cost Margin'!$B$9,'Cost Margin'!$I22),J$6),INDEX(Settings!$J$7:$M$60,0,MATCH('Cost Margin'!$C22,Settings!$J$6:$M$6,0))),NETWORKDAYS(MAX(IF('Cost Margin'!$H22="",'Cost Margin'!$B$8,'Cost Margin'!$H22),J$5),MIN(IF('Cost Margin'!$I22="",'Cost Margin'!$B$9,'Cost Margin'!$I22),J$6))))) -> 0 | ... Z14: =IF(OR(Z$5="",'Cost Margin'!$A22="",IF('Cost Margin'!$H22="",'Cost Margin'!$B$8,'Cost Margin'!$H22)="",IF('Cost Margin'!$I22="",'Cost Margin'!$B$9,'Cost Margin'!$I22)=""),0,IF(MIN(IF('Cost Margin'!$I22="",'Cost Margin'!$B$9,'Cost Margin'!$I22),Z$6)<MAX(IF('Cost Margin'!$H22="",'Cost Margin'!$B$8,'Cost Margin'!$H22),Z$5),0,IFERROR(NETWORKDAYS(MAX(IF('Cost Margin'!$H22="",'Cost Margin'!$B$8,'Cost Margin'!$H22),Z$5),MIN(IF('Cost Margin'!$I22="",'Cost Margin'!$B$9,'Cost Margin'!$I22),Z$6),INDEX(Settings!$J$7:$M$60,0,MATCH('Cost Margin'!$C22,Settings!$J$6:$M$6,0))),NETWORKDAYS(MAX(IF('Cost Margin'!$H22="",'Cost Margin'!$B$8,'Cost Margin'!$H22),Z$5),MIN(IF('Cost Margin'!$I22="",'Cost Margin'!$B$9,'Cost Margin'!$I22),Z$6))))) -> 0
A15: 7 | B15: =IF('Cost Margin'!A23="","",'Cost Margin'!A23) | C15: =IF(OR(C$5="",'Cost Margin'!$A23="",IF('Cost Margin'!$H23="",'Cost Margin'!$B$8,'Cost Margin'!$H23)="",IF('Cost Margin'!$I23="",'Cost Margin'!$B$9,'Cost Margin'!$I23)=""),0,IF(MIN(IF('Cost Margin'!$I23="",'Cost Margin'!$B$9,'Cost Margin'!$I23),C$6)<MAX(IF('Cost Margin'!$H23="",'Cost Margin'!$B$8,'Cost Margin'!$H23),C$5),0,IFERROR(NETWORKDAYS(MAX(IF('Cost Margin'!$H23="",'Cost Margin'!$B$8,'Cost Margin'!$H23),C$5),MIN(IF('Cost Margin'!$I23="",'Cost Margin'!$B$9,'Cost Margin'!$I23),C$6),INDEX(Settings!$J$7:$M$60,0,MATCH('Cost Margin'!$C23,Settings!$J$6:$M$6,0))),NETWORKDAYS(MAX(IF('Cost Margin'!$H23="",'Cost Margin'!$B$8,'Cost Margin'!$H23),C$5),MIN(IF('Cost Margin'!$I23="",'Cost Margin'!$B$9,'Cost Margin'!$I23),C$6))))) -> 0 | D15: =IF(OR(D$5="",'Cost Margin'!$A23="",IF('Cost Margin'!$H23="",'Cost Margin'!$B$8,'Cost Margin'!$H23)="",IF('Cost Margin'!$I23="",'Cost Margin'!$B$9,'Cost Margin'!$I23)=""),0,IF(MIN(IF('Cost Margin'!$I23="",'Cost Margin'!$B$9,'Cost Margin'!$I23),D$6)<MAX(IF('Cost Margin'!$H23="",'Cost Margin'!$B$8,'Cost Margin'!$H23),D$5),0,IFERROR(NETWORKDAYS(MAX(IF('Cost Margin'!$H23="",'Cost Margin'!$B$8,'Cost Margin'!$H23),D$5),MIN(IF('Cost Margin'!$I23="",'Cost Margin'!$B$9,'Cost Margin'!$I23),D$6),INDEX(Settings!$J$7:$M$60,0,MATCH('Cost Margin'!$C23,Settings!$J$6:$M$6,0))),NETWORKDAYS(MAX(IF('Cost Margin'!$H23="",'Cost Margin'!$B$8,'Cost Margin'!$H23),D$5),MIN(IF('Cost Margin'!$I23="",'Cost Margin'!$B$9,'Cost Margin'!$I23),D$6))))) -> 0 | E15: =IF(OR(E$5="",'Cost Margin'!$A23="",IF('Cost Margin'!$H23="",'Cost Margin'!$B$8,'Cost Margin'!$H23)="",IF('Cost Margin'!$I23="",'Cost Margin'!$B$9,'Cost Margin'!$I23)=""),0,IF(MIN(IF('Cost Margin'!$I23="",'Cost Margin'!$B$9,'Cost Margin'!$I23),E$6)<MAX(IF('Cost Margin'!$H23="",'Cost Margin'!$B$8,'Cost Margin'!$H23),E$5),0,IFERROR(NETWORKDAYS(MAX(IF('Cost Margin'!$H23="",'Cost Margin'!$B$8,'Cost Margin'!$H23),E$5),MIN(IF('Cost Margin'!$I23="",'Cost Margin'!$B$9,'Cost Margin'!$I23),E$6),INDEX(Settings!$J$7:$M$60,0,MATCH('Cost Margin'!$C23,Settings!$J$6:$M$6,0))),NETWORKDAYS(MAX(IF('Cost Margin'!$H23="",'Cost Margin'!$B$8,'Cost Margin'!$H23),E$5),MIN(IF('Cost Margin'!$I23="",'Cost Margin'!$B$9,'Cost Margin'!$I23),E$6))))) -> 0 | F15: =IF(OR(F$5="",'Cost Margin'!$A23="",IF('Cost Margin'!$H23="",'Cost Margin'!$B$8,'Cost Margin'!$H23)="",IF('Cost Margin'!$I23="",'Cost Margin'!$B$9,'Cost Margin'!$I23)=""),0,IF(MIN(IF('Cost Margin'!$I23="",'Cost Margin'!$B$9,'Cost Margin'!$I23),F$6)<MAX(IF('Cost Margin'!$H23="",'Cost Margin'!$B$8,'Cost Margin'!$H23),F$5),0,IFERROR(NETWORKDAYS(MAX(IF('Cost Margin'!$H23="",'Cost Margin'!$B$8,'Cost Margin'!$H23),F$5),MIN(IF('Cost Margin'!$I23="",'Cost Margin'!$B$9,'Cost Margin'!$I23),F$6),INDEX(Settings!$J$7:$M$60,0,MATCH('Cost Margin'!$C23,Settings!$J$6:$M$6,0))),NETWORKDAYS(MAX(IF('Cost Margin'!$H23="",'Cost Margin'!$B$8,'Cost Margin'!$H23),F$5),MIN(IF('Cost Margin'!$I23="",'Cost Margin'!$B$9,'Cost Margin'!$I23),F$6))))) -> 0 | G15: =IF(OR(G$5="",'Cost Margin'!$A23="",IF('Cost Margin'!$H23="",'Cost Margin'!$B$8,'Cost Margin'!$H23)="",IF('Cost Margin'!$I23="",'Cost Margin'!$B$9,'Cost Margin'!$I23)=""),0,IF(MIN(IF('Cost Margin'!$I23="",'Cost Margin'!$B$9,'Cost Margin'!$I23),G$6)<MAX(IF('Cost Margin'!$H23="",'Cost Margin'!$B$8,'Cost Margin'!$H23),G$5),0,IFERROR(NETWORKDAYS(MAX(IF('Cost Margin'!$H23="",'Cost Margin'!$B$8,'Cost Margin'!$H23),G$5),MIN(IF('Cost Margin'!$I23="",'Cost Margin'!$B$9,'Cost Margin'!$I23),G$6),INDEX(Settings!$J$7:$M$60,0,MATCH('Cost Margin'!$C23,Settings!$J$6:$M$6,0))),NETWORKDAYS(MAX(IF('Cost Margin'!$H23="",'Cost Margin'!$B$8,'Cost Margin'!$H23),G$5),MIN(IF('Cost Margin'!$I23="",'Cost Margin'!$B$9,'Cost Margin'!$I23),G$6))))) -> 0 | H15: =IF(OR(H$5="",'Cost Margin'!$A23="",IF('Cost Margin'!$H23="",'Cost Margin'!$B$8,'Cost Margin'!$H23)="",IF('Cost Margin'!$I23="",'Cost Margin'!$B$9,'Cost Margin'!$I23)=""),0,IF(MIN(IF('Cost Margin'!$I23="",'Cost Margin'!$B$9,'Cost Margin'!$I23),H$6)<MAX(IF('Cost Margin'!$H23="",'Cost Margin'!$B$8,'Cost Margin'!$H23),H$5),0,IFERROR(NETWORKDAYS(MAX(IF('Cost Margin'!$H23="",'Cost Margin'!$B$8,'Cost Margin'!$H23),H$5),MIN(IF('Cost Margin'!$I23="",'Cost Margin'!$B$9,'Cost Margin'!$I23),H$6),INDEX(Settings!$J$7:$M$60,0,MATCH('Cost Margin'!$C23,Settings!$J$6:$M$6,0))),NETWORKDAYS(MAX(IF('Cost Margin'!$H23="",'Cost Margin'!$B$8,'Cost Margin'!$H23),H$5),MIN(IF('Cost Margin'!$I23="",'Cost Margin'!$B$9,'Cost Margin'!$I23),H$6))))) -> 0 | I15: =IF(OR(I$5="",'Cost Margin'!$A23="",IF('Cost Margin'!$H23="",'Cost Margin'!$B$8,'Cost Margin'!$H23)="",IF('Cost Margin'!$I23="",'Cost Margin'!$B$9,'Cost Margin'!$I23)=""),0,IF(MIN(IF('Cost Margin'!$I23="",'Cost Margin'!$B$9,'Cost Margin'!$I23),I$6)<MAX(IF('Cost Margin'!$H23="",'Cost Margin'!$B$8,'Cost Margin'!$H23),I$5),0,IFERROR(NETWORKDAYS(MAX(IF('Cost Margin'!$H23="",'Cost Margin'!$B$8,'Cost Margin'!$H23),I$5),MIN(IF('Cost Margin'!$I23="",'Cost Margin'!$B$9,'Cost Margin'!$I23),I$6),INDEX(Settings!$J$7:$M$60,0,MATCH('Cost Margin'!$C23,Settings!$J$6:$M$6,0))),NETWORKDAYS(MAX(IF('Cost Margin'!$H23="",'Cost Margin'!$B$8,'Cost Margin'!$H23),I$5),MIN(IF('Cost Margin'!$I23="",'Cost Margin'!$B$9,'Cost Margin'!$I23),I$6))))) -> 0 | J15: =IF(OR(J$5="",'Cost Margin'!$A23="",IF('Cost Margin'!$H23="",'Cost Margin'!$B$8,'Cost Margin'!$H23)="",IF('Cost Margin'!$I23="",'Cost Margin'!$B$9,'Cost Margin'!$I23)=""),0,IF(MIN(IF('Cost Margin'!$I23="",'Cost Margin'!$B$9,'Cost Margin'!$I23),J$6)<MAX(IF('Cost Margin'!$H23="",'Cost Margin'!$B$8,'Cost Margin'!$H23),J$5),0,IFERROR(NETWORKDAYS(MAX(IF('Cost Margin'!$H23="",'Cost Margin'!$B$8,'Cost Margin'!$H23),J$5),MIN(IF('Cost Margin'!$I23="",'Cost Margin'!$B$9,'Cost Margin'!$I23),J$6),INDEX(Settings!$J$7:$M$60,0,MATCH('Cost Margin'!$C23,Settings!$J$6:$M$6,0))),NETWORKDAYS(MAX(IF('Cost Margin'!$H23="",'Cost Margin'!$B$8,'Cost Margin'!$H23),J$5),MIN(IF('Cost Margin'!$I23="",'Cost Margin'!$B$9,'Cost Margin'!$I23),J$6))))) -> 0 | ... Z15: =IF(OR(Z$5="",'Cost Margin'!$A23="",IF('Cost Margin'!$H23="",'Cost Margin'!$B$8,'Cost Margin'!$H23)="",IF('Cost Margin'!$I23="",'Cost Margin'!$B$9,'Cost Margin'!$I23)=""),0,IF(MIN(IF('Cost Margin'!$I23="",'Cost Margin'!$B$9,'Cost Margin'!$I23),Z$6)<MAX(IF('Cost Margin'!$H23="",'Cost Margin'!$B$8,'Cost Margin'!$H23),Z$5),0,IFERROR(NETWORKDAYS(MAX(IF('Cost Margin'!$H23="",'Cost Margin'!$B$8,'Cost Margin'!$H23),Z$5),MIN(IF('Cost Margin'!$I23="",'Cost Margin'!$B$9,'Cost Margin'!$I23),Z$6),INDEX(Settings!$J$7:$M$60,0,MATCH('Cost Margin'!$C23,Settings!$J$6:$M$6,0))),NETWORKDAYS(MAX(IF('Cost Margin'!$H23="",'Cost Margin'!$B$8,'Cost Margin'!$H23),Z$5),MIN(IF('Cost Margin'!$I23="",'Cost Margin'!$B$9,'Cost Margin'!$I23),Z$6))))) -> 0
A16: 8 | B16: =IF('Cost Margin'!A24="","",'Cost Margin'!A24) | C16: =IF(OR(C$5="",'Cost Margin'!$A24="",IF('Cost Margin'!$H24="",'Cost Margin'!$B$8,'Cost Margin'!$H24)="",IF('Cost Margin'!$I24="",'Cost Margin'!$B$9,'Cost Margin'!$I24)=""),0,IF(MIN(IF('Cost Margin'!$I24="",'Cost Margin'!$B$9,'Cost Margin'!$I24),C$6)<MAX(IF('Cost Margin'!$H24="",'Cost Margin'!$B$8,'Cost Margin'!$H24),C$5),0,IFERROR(NETWORKDAYS(MAX(IF('Cost Margin'!$H24="",'Cost Margin'!$B$8,'Cost Margin'!$H24),C$5),MIN(IF('Cost Margin'!$I24="",'Cost Margin'!$B$9,'Cost Margin'!$I24),C$6),INDEX(Settings!$J$7:$M$60,0,MATCH('Cost Margin'!$C24,Settings!$J$6:$M$6,0))),NETWORKDAYS(MAX(IF('Cost Margin'!$H24="",'Cost Margin'!$B$8,'Cost Margin'!$H24),C$5),MIN(IF('Cost Margin'!$I24="",'Cost Margin'!$B$9,'Cost Margin'!$I24),C$6))))) -> 0 | D16: =IF(OR(D$5="",'Cost Margin'!$A24="",IF('Cost Margin'!$H24="",'Cost Margin'!$B$8,'Cost Margin'!$H24)="",IF('Cost Margin'!$I24="",'Cost Margin'!$B$9,'Cost Margin'!$I24)=""),0,IF(MIN(IF('Cost Margin'!$I24="",'Cost Margin'!$B$9,'Cost Margin'!$I24),D$6)<MAX(IF('Cost Margin'!$H24="",'Cost Margin'!$B$8,'Cost Margin'!$H24),D$5),0,IFERROR(NETWORKDAYS(MAX(IF('Cost Margin'!$H24="",'Cost Margin'!$B$8,'Cost Margin'!$H24),D$5),MIN(IF('Cost Margin'!$I24="",'Cost Margin'!$B$9,'Cost Margin'!$I24),D$6),INDEX(Settings!$J$7:$M$60,0,MATCH('Cost Margin'!$C24,Settings!$J$6:$M$6,0))),NETWORKDAYS(MAX(IF('Cost Margin'!$H24="",'Cost Margin'!$B$8,'Cost Margin'!$H24),D$5),MIN(IF('Cost Margin'!$I24="",'Cost Margin'!$B$9,'Cost Margin'!$I24),D$6))))) -> 0 | E16: =IF(OR(E$5="",'Cost Margin'!$A24="",IF('Cost Margin'!$H24="",'Cost Margin'!$B$8,'Cost Margin'!$H24)="",IF('Cost Margin'!$I24="",'Cost Margin'!$B$9,'Cost Margin'!$I24)=""),0,IF(MIN(IF('Cost Margin'!$I24="",'Cost Margin'!$B$9,'Cost Margin'!$I24),E$6)<MAX(IF('Cost Margin'!$H24="",'Cost Margin'!$B$8,'Cost Margin'!$H24),E$5),0,IFERROR(NETWORKDAYS(MAX(IF('Cost Margin'!$H24="",'Cost Margin'!$B$8,'Cost Margin'!$H24),E$5),MIN(IF('Cost Margin'!$I24="",'Cost Margin'!$B$9,'Cost Margin'!$I24),E$6),INDEX(Settings!$J$7:$M$60,0,MATCH('Cost Margin'!$C24,Settings!$J$6:$M$6,0))),NETWORKDAYS(MAX(IF('Cost Margin'!$H24="",'Cost Margin'!$B$8,'Cost Margin'!$H24),E$5),MIN(IF('Cost Margin'!$I24="",'Cost Margin'!$B$9,'Cost Margin'!$I24),E$6))))) -> 0 | F16: =IF(OR(F$5="",'Cost Margin'!$A24="",IF('Cost Margin'!$H24="",'Cost Margin'!$B$8,'Cost Margin'!$H24)="",IF('Cost Margin'!$I24="",'Cost Margin'!$B$9,'Cost Margin'!$I24)=""),0,IF(MIN(IF('Cost Margin'!$I24="",'Cost Margin'!$B$9,'Cost Margin'!$I24),F$6)<MAX(IF('Cost Margin'!$H24="",'Cost Margin'!$B$8,'Cost Margin'!$H24),F$5),0,IFERROR(NETWORKDAYS(MAX(IF('Cost Margin'!$H24="",'Cost Margin'!$B$8,'Cost Margin'!$H24),F$5),MIN(IF('Cost Margin'!$I24="",'Cost Margin'!$B$9,'Cost Margin'!$I24),F$6),INDEX(Settings!$J$7:$M$60,0,MATCH('Cost Margin'!$C24,Settings!$J$6:$M$6,0))),NETWORKDAYS(MAX(IF('Cost Margin'!$H24="",'Cost Margin'!$B$8,'Cost Margin'!$H24),F$5),MIN(IF('Cost Margin'!$I24="",'Cost Margin'!$B$9,'Cost Margin'!$I24),F$6))))) -> 0 | G16: =IF(OR(G$5="",'Cost Margin'!$A24="",IF('Cost Margin'!$H24="",'Cost Margin'!$B$8,'Cost Margin'!$H24)="",IF('Cost Margin'!$I24="",'Cost Margin'!$B$9,'Cost Margin'!$I24)=""),0,IF(MIN(IF('Cost Margin'!$I24="",'Cost Margin'!$B$9,'Cost Margin'!$I24),G$6)<MAX(IF('Cost Margin'!$H24="",'Cost Margin'!$B$8,'Cost Margin'!$H24),G$5),0,IFERROR(NETWORKDAYS(MAX(IF('Cost Margin'!$H24="",'Cost Margin'!$B$8,'Cost Margin'!$H24),G$5),MIN(IF('Cost Margin'!$I24="",'Cost Margin'!$B$9,'Cost Margin'!$I24),G$6),INDEX(Settings!$J$7:$M$60,0,MATCH('Cost Margin'!$C24,Settings!$J$6:$M$6,0))),NETWORKDAYS(MAX(IF('Cost Margin'!$H24="",'Cost Margin'!$B$8,'Cost Margin'!$H24),G$5),MIN(IF('Cost Margin'!$I24="",'Cost Margin'!$B$9,'Cost Margin'!$I24),G$6))))) -> 0 | H16: =IF(OR(H$5="",'Cost Margin'!$A24="",IF('Cost Margin'!$H24="",'Cost Margin'!$B$8,'Cost Margin'!$H24)="",IF('Cost Margin'!$I24="",'Cost Margin'!$B$9,'Cost Margin'!$I24)=""),0,IF(MIN(IF('Cost Margin'!$I24="",'Cost Margin'!$B$9,'Cost Margin'!$I24),H$6)<MAX(IF('Cost Margin'!$H24="",'Cost Margin'!$B$8,'Cost Margin'!$H24),H$5),0,IFERROR(NETWORKDAYS(MAX(IF('Cost Margin'!$H24="",'Cost Margin'!$B$8,'Cost Margin'!$H24),H$5),MIN(IF('Cost Margin'!$I24="",'Cost Margin'!$B$9,'Cost Margin'!$I24),H$6),INDEX(Settings!$J$7:$M$60,0,MATCH('Cost Margin'!$C24,Settings!$J$6:$M$6,0))),NETWORKDAYS(MAX(IF('Cost Margin'!$H24="",'Cost Margin'!$B$8,'Cost Margin'!$H24),H$5),MIN(IF('Cost Margin'!$I24="",'Cost Margin'!$B$9,'Cost Margin'!$I24),H$6))))) -> 0 | I16: =IF(OR(I$5="",'Cost Margin'!$A24="",IF('Cost Margin'!$H24="",'Cost Margin'!$B$8,'Cost Margin'!$H24)="",IF('Cost Margin'!$I24="",'Cost Margin'!$B$9,'Cost Margin'!$I24)=""),0,IF(MIN(IF('Cost Margin'!$I24="",'Cost Margin'!$B$9,'Cost Margin'!$I24),I$6)<MAX(IF('Cost Margin'!$H24="",'Cost Margin'!$B$8,'Cost Margin'!$H24),I$5),0,IFERROR(NETWORKDAYS(MAX(IF('Cost Margin'!$H24="",'Cost Margin'!$B$8,'Cost Margin'!$H24),I$5),MIN(IF('Cost Margin'!$I24="",'Cost Margin'!$B$9,'Cost Margin'!$I24),I$6),INDEX(Settings!$J$7:$M$60,0,MATCH('Cost Margin'!$C24,Settings!$J$6:$M$6,0))),NETWORKDAYS(MAX(IF('Cost Margin'!$H24="",'Cost Margin'!$B$8,'Cost Margin'!$H24),I$5),MIN(IF('Cost Margin'!$I24="",'Cost Margin'!$B$9,'Cost Margin'!$I24),I$6))))) -> 0 | J16: =IF(OR(J$5="",'Cost Margin'!$A24="",IF('Cost Margin'!$H24="",'Cost Margin'!$B$8,'Cost Margin'!$H24)="",IF('Cost Margin'!$I24="",'Cost Margin'!$B$9,'Cost Margin'!$I24)=""),0,IF(MIN(IF('Cost Margin'!$I24="",'Cost Margin'!$B$9,'Cost Margin'!$I24),J$6)<MAX(IF('Cost Margin'!$H24="",'Cost Margin'!$B$8,'Cost Margin'!$H24),J$5),0,IFERROR(NETWORKDAYS(MAX(IF('Cost Margin'!$H24="",'Cost Margin'!$B$8,'Cost Margin'!$H24),J$5),MIN(IF('Cost Margin'!$I24="",'Cost Margin'!$B$9,'Cost Margin'!$I24),J$6),INDEX(Settings!$J$7:$M$60,0,MATCH('Cost Margin'!$C24,Settings!$J$6:$M$6,0))),NETWORKDAYS(MAX(IF('Cost Margin'!$H24="",'Cost Margin'!$B$8,'Cost Margin'!$H24),J$5),MIN(IF('Cost Margin'!$I24="",'Cost Margin'!$B$9,'Cost Margin'!$I24),J$6))))) -> 0 | ... Z16: =IF(OR(Z$5="",'Cost Margin'!$A24="",IF('Cost Margin'!$H24="",'Cost Margin'!$B$8,'Cost Margin'!$H24)="",IF('Cost Margin'!$I24="",'Cost Margin'!$B$9,'Cost Margin'!$I24)=""),0,IF(MIN(IF('Cost Margin'!$I24="",'Cost Margin'!$B$9,'Cost Margin'!$I24),Z$6)<MAX(IF('Cost Margin'!$H24="",'Cost Margin'!$B$8,'Cost Margin'!$H24),Z$5),0,IFERROR(NETWORKDAYS(MAX(IF('Cost Margin'!$H24="",'Cost Margin'!$B$8,'Cost Margin'!$H24),Z$5),MIN(IF('Cost Margin'!$I24="",'Cost Margin'!$B$9,'Cost Margin'!$I24),Z$6),INDEX(Settings!$J$7:$M$60,0,MATCH('Cost Margin'!$C24,Settings!$J$6:$M$6,0))),NETWORKDAYS(MAX(IF('Cost Margin'!$H24="",'Cost Margin'!$B$8,'Cost Margin'!$H24),Z$5),MIN(IF('Cost Margin'!$I24="",'Cost Margin'!$B$9,'Cost Margin'!$I24),Z$6))))) -> 0
A17: 9 | B17: =IF('Cost Margin'!A25="","",'Cost Margin'!A25) | C17: =IF(OR(C$5="",'Cost Margin'!$A25="",IF('Cost Margin'!$H25="",'Cost Margin'!$B$8,'Cost Margin'!$H25)="",IF('Cost Margin'!$I25="",'Cost Margin'!$B$9,'Cost Margin'!$I25)=""),0,IF(MIN(IF('Cost Margin'!$I25="",'Cost Margin'!$B$9,'Cost Margin'!$I25),C$6)<MAX(IF('Cost Margin'!$H25="",'Cost Margin'!$B$8,'Cost Margin'!$H25),C$5),0,IFERROR(NETWORKDAYS(MAX(IF('Cost Margin'!$H25="",'Cost Margin'!$B$8,'Cost Margin'!$H25),C$5),MIN(IF('Cost Margin'!$I25="",'Cost Margin'!$B$9,'Cost Margin'!$I25),C$6),INDEX(Settings!$J$7:$M$60,0,MATCH('Cost Margin'!$C25,Settings!$J$6:$M$6,0))),NETWORKDAYS(MAX(IF('Cost Margin'!$H25="",'Cost Margin'!$B$8,'Cost Margin'!$H25),C$5),MIN(IF('Cost Margin'!$I25="",'Cost Margin'!$B$9,'Cost Margin'!$I25),C$6))))) -> 0 | D17: =IF(OR(D$5="",'Cost Margin'!$A25="",IF('Cost Margin'!$H25="",'Cost Margin'!$B$8,'Cost Margin'!$H25)="",IF('Cost Margin'!$I25="",'Cost Margin'!$B$9,'Cost Margin'!$I25)=""),0,IF(MIN(IF('Cost Margin'!$I25="",'Cost Margin'!$B$9,'Cost Margin'!$I25),D$6)<MAX(IF('Cost Margin'!$H25="",'Cost Margin'!$B$8,'Cost Margin'!$H25),D$5),0,IFERROR(NETWORKDAYS(MAX(IF('Cost Margin'!$H25="",'Cost Margin'!$B$8,'Cost Margin'!$H25),D$5),MIN(IF('Cost Margin'!$I25="",'Cost Margin'!$B$9,'Cost Margin'!$I25),D$6),INDEX(Settings!$J$7:$M$60,0,MATCH('Cost Margin'!$C25,Settings!$J$6:$M$6,0))),NETWORKDAYS(MAX(IF('Cost Margin'!$H25="",'Cost Margin'!$B$8,'Cost Margin'!$H25),D$5),MIN(IF('Cost Margin'!$I25="",'Cost Margin'!$B$9,'Cost Margin'!$I25),D$6))))) -> 0 | E17: =IF(OR(E$5="",'Cost Margin'!$A25="",IF('Cost Margin'!$H25="",'Cost Margin'!$B$8,'Cost Margin'!$H25)="",IF('Cost Margin'!$I25="",'Cost Margin'!$B$9,'Cost Margin'!$I25)=""),0,IF(MIN(IF('Cost Margin'!$I25="",'Cost Margin'!$B$9,'Cost Margin'!$I25),E$6)<MAX(IF('Cost Margin'!$H25="",'Cost Margin'!$B$8,'Cost Margin'!$H25),E$5),0,IFERROR(NETWORKDAYS(MAX(IF('Cost Margin'!$H25="",'Cost Margin'!$B$8,'Cost Margin'!$H25),E$5),MIN(IF('Cost Margin'!$I25="",'Cost Margin'!$B$9,'Cost Margin'!$I25),E$6),INDEX(Settings!$J$7:$M$60,0,MATCH('Cost Margin'!$C25,Settings!$J$6:$M$6,0))),NETWORKDAYS(MAX(IF('Cost Margin'!$H25="",'Cost Margin'!$B$8,'Cost Margin'!$H25),E$5),MIN(IF('Cost Margin'!$I25="",'Cost Margin'!$B$9,'Cost Margin'!$I25),E$6))))) -> 0 | F17: =IF(OR(F$5="",'Cost Margin'!$A25="",IF('Cost Margin'!$H25="",'Cost Margin'!$B$8,'Cost Margin'!$H25)="",IF('Cost Margin'!$I25="",'Cost Margin'!$B$9,'Cost Margin'!$I25)=""),0,IF(MIN(IF('Cost Margin'!$I25="",'Cost Margin'!$B$9,'Cost Margin'!$I25),F$6)<MAX(IF('Cost Margin'!$H25="",'Cost Margin'!$B$8,'Cost Margin'!$H25),F$5),0,IFERROR(NETWORKDAYS(MAX(IF('Cost Margin'!$H25="",'Cost Margin'!$B$8,'Cost Margin'!$H25),F$5),MIN(IF('Cost Margin'!$I25="",'Cost Margin'!$B$9,'Cost Margin'!$I25),F$6),INDEX(Settings!$J$7:$M$60,0,MATCH('Cost Margin'!$C25,Settings!$J$6:$M$6,0))),NETWORKDAYS(MAX(IF('Cost Margin'!$H25="",'Cost Margin'!$B$8,'Cost Margin'!$H25),F$5),MIN(IF('Cost Margin'!$I25="",'Cost Margin'!$B$9,'Cost Margin'!$I25),F$6))))) -> 0 | G17: =IF(OR(G$5="",'Cost Margin'!$A25="",IF('Cost Margin'!$H25="",'Cost Margin'!$B$8,'Cost Margin'!$H25)="",IF('Cost Margin'!$I25="",'Cost Margin'!$B$9,'Cost Margin'!$I25)=""),0,IF(MIN(IF('Cost Margin'!$I25="",'Cost Margin'!$B$9,'Cost Margin'!$I25),G$6)<MAX(IF('Cost Margin'!$H25="",'Cost Margin'!$B$8,'Cost Margin'!$H25),G$5),0,IFERROR(NETWORKDAYS(MAX(IF('Cost Margin'!$H25="",'Cost Margin'!$B$8,'Cost Margin'!$H25),G$5),MIN(IF('Cost Margin'!$I25="",'Cost Margin'!$B$9,'Cost Margin'!$I25),G$6),INDEX(Settings!$J$7:$M$60,0,MATCH('Cost Margin'!$C25,Settings!$J$6:$M$6,0))),NETWORKDAYS(MAX(IF('Cost Margin'!$H25="",'Cost Margin'!$B$8,'Cost Margin'!$H25),G$5),MIN(IF('Cost Margin'!$I25="",'Cost Margin'!$B$9,'Cost Margin'!$I25),G$6))))) -> 0 | H17: =IF(OR(H$5="",'Cost Margin'!$A25="",IF('Cost Margin'!$H25="",'Cost Margin'!$B$8,'Cost Margin'!$H25)="",IF('Cost Margin'!$I25="",'Cost Margin'!$B$9,'Cost Margin'!$I25)=""),0,IF(MIN(IF('Cost Margin'!$I25="",'Cost Margin'!$B$9,'Cost Margin'!$I25),H$6)<MAX(IF('Cost Margin'!$H25="",'Cost Margin'!$B$8,'Cost Margin'!$H25),H$5),0,IFERROR(NETWORKDAYS(MAX(IF('Cost Margin'!$H25="",'Cost Margin'!$B$8,'Cost Margin'!$H25),H$5),MIN(IF('Cost Margin'!$I25="",'Cost Margin'!$B$9,'Cost Margin'!$I25),H$6),INDEX(Settings!$J$7:$M$60,0,MATCH('Cost Margin'!$C25,Settings!$J$6:$M$6,0))),NETWORKDAYS(MAX(IF('Cost Margin'!$H25="",'Cost Margin'!$B$8,'Cost Margin'!$H25),H$5),MIN(IF('Cost Margin'!$I25="",'Cost Margin'!$B$9,'Cost Margin'!$I25),H$6))))) -> 0 | I17: =IF(OR(I$5="",'Cost Margin'!$A25="",IF('Cost Margin'!$H25="",'Cost Margin'!$B$8,'Cost Margin'!$H25)="",IF('Cost Margin'!$I25="",'Cost Margin'!$B$9,'Cost Margin'!$I25)=""),0,IF(MIN(IF('Cost Margin'!$I25="",'Cost Margin'!$B$9,'Cost Margin'!$I25),I$6)<MAX(IF('Cost Margin'!$H25="",'Cost Margin'!$B$8,'Cost Margin'!$H25),I$5),0,IFERROR(NETWORKDAYS(MAX(IF('Cost Margin'!$H25="",'Cost Margin'!$B$8,'Cost Margin'!$H25),I$5),MIN(IF('Cost Margin'!$I25="",'Cost Margin'!$B$9,'Cost Margin'!$I25),I$6),INDEX(Settings!$J$7:$M$60,0,MATCH('Cost Margin'!$C25,Settings!$J$6:$M$6,0))),NETWORKDAYS(MAX(IF('Cost Margin'!$H25="",'Cost Margin'!$B$8,'Cost Margin'!$H25),I$5),MIN(IF('Cost Margin'!$I25="",'Cost Margin'!$B$9,'Cost Margin'!$I25),I$6))))) -> 0 | J17: =IF(OR(J$5="",'Cost Margin'!$A25="",IF('Cost Margin'!$H25="",'Cost Margin'!$B$8,'Cost Margin'!$H25)="",IF('Cost Margin'!$I25="",'Cost Margin'!$B$9,'Cost Margin'!$I25)=""),0,IF(MIN(IF('Cost Margin'!$I25="",'Cost Margin'!$B$9,'Cost Margin'!$I25),J$6)<MAX(IF('Cost Margin'!$H25="",'Cost Margin'!$B$8,'Cost Margin'!$H25),J$5),0,IFERROR(NETWORKDAYS(MAX(IF('Cost Margin'!$H25="",'Cost Margin'!$B$8,'Cost Margin'!$H25),J$5),MIN(IF('Cost Margin'!$I25="",'Cost Margin'!$B$9,'Cost Margin'!$I25),J$6),INDEX(Settings!$J$7:$M$60,0,MATCH('Cost Margin'!$C25,Settings!$J$6:$M$6,0))),NETWORKDAYS(MAX(IF('Cost Margin'!$H25="",'Cost Margin'!$B$8,'Cost Margin'!$H25),J$5),MIN(IF('Cost Margin'!$I25="",'Cost Margin'!$B$9,'Cost Margin'!$I25),J$6))))) -> 0 | ... Z17: =IF(OR(Z$5="",'Cost Margin'!$A25="",IF('Cost Margin'!$H25="",'Cost Margin'!$B$8,'Cost Margin'!$H25)="",IF('Cost Margin'!$I25="",'Cost Margin'!$B$9,'Cost Margin'!$I25)=""),0,IF(MIN(IF('Cost Margin'!$I25="",'Cost Margin'!$B$9,'Cost Margin'!$I25),Z$6)<MAX(IF('Cost Margin'!$H25="",'Cost Margin'!$B$8,'Cost Margin'!$H25),Z$5),0,IFERROR(NETWORKDAYS(MAX(IF('Cost Margin'!$H25="",'Cost Margin'!$B$8,'Cost Margin'!$H25),Z$5),MIN(IF('Cost Margin'!$I25="",'Cost Margin'!$B$9,'Cost Margin'!$I25),Z$6),INDEX(Settings!$J$7:$M$60,0,MATCH('Cost Margin'!$C25,Settings!$J$6:$M$6,0))),NETWORKDAYS(MAX(IF('Cost Margin'!$H25="",'Cost Margin'!$B$8,'Cost Margin'!$H25),Z$5),MIN(IF('Cost Margin'!$I25="",'Cost Margin'!$B$9,'Cost Margin'!$I25),Z$6))))) -> 0
A18: 10 | B18: =IF('Cost Margin'!A26="","",'Cost Margin'!A26) | C18: =IF(OR(C$5="",'Cost Margin'!$A26="",IF('Cost Margin'!$H26="",'Cost Margin'!$B$8,'Cost Margin'!$H26)="",IF('Cost Margin'!$I26="",'Cost Margin'!$B$9,'Cost Margin'!$I26)=""),0,IF(MIN(IF('Cost Margin'!$I26="",'Cost Margin'!$B$9,'Cost Margin'!$I26),C$6)<MAX(IF('Cost Margin'!$H26="",'Cost Margin'!$B$8,'Cost Margin'!$H26),C$5),0,IFERROR(NETWORKDAYS(MAX(IF('Cost Margin'!$H26="",'Cost Margin'!$B$8,'Cost Margin'!$H26),C$5),MIN(IF('Cost Margin'!$I26="",'Cost Margin'!$B$9,'Cost Margin'!$I26),C$6),INDEX(Settings!$J$7:$M$60,0,MATCH('Cost Margin'!$C26,Settings!$J$6:$M$6,0))),NETWORKDAYS(MAX(IF('Cost Margin'!$H26="",'Cost Margin'!$B$8,'Cost Margin'!$H26),C$5),MIN(IF('Cost Margin'!$I26="",'Cost Margin'!$B$9,'Cost Margin'!$I26),C$6))))) -> 0 | D18: =IF(OR(D$5="",'Cost Margin'!$A26="",IF('Cost Margin'!$H26="",'Cost Margin'!$B$8,'Cost Margin'!$H26)="",IF('Cost Margin'!$I26="",'Cost Margin'!$B$9,'Cost Margin'!$I26)=""),0,IF(MIN(IF('Cost Margin'!$I26="",'Cost Margin'!$B$9,'Cost Margin'!$I26),D$6)<MAX(IF('Cost Margin'!$H26="",'Cost Margin'!$B$8,'Cost Margin'!$H26),D$5),0,IFERROR(NETWORKDAYS(MAX(IF('Cost Margin'!$H26="",'Cost Margin'!$B$8,'Cost Margin'!$H26),D$5),MIN(IF('Cost Margin'!$I26="",'Cost Margin'!$B$9,'Cost Margin'!$I26),D$6),INDEX(Settings!$J$7:$M$60,0,MATCH('Cost Margin'!$C26,Settings!$J$6:$M$6,0))),NETWORKDAYS(MAX(IF('Cost Margin'!$H26="",'Cost Margin'!$B$8,'Cost Margin'!$H26),D$5),MIN(IF('Cost Margin'!$I26="",'Cost Margin'!$B$9,'Cost Margin'!$I26),D$6))))) -> 0 | E18: =IF(OR(E$5="",'Cost Margin'!$A26="",IF('Cost Margin'!$H26="",'Cost Margin'!$B$8,'Cost Margin'!$H26)="",IF('Cost Margin'!$I26="",'Cost Margin'!$B$9,'Cost Margin'!$I26)=""),0,IF(MIN(IF('Cost Margin'!$I26="",'Cost Margin'!$B$9,'Cost Margin'!$I26),E$6)<MAX(IF('Cost Margin'!$H26="",'Cost Margin'!$B$8,'Cost Margin'!$H26),E$5),0,IFERROR(NETWORKDAYS(MAX(IF('Cost Margin'!$H26="",'Cost Margin'!$B$8,'Cost Margin'!$H26),E$5),MIN(IF('Cost Margin'!$I26="",'Cost Margin'!$B$9,'Cost Margin'!$I26),E$6),INDEX(Settings!$J$7:$M$60,0,MATCH('Cost Margin'!$C26,Settings!$J$6:$M$6,0))),NETWORKDAYS(MAX(IF('Cost Margin'!$H26="",'Cost Margin'!$B$8,'Cost Margin'!$H26),E$5),MIN(IF('Cost Margin'!$I26="",'Cost Margin'!$B$9,'Cost Margin'!$I26),E$6))))) -> 0 | F18: =IF(OR(F$5="",'Cost Margin'!$A26="",IF('Cost Margin'!$H26="",'Cost Margin'!$B$8,'Cost Margin'!$H26)="",IF('Cost Margin'!$I26="",'Cost Margin'!$B$9,'Cost Margin'!$I26)=""),0,IF(MIN(IF('Cost Margin'!$I26="",'Cost Margin'!$B$9,'Cost Margin'!$I26),F$6)<MAX(IF('Cost Margin'!$H26="",'Cost Margin'!$B$8,'Cost Margin'!$H26),F$5),0,IFERROR(NETWORKDAYS(MAX(IF('Cost Margin'!$H26="",'Cost Margin'!$B$8,'Cost Margin'!$H26),F$5),MIN(IF('Cost Margin'!$I26="",'Cost Margin'!$B$9,'Cost Margin'!$I26),F$6),INDEX(Settings!$J$7:$M$60,0,MATCH('Cost Margin'!$C26,Settings!$J$6:$M$6,0))),NETWORKDAYS(MAX(IF('Cost Margin'!$H26="",'Cost Margin'!$B$8,'Cost Margin'!$H26),F$5),MIN(IF('Cost Margin'!$I26="",'Cost Margin'!$B$9,'Cost Margin'!$I26),F$6))))) -> 0 | G18: =IF(OR(G$5="",'Cost Margin'!$A26="",IF('Cost Margin'!$H26="",'Cost Margin'!$B$8,'Cost Margin'!$H26)="",IF('Cost Margin'!$I26="",'Cost Margin'!$B$9,'Cost Margin'!$I26)=""),0,IF(MIN(IF('Cost Margin'!$I26="",'Cost Margin'!$B$9,'Cost Margin'!$I26),G$6)<MAX(IF('Cost Margin'!$H26="",'Cost Margin'!$B$8,'Cost Margin'!$H26),G$5),0,IFERROR(NETWORKDAYS(MAX(IF('Cost Margin'!$H26="",'Cost Margin'!$B$8,'Cost Margin'!$H26),G$5),MIN(IF('Cost Margin'!$I26="",'Cost Margin'!$B$9,'Cost Margin'!$I26),G$6),INDEX(Settings!$J$7:$M$60,0,MATCH('Cost Margin'!$C26,Settings!$J$6:$M$6,0))),NETWORKDAYS(MAX(IF('Cost Margin'!$H26="",'Cost Margin'!$B$8,'Cost Margin'!$H26),G$5),MIN(IF('Cost Margin'!$I26="",'Cost Margin'!$B$9,'Cost Margin'!$I26),G$6))))) -> 0 | H18: =IF(OR(H$5="",'Cost Margin'!$A26="",IF('Cost Margin'!$H26="",'Cost Margin'!$B$8,'Cost Margin'!$H26)="",IF('Cost Margin'!$I26="",'Cost Margin'!$B$9,'Cost Margin'!$I26)=""),0,IF(MIN(IF('Cost Margin'!$I26="",'Cost Margin'!$B$9,'Cost Margin'!$I26),H$6)<MAX(IF('Cost Margin'!$H26="",'Cost Margin'!$B$8,'Cost Margin'!$H26),H$5),0,IFERROR(NETWORKDAYS(MAX(IF('Cost Margin'!$H26="",'Cost Margin'!$B$8,'Cost Margin'!$H26),H$5),MIN(IF('Cost Margin'!$I26="",'Cost Margin'!$B$9,'Cost Margin'!$I26),H$6),INDEX(Settings!$J$7:$M$60,0,MATCH('Cost Margin'!$C26,Settings!$J$6:$M$6,0))),NETWORKDAYS(MAX(IF('Cost Margin'!$H26="",'Cost Margin'!$B$8,'Cost Margin'!$H26),H$5),MIN(IF('Cost Margin'!$I26="",'Cost Margin'!$B$9,'Cost Margin'!$I26),H$6))))) -> 0 | I18: =IF(OR(I$5="",'Cost Margin'!$A26="",IF('Cost Margin'!$H26="",'Cost Margin'!$B$8,'Cost Margin'!$H26)="",IF('Cost Margin'!$I26="",'Cost Margin'!$B$9,'Cost Margin'!$I26)=""),0,IF(MIN(IF('Cost Margin'!$I26="",'Cost Margin'!$B$9,'Cost Margin'!$I26),I$6)<MAX(IF('Cost Margin'!$H26="",'Cost Margin'!$B$8,'Cost Margin'!$H26),I$5),0,IFERROR(NETWORKDAYS(MAX(IF('Cost Margin'!$H26="",'Cost Margin'!$B$8,'Cost Margin'!$H26),I$5),MIN(IF('Cost Margin'!$I26="",'Cost Margin'!$B$9,'Cost Margin'!$I26),I$6),INDEX(Settings!$J$7:$M$60,0,MATCH('Cost Margin'!$C26,Settings!$J$6:$M$6,0))),NETWORKDAYS(MAX(IF('Cost Margin'!$H26="",'Cost Margin'!$B$8,'Cost Margin'!$H26),I$5),MIN(IF('Cost Margin'!$I26="",'Cost Margin'!$B$9,'Cost Margin'!$I26),I$6))))) -> 0 | J18: =IF(OR(J$5="",'Cost Margin'!$A26="",IF('Cost Margin'!$H26="",'Cost Margin'!$B$8,'Cost Margin'!$H26)="",IF('Cost Margin'!$I26="",'Cost Margin'!$B$9,'Cost Margin'!$I26)=""),0,IF(MIN(IF('Cost Margin'!$I26="",'Cost Margin'!$B$9,'Cost Margin'!$I26),J$6)<MAX(IF('Cost Margin'!$H26="",'Cost Margin'!$B$8,'Cost Margin'!$H26),J$5),0,IFERROR(NETWORKDAYS(MAX(IF('Cost Margin'!$H26="",'Cost Margin'!$B$8,'Cost Margin'!$H26),J$5),MIN(IF('Cost Margin'!$I26="",'Cost Margin'!$B$9,'Cost Margin'!$I26),J$6),INDEX(Settings!$J$7:$M$60,0,MATCH('Cost Margin'!$C26,Settings!$J$6:$M$6,0))),NETWORKDAYS(MAX(IF('Cost Margin'!$H26="",'Cost Margin'!$B$8,'Cost Margin'!$H26),J$5),MIN(IF('Cost Margin'!$I26="",'Cost Margin'!$B$9,'Cost Margin'!$I26),J$6))))) -> 0 | ... Z18: =IF(OR(Z$5="",'Cost Margin'!$A26="",IF('Cost Margin'!$H26="",'Cost Margin'!$B$8,'Cost Margin'!$H26)="",IF('Cost Margin'!$I26="",'Cost Margin'!$B$9,'Cost Margin'!$I26)=""),0,IF(MIN(IF('Cost Margin'!$I26="",'Cost Margin'!$B$9,'Cost Margin'!$I26),Z$6)<MAX(IF('Cost Margin'!$H26="",'Cost Margin'!$B$8,'Cost Margin'!$H26),Z$5),0,IFERROR(NETWORKDAYS(MAX(IF('Cost Margin'!$H26="",'Cost Margin'!$B$8,'Cost Margin'!$H26),Z$5),MIN(IF('Cost Margin'!$I26="",'Cost Margin'!$B$9,'Cost Margin'!$I26),Z$6),INDEX(Settings!$J$7:$M$60,0,MATCH('Cost Margin'!$C26,Settings!$J$6:$M$6,0))),NETWORKDAYS(MAX(IF('Cost Margin'!$H26="",'Cost Margin'!$B$8,'Cost Margin'!$H26),Z$5),MIN(IF('Cost Margin'!$I26="",'Cost Margin'!$B$9,'Cost Margin'!$I26),Z$6))))) -> 0
A19: 11 | B19: =IF('Cost Margin'!A27="","",'Cost Margin'!A27) | C19: =IF(OR(C$5="",'Cost Margin'!$A27="",IF('Cost Margin'!$H27="",'Cost Margin'!$B$8,'Cost Margin'!$H27)="",IF('Cost Margin'!$I27="",'Cost Margin'!$B$9,'Cost Margin'!$I27)=""),0,IF(MIN(IF('Cost Margin'!$I27="",'Cost Margin'!$B$9,'Cost Margin'!$I27),C$6)<MAX(IF('Cost Margin'!$H27="",'Cost Margin'!$B$8,'Cost Margin'!$H27),C$5),0,IFERROR(NETWORKDAYS(MAX(IF('Cost Margin'!$H27="",'Cost Margin'!$B$8,'Cost Margin'!$H27),C$5),MIN(IF('Cost Margin'!$I27="",'Cost Margin'!$B$9,'Cost Margin'!$I27),C$6),INDEX(Settings!$J$7:$M$60,0,MATCH('Cost Margin'!$C27,Settings!$J$6:$M$6,0))),NETWORKDAYS(MAX(IF('Cost Margin'!$H27="",'Cost Margin'!$B$8,'Cost Margin'!$H27),C$5),MIN(IF('Cost Margin'!$I27="",'Cost Margin'!$B$9,'Cost Margin'!$I27),C$6))))) -> 0 | D19: =IF(OR(D$5="",'Cost Margin'!$A27="",IF('Cost Margin'!$H27="",'Cost Margin'!$B$8,'Cost Margin'!$H27)="",IF('Cost Margin'!$I27="",'Cost Margin'!$B$9,'Cost Margin'!$I27)=""),0,IF(MIN(IF('Cost Margin'!$I27="",'Cost Margin'!$B$9,'Cost Margin'!$I27),D$6)<MAX(IF('Cost Margin'!$H27="",'Cost Margin'!$B$8,'Cost Margin'!$H27),D$5),0,IFERROR(NETWORKDAYS(MAX(IF('Cost Margin'!$H27="",'Cost Margin'!$B$8,'Cost Margin'!$H27),D$5),MIN(IF('Cost Margin'!$I27="",'Cost Margin'!$B$9,'Cost Margin'!$I27),D$6),INDEX(Settings!$J$7:$M$60,0,MATCH('Cost Margin'!$C27,Settings!$J$6:$M$6,0))),NETWORKDAYS(MAX(IF('Cost Margin'!$H27="",'Cost Margin'!$B$8,'Cost Margin'!$H27),D$5),MIN(IF('Cost Margin'!$I27="",'Cost Margin'!$B$9,'Cost Margin'!$I27),D$6))))) -> 0 | E19: =IF(OR(E$5="",'Cost Margin'!$A27="",IF('Cost Margin'!$H27="",'Cost Margin'!$B$8,'Cost Margin'!$H27)="",IF('Cost Margin'!$I27="",'Cost Margin'!$B$9,'Cost Margin'!$I27)=""),0,IF(MIN(IF('Cost Margin'!$I27="",'Cost Margin'!$B$9,'Cost Margin'!$I27),E$6)<MAX(IF('Cost Margin'!$H27="",'Cost Margin'!$B$8,'Cost Margin'!$H27),E$5),0,IFERROR(NETWORKDAYS(MAX(IF('Cost Margin'!$H27="",'Cost Margin'!$B$8,'Cost Margin'!$H27),E$5),MIN(IF('Cost Margin'!$I27="",'Cost Margin'!$B$9,'Cost Margin'!$I27),E$6),INDEX(Settings!$J$7:$M$60,0,MATCH('Cost Margin'!$C27,Settings!$J$6:$M$6,0))),NETWORKDAYS(MAX(IF('Cost Margin'!$H27="",'Cost Margin'!$B$8,'Cost Margin'!$H27),E$5),MIN(IF('Cost Margin'!$I27="",'Cost Margin'!$B$9,'Cost Margin'!$I27),E$6))))) -> 0 | F19: =IF(OR(F$5="",'Cost Margin'!$A27="",IF('Cost Margin'!$H27="",'Cost Margin'!$B$8,'Cost Margin'!$H27)="",IF('Cost Margin'!$I27="",'Cost Margin'!$B$9,'Cost Margin'!$I27)=""),0,IF(MIN(IF('Cost Margin'!$I27="",'Cost Margin'!$B$9,'Cost Margin'!$I27),F$6)<MAX(IF('Cost Margin'!$H27="",'Cost Margin'!$B$8,'Cost Margin'!$H27),F$5),0,IFERROR(NETWORKDAYS(MAX(IF('Cost Margin'!$H27="",'Cost Margin'!$B$8,'Cost Margin'!$H27),F$5),MIN(IF('Cost Margin'!$I27="",'Cost Margin'!$B$9,'Cost Margin'!$I27),F$6),INDEX(Settings!$J$7:$M$60,0,MATCH('Cost Margin'!$C27,Settings!$J$6:$M$6,0))),NETWORKDAYS(MAX(IF('Cost Margin'!$H27="",'Cost Margin'!$B$8,'Cost Margin'!$H27),F$5),MIN(IF('Cost Margin'!$I27="",'Cost Margin'!$B$9,'Cost Margin'!$I27),F$6))))) -> 0 | G19: =IF(OR(G$5="",'Cost Margin'!$A27="",IF('Cost Margin'!$H27="",'Cost Margin'!$B$8,'Cost Margin'!$H27)="",IF('Cost Margin'!$I27="",'Cost Margin'!$B$9,'Cost Margin'!$I27)=""),0,IF(MIN(IF('Cost Margin'!$I27="",'Cost Margin'!$B$9,'Cost Margin'!$I27),G$6)<MAX(IF('Cost Margin'!$H27="",'Cost Margin'!$B$8,'Cost Margin'!$H27),G$5),0,IFERROR(NETWORKDAYS(MAX(IF('Cost Margin'!$H27="",'Cost Margin'!$B$8,'Cost Margin'!$H27),G$5),MIN(IF('Cost Margin'!$I27="",'Cost Margin'!$B$9,'Cost Margin'!$I27),G$6),INDEX(Settings!$J$7:$M$60,0,MATCH('Cost Margin'!$C27,Settings!$J$6:$M$6,0))),NETWORKDAYS(MAX(IF('Cost Margin'!$H27="",'Cost Margin'!$B$8,'Cost Margin'!$H27),G$5),MIN(IF('Cost Margin'!$I27="",'Cost Margin'!$B$9,'Cost Margin'!$I27),G$6))))) -> 0 | H19: =IF(OR(H$5="",'Cost Margin'!$A27="",IF('Cost Margin'!$H27="",'Cost Margin'!$B$8,'Cost Margin'!$H27)="",IF('Cost Margin'!$I27="",'Cost Margin'!$B$9,'Cost Margin'!$I27)=""),0,IF(MIN(IF('Cost Margin'!$I27="",'Cost Margin'!$B$9,'Cost Margin'!$I27),H$6)<MAX(IF('Cost Margin'!$H27="",'Cost Margin'!$B$8,'Cost Margin'!$H27),H$5),0,IFERROR(NETWORKDAYS(MAX(IF('Cost Margin'!$H27="",'Cost Margin'!$B$8,'Cost Margin'!$H27),H$5),MIN(IF('Cost Margin'!$I27="",'Cost Margin'!$B$9,'Cost Margin'!$I27),H$6),INDEX(Settings!$J$7:$M$60,0,MATCH('Cost Margin'!$C27,Settings!$J$6:$M$6,0))),NETWORKDAYS(MAX(IF('Cost Margin'!$H27="",'Cost Margin'!$B$8,'Cost Margin'!$H27),H$5),MIN(IF('Cost Margin'!$I27="",'Cost Margin'!$B$9,'Cost Margin'!$I27),H$6))))) -> 0 | I19: =IF(OR(I$5="",'Cost Margin'!$A27="",IF('Cost Margin'!$H27="",'Cost Margin'!$B$8,'Cost Margin'!$H27)="",IF('Cost Margin'!$I27="",'Cost Margin'!$B$9,'Cost Margin'!$I27)=""),0,IF(MIN(IF('Cost Margin'!$I27="",'Cost Margin'!$B$9,'Cost Margin'!$I27),I$6)<MAX(IF('Cost Margin'!$H27="",'Cost Margin'!$B$8,'Cost Margin'!$H27),I$5),0,IFERROR(NETWORKDAYS(MAX(IF('Cost Margin'!$H27="",'Cost Margin'!$B$8,'Cost Margin'!$H27),I$5),MIN(IF('Cost Margin'!$I27="",'Cost Margin'!$B$9,'Cost Margin'!$I27),I$6),INDEX(Settings!$J$7:$M$60,0,MATCH('Cost Margin'!$C27,Settings!$J$6:$M$6,0))),NETWORKDAYS(MAX(IF('Cost Margin'!$H27="",'Cost Margin'!$B$8,'Cost Margin'!$H27),I$5),MIN(IF('Cost Margin'!$I27="",'Cost Margin'!$B$9,'Cost Margin'!$I27),I$6))))) -> 0 | J19: =IF(OR(J$5="",'Cost Margin'!$A27="",IF('Cost Margin'!$H27="",'Cost Margin'!$B$8,'Cost Margin'!$H27)="",IF('Cost Margin'!$I27="",'Cost Margin'!$B$9,'Cost Margin'!$I27)=""),0,IF(MIN(IF('Cost Margin'!$I27="",'Cost Margin'!$B$9,'Cost Margin'!$I27),J$6)<MAX(IF('Cost Margin'!$H27="",'Cost Margin'!$B$8,'Cost Margin'!$H27),J$5),0,IFERROR(NETWORKDAYS(MAX(IF('Cost Margin'!$H27="",'Cost Margin'!$B$8,'Cost Margin'!$H27),J$5),MIN(IF('Cost Margin'!$I27="",'Cost Margin'!$B$9,'Cost Margin'!$I27),J$6),INDEX(Settings!$J$7:$M$60,0,MATCH('Cost Margin'!$C27,Settings!$J$6:$M$6,0))),NETWORKDAYS(MAX(IF('Cost Margin'!$H27="",'Cost Margin'!$B$8,'Cost Margin'!$H27),J$5),MIN(IF('Cost Margin'!$I27="",'Cost Margin'!$B$9,'Cost Margin'!$I27),J$6))))) -> 0 | ... Z19: =IF(OR(Z$5="",'Cost Margin'!$A27="",IF('Cost Margin'!$H27="",'Cost Margin'!$B$8,'Cost Margin'!$H27)="",IF('Cost Margin'!$I27="",'Cost Margin'!$B$9,'Cost Margin'!$I27)=""),0,IF(MIN(IF('Cost Margin'!$I27="",'Cost Margin'!$B$9,'Cost Margin'!$I27),Z$6)<MAX(IF('Cost Margin'!$H27="",'Cost Margin'!$B$8,'Cost Margin'!$H27),Z$5),0,IFERROR(NETWORKDAYS(MAX(IF('Cost Margin'!$H27="",'Cost Margin'!$B$8,'Cost Margin'!$H27),Z$5),MIN(IF('Cost Margin'!$I27="",'Cost Margin'!$B$9,'Cost Margin'!$I27),Z$6),INDEX(Settings!$J$7:$M$60,0,MATCH('Cost Margin'!$C27,Settings!$J$6:$M$6,0))),NETWORKDAYS(MAX(IF('Cost Margin'!$H27="",'Cost Margin'!$B$8,'Cost Margin'!$H27),Z$5),MIN(IF('Cost Margin'!$I27="",'Cost Margin'!$B$9,'Cost Margin'!$I27),Z$6))))) -> 0
A20: 12 | B20: =IF('Cost Margin'!A28="","",'Cost Margin'!A28) | C20: =IF(OR(C$5="",'Cost Margin'!$A28="",IF('Cost Margin'!$H28="",'Cost Margin'!$B$8,'Cost Margin'!$H28)="",IF('Cost Margin'!$I28="",'Cost Margin'!$B$9,'Cost Margin'!$I28)=""),0,IF(MIN(IF('Cost Margin'!$I28="",'Cost Margin'!$B$9,'Cost Margin'!$I28),C$6)<MAX(IF('Cost Margin'!$H28="",'Cost Margin'!$B$8,'Cost Margin'!$H28),C$5),0,IFERROR(NETWORKDAYS(MAX(IF('Cost Margin'!$H28="",'Cost Margin'!$B$8,'Cost Margin'!$H28),C$5),MIN(IF('Cost Margin'!$I28="",'Cost Margin'!$B$9,'Cost Margin'!$I28),C$6),INDEX(Settings!$J$7:$M$60,0,MATCH('Cost Margin'!$C28,Settings!$J$6:$M$6,0))),NETWORKDAYS(MAX(IF('Cost Margin'!$H28="",'Cost Margin'!$B$8,'Cost Margin'!$H28),C$5),MIN(IF('Cost Margin'!$I28="",'Cost Margin'!$B$9,'Cost Margin'!$I28),C$6))))) -> 0 | D20: =IF(OR(D$5="",'Cost Margin'!$A28="",IF('Cost Margin'!$H28="",'Cost Margin'!$B$8,'Cost Margin'!$H28)="",IF('Cost Margin'!$I28="",'Cost Margin'!$B$9,'Cost Margin'!$I28)=""),0,IF(MIN(IF('Cost Margin'!$I28="",'Cost Margin'!$B$9,'Cost Margin'!$I28),D$6)<MAX(IF('Cost Margin'!$H28="",'Cost Margin'!$B$8,'Cost Margin'!$H28),D$5),0,IFERROR(NETWORKDAYS(MAX(IF('Cost Margin'!$H28="",'Cost Margin'!$B$8,'Cost Margin'!$H28),D$5),MIN(IF('Cost Margin'!$I28="",'Cost Margin'!$B$9,'Cost Margin'!$I28),D$6),INDEX(Settings!$J$7:$M$60,0,MATCH('Cost Margin'!$C28,Settings!$J$6:$M$6,0))),NETWORKDAYS(MAX(IF('Cost Margin'!$H28="",'Cost Margin'!$B$8,'Cost Margin'!$H28),D$5),MIN(IF('Cost Margin'!$I28="",'Cost Margin'!$B$9,'Cost Margin'!$I28),D$6))))) -> 0 | E20: =IF(OR(E$5="",'Cost Margin'!$A28="",IF('Cost Margin'!$H28="",'Cost Margin'!$B$8,'Cost Margin'!$H28)="",IF('Cost Margin'!$I28="",'Cost Margin'!$B$9,'Cost Margin'!$I28)=""),0,IF(MIN(IF('Cost Margin'!$I28="",'Cost Margin'!$B$9,'Cost Margin'!$I28),E$6)<MAX(IF('Cost Margin'!$H28="",'Cost Margin'!$B$8,'Cost Margin'!$H28),E$5),0,IFERROR(NETWORKDAYS(MAX(IF('Cost Margin'!$H28="",'Cost Margin'!$B$8,'Cost Margin'!$H28),E$5),MIN(IF('Cost Margin'!$I28="",'Cost Margin'!$B$9,'Cost Margin'!$I28),E$6),INDEX(Settings!$J$7:$M$60,0,MATCH('Cost Margin'!$C28,Settings!$J$6:$M$6,0))),NETWORKDAYS(MAX(IF('Cost Margin'!$H28="",'Cost Margin'!$B$8,'Cost Margin'!$H28),E$5),MIN(IF('Cost Margin'!$I28="",'Cost Margin'!$B$9,'Cost Margin'!$I28),E$6))))) -> 0 | F20: =IF(OR(F$5="",'Cost Margin'!$A28="",IF('Cost Margin'!$H28="",'Cost Margin'!$B$8,'Cost Margin'!$H28)="",IF('Cost Margin'!$I28="",'Cost Margin'!$B$9,'Cost Margin'!$I28)=""),0,IF(MIN(IF('Cost Margin'!$I28="",'Cost Margin'!$B$9,'Cost Margin'!$I28),F$6)<MAX(IF('Cost Margin'!$H28="",'Cost Margin'!$B$8,'Cost Margin'!$H28),F$5),0,IFERROR(NETWORKDAYS(MAX(IF('Cost Margin'!$H28="",'Cost Margin'!$B$8,'Cost Margin'!$H28),F$5),MIN(IF('Cost Margin'!$I28="",'Cost Margin'!$B$9,'Cost Margin'!$I28),F$6),INDEX(Settings!$J$7:$M$60,0,MATCH('Cost Margin'!$C28,Settings!$J$6:$M$6,0))),NETWORKDAYS(MAX(IF('Cost Margin'!$H28="",'Cost Margin'!$B$8,'Cost Margin'!$H28),F$5),MIN(IF('Cost Margin'!$I28="",'Cost Margin'!$B$9,'Cost Margin'!$I28),F$6))))) -> 0 | G20: =IF(OR(G$5="",'Cost Margin'!$A28="",IF('Cost Margin'!$H28="",'Cost Margin'!$B$8,'Cost Margin'!$H28)="",IF('Cost Margin'!$I28="",'Cost Margin'!$B$9,'Cost Margin'!$I28)=""),0,IF(MIN(IF('Cost Margin'!$I28="",'Cost Margin'!$B$9,'Cost Margin'!$I28),G$6)<MAX(IF('Cost Margin'!$H28="",'Cost Margin'!$B$8,'Cost Margin'!$H28),G$5),0,IFERROR(NETWORKDAYS(MAX(IF('Cost Margin'!$H28="",'Cost Margin'!$B$8,'Cost Margin'!$H28),G$5),MIN(IF('Cost Margin'!$I28="",'Cost Margin'!$B$9,'Cost Margin'!$I28),G$6),INDEX(Settings!$J$7:$M$60,0,MATCH('Cost Margin'!$C28,Settings!$J$6:$M$6,0))),NETWORKDAYS(MAX(IF('Cost Margin'!$H28="",'Cost Margin'!$B$8,'Cost Margin'!$H28),G$5),MIN(IF('Cost Margin'!$I28="",'Cost Margin'!$B$9,'Cost Margin'!$I28),G$6))))) -> 0 | H20: =IF(OR(H$5="",'Cost Margin'!$A28="",IF('Cost Margin'!$H28="",'Cost Margin'!$B$8,'Cost Margin'!$H28)="",IF('Cost Margin'!$I28="",'Cost Margin'!$B$9,'Cost Margin'!$I28)=""),0,IF(MIN(IF('Cost Margin'!$I28="",'Cost Margin'!$B$9,'Cost Margin'!$I28),H$6)<MAX(IF('Cost Margin'!$H28="",'Cost Margin'!$B$8,'Cost Margin'!$H28),H$5),0,IFERROR(NETWORKDAYS(MAX(IF('Cost Margin'!$H28="",'Cost Margin'!$B$8,'Cost Margin'!$H28),H$5),MIN(IF('Cost Margin'!$I28="",'Cost Margin'!$B$9,'Cost Margin'!$I28),H$6),INDEX(Settings!$J$7:$M$60,0,MATCH('Cost Margin'!$C28,Settings!$J$6:$M$6,0))),NETWORKDAYS(MAX(IF('Cost Margin'!$H28="",'Cost Margin'!$B$8,'Cost Margin'!$H28),H$5),MIN(IF('Cost Margin'!$I28="",'Cost Margin'!$B$9,'Cost Margin'!$I28),H$6))))) -> 0 | I20: =IF(OR(I$5="",'Cost Margin'!$A28="",IF('Cost Margin'!$H28="",'Cost Margin'!$B$8,'Cost Margin'!$H28)="",IF('Cost Margin'!$I28="",'Cost Margin'!$B$9,'Cost Margin'!$I28)=""),0,IF(MIN(IF('Cost Margin'!$I28="",'Cost Margin'!$B$9,'Cost Margin'!$I28),I$6)<MAX(IF('Cost Margin'!$H28="",'Cost Margin'!$B$8,'Cost Margin'!$H28),I$5),0,IFERROR(NETWORKDAYS(MAX(IF('Cost Margin'!$H28="",'Cost Margin'!$B$8,'Cost Margin'!$H28),I$5),MIN(IF('Cost Margin'!$I28="",'Cost Margin'!$B$9,'Cost Margin'!$I28),I$6),INDEX(Settings!$J$7:$M$60,0,MATCH('Cost Margin'!$C28,Settings!$J$6:$M$6,0))),NETWORKDAYS(MAX(IF('Cost Margin'!$H28="",'Cost Margin'!$B$8,'Cost Margin'!$H28),I$5),MIN(IF('Cost Margin'!$I28="",'Cost Margin'!$B$9,'Cost Margin'!$I28),I$6))))) -> 0 | J20: =IF(OR(J$5="",'Cost Margin'!$A28="",IF('Cost Margin'!$H28="",'Cost Margin'!$B$8,'Cost Margin'!$H28)="",IF('Cost Margin'!$I28="",'Cost Margin'!$B$9,'Cost Margin'!$I28)=""),0,IF(MIN(IF('Cost Margin'!$I28="",'Cost Margin'!$B$9,'Cost Margin'!$I28),J$6)<MAX(IF('Cost Margin'!$H28="",'Cost Margin'!$B$8,'Cost Margin'!$H28),J$5),0,IFERROR(NETWORKDAYS(MAX(IF('Cost Margin'!$H28="",'Cost Margin'!$B$8,'Cost Margin'!$H28),J$5),MIN(IF('Cost Margin'!$I28="",'Cost Margin'!$B$9,'Cost Margin'!$I28),J$6),INDEX(Settings!$J$7:$M$60,0,MATCH('Cost Margin'!$C28,Settings!$J$6:$M$6,0))),NETWORKDAYS(MAX(IF('Cost Margin'!$H28="",'Cost Margin'!$B$8,'Cost Margin'!$H28),J$5),MIN(IF('Cost Margin'!$I28="",'Cost Margin'!$B$9,'Cost Margin'!$I28),J$6))))) -> 0 | ... Z20: =IF(OR(Z$5="",'Cost Margin'!$A28="",IF('Cost Margin'!$H28="",'Cost Margin'!$B$8,'Cost Margin'!$H28)="",IF('Cost Margin'!$I28="",'Cost Margin'!$B$9,'Cost Margin'!$I28)=""),0,IF(MIN(IF('Cost Margin'!$I28="",'Cost Margin'!$B$9,'Cost Margin'!$I28),Z$6)<MAX(IF('Cost Margin'!$H28="",'Cost Margin'!$B$8,'Cost Margin'!$H28),Z$5),0,IFERROR(NETWORKDAYS(MAX(IF('Cost Margin'!$H28="",'Cost Margin'!$B$8,'Cost Margin'!$H28),Z$5),MIN(IF('Cost Margin'!$I28="",'Cost Margin'!$B$9,'Cost Margin'!$I28),Z$6),INDEX(Settings!$J$7:$M$60,0,MATCH('Cost Margin'!$C28,Settings!$J$6:$M$6,0))),NETWORKDAYS(MAX(IF('Cost Margin'!$H28="",'Cost Margin'!$B$8,'Cost Margin'!$H28),Z$5),MIN(IF('Cost Margin'!$I28="",'Cost Margin'!$B$9,'Cost Margin'!$I28),Z$6))))) -> 0
... A28: 20 | B28: =IF('Cost Margin'!A36="","",'Cost Margin'!A36) | C28: =IF(OR(C$5="",'Cost Margin'!$A36="",IF('Cost Margin'!$H36="",'Cost Margin'!$B$8,'Cost Margin'!$H36)="",IF('Cost Margin'!$I36="",'Cost Margin'!$B$9,'Cost Margin'!$I36)=""),0,IF(MIN(IF('Cost Margin'!$I36="",'Cost Margin'!$B$9,'Cost Margin'!$I36),C$6)<MAX(IF('Cost Margin'!$H36="",'Cost Margin'!$B$8,'Cost Margin'!$H36),C$5),0,IFERROR(NETWORKDAYS(MAX(IF('Cost Margin'!$H36="",'Cost Margin'!$B$8,'Cost Margin'!$H36),C$5),MIN(IF('Cost Margin'!$I36="",'Cost Margin'!$B$9,'Cost Margin'!$I36),C$6),INDEX(Settings!$J$7:$M$60,0,MATCH('Cost Margin'!$C36,Settings!$J$6:$M$6,0))),NETWORKDAYS(MAX(IF('Cost Margin'!$H36="",'Cost Margin'!$B$8,'Cost Margin'!$H36),C$5),MIN(IF('Cost Margin'!$I36="",'Cost Margin'!$B$9,'Cost Margin'!$I36),C$6))))) -> 0 | D28: =IF(OR(D$5="",'Cost Margin'!$A36="",IF('Cost Margin'!$H36="",'Cost Margin'!$B$8,'Cost Margin'!$H36)="",IF('Cost Margin'!$I36="",'Cost Margin'!$B$9,'Cost Margin'!$I36)=""),0,IF(MIN(IF('Cost Margin'!$I36="",'Cost Margin'!$B$9,'Cost Margin'!$I36),D$6)<MAX(IF('Cost Margin'!$H36="",'Cost Margin'!$B$8,'Cost Margin'!$H36),D$5),0,IFERROR(NETWORKDAYS(MAX(IF('Cost Margin'!$H36="",'Cost Margin'!$B$8,'Cost Margin'!$H36),D$5),MIN(IF('Cost Margin'!$I36="",'Cost Margin'!$B$9,'Cost Margin'!$I36),D$6),INDEX(Settings!$J$7:$M$60,0,MATCH('Cost Margin'!$C36,Settings!$J$6:$M$6,0))),NETWORKDAYS(MAX(IF('Cost Margin'!$H36="",'Cost Margin'!$B$8,'Cost Margin'!$H36),D$5),MIN(IF('Cost Margin'!$I36="",'Cost Margin'!$B$9,'Cost Margin'!$I36),D$6))))) -> 0 | E28: =IF(OR(E$5="",'Cost Margin'!$A36="",IF('Cost Margin'!$H36="",'Cost Margin'!$B$8,'Cost Margin'!$H36)="",IF('Cost Margin'!$I36="",'Cost Margin'!$B$9,'Cost Margin'!$I36)=""),0,IF(MIN(IF('Cost Margin'!$I36="",'Cost Margin'!$B$9,'Cost Margin'!$I36),E$6)<MAX(IF('Cost Margin'!$H36="",'Cost Margin'!$B$8,'Cost Margin'!$H36),E$5),0,IFERROR(NETWORKDAYS(MAX(IF('Cost Margin'!$H36="",'Cost Margin'!$B$8,'Cost Margin'!$H36),E$5),MIN(IF('Cost Margin'!$I36="",'Cost Margin'!$B$9,'Cost Margin'!$I36),E$6),INDEX(Settings!$J$7:$M$60,0,MATCH('Cost Margin'!$C36,Settings!$J$6:$M$6,0))),NETWORKDAYS(MAX(IF('Cost Margin'!$H36="",'Cost Margin'!$B$8,'Cost Margin'!$H36),E$5),MIN(IF('Cost Margin'!$I36="",'Cost Margin'!$B$9,'Cost Margin'!$I36),E$6))))) -> 0 | F28: =IF(OR(F$5="",'Cost Margin'!$A36="",IF('Cost Margin'!$H36="",'Cost Margin'!$B$8,'Cost Margin'!$H36)="",IF('Cost Margin'!$I36="",'Cost Margin'!$B$9,'Cost Margin'!$I36)=""),0,IF(MIN(IF('Cost Margin'!$I36="",'Cost Margin'!$B$9,'Cost Margin'!$I36),F$6)<MAX(IF('Cost Margin'!$H36="",'Cost Margin'!$B$8,'Cost Margin'!$H36),F$5),0,IFERROR(NETWORKDAYS(MAX(IF('Cost Margin'!$H36="",'Cost Margin'!$B$8,'Cost Margin'!$H36),F$5),MIN(IF('Cost Margin'!$I36="",'Cost Margin'!$B$9,'Cost Margin'!$I36),F$6),INDEX(Settings!$J$7:$M$60,0,MATCH('Cost Margin'!$C36,Settings!$J$6:$M$6,0))),NETWORKDAYS(MAX(IF('Cost Margin'!$H36="",'Cost Margin'!$B$8,'Cost Margin'!$H36),F$5),MIN(IF('Cost Margin'!$I36="",'Cost Margin'!$B$9,'Cost Margin'!$I36),F$6))))) -> 0 | G28: =IF(OR(G$5="",'Cost Margin'!$A36="",IF('Cost Margin'!$H36="",'Cost Margin'!$B$8,'Cost Margin'!$H36)="",IF('Cost Margin'!$I36="",'Cost Margin'!$B$9,'Cost Margin'!$I36)=""),0,IF(MIN(IF('Cost Margin'!$I36="",'Cost Margin'!$B$9,'Cost Margin'!$I36),G$6)<MAX(IF('Cost Margin'!$H36="",'Cost Margin'!$B$8,'Cost Margin'!$H36),G$5),0,IFERROR(NETWORKDAYS(MAX(IF('Cost Margin'!$H36="",'Cost Margin'!$B$8,'Cost Margin'!$H36),G$5),MIN(IF('Cost Margin'!$I36="",'Cost Margin'!$B$9,'Cost Margin'!$I36),G$6),INDEX(Settings!$J$7:$M$60,0,MATCH('Cost Margin'!$C36,Settings!$J$6:$M$6,0))),NETWORKDAYS(MAX(IF('Cost Margin'!$H36="",'Cost Margin'!$B$8,'Cost Margin'!$H36),G$5),MIN(IF('Cost Margin'!$I36="",'Cost Margin'!$B$9,'Cost Margin'!$I36),G$6))))) -> 0 | H28: =IF(OR(H$5="",'Cost Margin'!$A36="",IF('Cost Margin'!$H36="",'Cost Margin'!$B$8,'Cost Margin'!$H36)="",IF('Cost Margin'!$I36="",'Cost Margin'!$B$9,'Cost Margin'!$I36)=""),0,IF(MIN(IF('Cost Margin'!$I36="",'Cost Margin'!$B$9,'Cost Margin'!$I36),H$6)<MAX(IF('Cost Margin'!$H36="",'Cost Margin'!$B$8,'Cost Margin'!$H36),H$5),0,IFERROR(NETWORKDAYS(MAX(IF('Cost Margin'!$H36="",'Cost Margin'!$B$8,'Cost Margin'!$H36),H$5),MIN(IF('Cost Margin'!$I36="",'Cost Margin'!$B$9,'Cost Margin'!$I36),H$6),INDEX(Settings!$J$7:$M$60,0,MATCH('Cost Margin'!$C36,Settings!$J$6:$M$6,0))),NETWORKDAYS(MAX(IF('Cost Margin'!$H36="",'Cost Margin'!$B$8,'Cost Margin'!$H36),H$5),MIN(IF('Cost Margin'!$I36="",'Cost Margin'!$B$9,'Cost Margin'!$I36),H$6))))) -> 0 | I28: =IF(OR(I$5="",'Cost Margin'!$A36="",IF('Cost Margin'!$H36="",'Cost Margin'!$B$8,'Cost Margin'!$H36)="",IF('Cost Margin'!$I36="",'Cost Margin'!$B$9,'Cost Margin'!$I36)=""),0,IF(MIN(IF('Cost Margin'!$I36="",'Cost Margin'!$B$9,'Cost Margin'!$I36),I$6)<MAX(IF('Cost Margin'!$H36="",'Cost Margin'!$B$8,'Cost Margin'!$H36),I$5),0,IFERROR(NETWORKDAYS(MAX(IF('Cost Margin'!$H36="",'Cost Margin'!$B$8,'Cost Margin'!$H36),I$5),MIN(IF('Cost Margin'!$I36="",'Cost Margin'!$B$9,'Cost Margin'!$I36),I$6),INDEX(Settings!$J$7:$M$60,0,MATCH('Cost Margin'!$C36,Settings!$J$6:$M$6,0))),NETWORKDAYS(MAX(IF('Cost Margin'!$H36="",'Cost Margin'!$B$8,'Cost Margin'!$H36),I$5),MIN(IF('Cost Margin'!$I36="",'Cost Margin'!$B$9,'Cost Margin'!$I36),I$6))))) -> 0 | J28: =IF(OR(J$5="",'Cost Margin'!$A36="",IF('Cost Margin'!$H36="",'Cost Margin'!$B$8,'Cost Margin'!$H36)="",IF('Cost Margin'!$I36="",'Cost Margin'!$B$9,'Cost Margin'!$I36)=""),0,IF(MIN(IF('Cost Margin'!$I36="",'Cost Margin'!$B$9,'Cost Margin'!$I36),J$6)<MAX(IF('Cost Margin'!$H36="",'Cost Margin'!$B$8,'Cost Margin'!$H36),J$5),0,IFERROR(NETWORKDAYS(MAX(IF('Cost Margin'!$H36="",'Cost Margin'!$B$8,'Cost Margin'!$H36),J$5),MIN(IF('Cost Margin'!$I36="",'Cost Margin'!$B$9,'Cost Margin'!$I36),J$6),INDEX(Settings!$J$7:$M$60,0,MATCH('Cost Margin'!$C36,Settings!$J$6:$M$6,0))),NETWORKDAYS(MAX(IF('Cost Margin'!$H36="",'Cost Margin'!$B$8,'Cost Margin'!$H36),J$5),MIN(IF('Cost Margin'!$I36="",'Cost Margin'!$B$9,'Cost Margin'!$I36),J$6))))) -> 0 | ... Z28: =IF(OR(Z$5="",'Cost Margin'!$A36="",IF('Cost Margin'!$H36="",'Cost Margin'!$B$8,'Cost Margin'!$H36)="",IF('Cost Margin'!$I36="",'Cost Margin'!$B$9,'Cost Margin'!$I36)=""),0,IF(MIN(IF('Cost Margin'!$I36="",'Cost Margin'!$B$9,'Cost Margin'!$I36),Z$6)<MAX(IF('Cost Margin'!$H36="",'Cost Margin'!$B$8,'Cost Margin'!$H36),Z$5),0,IFERROR(NETWORKDAYS(MAX(IF('Cost Margin'!$H36="",'Cost Margin'!$B$8,'Cost Margin'!$H36),Z$5),MIN(IF('Cost Margin'!$I36="",'Cost Margin'!$B$9,'Cost Margin'!$I36),Z$6),INDEX(Settings!$J$7:$M$60,0,MATCH('Cost Margin'!$C36,Settings!$J$6:$M$6,0))),NETWORKDAYS(MAX(IF('Cost Margin'!$H36="",'Cost Margin'!$B$8,'Cost Margin'!$H36),Z$5),MIN(IF('Cost Margin'!$I36="",'Cost Margin'!$B$9,'Cost Margin'!$I36),Z$6))))) -> 0
A30: Hours in month, per person (override hours are spread by working-day share)
A31: 1 | B31: =IF('Cost Margin'!A17="","",'Cost Margin'!A17) -> Vikrin | C31: =IF(C9=0,0,IF('Cost Margin'!$K17<>"",'Cost Margin'!$K17*C9/'Cost Margin'!$J17,C9*Settings!$B$3*IF('Cost Margin'!$D17="",1,'Cost Margin'!$D17))) -> 144 | D31: =IF(D9=0,0,IF('Cost Margin'!$K17<>"",'Cost Margin'!$K17*D9/'Cost Margin'!$J17,D9*Settings!$B$3*IF('Cost Margin'!$D17="",1,'Cost Margin'!$D17))) -> 24 | E31: =IF(E9=0,0,IF('Cost Margin'!$K17<>"",'Cost Margin'!$K17*E9/'Cost Margin'!$J17,E9*Settings!$B$3*IF('Cost Margin'!$D17="",1,'Cost Margin'!$D17))) -> 0 | F31: =IF(F9=0,0,IF('Cost Margin'!$K17<>"",'Cost Margin'!$K17*F9/'Cost Margin'!$J17,F9*Settings!$B$3*IF('Cost Margin'!$D17="",1,'Cost Margin'!$D17))) -> 0 | G31: =IF(G9=0,0,IF('Cost Margin'!$K17<>"",'Cost Margin'!$K17*G9/'Cost Margin'!$J17,G9*Settings!$B$3*IF('Cost Margin'!$D17="",1,'Cost Margin'!$D17))) -> 0 | H31: =IF(H9=0,0,IF('Cost Margin'!$K17<>"",'Cost Margin'!$K17*H9/'Cost Margin'!$J17,H9*Settings!$B$3*IF('Cost Margin'!$D17="",1,'Cost Margin'!$D17))) -> 0 | I31: =IF(I9=0,0,IF('Cost Margin'!$K17<>"",'Cost Margin'!$K17*I9/'Cost Margin'!$J17,I9*Settings!$B$3*IF('Cost Margin'!$D17="",1,'Cost Margin'!$D17))) -> 0 | J31: =IF(J9=0,0,IF('Cost Margin'!$K17<>"",'Cost Margin'!$K17*J9/'Cost Margin'!$J17,J9*Settings!$B$3*IF('Cost Margin'!$D17="",1,'Cost Margin'!$D17))) -> 0 | ... Z31: =IF(Z9=0,0,IF('Cost Margin'!$K17<>"",'Cost Margin'!$K17*Z9/'Cost Margin'!$J17,Z9*Settings!$B$3*IF('Cost Margin'!$D17="",1,'Cost Margin'!$D17))) -> 0
A32: 2 | B32: =IF('Cost Margin'!A18="","",'Cost Margin'!A18) -> srikanth | C32: =IF(C10=0,0,IF('Cost Margin'!$K18<>"",'Cost Margin'!$K18*C10/'Cost Margin'!$J18,C10*Settings!$B$3*IF('Cost Margin'!$D18="",1,'Cost Margin'!$D18))) -> 34.56 | D32: =IF(D10=0,0,IF('Cost Margin'!$K18<>"",'Cost Margin'!$K18*D10/'Cost Margin'!$J18,D10*Settings!$B$3*IF('Cost Margin'!$D18="",1,'Cost Margin'!$D18))) -> 5.76 | E32: =IF(E10=0,0,IF('Cost Margin'!$K18<>"",'Cost Margin'!$K18*E10/'Cost Margin'!$J18,E10*Settings!$B$3*IF('Cost Margin'!$D18="",1,'Cost Margin'!$D18))) -> 0 | F32: =IF(F10=0,0,IF('Cost Margin'!$K18<>"",'Cost Margin'!$K18*F10/'Cost Margin'!$J18,F10*Settings!$B$3*IF('Cost Margin'!$D18="",1,'Cost Margin'!$D18))) -> 0 | G32: =IF(G10=0,0,IF('Cost Margin'!$K18<>"",'Cost Margin'!$K18*G10/'Cost Margin'!$J18,G10*Settings!$B$3*IF('Cost Margin'!$D18="",1,'Cost Margin'!$D18))) -> 0 | H32: =IF(H10=0,0,IF('Cost Margin'!$K18<>"",'Cost Margin'!$K18*H10/'Cost Margin'!$J18,H10*Settings!$B$3*IF('Cost Margin'!$D18="",1,'Cost Margin'!$D18))) -> 0 | I32: =IF(I10=0,0,IF('Cost Margin'!$K18<>"",'Cost Margin'!$K18*I10/'Cost Margin'!$J18,I10*Settings!$B$3*IF('Cost Margin'!$D18="",1,'Cost Margin'!$D18))) -> 0 | J32: =IF(J10=0,0,IF('Cost Margin'!$K18<>"",'Cost Margin'!$K18*J10/'Cost Margin'!$J18,J10*Settings!$B$3*IF('Cost Margin'!$D18="",1,'Cost Margin'!$D18))) -> 0 | ... Z32: =IF(Z10=0,0,IF('Cost Margin'!$K18<>"",'Cost Margin'!$K18*Z10/'Cost Margin'!$J18,Z10*Settings!$B$3*IF('Cost Margin'!$D18="",1,'Cost Margin'!$D18))) -> 0
A33: 3 | B33: =IF('Cost Margin'!A19="","",'Cost Margin'!A19) | C33: =IF(C11=0,0,IF('Cost Margin'!$K19<>"",'Cost Margin'!$K19*C11/'Cost Margin'!$J19,C11*Settings!$B$3*IF('Cost Margin'!$D19="",1,'Cost Margin'!$D19))) -> 0 | D33: =IF(D11=0,0,IF('Cost Margin'!$K19<>"",'Cost Margin'!$K19*D11/'Cost Margin'!$J19,D11*Settings!$B$3*IF('Cost Margin'!$D19="",1,'Cost Margin'!$D19))) -> 0 | E33: =IF(E11=0,0,IF('Cost Margin'!$K19<>"",'Cost Margin'!$K19*E11/'Cost Margin'!$J19,E11*Settings!$B$3*IF('Cost Margin'!$D19="",1,'Cost Margin'!$D19))) -> 0 | F33: =IF(F11=0,0,IF('Cost Margin'!$K19<>"",'Cost Margin'!$K19*F11/'Cost Margin'!$J19,F11*Settings!$B$3*IF('Cost Margin'!$D19="",1,'Cost Margin'!$D19))) -> 0 | G33: =IF(G11=0,0,IF('Cost Margin'!$K19<>"",'Cost Margin'!$K19*G11/'Cost Margin'!$J19,G11*Settings!$B$3*IF('Cost Margin'!$D19="",1,'Cost Margin'!$D19))) -> 0 | H33: =IF(H11=0,0,IF('Cost Margin'!$K19<>"",'Cost Margin'!$K19*H11/'Cost Margin'!$J19,H11*Settings!$B$3*IF('Cost Margin'!$D19="",1,'Cost Margin'!$D19))) -> 0 | I33: =IF(I11=0,0,IF('Cost Margin'!$K19<>"",'Cost Margin'!$K19*I11/'Cost Margin'!$J19,I11*Settings!$B$3*IF('Cost Margin'!$D19="",1,'Cost Margin'!$D19))) -> 0 | J33: =IF(J11=0,0,IF('Cost Margin'!$K19<>"",'Cost Margin'!$K19*J11/'Cost Margin'!$J19,J11*Settings!$B$3*IF('Cost Margin'!$D19="",1,'Cost Margin'!$D19))) -> 0 | ... Z33: =IF(Z11=0,0,IF('Cost Margin'!$K19<>"",'Cost Margin'!$K19*Z11/'Cost Margin'!$J19,Z11*Settings!$B$3*IF('Cost Margin'!$D19="",1,'Cost Margin'!$D19))) -> 0
A34: 4 | B34: =IF('Cost Margin'!A20="","",'Cost Margin'!A20) | C34: =IF(C12=0,0,IF('Cost Margin'!$K20<>"",'Cost Margin'!$K20*C12/'Cost Margin'!$J20,C12*Settings!$B$3*IF('Cost Margin'!$D20="",1,'Cost Margin'!$D20))) -> 0 | D34: =IF(D12=0,0,IF('Cost Margin'!$K20<>"",'Cost Margin'!$K20*D12/'Cost Margin'!$J20,D12*Settings!$B$3*IF('Cost Margin'!$D20="",1,'Cost Margin'!$D20))) -> 0 | E34: =IF(E12=0,0,IF('Cost Margin'!$K20<>"",'Cost Margin'!$K20*E12/'Cost Margin'!$J20,E12*Settings!$B$3*IF('Cost Margin'!$D20="",1,'Cost Margin'!$D20))) -> 0 | F34: =IF(F12=0,0,IF('Cost Margin'!$K20<>"",'Cost Margin'!$K20*F12/'Cost Margin'!$J20,F12*Settings!$B$3*IF('Cost Margin'!$D20="",1,'Cost Margin'!$D20))) -> 0 | G34: =IF(G12=0,0,IF('Cost Margin'!$K20<>"",'Cost Margin'!$K20*G12/'Cost Margin'!$J20,G12*Settings!$B$3*IF('Cost Margin'!$D20="",1,'Cost Margin'!$D20))) -> 0 | H34: =IF(H12=0,0,IF('Cost Margin'!$K20<>"",'Cost Margin'!$K20*H12/'Cost Margin'!$J20,H12*Settings!$B$3*IF('Cost Margin'!$D20="",1,'Cost Margin'!$D20))) -> 0 | I34: =IF(I12=0,0,IF('Cost Margin'!$K20<>"",'Cost Margin'!$K20*I12/'Cost Margin'!$J20,I12*Settings!$B$3*IF('Cost Margin'!$D20="",1,'Cost Margin'!$D20))) -> 0 | J34: =IF(J12=0,0,IF('Cost Margin'!$K20<>"",'Cost Margin'!$K20*J12/'Cost Margin'!$J20,J12*Settings!$B$3*IF('Cost Margin'!$D20="",1,'Cost Margin'!$D20))) -> 0 | ... Z34: =IF(Z12=0,0,IF('Cost Margin'!$K20<>"",'Cost Margin'!$K20*Z12/'Cost Margin'!$J20,Z12*Settings!$B$3*IF('Cost Margin'!$D20="",1,'Cost Margin'!$D20))) -> 0
A35: 5 | B35: =IF('Cost Margin'!A21="","",'Cost Margin'!A21) | C35: =IF(C13=0,0,IF('Cost Margin'!$K21<>"",'Cost Margin'!$K21*C13/'Cost Margin'!$J21,C13*Settings!$B$3*IF('Cost Margin'!$D21="",1,'Cost Margin'!$D21))) -> 0 | D35: =IF(D13=0,0,IF('Cost Margin'!$K21<>"",'Cost Margin'!$K21*D13/'Cost Margin'!$J21,D13*Settings!$B$3*IF('Cost Margin'!$D21="",1,'Cost Margin'!$D21))) -> 0 | E35: =IF(E13=0,0,IF('Cost Margin'!$K21<>"",'Cost Margin'!$K21*E13/'Cost Margin'!$J21,E13*Settings!$B$3*IF('Cost Margin'!$D21="",1,'Cost Margin'!$D21))) -> 0 | F35: =IF(F13=0,0,IF('Cost Margin'!$K21<>"",'Cost Margin'!$K21*F13/'Cost Margin'!$J21,F13*Settings!$B$3*IF('Cost Margin'!$D21="",1,'Cost Margin'!$D21))) -> 0 | G35: =IF(G13=0,0,IF('Cost Margin'!$K21<>"",'Cost Margin'!$K21*G13/'Cost Margin'!$J21,G13*Settings!$B$3*IF('Cost Margin'!$D21="",1,'Cost Margin'!$D21))) -> 0 | H35: =IF(H13=0,0,IF('Cost Margin'!$K21<>"",'Cost Margin'!$K21*H13/'Cost Margin'!$J21,H13*Settings!$B$3*IF('Cost Margin'!$D21="",1,'Cost Margin'!$D21))) -> 0 | I35: =IF(I13=0,0,IF('Cost Margin'!$K21<>"",'Cost Margin'!$K21*I13/'Cost Margin'!$J21,I13*Settings!$B$3*IF('Cost Margin'!$D21="",1,'Cost Margin'!$D21))) -> 0 | J35: =IF(J13=0,0,IF('Cost Margin'!$K21<>"",'Cost Margin'!$K21*J13/'Cost Margin'!$J21,J13*Settings!$B$3*IF('Cost Margin'!$D21="",1,'Cost Margin'!$D21))) -> 0 | ... Z35: =IF(Z13=0,0,IF('Cost Margin'!$K21<>"",'Cost Margin'!$K21*Z13/'Cost Margin'!$J21,Z13*Settings!$B$3*IF('Cost Margin'!$D21="",1,'Cost Margin'!$D21))) -> 0
A36: 6 | B36: =IF('Cost Margin'!A22="","",'Cost Margin'!A22) | C36: =IF(C14=0,0,IF('Cost Margin'!$K22<>"",'Cost Margin'!$K22*C14/'Cost Margin'!$J22,C14*Settings!$B$3*IF('Cost Margin'!$D22="",1,'Cost Margin'!$D22))) -> 0 | D36: =IF(D14=0,0,IF('Cost Margin'!$K22<>"",'Cost Margin'!$K22*D14/'Cost Margin'!$J22,D14*Settings!$B$3*IF('Cost Margin'!$D22="",1,'Cost Margin'!$D22))) -> 0 | E36: =IF(E14=0,0,IF('Cost Margin'!$K22<>"",'Cost Margin'!$K22*E14/'Cost Margin'!$J22,E14*Settings!$B$3*IF('Cost Margin'!$D22="",1,'Cost Margin'!$D22))) -> 0 | F36: =IF(F14=0,0,IF('Cost Margin'!$K22<>"",'Cost Margin'!$K22*F14/'Cost Margin'!$J22,F14*Settings!$B$3*IF('Cost Margin'!$D22="",1,'Cost Margin'!$D22))) -> 0 | G36: =IF(G14=0,0,IF('Cost Margin'!$K22<>"",'Cost Margin'!$K22*G14/'Cost Margin'!$J22,G14*Settings!$B$3*IF('Cost Margin'!$D22="",1,'Cost Margin'!$D22))) -> 0 | H36: =IF(H14=0,0,IF('Cost Margin'!$K22<>"",'Cost Margin'!$K22*H14/'Cost Margin'!$J22,H14*Settings!$B$3*IF('Cost Margin'!$D22="",1,'Cost Margin'!$D22))) -> 0 | I36: =IF(I14=0,0,IF('Cost Margin'!$K22<>"",'Cost Margin'!$K22*I14/'Cost Margin'!$J22,I14*Settings!$B$3*IF('Cost Margin'!$D22="",1,'Cost Margin'!$D22))) -> 0 | J36: =IF(J14=0,0,IF('Cost Margin'!$K22<>"",'Cost Margin'!$K22*J14/'Cost Margin'!$J22,J14*Settings!$B$3*IF('Cost Margin'!$D22="",1,'Cost Margin'!$D22))) -> 0 | ... Z36: =IF(Z14=0,0,IF('Cost Margin'!$K22<>"",'Cost Margin'!$K22*Z14/'Cost Margin'!$J22,Z14*Settings!$B$3*IF('Cost Margin'!$D22="",1,'Cost Margin'!$D22))) -> 0
A37: 7 | B37: =IF('Cost Margin'!A23="","",'Cost Margin'!A23) | C37: =IF(C15=0,0,IF('Cost Margin'!$K23<>"",'Cost Margin'!$K23*C15/'Cost Margin'!$J23,C15*Settings!$B$3*IF('Cost Margin'!$D23="",1,'Cost Margin'!$D23))) -> 0 | D37: =IF(D15=0,0,IF('Cost Margin'!$K23<>"",'Cost Margin'!$K23*D15/'Cost Margin'!$J23,D15*Settings!$B$3*IF('Cost Margin'!$D23="",1,'Cost Margin'!$D23))) -> 0 | E37: =IF(E15=0,0,IF('Cost Margin'!$K23<>"",'Cost Margin'!$K23*E15/'Cost Margin'!$J23,E15*Settings!$B$3*IF('Cost Margin'!$D23="",1,'Cost Margin'!$D23))) -> 0 | F37: =IF(F15=0,0,IF('Cost Margin'!$K23<>"",'Cost Margin'!$K23*F15/'Cost Margin'!$J23,F15*Settings!$B$3*IF('Cost Margin'!$D23="",1,'Cost Margin'!$D23))) -> 0 | G37: =IF(G15=0,0,IF('Cost Margin'!$K23<>"",'Cost Margin'!$K23*G15/'Cost Margin'!$J23,G15*Settings!$B$3*IF('Cost Margin'!$D23="",1,'Cost Margin'!$D23))) -> 0 | H37: =IF(H15=0,0,IF('Cost Margin'!$K23<>"",'Cost Margin'!$K23*H15/'Cost Margin'!$J23,H15*Settings!$B$3*IF('Cost Margin'!$D23="",1,'Cost Margin'!$D23))) -> 0 | I37: =IF(I15=0,0,IF('Cost Margin'!$K23<>"",'Cost Margin'!$K23*I15/'Cost Margin'!$J23,I15*Settings!$B$3*IF('Cost Margin'!$D23="",1,'Cost Margin'!$D23))) -> 0 | J37: =IF(J15=0,0,IF('Cost Margin'!$K23<>"",'Cost Margin'!$K23*J15/'Cost Margin'!$J23,J15*Settings!$B$3*IF('Cost Margin'!$D23="",1,'Cost Margin'!$D23))) -> 0 | ... Z37: =IF(Z15=0,0,IF('Cost Margin'!$K23<>"",'Cost Margin'!$K23*Z15/'Cost Margin'!$J23,Z15*Settings!$B$3*IF('Cost Margin'!$D23="",1,'Cost Margin'!$D23))) -> 0
A38: 8 | B38: =IF('Cost Margin'!A24="","",'Cost Margin'!A24) | C38: =IF(C16=0,0,IF('Cost Margin'!$K24<>"",'Cost Margin'!$K24*C16/'Cost Margin'!$J24,C16*Settings!$B$3*IF('Cost Margin'!$D24="",1,'Cost Margin'!$D24))) -> 0 | D38: =IF(D16=0,0,IF('Cost Margin'!$K24<>"",'Cost Margin'!$K24*D16/'Cost Margin'!$J24,D16*Settings!$B$3*IF('Cost Margin'!$D24="",1,'Cost Margin'!$D24))) -> 0 | E38: =IF(E16=0,0,IF('Cost Margin'!$K24<>"",'Cost Margin'!$K24*E16/'Cost Margin'!$J24,E16*Settings!$B$3*IF('Cost Margin'!$D24="",1,'Cost Margin'!$D24))) -> 0 | F38: =IF(F16=0,0,IF('Cost Margin'!$K24<>"",'Cost Margin'!$K24*F16/'Cost Margin'!$J24,F16*Settings!$B$3*IF('Cost Margin'!$D24="",1,'Cost Margin'!$D24))) -> 0 | G38: =IF(G16=0,0,IF('Cost Margin'!$K24<>"",'Cost Margin'!$K24*G16/'Cost Margin'!$J24,G16*Settings!$B$3*IF('Cost Margin'!$D24="",1,'Cost Margin'!$D24))) -> 0 | H38: =IF(H16=0,0,IF('Cost Margin'!$K24<>"",'Cost Margin'!$K24*H16/'Cost Margin'!$J24,H16*Settings!$B$3*IF('Cost Margin'!$D24="",1,'Cost Margin'!$D24))) -> 0 | I38: =IF(I16=0,0,IF('Cost Margin'!$K24<>"",'Cost Margin'!$K24*I16/'Cost Margin'!$J24,I16*Settings!$B$3*IF('Cost Margin'!$D24="",1,'Cost Margin'!$D24))) -> 0 | J38: =IF(J16=0,0,IF('Cost Margin'!$K24<>"",'Cost Margin'!$K24*J16/'Cost Margin'!$J24,J16*Settings!$B$3*IF('Cost Margin'!$D24="",1,'Cost Margin'!$D24))) -> 0 | ... Z38: =IF(Z16=0,0,IF('Cost Margin'!$K24<>"",'Cost Margin'!$K24*Z16/'Cost Margin'!$J24,Z16*Settings!$B$3*IF('Cost Margin'!$D24="",1,'Cost Margin'!$D24))) -> 0
A39: 9 | B39: =IF('Cost Margin'!A25="","",'Cost Margin'!A25) | C39: =IF(C17=0,0,IF('Cost Margin'!$K25<>"",'Cost Margin'!$K25*C17/'Cost Margin'!$J25,C17*Settings!$B$3*IF('Cost Margin'!$D25="",1,'Cost Margin'!$D25))) -> 0 | D39: =IF(D17=0,0,IF('Cost Margin'!$K25<>"",'Cost Margin'!$K25*D17/'Cost Margin'!$J25,D17*Settings!$B$3*IF('Cost Margin'!$D25="",1,'Cost Margin'!$D25))) -> 0 | E39: =IF(E17=0,0,IF('Cost Margin'!$K25<>"",'Cost Margin'!$K25*E17/'Cost Margin'!$J25,E17*Settings!$B$3*IF('Cost Margin'!$D25="",1,'Cost Margin'!$D25))) -> 0 | F39: =IF(F17=0,0,IF('Cost Margin'!$K25<>"",'Cost Margin'!$K25*F17/'Cost Margin'!$J25,F17*Settings!$B$3*IF('Cost Margin'!$D25="",1,'Cost Margin'!$D25))) -> 0 | G39: =IF(G17=0,0,IF('Cost Margin'!$K25<>"",'Cost Margin'!$K25*G17/'Cost Margin'!$J25,G17*Settings!$B$3*IF('Cost Margin'!$D25="",1,'Cost Margin'!$D25))) -> 0 | H39: =IF(H17=0,0,IF('Cost Margin'!$K25<>"",'Cost Margin'!$K25*H17/'Cost Margin'!$J25,H17*Settings!$B$3*IF('Cost Margin'!$D25="",1,'Cost Margin'!$D25))) -> 0 | I39: =IF(I17=0,0,IF('Cost Margin'!$K25<>"",'Cost Margin'!$K25*I17/'Cost Margin'!$J25,I17*Settings!$B$3*IF('Cost Margin'!$D25="",1,'Cost Margin'!$D25))) -> 0 | J39: =IF(J17=0,0,IF('Cost Margin'!$K25<>"",'Cost Margin'!$K25*J17/'Cost Margin'!$J25,J17*Settings!$B$3*IF('Cost Margin'!$D25="",1,'Cost Margin'!$D25))) -> 0 | ... Z39: =IF(Z17=0,0,IF('Cost Margin'!$K25<>"",'Cost Margin'!$K25*Z17/'Cost Margin'!$J25,Z17*Settings!$B$3*IF('Cost Margin'!$D25="",1,'Cost Margin'!$D25))) -> 0
A40: 10 | B40: =IF('Cost Margin'!A26="","",'Cost Margin'!A26) | C40: =IF(C18=0,0,IF('Cost Margin'!$K26<>"",'Cost Margin'!$K26*C18/'Cost Margin'!$J26,C18*Settings!$B$3*IF('Cost Margin'!$D26="",1,'Cost Margin'!$D26))) -> 0 | D40: =IF(D18=0,0,IF('Cost Margin'!$K26<>"",'Cost Margin'!$K26*D18/'Cost Margin'!$J26,D18*Settings!$B$3*IF('Cost Margin'!$D26="",1,'Cost Margin'!$D26))) -> 0 | E40: =IF(E18=0,0,IF('Cost Margin'!$K26<>"",'Cost Margin'!$K26*E18/'Cost Margin'!$J26,E18*Settings!$B$3*IF('Cost Margin'!$D26="",1,'Cost Margin'!$D26))) -> 0 | F40: =IF(F18=0,0,IF('Cost Margin'!$K26<>"",'Cost Margin'!$K26*F18/'Cost Margin'!$J26,F18*Settings!$B$3*IF('Cost Margin'!$D26="",1,'Cost Margin'!$D26))) -> 0 | G40: =IF(G18=0,0,IF('Cost Margin'!$K26<>"",'Cost Margin'!$K26*G18/'Cost Margin'!$J26,G18*Settings!$B$3*IF('Cost Margin'!$D26="",1,'Cost Margin'!$D26))) -> 0 | H40: =IF(H18=0,0,IF('Cost Margin'!$K26<>"",'Cost Margin'!$K26*H18/'Cost Margin'!$J26,H18*Settings!$B$3*IF('Cost Margin'!$D26="",1,'Cost Margin'!$D26))) -> 0 | I40: =IF(I18=0,0,IF('Cost Margin'!$K26<>"",'Cost Margin'!$K26*I18/'Cost Margin'!$J26,I18*Settings!$B$3*IF('Cost Margin'!$D26="",1,'Cost Margin'!$D26))) -> 0 | J40: =IF(J18=0,0,IF('Cost Margin'!$K26<>"",'Cost Margin'!$K26*J18/'Cost Margin'!$J26,J18*Settings!$B$3*IF('Cost Margin'!$D26="",1,'Cost Margin'!$D26))) -> 0 | ... Z40: =IF(Z18=0,0,IF('Cost Margin'!$K26<>"",'Cost Margin'!$K26*Z18/'Cost Margin'!$J26,Z18*Settings!$B$3*IF('Cost Margin'!$D26="",1,'Cost Margin'!$D26))) -> 0
A41: 11 | B41: =IF('Cost Margin'!A27="","",'Cost Margin'!A27) | C41: =IF(C19=0,0,IF('Cost Margin'!$K27<>"",'Cost Margin'!$K27*C19/'Cost Margin'!$J27,C19*Settings!$B$3*IF('Cost Margin'!$D27="",1,'Cost Margin'!$D27))) -> 0 | D41: =IF(D19=0,0,IF('Cost Margin'!$K27<>"",'Cost Margin'!$K27*D19/'Cost Margin'!$J27,D19*Settings!$B$3*IF('Cost Margin'!$D27="",1,'Cost Margin'!$D27))) -> 0 | E41: =IF(E19=0,0,IF('Cost Margin'!$K27<>"",'Cost Margin'!$K27*E19/'Cost Margin'!$J27,E19*Settings!$B$3*IF('Cost Margin'!$D27="",1,'Cost Margin'!$D27))) -> 0 | F41: =IF(F19=0,0,IF('Cost Margin'!$K27<>"",'Cost Margin'!$K27*F19/'Cost Margin'!$J27,F19*Settings!$B$3*IF('Cost Margin'!$D27="",1,'Cost Margin'!$D27))) -> 0 | G41: =IF(G19=0,0,IF('Cost Margin'!$K27<>"",'Cost Margin'!$K27*G19/'Cost Margin'!$J27,G19*Settings!$B$3*IF('Cost Margin'!$D27="",1,'Cost Margin'!$D27))) -> 0 | H41: =IF(H19=0,0,IF('Cost Margin'!$K27<>"",'Cost Margin'!$K27*H19/'Cost Margin'!$J27,H19*Settings!$B$3*IF('Cost Margin'!$D27="",1,'Cost Margin'!$D27))) -> 0 | I41: =IF(I19=0,0,IF('Cost Margin'!$K27<>"",'Cost Margin'!$K27*I19/'Cost Margin'!$J27,I19*Settings!$B$3*IF('Cost Margin'!$D27="",1,'Cost Margin'!$D27))) -> 0 | J41: =IF(J19=0,0,IF('Cost Margin'!$K27<>"",'Cost Margin'!$K27*J19/'Cost Margin'!$J27,J19*Settings!$B$3*IF('Cost Margin'!$D27="",1,'Cost Margin'!$D27))) -> 0 | ... Z41: =IF(Z19=0,0,IF('Cost Margin'!$K27<>"",'Cost Margin'!$K27*Z19/'Cost Margin'!$J27,Z19*Settings!$B$3*IF('Cost Margin'!$D27="",1,'Cost Margin'!$D27))) -> 0
A42: 12 | B42: =IF('Cost Margin'!A28="","",'Cost Margin'!A28) | C42: =IF(C20=0,0,IF('Cost Margin'!$K28<>"",'Cost Margin'!$K28*C20/'Cost Margin'!$J28,C20*Settings!$B$3*IF('Cost Margin'!$D28="",1,'Cost Margin'!$D28))) -> 0 | D42: =IF(D20=0,0,IF('Cost Margin'!$K28<>"",'Cost Margin'!$K28*D20/'Cost Margin'!$J28,D20*Settings!$B$3*IF('Cost Margin'!$D28="",1,'Cost Margin'!$D28))) -> 0 | E42: =IF(E20=0,0,IF('Cost Margin'!$K28<>"",'Cost Margin'!$K28*E20/'Cost Margin'!$J28,E20*Settings!$B$3*IF('Cost Margin'!$D28="",1,'Cost Margin'!$D28))) -> 0 | F42: =IF(F20=0,0,IF('Cost Margin'!$K28<>"",'Cost Margin'!$K28*F20/'Cost Margin'!$J28,F20*Settings!$B$3*IF('Cost Margin'!$D28="",1,'Cost Margin'!$D28))) -> 0 | G42: =IF(G20=0,0,IF('Cost Margin'!$K28<>"",'Cost Margin'!$K28*G20/'Cost Margin'!$J28,G20*Settings!$B$3*IF('Cost Margin'!$D28="",1,'Cost Margin'!$D28))) -> 0 | H42: =IF(H20=0,0,IF('Cost Margin'!$K28<>"",'Cost Margin'!$K28*H20/'Cost Margin'!$J28,H20*Settings!$B$3*IF('Cost Margin'!$D28="",1,'Cost Margin'!$D28))) -> 0 | I42: =IF(I20=0,0,IF('Cost Margin'!$K28<>"",'Cost Margin'!$K28*I20/'Cost Margin'!$J28,I20*Settings!$B$3*IF('Cost Margin'!$D28="",1,'Cost Margin'!$D28))) -> 0 | J42: =IF(J20=0,0,IF('Cost Margin'!$K28<>"",'Cost Margin'!$K28*J20/'Cost Margin'!$J28,J20*Settings!$B$3*IF('Cost Margin'!$D28="",1,'Cost Margin'!$D28))) -> 0 | ... Z42: =IF(Z20=0,0,IF('Cost Margin'!$K28<>"",'Cost Margin'!$K28*Z20/'Cost Margin'!$J28,Z20*Settings!$B$3*IF('Cost Margin'!$D28="",1,'Cost Margin'!$D28))) -> 0
... A50: 20 | B50: =IF('Cost Margin'!A36="","",'Cost Margin'!A36) | C50: =IF(C28=0,0,IF('Cost Margin'!$K36<>"",'Cost Margin'!$K36*C28/'Cost Margin'!$J36,C28*Settings!$B$3*IF('Cost Margin'!$D36="",1,'Cost Margin'!$D36))) -> 0 | D50: =IF(D28=0,0,IF('Cost Margin'!$K36<>"",'Cost Margin'!$K36*D28/'Cost Margin'!$J36,D28*Settings!$B$3*IF('Cost Margin'!$D36="",1,'Cost Margin'!$D36))) -> 0 | E50: =IF(E28=0,0,IF('Cost Margin'!$K36<>"",'Cost Margin'!$K36*E28/'Cost Margin'!$J36,E28*Settings!$B$3*IF('Cost Margin'!$D36="",1,'Cost Margin'!$D36))) -> 0 | F50: =IF(F28=0,0,IF('Cost Margin'!$K36<>"",'Cost Margin'!$K36*F28/'Cost Margin'!$J36,F28*Settings!$B$3*IF('Cost Margin'!$D36="",1,'Cost Margin'!$D36))) -> 0 | G50: =IF(G28=0,0,IF('Cost Margin'!$K36<>"",'Cost Margin'!$K36*G28/'Cost Margin'!$J36,G28*Settings!$B$3*IF('Cost Margin'!$D36="",1,'Cost Margin'!$D36))) -> 0 | H50: =IF(H28=0,0,IF('Cost Margin'!$K36<>"",'Cost Margin'!$K36*H28/'Cost Margin'!$J36,H28*Settings!$B$3*IF('Cost Margin'!$D36="",1,'Cost Margin'!$D36))) -> 0 | I50: =IF(I28=0,0,IF('Cost Margin'!$K36<>"",'Cost Margin'!$K36*I28/'Cost Margin'!$J36,I28*Settings!$B$3*IF('Cost Margin'!$D36="",1,'Cost Margin'!$D36))) -> 0 | J50: =IF(J28=0,0,IF('Cost Margin'!$K36<>"",'Cost Margin'!$K36*J28/'Cost Margin'!$J36,J28*Settings!$B$3*IF('Cost Margin'!$D36="",1,'Cost Margin'!$D36))) -> 0 | ... Z50: =IF(Z28=0,0,IF('Cost Margin'!$K36<>"",'Cost Margin'!$K36*Z28/'Cost Margin'!$J36,Z28*Settings!$B$3*IF('Cost Margin'!$D36="",1,'Cost Margin'!$D36))) -> 0
A52: Monthly P&L
B53: People on project | C53: =IF(C$5="","",COUNTIF(C31:C50,">0")) -> 2 | D53: =IF(D$5="","",COUNTIF(D31:D50,">0")) -> 2 | E53: =IF(E$5="","",COUNTIF(E31:E50,">0")) | F53: =IF(F$5="","",COUNTIF(F31:F50,">0")) | G53: =IF(G$5="","",COUNTIF(G31:G50,">0")) | H53: =IF(H$5="","",COUNTIF(H31:H50,">0")) | I53: =IF(I$5="","",COUNTIF(I31:I50,">0")) | J53: =IF(J$5="","",COUNTIF(J31:J50,">0")) | ... Z53: =IF(Z$5="","",COUNTIF(Z31:Z50,">0")) | AA53: =MAX(C53:Z53) -> 2
B54: Hours | C54: =IF(C$5="","",SUM(C31:C50)) -> 178.56 | D54: =IF(D$5="","",SUM(D31:D50)) -> 29.76 | E54: =IF(E$5="","",SUM(E31:E50)) | F54: =IF(F$5="","",SUM(F31:F50)) | G54: =IF(G$5="","",SUM(G31:G50)) | H54: =IF(H$5="","",SUM(H31:H50)) | I54: =IF(I$5="","",SUM(I31:I50)) | J54: =IF(J$5="","",SUM(J31:J50)) | ... Z54: =IF(Z$5="","",SUM(Z31:Z50)) | AA54: =SUM(C54:Z54) -> 208.32
B55: Labour cost (loaded, incl. burden) | C55: =IF(C$5="","",SUMPRODUCT(C31:C50,'Cost Margin'!$G$17:$G$36,1+'Cost Margin'!$L$17:$L$36)) -> 26193.605 | D55: =IF(D$5="","",SUMPRODUCT(D31:D50,'Cost Margin'!$G$17:$G$36,1+'Cost Margin'!$L$17:$L$36)) -> 4365.6008 | E55: =IF(E$5="","",SUMPRODUCT(E31:E50,'Cost Margin'!$G$17:$G$36,1+'Cost Margin'!$L$17:$L$36)) | F55: =IF(F$5="","",SUMPRODUCT(F31:F50,'Cost Margin'!$G$17:$G$36,1+'Cost Margin'!$L$17:$L$36)) | G55: =IF(G$5="","",SUMPRODUCT(G31:G50,'Cost Margin'!$G$17:$G$36,1+'Cost Margin'!$L$17:$L$36)) | H55: =IF(H$5="","",SUMPRODUCT(H31:H50,'Cost Margin'!$G$17:$G$36,1+'Cost Margin'!$L$17:$L$36)) | I55: =IF(I$5="","",SUMPRODUCT(I31:I50,'Cost Margin'!$G$17:$G$36,1+'Cost Margin'!$L$17:$L$36)) | J55: =IF(J$5="","",SUMPRODUCT(J31:J50,'Cost Margin'!$G$17:$G$36,1+'Cost Margin'!$L$17:$L$36)) | ... Z55: =IF(Z$5="","",SUMPRODUCT(Z31:Z50,'Cost Margin'!$G$17:$G$36,1+'Cost Margin'!$L$17:$L$36)) | AA55: =SUM(C55:Z55) -> 30559.205
B56: Additional costs | C56: =IF(C$5="","",IF('Cost Margin'!$B$13<>"Y",0,C$4*SUMIFS('Cost Margin'!$D$41:$D$52,'Cost Margin'!$E$41:$E$52,"Monthly")+IF(0=0,SUMIFS('Cost Margin'!$D$41:$D$52,'Cost Margin'!$E$41:$E$52,"<>Monthly"),0))) -> 3000 | D56: =IF(D$5="","",IF('Cost Margin'!$B$13<>"Y",0,D$4*SUMIFS('Cost Margin'!$D$41:$D$52,'Cost Margin'!$E$41:$E$52,"Monthly")+IF(1=0,SUMIFS('Cost Margin'!$D$41:$D$52,'Cost Margin'!$E$41:$E$52,"<>Monthly"),0))) -> 0 | E56: =IF(E$5="","",IF('Cost Margin'!$B$13<>"Y",0,E$4*SUMIFS('Cost Margin'!$D$41:$D$52,'Cost Margin'!$E$41:$E$52,"Monthly")+IF(2=0,SUMIFS('Cost Margin'!$D$41:$D$52,'Cost Margin'!$E$41:$E$52,"<>Monthly"),0))) | F56: =IF(F$5="","",IF('Cost Margin'!$B$13<>"Y",0,F$4*SUMIFS('Cost Margin'!$D$41:$D$52,'Cost Margin'!$E$41:$E$52,"Monthly")+IF(3=0,SUMIFS('Cost Margin'!$D$41:$D$52,'Cost Margin'!$E$41:$E$52,"<>Monthly"),0))) | G56: =IF(G$5="","",IF('Cost Margin'!$B$13<>"Y",0,G$4*SUMIFS('Cost Margin'!$D$41:$D$52,'Cost Margin'!$E$41:$E$52,"Monthly")+IF(4=0,SUMIFS('Cost Margin'!$D$41:$D$52,'Cost Margin'!$E$41:$E$52,"<>Monthly"),0))) | H56: =IF(H$5="","",IF('Cost Margin'!$B$13<>"Y",0,H$4*SUMIFS('Cost Margin'!$D$41:$D$52,'Cost Margin'!$E$41:$E$52,"Monthly")+IF(5=0,SUMIFS('Cost Margin'!$D$41:$D$52,'Cost Margin'!$E$41:$E$52,"<>Monthly"),0))) | I56: =IF(I$5="","",IF('Cost Margin'!$B$13<>"Y",0,I$4*SUMIFS('Cost Margin'!$D$41:$D$52,'Cost Margin'!$E$41:$E$52,"Monthly")+IF(6=0,SUMIFS('Cost Margin'!$D$41:$D$52,'Cost Margin'!$E$41:$E$52,"<>Monthly"),0))) | J56: =IF(J$5="","",IF('Cost Margin'!$B$13<>"Y",0,J$4*SUMIFS('Cost Margin'!$D$41:$D$52,'Cost Margin'!$E$41:$E$52,"Monthly")+IF(7=0,SUMIFS('Cost Margin'!$D$41:$D$52,'Cost Margin'!$E$41:$E$52,"<>Monthly"),0))) | K56: =IF(K$5="","",IF('Cost Margin'!$B$13<>"Y",0,K$4*SUMIFS('Cost Margin'!$D$41:$D$52,'Cost Margin'!$E$41:$E$52,"Monthly")+IF(8=0,SUMIFS('Cost Margin'!$D$41:$D$52,'Cost Margin'!$E$41:$E$52,"<>Monthly"),0))) | L56: =IF(L$5="","",IF('Cost Margin'!$B$13<>"Y",0,L$4*SUMIFS('Cost Margin'!$D$41:$D$52,'Cost Margin'!$E$41:$E$52,"Monthly")+IF(9=0,SUMIFS('Cost Margin'!$D$41:$D$52,'Cost Margin'!$E$41:$E$52,"<>Monthly"),0))) | M56: =IF(M$5="","",IF('Cost Margin'!$B$13<>"Y",0,M$4*SUMIFS('Cost Margin'!$D$41:$D$52,'Cost Margin'!$E$41:$E$52,"Monthly")+IF(10=0,SUMIFS('Cost Margin'!$D$41:$D$52,'Cost Margin'!$E$41:$E$52,"<>Monthly"),0))) | N56: =IF(N$5="","",IF('Cost Margin'!$B$13<>"Y",0,N$4*SUMIFS('Cost Margin'!$D$41:$D$52,'Cost Margin'!$E$41:$E$52,"Monthly")+IF(11=0,SUMIFS('Cost Margin'!$D$41:$D$52,'Cost Margin'!$E$41:$E$52,"<>Monthly"),0))) | O56: =IF(O$5="","",IF('Cost Margin'!$B$13<>"Y",0,O$4*SUMIFS('Cost Margin'!$D$41:$D$52,'Cost Margin'!$E$41:$E$52,"Monthly")+IF(12=0,SUMIFS('Cost Margin'!$D$41:$D$52,'Cost Margin'!$E$41:$E$52,"<>Monthly"),0))) | P56: =IF(P$5="","",IF('Cost Margin'!$B$13<>"Y",0,P$4*SUMIFS('Cost Margin'!$D$41:$D$52,'Cost Margin'!$E$41:$E$52,"Monthly")+IF(13=0,SUMIFS('Cost Margin'!$D$41:$D$52,'Cost Margin'!$E$41:$E$52,"<>Monthly"),0))) | Q56: =IF(Q$5="","",IF('Cost Margin'!$B$13<>"Y",0,Q$4*SUMIFS('Cost Margin'!$D$41:$D$52,'Cost Margin'!$E$41:$E$52,"Monthly")+IF(14=0,SUMIFS('Cost Margin'!$D$41:$D$52,'Cost Margin'!$E$41:$E$52,"<>Monthly"),0))) | R56: =IF(R$5="","",IF('Cost Margin'!$B$13<>"Y",0,R$4*SUMIFS('Cost Margin'!$D$41:$D$52,'Cost Margin'!$E$41:$E$52,"Monthly")+IF(15=0,SUMIFS('Cost Margin'!$D$41:$D$52,'Cost Margin'!$E$41:$E$52,"<>Monthly"),0))) | S56: =IF(S$5="","",IF('Cost Margin'!$B$13<>"Y",0,S$4*SUMIFS('Cost Margin'!$D$41:$D$52,'Cost Margin'!$E$41:$E$52,"Monthly")+IF(16=0,SUMIFS('Cost Margin'!$D$41:$D$52,'Cost Margin'!$E$41:$E$52,"<>Monthly"),0))) | T56: =IF(T$5="","",IF('Cost Margin'!$B$13<>"Y",0,T$4*SUMIFS('Cost Margin'!$D$41:$D$52,'Cost Margin'!$E$41:$E$52,"Monthly")+IF(17=0,SUMIFS('Cost Margin'!$D$41:$D$52,'Cost Margin'!$E$41:$E$52,"<>Monthly"),0))) | U56: =IF(U$5="","",IF('Cost Margin'!$B$13<>"Y",0,U$4*SUMIFS('Cost Margin'!$D$41:$D$52,'Cost Margin'!$E$41:$E$52,"Monthly")+IF(18=0,SUMIFS('Cost Margin'!$D$41:$D$52,'Cost Margin'!$E$41:$E$52,"<>Monthly"),0))) | V56: =IF(V$5="","",IF('Cost Margin'!$B$13<>"Y",0,V$4*SUMIFS('Cost Margin'!$D$41:$D$52,'Cost Margin'!$E$41:$E$52,"Monthly")+IF(19=0,SUMIFS('Cost Margin'!$D$41:$D$52,'Cost Margin'!$E$41:$E$52,"<>Monthly"),0))) | W56: =IF(W$5="","",IF('Cost Margin'!$B$13<>"Y",0,W$4*SUMIFS('Cost Margin'!$D$41:$D$52,'Cost Margin'!$E$41:$E$52,"Monthly")+IF(20=0,SUMIFS('Cost Margin'!$D$41:$D$52,'Cost Margin'!$E$41:$E$52,"<>Monthly"),0))) | X56: =IF(X$5="","",IF('Cost Margin'!$B$13<>"Y",0,X$4*SUMIFS('Cost Margin'!$D$41:$D$52,'Cost Margin'!$E$41:$E$52,"Monthly")+IF(21=0,SUMIFS('Cost Margin'!$D$41:$D$52,'Cost Margin'!$E$41:$E$52,"<>Monthly"),0))) | Y56: =IF(Y$5="","",IF('Cost Margin'!$B$13<>"Y",0,Y$4*SUMIFS('Cost Margin'!$D$41:$D$52,'Cost Margin'!$E$41:$E$52,"Monthly")+IF(22=0,SUMIFS('Cost Margin'!$D$41:$D$52,'Cost Margin'!$E$41:$E$52,"<>Monthly"),0))) | Z56: =IF(Z$5="","",IF('Cost Margin'!$B$13<>"Y",0,Z$4*SUMIFS('Cost Margin'!$D$41:$D$52,'Cost Margin'!$E$41:$E$52,"Monthly")+IF(23=0,SUMIFS('Cost Margin'!$D$41:$D$52,'Cost Margin'!$E$41:$E$52,"<>Monthly"),0))) | AA56: =SUM(C56:Z56) -> 3000
B57: Total cost | C57: =IF(C$5="","",C55+C56) -> 29193.605 | D57: =IF(D$5="","",D55+D56) -> 4365.6008 | E57: =IF(E$5="","",E55+E56) | F57: =IF(F$5="","",F55+F56) | G57: =IF(G$5="","",G55+G56) | H57: =IF(H$5="","",H55+H56) | I57: =IF(I$5="","",I55+I56) | J57: =IF(J$5="","",J55+J56) | ... Z57: =IF(Z$5="","",Z55+Z56) | AA57: =SUM(C57:Z57) -> 33559.205
B58: Revenue | C58: =IF(C$5="","",IF('Cost Margin'!$B$4="MSP",IF('Cost Margin'!$B$12="",0,'Cost Margin'!$B$12*C$4),IF('Cost Margin'!$B$4="Time & materials",SUMPRODUCT(C31:C50,'Cost Margin'!$F$17:$F$36),IF(OR('Cost Margin'!$B$11="",'Cost Margin'!$B$10=""),0,'Cost Margin'!$B$11*C$4/'Cost Margin'!$B$10)))+IF('Cost Margin'!$B$13<>"Y",0,C$4*SUMIFS('Cost Margin'!$D$41:$D$52,'Cost Margin'!$E$41:$E$52,"Monthly",'Cost Margin'!$F$41:$F$52,"Y")+IF(0=0,SUMIFS('Cost Margin'!$D$41:$D$52,'Cost Margin'!$E$41:$E$52,"<>Monthly",'Cost Margin'!$F$41:$F$52,"Y"),0))) -> 41610.738 | D58: =IF(D$5="","",IF('Cost Margin'!$B$4="MSP",IF('Cost Margin'!$B$12="",0,'Cost Margin'!$B$12*D$4),IF('Cost Margin'!$B$4="Time & materials",SUMPRODUCT(D31:D50,'Cost Margin'!$F$17:$F$36),IF(OR('Cost Margin'!$B$11="",'Cost Margin'!$B$10=""),0,'Cost Margin'!$B$11*D$4/'Cost Margin'!$B$10)))+IF('Cost Margin'!$B$13<>"Y",0,D$4*SUMIFS('Cost Margin'!$D$41:$D$52,'Cost Margin'!$E$41:$E$52,"Monthly",'Cost Margin'!$F$41:$F$52,"Y")+IF(1=0,SUMIFS('Cost Margin'!$D$41:$D$52,'Cost Margin'!$E$41:$E$52,"<>Monthly",'Cost Margin'!$F$41:$F$52,"Y"),0))) -> 8389.2617 | E58: =IF(E$5="","",IF('Cost Margin'!$B$4="MSP",IF('Cost Margin'!$B$12="",0,'Cost Margin'!$B$12*E$4),IF('Cost Margin'!$B$4="Time & materials",SUMPRODUCT(E31:E50,'Cost Margin'!$F$17:$F$36),IF(OR('Cost Margin'!$B$11="",'Cost Margin'!$B$10=""),0,'Cost Margin'!$B$11*E$4/'Cost Margin'!$B$10)))+IF('Cost Margin'!$B$13<>"Y",0,E$4*SUMIFS('Cost Margin'!$D$41:$D$52,'Cost Margin'!$E$41:$E$52,"Monthly",'Cost Margin'!$F$41:$F$52,"Y")+IF(2=0,SUMIFS('Cost Margin'!$D$41:$D$52,'Cost Margin'!$E$41:$E$52,"<>Monthly",'Cost Margin'!$F$41:$F$52,"Y"),0))) | F58: =IF(F$5="","",IF('Cost Margin'!$B$4="MSP",IF('Cost Margin'!$B$12="",0,'Cost Margin'!$B$12*F$4),IF('Cost Margin'!$B$4="Time & materials",SUMPRODUCT(F31:F50,'Cost Margin'!$F$17:$F$36),IF(OR('Cost Margin'!$B$11="",'Cost Margin'!$B$10=""),0,'Cost Margin'!$B$11*F$4/'Cost Margin'!$B$10)))+IF('Cost Margin'!$B$13<>"Y",0,F$4*SUMIFS('Cost Margin'!$D$41:$D$52,'Cost Margin'!$E$41:$E$52,"Monthly",'Cost Margin'!$F$41:$F$52,"Y")+IF(3=0,SUMIFS('Cost Margin'!$D$41:$D$52,'Cost Margin'!$E$41:$E$52,"<>Monthly",'Cost Margin'!$F$41:$F$52,"Y"),0))) | G58: =IF(G$5="","",IF('Cost Margin'!$B$4="MSP",IF('Cost Margin'!$B$12="",0,'Cost Margin'!$B$12*G$4),IF('Cost Margin'!$B$4="Time & materials",SUMPRODUCT(G31:G50,'Cost Margin'!$F$17:$F$36),IF(OR('Cost Margin'!$B$11="",'Cost Margin'!$B$10=""),0,'Cost Margin'!$B$11*G$4/'Cost Margin'!$B$10)))+IF('Cost Margin'!$B$13<>"Y",0,G$4*SUMIFS('Cost Margin'!$D$41:$D$52,'Cost Margin'!$E$41:$E$52,"Monthly",'Cost Margin'!$F$41:$F$52,"Y")+IF(4=0,SUMIFS('Cost Margin'!$D$41:$D$52,'Cost Margin'!$E$41:$E$52,"<>Monthly",'Cost Margin'!$F$41:$F$52,"Y"),0))) | H58: =IF(H$5="","",IF('Cost Margin'!$B$4="MSP",IF('Cost Margin'!$B$12="",0,'Cost Margin'!$B$12*H$4),IF('Cost Margin'!$B$4="Time & materials",SUMPRODUCT(H31:H50,'Cost Margin'!$F$17:$F$36),IF(OR('Cost Margin'!$B$11="",'Cost Margin'!$B$10=""),0,'Cost Margin'!$B$11*H$4/'Cost Margin'!$B$10)))+IF('Cost Margin'!$B$13<>"Y",0,H$4*SUMIFS('Cost Margin'!$D$41:$D$52,'Cost Margin'!$E$41:$E$52,"Monthly",'Cost Margin'!$F$41:$F$52,"Y")+IF(5=0,SUMIFS('Cost Margin'!$D$41:$D$52,'Cost Margin'!$E$41:$E$52,"<>Monthly",'Cost Margin'!$F$41:$F$52,"Y"),0))) | I58: =IF(I$5="","",IF('Cost Margin'!$B$4="MSP",IF('Cost Margin'!$B$12="",0,'Cost Margin'!$B$12*I$4),IF('Cost Margin'!$B$4="Time & materials",SUMPRODUCT(I31:I50,'Cost Margin'!$F$17:$F$36),IF(OR('Cost Margin'!$B$11="",'Cost Margin'!$B$10=""),0,'Cost Margin'!$B$11*I$4/'Cost Margin'!$B$10)))+IF('Cost Margin'!$B$13<>"Y",0,I$4*SUMIFS('Cost Margin'!$D$41:$D$52,'Cost Margin'!$E$41:$E$52,"Monthly",'Cost Margin'!$F$41:$F$52,"Y")+IF(6=0,SUMIFS('Cost Margin'!$D$41:$D$52,'Cost Margin'!$E$41:$E$52,"<>Monthly",'Cost Margin'!$F$41:$F$52,"Y"),0))) | J58: =IF(J$5="","",IF('Cost Margin'!$B$4="MSP",IF('Cost Margin'!$B$12="",0,'Cost Margin'!$B$12*J$4),IF('Cost Margin'!$B$4="Time & materials",SUMPRODUCT(J31:J50,'Cost Margin'!$F$17:$F$36),IF(OR('Cost Margin'!$B$11="",'Cost Margin'!$B$10=""),0,'Cost Margin'!$B$11*J$4/'Cost Margin'!$B$10)))+IF('Cost Margin'!$B$13<>"Y",0,J$4*SUMIFS('Cost Margin'!$D$41:$D$52,'Cost Margin'!$E$41:$E$52,"Monthly",'Cost Margin'!$F$41:$F$52,"Y")+IF(7=0,SUMIFS('Cost Margin'!$D$41:$D$52,'Cost Margin'!$E$41:$E$52,"<>Monthly",'Cost Margin'!$F$41:$F$52,"Y"),0))) | K58: =IF(K$5="","",IF('Cost Margin'!$B$4="MSP",IF('Cost Margin'!$B$12="",0,'Cost Margin'!$B$12*K$4),IF('Cost Margin'!$B$4="Time & materials",SUMPRODUCT(K31:K50,'Cost Margin'!$F$17:$F$36),IF(OR('Cost Margin'!$B$11="",'Cost Margin'!$B$10=""),0,'Cost Margin'!$B$11*K$4/'Cost Margin'!$B$10)))+IF('Cost Margin'!$B$13<>"Y",0,K$4*SUMIFS('Cost Margin'!$D$41:$D$52,'Cost Margin'!$E$41:$E$52,"Monthly",'Cost Margin'!$F$41:$F$52,"Y")+IF(8=0,SUMIFS('Cost Margin'!$D$41:$D$52,'Cost Margin'!$E$41:$E$52,"<>Monthly",'Cost Margin'!$F$41:$F$52,"Y"),0))) | L58: =IF(L$5="","",IF('Cost Margin'!$B$4="MSP",IF('Cost Margin'!$B$12="",0,'Cost Margin'!$B$12*L$4),IF('Cost Margin'!$B$4="Time & materials",SUMPRODUCT(L31:L50,'Cost Margin'!$F$17:$F$36),IF(OR('Cost Margin'!$B$11="",'Cost Margin'!$B$10=""),0,'Cost Margin'!$B$11*L$4/'Cost Margin'!$B$10)))+IF('Cost Margin'!$B$13<>"Y",0,L$4*SUMIFS('Cost Margin'!$D$41:$D$52,'Cost Margin'!$E$41:$E$52,"Monthly",'Cost Margin'!$F$41:$F$52,"Y")+IF(9=0,SUMIFS('Cost Margin'!$D$41:$D$52,'Cost Margin'!$E$41:$E$52,"<>Monthly",'Cost Margin'!$F$41:$F$52,"Y"),0))) | M58: =IF(M$5="","",IF('Cost Margin'!$B$4="MSP",IF('Cost Margin'!$B$12="",0,'Cost Margin'!$B$12*M$4),IF('Cost Margin'!$B$4="Time & materials",SUMPRODUCT(M31:M50,'Cost Margin'!$F$17:$F$36),IF(OR('Cost Margin'!$B$11="",'Cost Margin'!$B$10=""),0,'Cost Margin'!$B$11*M$4/'Cost Margin'!$B$10)))+IF('Cost Margin'!$B$13<>"Y",0,M$4*SUMIFS('Cost Margin'!$D$41:$D$52,'Cost Margin'!$E$41:$E$52,"Monthly",'Cost Margin'!$F$41:$F$52,"Y")+IF(10=0,SUMIFS('Cost Margin'!$D$41:$D$52,'Cost Margin'!$E$41:$E$52,"<>Monthly",'Cost Margin'!$F$41:$F$52,"Y"),0))) | N58: =IF(N$5="","",IF('Cost Margin'!$B$4="MSP",IF('Cost Margin'!$B$12="",0,'Cost Margin'!$B$12*N$4),IF('Cost Margin'!$B$4="Time & materials",SUMPRODUCT(N31:N50,'Cost Margin'!$F$17:$F$36),IF(OR('Cost Margin'!$B$11="",'Cost Margin'!$B$10=""),0,'Cost Margin'!$B$11*N$4/'Cost Margin'!$B$10)))+IF('Cost Margin'!$B$13<>"Y",0,N$4*SUMIFS('Cost Margin'!$D$41:$D$52,'Cost Margin'!$E$41:$E$52,"Monthly",'Cost Margin'!$F$41:$F$52,"Y")+IF(11=0,SUMIFS('Cost Margin'!$D$41:$D$52,'Cost Margin'!$E$41:$E$52,"<>Monthly",'Cost Margin'!$F$41:$F$52,"Y"),0))) | O58: =IF(O$5="","",IF('Cost Margin'!$B$4="MSP",IF('Cost Margin'!$B$12="",0,'Cost Margin'!$B$12*O$4),IF('Cost Margin'!$B$4="Time & materials",SUMPRODUCT(O31:O50,'Cost Margin'!$F$17:$F$36),IF(OR('Cost Margin'!$B$11="",'Cost Margin'!$B$10=""),0,'Cost Margin'!$B$11*O$4/'Cost Margin'!$B$10)))+IF('Cost Margin'!$B$13<>"Y",0,O$4*SUMIFS('Cost Margin'!$D$41:$D$52,'Cost Margin'!$E$41:$E$52,"Monthly",'Cost Margin'!$F$41:$F$52,"Y")+IF(12=0,SUMIFS('Cost Margin'!$D$41:$D$52,'Cost Margin'!$E$41:$E$52,"<>Monthly",'Cost Margin'!$F$41:$F$52,"Y"),0))) | P58: =IF(P$5="","",IF('Cost Margin'!$B$4="MSP",IF('Cost Margin'!$B$12="",0,'Cost Margin'!$B$12*P$4),IF('Cost Margin'!$B$4="Time & materials",SUMPRODUCT(P31:P50,'Cost Margin'!$F$17:$F$36),IF(OR('Cost Margin'!$B$11="",'Cost Margin'!$B$10=""),0,'Cost Margin'!$B$11*P$4/'Cost Margin'!$B$10)))+IF('Cost Margin'!$B$13<>"Y",0,P$4*SUMIFS('Cost Margin'!$D$41:$D$52,'Cost Margin'!$E$41:$E$52,"Monthly",'Cost Margin'!$F$41:$F$52,"Y")+IF(13=0,SUMIFS('Cost Margin'!$D$41:$D$52,'Cost Margin'!$E$41:$E$52,"<>Monthly",'Cost Margin'!$F$41:$F$52,"Y"),0))) | Q58: =IF(Q$5="","",IF('Cost Margin'!$B$4="MSP",IF('Cost Margin'!$B$12="",0,'Cost Margin'!$B$12*Q$4),IF('Cost Margin'!$B$4="Time & materials",SUMPRODUCT(Q31:Q50,'Cost Margin'!$F$17:$F$36),IF(OR('Cost Margin'!$B$11="",'Cost Margin'!$B$10=""),0,'Cost Margin'!$B$11*Q$4/'Cost Margin'!$B$10)))+IF('Cost Margin'!$B$13<>"Y",0,Q$4*SUMIFS('Cost Margin'!$D$41:$D$52,'Cost Margin'!$E$41:$E$52,"Monthly",'Cost Margin'!$F$41:$F$52,"Y")+IF(14=0,SUMIFS('Cost Margin'!$D$41:$D$52,'Cost Margin'!$E$41:$E$52,"<>Monthly",'Cost Margin'!$F$41:$F$52,"Y"),0))) | R58: =IF(R$5="","",IF('Cost Margin'!$B$4="MSP",IF('Cost Margin'!$B$12="",0,'Cost Margin'!$B$12*R$4),IF('Cost Margin'!$B$4="Time & materials",SUMPRODUCT(R31:R50,'Cost Margin'!$F$17:$F$36),IF(OR('Cost Margin'!$B$11="",'Cost Margin'!$B$10=""),0,'Cost Margin'!$B$11*R$4/'Cost Margin'!$B$10)))+IF('Cost Margin'!$B$13<>"Y",0,R$4*SUMIFS('Cost Margin'!$D$41:$D$52,'Cost Margin'!$E$41:$E$52,"Monthly",'Cost Margin'!$F$41:$F$52,"Y")+IF(15=0,SUMIFS('Cost Margin'!$D$41:$D$52,'Cost Margin'!$E$41:$E$52,"<>Monthly",'Cost Margin'!$F$41:$F$52,"Y"),0))) | S58: =IF(S$5="","",IF('Cost Margin'!$B$4="MSP",IF('Cost Margin'!$B$12="",0,'Cost Margin'!$B$12*S$4),IF('Cost Margin'!$B$4="Time & materials",SUMPRODUCT(S31:S50,'Cost Margin'!$F$17:$F$36),IF(OR('Cost Margin'!$B$11="",'Cost Margin'!$B$10=""),0,'Cost Margin'!$B$11*S$4/'Cost Margin'!$B$10)))+IF('Cost Margin'!$B$13<>"Y",0,S$4*SUMIFS('Cost Margin'!$D$41:$D$52,'Cost Margin'!$E$41:$E$52,"Monthly",'Cost Margin'!$F$41:$F$52,"Y")+IF(16=0,SUMIFS('Cost Margin'!$D$41:$D$52,'Cost Margin'!$E$41:$E$52,"<>Monthly",'Cost Margin'!$F$41:$F$52,"Y"),0))) | T58: =IF(T$5="","",IF('Cost Margin'!$B$4="MSP",IF('Cost Margin'!$B$12="",0,'Cost Margin'!$B$12*T$4),IF('Cost Margin'!$B$4="Time & materials",SUMPRODUCT(T31:T50,'Cost Margin'!$F$17:$F$36),IF(OR('Cost Margin'!$B$11="",'Cost Margin'!$B$10=""),0,'Cost Margin'!$B$11*T$4/'Cost Margin'!$B$10)))+IF('Cost Margin'!$B$13<>"Y",0,T$4*SUMIFS('Cost Margin'!$D$41:$D$52,'Cost Margin'!$E$41:$E$52,"Monthly",'Cost Margin'!$F$41:$F$52,"Y")+IF(17=0,SUMIFS('Cost Margin'!$D$41:$D$52,'Cost Margin'!$E$41:$E$52,"<>Monthly",'Cost Margin'!$F$41:$F$52,"Y"),0))) | U58: =IF(U$5="","",IF('Cost Margin'!$B$4="MSP",IF('Cost Margin'!$B$12="",0,'Cost Margin'!$B$12*U$4),IF('Cost Margin'!$B$4="Time & materials",SUMPRODUCT(U31:U50,'Cost Margin'!$F$17:$F$36),IF(OR('Cost Margin'!$B$11="",'Cost Margin'!$B$10=""),0,'Cost Margin'!$B$11*U$4/'Cost Margin'!$B$10)))+IF('Cost Margin'!$B$13<>"Y",0,U$4*SUMIFS('Cost Margin'!$D$41:$D$52,'Cost Margin'!$E$41:$E$52,"Monthly",'Cost Margin'!$F$41:$F$52,"Y")+IF(18=0,SUMIFS('Cost Margin'!$D$41:$D$52,'Cost Margin'!$E$41:$E$52,"<>Monthly",'Cost Margin'!$F$41:$F$52,"Y"),0))) | V58: =IF(V$5="","",IF('Cost Margin'!$B$4="MSP",IF('Cost Margin'!$B$12="",0,'Cost Margin'!$B$12*V$4),IF('Cost Margin'!$B$4="Time & materials",SUMPRODUCT(V31:V50,'Cost Margin'!$F$17:$F$36),IF(OR('Cost Margin'!$B$11="",'Cost Margin'!$B$10=""),0,'Cost Margin'!$B$11*V$4/'Cost Margin'!$B$10)))+IF('Cost Margin'!$B$13<>"Y",0,V$4*SUMIFS('Cost Margin'!$D$41:$D$52,'Cost Margin'!$E$41:$E$52,"Monthly",'Cost Margin'!$F$41:$F$52,"Y")+IF(19=0,SUMIFS('Cost Margin'!$D$41:$D$52,'Cost Margin'!$E$41:$E$52,"<>Monthly",'Cost Margin'!$F$41:$F$52,"Y"),0))) | W58: =IF(W$5="","",IF('Cost Margin'!$B$4="MSP",IF('Cost Margin'!$B$12="",0,'Cost Margin'!$B$12*W$4),IF('Cost Margin'!$B$4="Time & materials",SUMPRODUCT(W31:W50,'Cost Margin'!$F$17:$F$36),IF(OR('Cost Margin'!$B$11="",'Cost Margin'!$B$10=""),0,'Cost Margin'!$B$11*W$4/'Cost Margin'!$B$10)))+IF('Cost Margin'!$B$13<>"Y",0,W$4*SUMIFS('Cost Margin'!$D$41:$D$52,'Cost Margin'!$E$41:$E$52,"Monthly",'Cost Margin'!$F$41:$F$52,"Y")+IF(20=0,SUMIFS('Cost Margin'!$D$41:$D$52,'Cost Margin'!$E$41:$E$52,"<>Monthly",'Cost Margin'!$F$41:$F$52,"Y"),0))) | X58: =IF(X$5="","",IF('Cost Margin'!$B$4="MSP",IF('Cost Margin'!$B$12="",0,'Cost Margin'!$B$12*X$4),IF('Cost Margin'!$B$4="Time & materials",SUMPRODUCT(X31:X50,'Cost Margin'!$F$17:$F$36),IF(OR('Cost Margin'!$B$11="",'Cost Margin'!$B$10=""),0,'Cost Margin'!$B$11*X$4/'Cost Margin'!$B$10)))+IF('Cost Margin'!$B$13<>"Y",0,X$4*SUMIFS('Cost Margin'!$D$41:$D$52,'Cost Margin'!$E$41:$E$52,"Monthly",'Cost Margin'!$F$41:$F$52,"Y")+IF(21=0,SUMIFS('Cost Margin'!$D$41:$D$52,'Cost Margin'!$E$41:$E$52,"<>Monthly",'Cost Margin'!$F$41:$F$52,"Y"),0))) | Y58: =IF(Y$5="","",IF('Cost Margin'!$B$4="MSP",IF('Cost Margin'!$B$12="",0,'Cost Margin'!$B$12*Y$4),IF('Cost Margin'!$B$4="Time & materials",SUMPRODUCT(Y31:Y50,'Cost Margin'!$F$17:$F$36),IF(OR('Cost Margin'!$B$11="",'Cost Margin'!$B$10=""),0,'Cost Margin'!$B$11*Y$4/'Cost Margin'!$B$10)))+IF('Cost Margin'!$B$13<>"Y",0,Y$4*SUMIFS('Cost Margin'!$D$41:$D$52,'Cost Margin'!$E$41:$E$52,"Monthly",'Cost Margin'!$F$41:$F$52,"Y")+IF(22=0,SUMIFS('Cost Margin'!$D$41:$D$52,'Cost Margin'!$E$41:$E$52,"<>Monthly",'Cost Margin'!$F$41:$F$52,"Y"),0))) | Z58: =IF(Z$5="","",IF('Cost Margin'!$B$4="MSP",IF('Cost Margin'!$B$12="",0,'Cost Margin'!$B$12*Z$4),IF('Cost Margin'!$B$4="Time & materials",SUMPRODUCT(Z31:Z50,'Cost Margin'!$F$17:$F$36),IF(OR('Cost Margin'!$B$11="",'Cost Margin'!$B$10=""),0,'Cost Margin'!$B$11*Z$4/'Cost Margin'!$B$10)))+IF('Cost Margin'!$B$13<>"Y",0,Z$4*SUMIFS('Cost Margin'!$D$41:$D$52,'Cost Margin'!$E$41:$E$52,"Monthly",'Cost Margin'!$F$41:$F$52,"Y")+IF(23=0,SUMIFS('Cost Margin'!$D$41:$D$52,'Cost Margin'!$E$41:$E$52,"<>Monthly",'Cost Margin'!$F$41:$F$52,"Y"),0))) | AA58: =SUM(C58:Z58) -> 50000
B59: Gross margin $ | C59: =IF(C$5="","",C58-C57) -> 12417.134 | D59: =IF(D$5="","",D58-D57) -> 4023.661 | E59: =IF(E$5="","",E58-E57) | F59: =IF(F$5="","",F58-F57) | G59: =IF(G$5="","",G58-G57) | H59: =IF(H$5="","",H58-H57) | I59: =IF(I$5="","",I58-I57) | J59: =IF(J$5="","",J58-J57) | ... Z59: =IF(Z$5="","",Z58-Z57) | AA59: =SUM(C59:Z59) -> 16440.795
B60: Gross margin % | C60: =IF(OR(C$5="",C58=0),"",C59/C58) -> 0.29841176 | D60: =IF(OR(D$5="",D58=0),"",D59/D58) -> 0.47962039 | E60: =IF(OR(E$5="",E58=0),"",E59/E58) | F60: =IF(OR(F$5="",F58=0),"",F59/F58) | G60: =IF(OR(G$5="",G58=0),"",G59/G58) | H60: =IF(OR(H$5="",H58=0),"",H59/H58) | I60: =IF(OR(I$5="",I58=0),"",I59/I58) | J60: =IF(OR(J$5="",J58=0),"",J59/J58) | ... Z60: =IF(OR(Z$5="",Z58=0),"",Z59/Z58) | AA60: =IF(AA58=0,"",AA59/AA58) -> 0.32881589
B62: Check: project-total revenue and cost here should equal the Cost Margin summary. Difference → | C62: =IF('Cost Margin'!$T$8="","",AA58-'Cost Margin'!$T$8) -> 0 | D62: =IF('Cost Margin'!$T$8="","",AA57-'Cost Margin'!$T$12) -> 0 | E62: (revenue diff, cost diff — both should be 0; a non-zero cost diff means the project runs past 24 months)

Sheet Settings
A1: Settings
A3: Hours per working day | B3: 8 | C3: Hours = working days (Mon–Fri minus the location's holidays) × hours/day × utilization.
J4: Holidays by location — list weekday holidays; header must match the Location name
A5: Location | B5: Burden % | C5: Target GM % | D5: Note | F5: Seniority list | H5: Cost category list | P5: Cost rate card — OUR hourly cost per person, before burden (PLACEHOLDERS — set your real numbers)
A6: US | B6: 0.08 | C6: 0.35 | D6: Placeholder burden % — replace with your actual US uplift (benefits, payroll tax, overhead). | F6: Junior | H6: Travel | J6: =IF(A6="","",A6) -> US | K6: =IF(A7="","",A7) -> India | L6: =IF(A8="","",A8) | M6: =IF(A9="","",A9) | P6: Seniority | Q6: =IF(A6="","",A6) -> US | R6: =IF(A7="","",A7) -> India | S6: =IF(A8="","",A8) | T6: =IF(A9="","",A9)
A7: India | B7: 0.08 | C7: 0.5 | D7: Placeholder burden % — replace with your actual India uplift (PF, gratuity, insurance, overhead). | F7: Mid | H7: Lodging | J7: 46023 | K7: 46023 | P7: Junior | Q7: 60 | R7: 12
D8: Add a third location here; it appears in the dropdown and gets holiday column L. | F8: Senior | H8: Meals | J8: 46041 | K8: 46048 | P8: Mid | Q8: 80 | R8: 18
F9: Principal | H9: Software / licences | J9: 46069 | K9: 46249 | P9: Senior | Q9: 100 | R9: 25
H10: Hardware | J10: 46167 | K10: 46297 | P10: Principal | Q10: 130 | R10: 35
H11: Subcontractor | J11: 46192 | K11: 46381 | P11: A staffing row's cost/hour is pre-filled from here by Seniority × Location. Typing a value on the row overrides it.
H12: Miscellaneous | J12: 46206 | K12: 46388
J13: 46272 | K13: 46413
F14: Engagement types | J14: 46307 | K14: 46614
F15: Fixed cost | G15: Fixed cost / Assessment: one total price for the project. MSP: a fixed fee per month for the tenure. Time & materials: hours × bill rate. | J15: 46337 | K15: 46662
F16: Assessment | J16: 46352 | K16: 46746
F17: MSP | J17: 46381
F18: Time & materials | J18: 46388
J19: 46405
J20: 46433
J21: 46538
J22: 46556
J23: 46573
J24: 46636
J25: 46671
J26: 46702
J27: 46716
J28: 46745
J30: US = federal holidays 2026–27 (observed). India = national days only (Republic Day, Independence Day, Gandhi Jayanti, Jan 1, Dec 25); add Holi, Diwali and state/company days from your HR calendar.
