Workbook

Sheet Cost Margin
A1: Cost margin sheet
A2: Yellow = inputs (blue text). Grey = calculated. * = required. Pick the engagement type first — it decides how revenue is counted and which fields apply.
V3: Project summary
A4: Engagement type * (pick first) | C4: Fixed cost / Assessment → Total project price. MSP → Monthly fee. Time & materials / Staff augmentation → each row's bill rate. Fields not needed for the chosen type turn grey. | V4: Engagement type | W4: =IF(B4="","",B4)
A5: Project / engagement name | V5: Duration (months) | W5: =B10
A6: Client | V6: Project revenue | W6: =IF(B4="","",IF(B4="MSP",IF(OR(B12="",B10=""),"",B12*B10),IF(OR(B4="Time & materials",B4="Staff augmentation"),O37,IF(B11="","",B11))))
A7: Currency | B7: USD | V7: Pass-through expenses billed to client | W7: =H53 -> 0
A8: Project start * | C8: For Staff augmentation these are the forecast window; each resource's own dates default to them and can be changed. | V8: Total revenue | W8: =IF(W6="","",W6+W7)
A9: Project end * | V9: Labour cost | W9: =P37 -> 0
A10: Duration (months, partial months by days) | B10: =IF(OR(B8="",B9=""),"",SUM(Monthly!$C$4:$Z$4)) | C10: =IF(OR(B8="",B9=""),"",IF(B9<B8,"End is before start",DATEDIF(B8,B9+1,"M")&" month(s) "&DATEDIF(B8,B9+1,"MD")&" day(s) — "&(B9-B8+1)&" calendar days inclusive")) | V10: Burden cost | W10: =Q37 -> 0
A11: Total project price * (Fixed cost / Assessment) | C11: =IF(OR(B4="Fixed cost",B4="Assessment"),IF(B11="","← required for this engagement type",""),IF(B11="","","Not used for this engagement type")) | V11: Additional costs | W11: =G53 -> 0
A12: Monthly fee * (MSP) | C12: =IF(B4="MSP",IF(B12="","← required for MSP",""),IF(B12="","","Not used for this engagement type")) | V12: Total cost | W12: =W9+W10+W11 -> 0
A13: Additional costs on this project? * (Y/N) | C13: =IF(B13="","← required: Y if there are travel, licences, subcontractor or other costs; N if none","") -> ← required: Y if there are travel, licences, subcontractor or other costs; N if none | V13: Gross margin $ | W13: =IF(W8="","",W8-W12)
A14: Same start/end for every resource? * (Y/N) | C14: =IF(B14="","← required: Y = everyone works the full project window (row dates are ignored); N = set each person's own Start/End below","") -> ← required: Y = everyone works the full project window (row dates are ignored); N = set each person's own Start/End below | V14: Gross margin % | W14: =IF(OR(W8="",W8=0),"",W13/W8)
A15: Staffing — one row per person. To remove a person, clear that row's yellow cells; a row with no Role is ignored. Don't delete rows — the Monthly tab maps to them. | V15: Project GM floor % | W15: =Settings!$B$6 -> 0.35
A16: Role * | B16: Seniority * | C16: Location * | D16: Employment type * (W-2 or 1099 — sets the burden %) | E16: Assignment / project (optional — group resources; Staff augmentation) | F16: Utilization % | G16: Hours (auto — use Hours override to change) | H16: Bill rate (what we CHARGE the client per hour — T&M / Staff aug only) | I16: Our cost / hour * (what the person COSTS us, before burden — pre-filled from the Settings rate card; overwrite if known) | J16: Start (B14 = Y: project start for everyone, greyed. B14 = N: pre-filled, change if the person joins later) | K16: End (B14 = Y: project end for everyone. B14 = N: pre-filled, change if they leave earlier) | L16: Working days | M16: Hours override (optional) | N16: Burden % | O16: Labour at bill rate (revenue, T&M / Staff aug) | P16: Labour cost (hours × cost/hr) | Q16: Burden cost | R16: Loaded cost (labour + burden) | S16: GM floor % | T16: Row GM % (T&M / Staff aug) | V16: Status | W16: =IF(W18<>"","INCOMPLETE — see below",IF(OR(W14="",W15=""),"",IF(W14>=W15,"PASS — GM "&TEXT(W14,"0.0%")&" ≥ floor "&TEXT(W15,"0.0%"),"BELOW FLOOR — GM "&TEXT(W14,"0.0%")&" < floor "&TEXT(W15,"0.0%")))) -> INCOMPLETE — see below
G17: =IF(M17<>"",M17,IF(L17="","",L17*Settings!$B$5*IF(F17="",1,F17))) | I17: =IF(OR(B17="",C17="",D17=""),"",IFERROR(INDEX(Settings!$B$17:$I$20,MATCH(B17,Settings!$A$17:$A$20,0),(MATCH(C17,Settings!$A$9:$A$12,0)-1)*2+IF(D17="W-2 / Employee",1,2)),"")) | J17: =IF(OR(A17="",$B$8=""),"",$B$8) | K17: =IF(OR(A17="",$B$9=""),"",$B$9) | L17: =IF(OR(A17="",IF(OR($B$14="Y",J17=""),$B$8,J17)="",IF(OR($B$14="Y",K17=""),$B$9,K17)=""),"",IFERROR(NETWORKDAYS(IF(OR($B$14="Y",J17=""),$B$8,J17),IF(OR($B$14="Y",K17=""),$B$9,K17),INDEX(Settings!$A$35:$D$74,0,MATCH(C17,Settings!$A$34:$D$34,0))),NETWORKDAYS(IF(OR($B$14="Y",J17=""),$B$8,J17),IF(OR($B$14="Y",K17=""),$B$9,K17)))) | N17: =IF(OR(C17="",D17=""),0,IFERROR(INDEX(Settings!$B$9:$C$12,MATCH(C17,Settings!$A$9:$A$12,0),IF(D17="W-2 / Employee",1,2)),0)) -> 0 | O17: =IF(OR(G17="",H17=""),0,G17*H17) -> 0 | P17: =IF(OR(G17="",I17=""),0,G17*I17) -> 0 | Q17: =P17*N17 -> 0 | R17: =P17+Q17 -> 0 | S17: =IF(C17="",0,IFERROR(INDEX(Settings!$D$9:$D$12,MATCH(C17,Settings!$A$9:$A$12,0)),0)) -> 0 | T17: =IF(O17=0,"",(O17-R17)/O17)
G18: =IF(M18<>"",M18,IF(L18="","",L18*Settings!$B$5*IF(F18="",1,F18))) | I18: =IF(OR(B18="",C18="",D18=""),"",IFERROR(INDEX(Settings!$B$17:$I$20,MATCH(B18,Settings!$A$17:$A$20,0),(MATCH(C18,Settings!$A$9:$A$12,0)-1)*2+IF(D18="W-2 / Employee",1,2)),"")) | J18: =IF(OR(A18="",$B$8=""),"",$B$8) | K18: =IF(OR(A18="",$B$9=""),"",$B$9) | L18: =IF(OR(A18="",IF(OR($B$14="Y",J18=""),$B$8,J18)="",IF(OR($B$14="Y",K18=""),$B$9,K18)=""),"",IFERROR(NETWORKDAYS(IF(OR($B$14="Y",J18=""),$B$8,J18),IF(OR($B$14="Y",K18=""),$B$9,K18),INDEX(Settings!$A$35:$D$74,0,MATCH(C18,Settings!$A$34:$D$34,0))),NETWORKDAYS(IF(OR($B$14="Y",J18=""),$B$8,J18),IF(OR($B$14="Y",K18=""),$B$9,K18)))) | N18: =IF(OR(C18="",D18=""),0,IFERROR(INDEX(Settings!$B$9:$C$12,MATCH(C18,Settings!$A$9:$A$12,0),IF(D18="W-2 / Employee",1,2)),0)) -> 0 | O18: =IF(OR(G18="",H18=""),0,G18*H18) -> 0 | P18: =IF(OR(G18="",I18=""),0,G18*I18) -> 0 | Q18: =P18*N18 -> 0 | R18: =P18+Q18 -> 0 | S18: =IF(C18="",0,IFERROR(INDEX(Settings!$D$9:$D$12,MATCH(C18,Settings!$A$9:$A$12,0)),0)) -> 0 | T18: =IF(O18=0,"",(O18-R18)/O18) | V18: Missing inputs | W18: =TRIM(IF(B4="","Engagement type. ","")&IF(OR(B8="",B9=""),"Project dates. ","")&IF(AND(OR(B4="Fixed cost",B4="Assessment"),B11=""),"Total project price. ","")&IF(AND(B4="MSP",B12=""),"Monthly fee. ","")&IF(B13="","Additional costs Y/N. ","")&IF(B14="","Same start/end for every resource Y/N. ","")&IF(COUNTIF(I41:I52,"Pick*")>0,"Billed to client Y/N (column F) on additional cost rows. ","")&IF(COUNTIFS(A17:A36,"<>",D17:D36,"")>0,"Employment type (column D) on staffing rows. ","")&IF(COUNTIFS(A17:A36,"<>",I17:I36,"")>0,"Our cost/hour (column I) on staffing rows — pick Seniority + Location or type it. ","")&IF(AND(OR(B4="Time & materials",B4="Staff augmentation"),COUNTIFS(A17:A36,"<>",H17:H36,"")>0),"Bill rate (column H) on staffing rows. ","")) -> Engagement type. Project dates. Additional costs Y/N. Same start/end for every resource Y/N.
G19: =IF(M19<>"",M19,IF(L19="","",L19*Settings!$B$5*IF(F19="",1,F19))) | I19: =IF(OR(B19="",C19="",D19=""),"",IFERROR(INDEX(Settings!$B$17:$I$20,MATCH(B19,Settings!$A$17:$A$20,0),(MATCH(C19,Settings!$A$9:$A$12,0)-1)*2+IF(D19="W-2 / Employee",1,2)),"")) | J19: =IF(OR(A19="",$B$8=""),"",$B$8) | K19: =IF(OR(A19="",$B$9=""),"",$B$9) | L19: =IF(OR(A19="",IF(OR($B$14="Y",J19=""),$B$8,J19)="",IF(OR($B$14="Y",K19=""),$B$9,K19)=""),"",IFERROR(NETWORKDAYS(IF(OR($B$14="Y",J19=""),$B$8,J19),IF(OR($B$14="Y",K19=""),$B$9,K19),INDEX(Settings!$A$35:$D$74,0,MATCH(C19,Settings!$A$34:$D$34,0))),NETWORKDAYS(IF(OR($B$14="Y",J19=""),$B$8,J19),IF(OR($B$14="Y",K19=""),$B$9,K19)))) | N19: =IF(OR(C19="",D19=""),0,IFERROR(INDEX(Settings!$B$9:$C$12,MATCH(C19,Settings!$A$9:$A$12,0),IF(D19="W-2 / Employee",1,2)),0)) -> 0 | O19: =IF(OR(G19="",H19=""),0,G19*H19) -> 0 | P19: =IF(OR(G19="",I19=""),0,G19*I19) -> 0 | Q19: =P19*N19 -> 0 | R19: =P19+Q19 -> 0 | S19: =IF(C19="",0,IFERROR(INDEX(Settings!$D$9:$D$12,MATCH(C19,Settings!$A$9:$A$12,0)),0)) -> 0 | T19: =IF(O19=0,"",(O19-R19)/O19)
G20: =IF(M20<>"",M20,IF(L20="","",L20*Settings!$B$5*IF(F20="",1,F20))) | I20: =IF(OR(B20="",C20="",D20=""),"",IFERROR(INDEX(Settings!$B$17:$I$20,MATCH(B20,Settings!$A$17:$A$20,0),(MATCH(C20,Settings!$A$9:$A$12,0)-1)*2+IF(D20="W-2 / Employee",1,2)),"")) | J20: =IF(OR(A20="",$B$8=""),"",$B$8) | K20: =IF(OR(A20="",$B$9=""),"",$B$9) | L20: =IF(OR(A20="",IF(OR($B$14="Y",J20=""),$B$8,J20)="",IF(OR($B$14="Y",K20=""),$B$9,K20)=""),"",IFERROR(NETWORKDAYS(IF(OR($B$14="Y",J20=""),$B$8,J20),IF(OR($B$14="Y",K20=""),$B$9,K20),INDEX(Settings!$A$35:$D$74,0,MATCH(C20,Settings!$A$34:$D$34,0))),NETWORKDAYS(IF(OR($B$14="Y",J20=""),$B$8,J20),IF(OR($B$14="Y",K20=""),$B$9,K20)))) | N20: =IF(OR(C20="",D20=""),0,IFERROR(INDEX(Settings!$B$9:$C$12,MATCH(C20,Settings!$A$9:$A$12,0),IF(D20="W-2 / Employee",1,2)),0)) -> 0 | O20: =IF(OR(G20="",H20=""),0,G20*H20) -> 0 | P20: =IF(OR(G20="",I20=""),0,G20*I20) -> 0 | Q20: =P20*N20 -> 0 | R20: =P20+Q20 -> 0 | S20: =IF(C20="",0,IFERROR(INDEX(Settings!$D$9:$D$12,MATCH(C20,Settings!$A$9:$A$12,0)),0)) -> 0 | T20: =IF(O20=0,"",(O20-R20)/O20) | V20: Monthly view | W20: =IF(B10="","",IF(B10>2,"Required — see Monthly tab","Not needed (≤ 2 months)"))
G21: =IF(M21<>"",M21,IF(L21="","",L21*Settings!$B$5*IF(F21="",1,F21))) | I21: =IF(OR(B21="",C21="",D21=""),"",IFERROR(INDEX(Settings!$B$17:$I$20,MATCH(B21,Settings!$A$17:$A$20,0),(MATCH(C21,Settings!$A$9:$A$12,0)-1)*2+IF(D21="W-2 / Employee",1,2)),"")) | J21: =IF(OR(A21="",$B$8=""),"",$B$8) | K21: =IF(OR(A21="",$B$9=""),"",$B$9) | L21: =IF(OR(A21="",IF(OR($B$14="Y",J21=""),$B$8,J21)="",IF(OR($B$14="Y",K21=""),$B$9,K21)=""),"",IFERROR(NETWORKDAYS(IF(OR($B$14="Y",J21=""),$B$8,J21),IF(OR($B$14="Y",K21=""),$B$9,K21),INDEX(Settings!$A$35:$D$74,0,MATCH(C21,Settings!$A$34:$D$34,0))),NETWORKDAYS(IF(OR($B$14="Y",J21=""),$B$8,J21),IF(OR($B$14="Y",K21=""),$B$9,K21)))) | N21: =IF(OR(C21="",D21=""),0,IFERROR(INDEX(Settings!$B$9:$C$12,MATCH(C21,Settings!$A$9:$A$12,0),IF(D21="W-2 / Employee",1,2)),0)) -> 0 | O21: =IF(OR(G21="",H21=""),0,G21*H21) -> 0 | P21: =IF(OR(G21="",I21=""),0,G21*I21) -> 0 | Q21: =P21*N21 -> 0 | R21: =P21+Q21 -> 0 | S21: =IF(C21="",0,IFERROR(INDEX(Settings!$D$9:$D$12,MATCH(C21,Settings!$A$9:$A$12,0)),0)) -> 0 | T21: =IF(O21=0,"",(O21-R21)/O21)
G22: =IF(M22<>"",M22,IF(L22="","",L22*Settings!$B$5*IF(F22="",1,F22))) | I22: =IF(OR(B22="",C22="",D22=""),"",IFERROR(INDEX(Settings!$B$17:$I$20,MATCH(B22,Settings!$A$17:$A$20,0),(MATCH(C22,Settings!$A$9:$A$12,0)-1)*2+IF(D22="W-2 / Employee",1,2)),"")) | J22: =IF(OR(A22="",$B$8=""),"",$B$8) | K22: =IF(OR(A22="",$B$9=""),"",$B$9) | L22: =IF(OR(A22="",IF(OR($B$14="Y",J22=""),$B$8,J22)="",IF(OR($B$14="Y",K22=""),$B$9,K22)=""),"",IFERROR(NETWORKDAYS(IF(OR($B$14="Y",J22=""),$B$8,J22),IF(OR($B$14="Y",K22=""),$B$9,K22),INDEX(Settings!$A$35:$D$74,0,MATCH(C22,Settings!$A$34:$D$34,0))),NETWORKDAYS(IF(OR($B$14="Y",J22=""),$B$8,J22),IF(OR($B$14="Y",K22=""),$B$9,K22)))) | N22: =IF(OR(C22="",D22=""),0,IFERROR(INDEX(Settings!$B$9:$C$12,MATCH(C22,Settings!$A$9:$A$12,0),IF(D22="W-2 / Employee",1,2)),0)) -> 0 | O22: =IF(OR(G22="",H22=""),0,G22*H22) -> 0 | P22: =IF(OR(G22="",I22=""),0,G22*I22) -> 0 | Q22: =P22*N22 -> 0 | R22: =P22+Q22 -> 0 | S22: =IF(C22="",0,IFERROR(INDEX(Settings!$D$9:$D$12,MATCH(C22,Settings!$A$9:$A$12,0)),0)) -> 0 | T22: =IF(O22=0,"",(O22-R22)/O22) | V22: Location check — each location's resources against their own floor (hourly types; fixed-price work is judged on the project floor only)
G23: =IF(M23<>"",M23,IF(L23="","",L23*Settings!$B$5*IF(F23="",1,F23))) | I23: =IF(OR(B23="",C23="",D23=""),"",IFERROR(INDEX(Settings!$B$17:$I$20,MATCH(B23,Settings!$A$17:$A$20,0),(MATCH(C23,Settings!$A$9:$A$12,0)-1)*2+IF(D23="W-2 / Employee",1,2)),"")) | J23: =IF(OR(A23="",$B$8=""),"",$B$8) | K23: =IF(OR(A23="",$B$9=""),"",$B$9) | L23: =IF(OR(A23="",IF(OR($B$14="Y",J23=""),$B$8,J23)="",IF(OR($B$14="Y",K23=""),$B$9,K23)=""),"",IFERROR(NETWORKDAYS(IF(OR($B$14="Y",J23=""),$B$8,J23),IF(OR($B$14="Y",K23=""),$B$9,K23),INDEX(Settings!$A$35:$D$74,0,MATCH(C23,Settings!$A$34:$D$34,0))),NETWORKDAYS(IF(OR($B$14="Y",J23=""),$B$8,J23),IF(OR($B$14="Y",K23=""),$B$9,K23)))) | N23: =IF(OR(C23="",D23=""),0,IFERROR(INDEX(Settings!$B$9:$C$12,MATCH(C23,Settings!$A$9:$A$12,0),IF(D23="W-2 / Employee",1,2)),0)) -> 0 | O23: =IF(OR(G23="",H23=""),0,G23*H23) -> 0 | P23: =IF(OR(G23="",I23=""),0,G23*I23) -> 0 | Q23: =P23*N23 -> 0 | R23: =P23+Q23 -> 0 | S23: =IF(C23="",0,IFERROR(INDEX(Settings!$D$9:$D$12,MATCH(C23,Settings!$A$9:$A$12,0)),0)) -> 0 | T23: =IF(O23=0,"",(O23-R23)/O23) | V23: Location | W23: Labour cost | X23: Share of labour | Y23: Resource floor | Z23: Revenue (hourly types) | AA23: GM % (hourly types) | AB23: Check
G24: =IF(M24<>"",M24,IF(L24="","",L24*Settings!$B$5*IF(F24="",1,F24))) | I24: =IF(OR(B24="",C24="",D24=""),"",IFERROR(INDEX(Settings!$B$17:$I$20,MATCH(B24,Settings!$A$17:$A$20,0),(MATCH(C24,Settings!$A$9:$A$12,0)-1)*2+IF(D24="W-2 / Employee",1,2)),"")) | J24: =IF(OR(A24="",$B$8=""),"",$B$8) | K24: =IF(OR(A24="",$B$9=""),"",$B$9) | L24: =IF(OR(A24="",IF(OR($B$14="Y",J24=""),$B$8,J24)="",IF(OR($B$14="Y",K24=""),$B$9,K24)=""),"",IFERROR(NETWORKDAYS(IF(OR($B$14="Y",J24=""),$B$8,J24),IF(OR($B$14="Y",K24=""),$B$9,K24),INDEX(Settings!$A$35:$D$74,0,MATCH(C24,Settings!$A$34:$D$34,0))),NETWORKDAYS(IF(OR($B$14="Y",J24=""),$B$8,J24),IF(OR($B$14="Y",K24=""),$B$9,K24)))) | N24: =IF(OR(C24="",D24=""),0,IFERROR(INDEX(Settings!$B$9:$C$12,MATCH(C24,Settings!$A$9:$A$12,0),IF(D24="W-2 / Employee",1,2)),0)) -> 0 | O24: =IF(OR(G24="",H24=""),0,G24*H24) -> 0 | P24: =IF(OR(G24="",I24=""),0,G24*I24) -> 0 | Q24: =P24*N24 -> 0 | R24: =P24+Q24 -> 0 | S24: =IF(C24="",0,IFERROR(INDEX(Settings!$D$9:$D$12,MATCH(C24,Settings!$A$9:$A$12,0)),0)) -> 0 | T24: =IF(O24=0,"",(O24-R24)/O24) | V24: =IF(Settings!A9="","",Settings!A9) -> US | W24: =IF(V24="","",SUMIF($C$17:$C$36,V24,$P$17:$P$36)) -> 0 | X24: =IF(OR(V24="",$P$37=0),"",W24/$P$37) | Y24: =IF(V24="","",Settings!D9) -> 0.35 | Z24: =IF(OR(V24="",NOT(OR($B$4="Time & materials",$B$4="Staff augmentation"))),"",SUMIF($C$17:$C$36,V24,$O$17:$O$36)) | AA24: =IF(OR(Z24="",Z24=0),"",(Z24-SUMIF($C$17:$C$36,V24,$R$17:$R$36))/Z24) | AB24: =IF(AA24="","",IF(AA24>=Y24,"OK","Under floor — review rates"))
G25: =IF(M25<>"",M25,IF(L25="","",L25*Settings!$B$5*IF(F25="",1,F25))) | I25: =IF(OR(B25="",C25="",D25=""),"",IFERROR(INDEX(Settings!$B$17:$I$20,MATCH(B25,Settings!$A$17:$A$20,0),(MATCH(C25,Settings!$A$9:$A$12,0)-1)*2+IF(D25="W-2 / Employee",1,2)),"")) | J25: =IF(OR(A25="",$B$8=""),"",$B$8) | K25: =IF(OR(A25="",$B$9=""),"",$B$9) | L25: =IF(OR(A25="",IF(OR($B$14="Y",J25=""),$B$8,J25)="",IF(OR($B$14="Y",K25=""),$B$9,K25)=""),"",IFERROR(NETWORKDAYS(IF(OR($B$14="Y",J25=""),$B$8,J25),IF(OR($B$14="Y",K25=""),$B$9,K25),INDEX(Settings!$A$35:$D$74,0,MATCH(C25,Settings!$A$34:$D$34,0))),NETWORKDAYS(IF(OR($B$14="Y",J25=""),$B$8,J25),IF(OR($B$14="Y",K25=""),$B$9,K25)))) | N25: =IF(OR(C25="",D25=""),0,IFERROR(INDEX(Settings!$B$9:$C$12,MATCH(C25,Settings!$A$9:$A$12,0),IF(D25="W-2 / Employee",1,2)),0)) -> 0 | O25: =IF(OR(G25="",H25=""),0,G25*H25) -> 0 | P25: =IF(OR(G25="",I25=""),0,G25*I25) -> 0 | Q25: =P25*N25 -> 0 | R25: =P25+Q25 -> 0 | S25: =IF(C25="",0,IFERROR(INDEX(Settings!$D$9:$D$12,MATCH(C25,Settings!$A$9:$A$12,0)),0)) -> 0 | T25: =IF(O25=0,"",(O25-R25)/O25) | V25: =IF(Settings!A10="","",Settings!A10) -> India | W25: =IF(V25="","",SUMIF($C$17:$C$36,V25,$P$17:$P$36)) -> 0 | X25: =IF(OR(V25="",$P$37=0),"",W25/$P$37) | Y25: =IF(V25="","",Settings!D10) -> 0.5 | Z25: =IF(OR(V25="",NOT(OR($B$4="Time & materials",$B$4="Staff augmentation"))),"",SUMIF($C$17:$C$36,V25,$O$17:$O$36)) | AA25: =IF(OR(Z25="",Z25=0),"",(Z25-SUMIF($C$17:$C$36,V25,$R$17:$R$36))/Z25) | AB25: =IF(AA25="","",IF(AA25>=Y25,"OK","Under floor — review rates"))
G26: =IF(M26<>"",M26,IF(L26="","",L26*Settings!$B$5*IF(F26="",1,F26))) | I26: =IF(OR(B26="",C26="",D26=""),"",IFERROR(INDEX(Settings!$B$17:$I$20,MATCH(B26,Settings!$A$17:$A$20,0),(MATCH(C26,Settings!$A$9:$A$12,0)-1)*2+IF(D26="W-2 / Employee",1,2)),"")) | J26: =IF(OR(A26="",$B$8=""),"",$B$8) | K26: =IF(OR(A26="",$B$9=""),"",$B$9) | L26: =IF(OR(A26="",IF(OR($B$14="Y",J26=""),$B$8,J26)="",IF(OR($B$14="Y",K26=""),$B$9,K26)=""),"",IFERROR(NETWORKDAYS(IF(OR($B$14="Y",J26=""),$B$8,J26),IF(OR($B$14="Y",K26=""),$B$9,K26),INDEX(Settings!$A$35:$D$74,0,MATCH(C26,Settings!$A$34:$D$34,0))),NETWORKDAYS(IF(OR($B$14="Y",J26=""),$B$8,J26),IF(OR($B$14="Y",K26=""),$B$9,K26)))) | N26: =IF(OR(C26="",D26=""),0,IFERROR(INDEX(Settings!$B$9:$C$12,MATCH(C26,Settings!$A$9:$A$12,0),IF(D26="W-2 / Employee",1,2)),0)) -> 0 | O26: =IF(OR(G26="",H26=""),0,G26*H26) -> 0 | P26: =IF(OR(G26="",I26=""),0,G26*I26) -> 0 | Q26: =P26*N26 -> 0 | R26: =P26+Q26 -> 0 | S26: =IF(C26="",0,IFERROR(INDEX(Settings!$D$9:$D$12,MATCH(C26,Settings!$A$9:$A$12,0)),0)) -> 0 | T26: =IF(O26=0,"",(O26-R26)/O26) | V26: =IF(Settings!A11="","",Settings!A11) | W26: =IF(V26="","",SUMIF($C$17:$C$36,V26,$P$17:$P$36)) | X26: =IF(OR(V26="",$P$37=0),"",W26/$P$37) | Y26: =IF(V26="","",Settings!D11) | Z26: =IF(OR(V26="",NOT(OR($B$4="Time & materials",$B$4="Staff augmentation"))),"",SUMIF($C$17:$C$36,V26,$O$17:$O$36)) | AA26: =IF(OR(Z26="",Z26=0),"",(Z26-SUMIF($C$17:$C$36,V26,$R$17:$R$36))/Z26) | AB26: =IF(AA26="","",IF(AA26>=Y26,"OK","Under floor — review rates"))
G27: =IF(M27<>"",M27,IF(L27="","",L27*Settings!$B$5*IF(F27="",1,F27))) | I27: =IF(OR(B27="",C27="",D27=""),"",IFERROR(INDEX(Settings!$B$17:$I$20,MATCH(B27,Settings!$A$17:$A$20,0),(MATCH(C27,Settings!$A$9:$A$12,0)-1)*2+IF(D27="W-2 / Employee",1,2)),"")) | J27: =IF(OR(A27="",$B$8=""),"",$B$8) | K27: =IF(OR(A27="",$B$9=""),"",$B$9) | L27: =IF(OR(A27="",IF(OR($B$14="Y",J27=""),$B$8,J27)="",IF(OR($B$14="Y",K27=""),$B$9,K27)=""),"",IFERROR(NETWORKDAYS(IF(OR($B$14="Y",J27=""),$B$8,J27),IF(OR($B$14="Y",K27=""),$B$9,K27),INDEX(Settings!$A$35:$D$74,0,MATCH(C27,Settings!$A$34:$D$34,0))),NETWORKDAYS(IF(OR($B$14="Y",J27=""),$B$8,J27),IF(OR($B$14="Y",K27=""),$B$9,K27)))) | N27: =IF(OR(C27="",D27=""),0,IFERROR(INDEX(Settings!$B$9:$C$12,MATCH(C27,Settings!$A$9:$A$12,0),IF(D27="W-2 / Employee",1,2)),0)) -> 0 | O27: =IF(OR(G27="",H27=""),0,G27*H27) -> 0 | P27: =IF(OR(G27="",I27=""),0,G27*I27) -> 0 | Q27: =P27*N27 -> 0 | R27: =P27+Q27 -> 0 | S27: =IF(C27="",0,IFERROR(INDEX(Settings!$D$9:$D$12,MATCH(C27,Settings!$A$9:$A$12,0)),0)) -> 0 | T27: =IF(O27=0,"",(O27-R27)/O27) | V27: =IF(Settings!A12="","",Settings!A12) | W27: =IF(V27="","",SUMIF($C$17:$C$36,V27,$P$17:$P$36)) | X27: =IF(OR(V27="",$P$37=0),"",W27/$P$37) | Y27: =IF(V27="","",Settings!D12) | Z27: =IF(OR(V27="",NOT(OR($B$4="Time & materials",$B$4="Staff augmentation"))),"",SUMIF($C$17:$C$36,V27,$O$17:$O$36)) | AA27: =IF(OR(Z27="",Z27=0),"",(Z27-SUMIF($C$17:$C$36,V27,$R$17:$R$36))/Z27) | AB27: =IF(AA27="","",IF(AA27>=Y27,"OK","Under floor — review rates"))
G28: =IF(M28<>"",M28,IF(L28="","",L28*Settings!$B$5*IF(F28="",1,F28))) | I28: =IF(OR(B28="",C28="",D28=""),"",IFERROR(INDEX(Settings!$B$17:$I$20,MATCH(B28,Settings!$A$17:$A$20,0),(MATCH(C28,Settings!$A$9:$A$12,0)-1)*2+IF(D28="W-2 / Employee",1,2)),"")) | J28: =IF(OR(A28="",$B$8=""),"",$B$8) | K28: =IF(OR(A28="",$B$9=""),"",$B$9) | L28: =IF(OR(A28="",IF(OR($B$14="Y",J28=""),$B$8,J28)="",IF(OR($B$14="Y",K28=""),$B$9,K28)=""),"",IFERROR(NETWORKDAYS(IF(OR($B$14="Y",J28=""),$B$8,J28),IF(OR($B$14="Y",K28=""),$B$9,K28),INDEX(Settings!$A$35:$D$74,0,MATCH(C28,Settings!$A$34:$D$34,0))),NETWORKDAYS(IF(OR($B$14="Y",J28=""),$B$8,J28),IF(OR($B$14="Y",K28=""),$B$9,K28)))) | N28: =IF(OR(C28="",D28=""),0,IFERROR(INDEX(Settings!$B$9:$C$12,MATCH(C28,Settings!$A$9:$A$12,0),IF(D28="W-2 / Employee",1,2)),0)) -> 0 | O28: =IF(OR(G28="",H28=""),0,G28*H28) -> 0 | P28: =IF(OR(G28="",I28=""),0,G28*I28) -> 0 | Q28: =P28*N28 -> 0 | R28: =P28+Q28 -> 0 | S28: =IF(C28="",0,IFERROR(INDEX(Settings!$D$9:$D$12,MATCH(C28,Settings!$A$9:$A$12,0)),0)) -> 0 | T28: =IF(O28=0,"",(O28-R28)/O28) | V28: Row GM % in the staffing table turns red when a person is under their location's resource floor (hourly types).
G29: =IF(M29<>"",M29,IF(L29="","",L29*Settings!$B$5*IF(F29="",1,F29))) | I29: =IF(OR(B29="",C29="",D29=""),"",IFERROR(INDEX(Settings!$B$17:$I$20,MATCH(B29,Settings!$A$17:$A$20,0),(MATCH(C29,Settings!$A$9:$A$12,0)-1)*2+IF(D29="W-2 / Employee",1,2)),"")) | J29: =IF(OR(A29="",$B$8=""),"",$B$8) | K29: =IF(OR(A29="",$B$9=""),"",$B$9) | L29: =IF(OR(A29="",IF(OR($B$14="Y",J29=""),$B$8,J29)="",IF(OR($B$14="Y",K29=""),$B$9,K29)=""),"",IFERROR(NETWORKDAYS(IF(OR($B$14="Y",J29=""),$B$8,J29),IF(OR($B$14="Y",K29=""),$B$9,K29),INDEX(Settings!$A$35:$D$74,0,MATCH(C29,Settings!$A$34:$D$34,0))),NETWORKDAYS(IF(OR($B$14="Y",J29=""),$B$8,J29),IF(OR($B$14="Y",K29=""),$B$9,K29)))) | N29: =IF(OR(C29="",D29=""),0,IFERROR(INDEX(Settings!$B$9:$C$12,MATCH(C29,Settings!$A$9:$A$12,0),IF(D29="W-2 / Employee",1,2)),0)) -> 0 | O29: =IF(OR(G29="",H29=""),0,G29*H29) -> 0 | P29: =IF(OR(G29="",I29=""),0,G29*I29) -> 0 | Q29: =P29*N29 -> 0 | R29: =P29+Q29 -> 0 | S29: =IF(C29="",0,IFERROR(INDEX(Settings!$D$9:$D$12,MATCH(C29,Settings!$A$9:$A$12,0)),0)) -> 0 | T29: =IF(O29=0,"",(O29-R29)/O29)
G30: =IF(M30<>"",M30,IF(L30="","",L30*Settings!$B$5*IF(F30="",1,F30))) | I30: =IF(OR(B30="",C30="",D30=""),"",IFERROR(INDEX(Settings!$B$17:$I$20,MATCH(B30,Settings!$A$17:$A$20,0),(MATCH(C30,Settings!$A$9:$A$12,0)-1)*2+IF(D30="W-2 / Employee",1,2)),"")) | J30: =IF(OR(A30="",$B$8=""),"",$B$8) | K30: =IF(OR(A30="",$B$9=""),"",$B$9) | L30: =IF(OR(A30="",IF(OR($B$14="Y",J30=""),$B$8,J30)="",IF(OR($B$14="Y",K30=""),$B$9,K30)=""),"",IFERROR(NETWORKDAYS(IF(OR($B$14="Y",J30=""),$B$8,J30),IF(OR($B$14="Y",K30=""),$B$9,K30),INDEX(Settings!$A$35:$D$74,0,MATCH(C30,Settings!$A$34:$D$34,0))),NETWORKDAYS(IF(OR($B$14="Y",J30=""),$B$8,J30),IF(OR($B$14="Y",K30=""),$B$9,K30)))) | N30: =IF(OR(C30="",D30=""),0,IFERROR(INDEX(Settings!$B$9:$C$12,MATCH(C30,Settings!$A$9:$A$12,0),IF(D30="W-2 / Employee",1,2)),0)) -> 0 | O30: =IF(OR(G30="",H30=""),0,G30*H30) -> 0 | P30: =IF(OR(G30="",I30=""),0,G30*I30) -> 0 | Q30: =P30*N30 -> 0 | R30: =P30+Q30 -> 0 | S30: =IF(C30="",0,IFERROR(INDEX(Settings!$D$9:$D$12,MATCH(C30,Settings!$A$9:$A$12,0)),0)) -> 0 | T30: =IF(O30=0,"",(O30-R30)/O30) | V30: Assignments (Staff augmentation / T&M) — type the names used in column E; month-by-month numbers per assignment are on the Forecast tab
G31: =IF(M31<>"",M31,IF(L31="","",L31*Settings!$B$5*IF(F31="",1,F31))) | I31: =IF(OR(B31="",C31="",D31=""),"",IFERROR(INDEX(Settings!$B$17:$I$20,MATCH(B31,Settings!$A$17:$A$20,0),(MATCH(C31,Settings!$A$9:$A$12,0)-1)*2+IF(D31="W-2 / Employee",1,2)),"")) | J31: =IF(OR(A31="",$B$8=""),"",$B$8) | K31: =IF(OR(A31="",$B$9=""),"",$B$9) | L31: =IF(OR(A31="",IF(OR($B$14="Y",J31=""),$B$8,J31)="",IF(OR($B$14="Y",K31=""),$B$9,K31)=""),"",IFERROR(NETWORKDAYS(IF(OR($B$14="Y",J31=""),$B$8,J31),IF(OR($B$14="Y",K31=""),$B$9,K31),INDEX(Settings!$A$35:$D$74,0,MATCH(C31,Settings!$A$34:$D$34,0))),NETWORKDAYS(IF(OR($B$14="Y",J31=""),$B$8,J31),IF(OR($B$14="Y",K31=""),$B$9,K31)))) | N31: =IF(OR(C31="",D31=""),0,IFERROR(INDEX(Settings!$B$9:$C$12,MATCH(C31,Settings!$A$9:$A$12,0),IF(D31="W-2 / Employee",1,2)),0)) -> 0 | O31: =IF(OR(G31="",H31=""),0,G31*H31) -> 0 | P31: =IF(OR(G31="",I31=""),0,G31*I31) -> 0 | Q31: =P31*N31 -> 0 | R31: =P31+Q31 -> 0 | S31: =IF(C31="",0,IFERROR(INDEX(Settings!$D$9:$D$12,MATCH(C31,Settings!$A$9:$A$12,0)),0)) -> 0 | T31: =IF(O31=0,"",(O31-R31)/O31) | V31: Assignment / project | W31: People
G32: =IF(M32<>"",M32,IF(L32="","",L32*Settings!$B$5*IF(F32="",1,F32))) | I32: =IF(OR(B32="",C32="",D32=""),"",IFERROR(INDEX(Settings!$B$17:$I$20,MATCH(B32,Settings!$A$17:$A$20,0),(MATCH(C32,Settings!$A$9:$A$12,0)-1)*2+IF(D32="W-2 / Employee",1,2)),"")) | J32: =IF(OR(A32="",$B$8=""),"",$B$8) | K32: =IF(OR(A32="",$B$9=""),"",$B$9) | L32: =IF(OR(A32="",IF(OR($B$14="Y",J32=""),$B$8,J32)="",IF(OR($B$14="Y",K32=""),$B$9,K32)=""),"",IFERROR(NETWORKDAYS(IF(OR($B$14="Y",J32=""),$B$8,J32),IF(OR($B$14="Y",K32=""),$B$9,K32),INDEX(Settings!$A$35:$D$74,0,MATCH(C32,Settings!$A$34:$D$34,0))),NETWORKDAYS(IF(OR($B$14="Y",J32=""),$B$8,J32),IF(OR($B$14="Y",K32=""),$B$9,K32)))) | N32: =IF(OR(C32="",D32=""),0,IFERROR(INDEX(Settings!$B$9:$C$12,MATCH(C32,Settings!$A$9:$A$12,0),IF(D32="W-2 / Employee",1,2)),0)) -> 0 | O32: =IF(OR(G32="",H32=""),0,G32*H32) -> 0 | P32: =IF(OR(G32="",I32=""),0,G32*I32) -> 0 | Q32: =P32*N32 -> 0 | R32: =P32+Q32 -> 0 | S32: =IF(C32="",0,IFERROR(INDEX(Settings!$D$9:$D$12,MATCH(C32,Settings!$A$9:$A$12,0)),0)) -> 0 | T32: =IF(O32=0,"",(O32-R32)/O32) | W32: =IF(V32="","",COUNTIFS($E$17:$E$36,V32,$A$17:$A$36,"<>"))
G33: =IF(M33<>"",M33,IF(L33="","",L33*Settings!$B$5*IF(F33="",1,F33))) | I33: =IF(OR(B33="",C33="",D33=""),"",IFERROR(INDEX(Settings!$B$17:$I$20,MATCH(B33,Settings!$A$17:$A$20,0),(MATCH(C33,Settings!$A$9:$A$12,0)-1)*2+IF(D33="W-2 / Employee",1,2)),"")) | J33: =IF(OR(A33="",$B$8=""),"",$B$8) | K33: =IF(OR(A33="",$B$9=""),"",$B$9) | L33: =IF(OR(A33="",IF(OR($B$14="Y",J33=""),$B$8,J33)="",IF(OR($B$14="Y",K33=""),$B$9,K33)=""),"",IFERROR(NETWORKDAYS(IF(OR($B$14="Y",J33=""),$B$8,J33),IF(OR($B$14="Y",K33=""),$B$9,K33),INDEX(Settings!$A$35:$D$74,0,MATCH(C33,Settings!$A$34:$D$34,0))),NETWORKDAYS(IF(OR($B$14="Y",J33=""),$B$8,J33),IF(OR($B$14="Y",K33=""),$B$9,K33)))) | N33: =IF(OR(C33="",D33=""),0,IFERROR(INDEX(Settings!$B$9:$C$12,MATCH(C33,Settings!$A$9:$A$12,0),IF(D33="W-2 / Employee",1,2)),0)) -> 0 | O33: =IF(OR(G33="",H33=""),0,G33*H33) -> 0 | P33: =IF(OR(G33="",I33=""),0,G33*I33) -> 0 | Q33: =P33*N33 -> 0 | R33: =P33+Q33 -> 0 | S33: =IF(C33="",0,IFERROR(INDEX(Settings!$D$9:$D$12,MATCH(C33,Settings!$A$9:$A$12,0)),0)) -> 0 | T33: =IF(O33=0,"",(O33-R33)/O33) | W33: =IF(V33="","",COUNTIFS($E$17:$E$36,V33,$A$17:$A$36,"<>"))
G34: =IF(M34<>"",M34,IF(L34="","",L34*Settings!$B$5*IF(F34="",1,F34))) | I34: =IF(OR(B34="",C34="",D34=""),"",IFERROR(INDEX(Settings!$B$17:$I$20,MATCH(B34,Settings!$A$17:$A$20,0),(MATCH(C34,Settings!$A$9:$A$12,0)-1)*2+IF(D34="W-2 / Employee",1,2)),"")) | J34: =IF(OR(A34="",$B$8=""),"",$B$8) | K34: =IF(OR(A34="",$B$9=""),"",$B$9) | L34: =IF(OR(A34="",IF(OR($B$14="Y",J34=""),$B$8,J34)="",IF(OR($B$14="Y",K34=""),$B$9,K34)=""),"",IFERROR(NETWORKDAYS(IF(OR($B$14="Y",J34=""),$B$8,J34),IF(OR($B$14="Y",K34=""),$B$9,K34),INDEX(Settings!$A$35:$D$74,0,MATCH(C34,Settings!$A$34:$D$34,0))),NETWORKDAYS(IF(OR($B$14="Y",J34=""),$B$8,J34),IF(OR($B$14="Y",K34=""),$B$9,K34)))) | N34: =IF(OR(C34="",D34=""),0,IFERROR(INDEX(Settings!$B$9:$C$12,MATCH(C34,Settings!$A$9:$A$12,0),IF(D34="W-2 / Employee",1,2)),0)) -> 0 | O34: =IF(OR(G34="",H34=""),0,G34*H34) -> 0 | P34: =IF(OR(G34="",I34=""),0,G34*I34) -> 0 | Q34: =P34*N34 -> 0 | R34: =P34+Q34 -> 0 | S34: =IF(C34="",0,IFERROR(INDEX(Settings!$D$9:$D$12,MATCH(C34,Settings!$A$9:$A$12,0)),0)) -> 0 | T34: =IF(O34=0,"",(O34-R34)/O34) | W34: =IF(V34="","",COUNTIFS($E$17:$E$36,V34,$A$17:$A$36,"<>"))
G35: =IF(M35<>"",M35,IF(L35="","",L35*Settings!$B$5*IF(F35="",1,F35))) | I35: =IF(OR(B35="",C35="",D35=""),"",IFERROR(INDEX(Settings!$B$17:$I$20,MATCH(B35,Settings!$A$17:$A$20,0),(MATCH(C35,Settings!$A$9:$A$12,0)-1)*2+IF(D35="W-2 / Employee",1,2)),"")) | J35: =IF(OR(A35="",$B$8=""),"",$B$8) | K35: =IF(OR(A35="",$B$9=""),"",$B$9) | L35: =IF(OR(A35="",IF(OR($B$14="Y",J35=""),$B$8,J35)="",IF(OR($B$14="Y",K35=""),$B$9,K35)=""),"",IFERROR(NETWORKDAYS(IF(OR($B$14="Y",J35=""),$B$8,J35),IF(OR($B$14="Y",K35=""),$B$9,K35),INDEX(Settings!$A$35:$D$74,0,MATCH(C35,Settings!$A$34:$D$34,0))),NETWORKDAYS(IF(OR($B$14="Y",J35=""),$B$8,J35),IF(OR($B$14="Y",K35=""),$B$9,K35)))) | N35: =IF(OR(C35="",D35=""),0,IFERROR(INDEX(Settings!$B$9:$C$12,MATCH(C35,Settings!$A$9:$A$12,0),IF(D35="W-2 / Employee",1,2)),0)) -> 0 | O35: =IF(OR(G35="",H35=""),0,G35*H35) -> 0 | P35: =IF(OR(G35="",I35=""),0,G35*I35) -> 0 | Q35: =P35*N35 -> 0 | R35: =P35+Q35 -> 0 | S35: =IF(C35="",0,IFERROR(INDEX(Settings!$D$9:$D$12,MATCH(C35,Settings!$A$9:$A$12,0)),0)) -> 0 | T35: =IF(O35=0,"",(O35-R35)/O35) | W35: =IF(V35="","",COUNTIFS($E$17:$E$36,V35,$A$17:$A$36,"<>"))
G36: =IF(M36<>"",M36,IF(L36="","",L36*Settings!$B$5*IF(F36="",1,F36))) | I36: =IF(OR(B36="",C36="",D36=""),"",IFERROR(INDEX(Settings!$B$17:$I$20,MATCH(B36,Settings!$A$17:$A$20,0),(MATCH(C36,Settings!$A$9:$A$12,0)-1)*2+IF(D36="W-2 / Employee",1,2)),"")) | J36: =IF(OR(A36="",$B$8=""),"",$B$8) | K36: =IF(OR(A36="",$B$9=""),"",$B$9) | L36: =IF(OR(A36="",IF(OR($B$14="Y",J36=""),$B$8,J36)="",IF(OR($B$14="Y",K36=""),$B$9,K36)=""),"",IFERROR(NETWORKDAYS(IF(OR($B$14="Y",J36=""),$B$8,J36),IF(OR($B$14="Y",K36=""),$B$9,K36),INDEX(Settings!$A$35:$D$74,0,MATCH(C36,Settings!$A$34:$D$34,0))),NETWORKDAYS(IF(OR($B$14="Y",J36=""),$B$8,J36),IF(OR($B$14="Y",K36=""),$B$9,K36)))) | N36: =IF(OR(C36="",D36=""),0,IFERROR(INDEX(Settings!$B$9:$C$12,MATCH(C36,Settings!$A$9:$A$12,0),IF(D36="W-2 / Employee",1,2)),0)) -> 0 | O36: =IF(OR(G36="",H36=""),0,G36*H36) -> 0 | P36: =IF(OR(G36="",I36=""),0,G36*I36) -> 0 | Q36: =P36*N36 -> 0 | R36: =P36+Q36 -> 0 | S36: =IF(C36="",0,IFERROR(INDEX(Settings!$D$9:$D$12,MATCH(C36,Settings!$A$9:$A$12,0)),0)) -> 0 | T36: =IF(O36=0,"",(O36-R36)/O36) | W36: =IF(V36="","",COUNTIFS($E$17:$E$36,V36,$A$17:$A$36,"<>"))
A37: Staffing total | G37: =SUM(G17:G36) -> 0 | O37: =SUM(O17:O36) -> 0 | P37: =SUM(P17:P36) -> 0 | Q37: =SUM(Q17:Q36) -> 0 | R37: =SUM(R17:R36) -> 0 | T37: =IF(O37=0,"",(O37-R37)/O37) | W37: =IF(V37="","",COUNTIFS($E$17:$E$36,V37,$A$17:$A$36,"<>"))
W38: =IF(V38="","",COUNTIFS($E$17:$E$36,V38,$A$17:$A$36,"<>"))
A39: Additional costs — travel, meals, licences, hardware, subcontractors (required when B13 = Y). To remove one, clear its yellow cells. | W39: =IF(V39="","",COUNTIFS($E$17:$E$36,V39,$A$17:$A$36,"<>"))
A40: Description * | B40: Category * | C40: Location | D40: Amount * | E40: Frequency (dropdown: One-time or Monthly; blank = One-time) | F40: Billed to client? * (dropdown Y/N — required) | G40: Total cost counted | H40: Revenue counted (pass-through) | I40: Check | V40: Unassigned (blank column E) | W40: =COUNTIFS($E$17:$E$36,"",$A$17:$A$36,"<>") -> 0
G41: =IF(OR($B$13<>"Y",D41=""),0,D41*IF(E41="Monthly",IF($B$10="",1,$B$10),1)) -> 0 | H41: =IF(UPPER(F41)="Y",G41,0) -> 0 | I41: =IF($B$13="N","Not counted (B13 = N)",IF(D41="","",IF($B$13="","Answer B13 first",IF(F41="","Pick Billed to client Y/N","OK"))))
G42: =IF(OR($B$13<>"Y",D42=""),0,D42*IF(E42="Monthly",IF($B$10="",1,$B$10),1)) -> 0 | H42: =IF(UPPER(F42)="Y",G42,0) -> 0 | I42: =IF($B$13="N","Not counted (B13 = N)",IF(D42="","",IF($B$13="","Answer B13 first",IF(F42="","Pick Billed to client Y/N","OK"))))
G43: =IF(OR($B$13<>"Y",D43=""),0,D43*IF(E43="Monthly",IF($B$10="",1,$B$10),1)) -> 0 | H43: =IF(UPPER(F43)="Y",G43,0) -> 0 | I43: =IF($B$13="N","Not counted (B13 = N)",IF(D43="","",IF($B$13="","Answer B13 first",IF(F43="","Pick Billed to client Y/N","OK")))) | V43: How to use
G44: =IF(OR($B$13<>"Y",D44=""),0,D44*IF(E44="Monthly",IF($B$10="",1,$B$10),1)) -> 0 | H44: =IF(UPPER(F44)="Y",G44,0) -> 0 | I44: =IF($B$13="N","Not counted (B13 = N)",IF(D44="","",IF($B$13="","Answer B13 first",IF(F44="","Pick Billed to client Y/N","OK")))) | V44: 1. Project block: engagement type, dates, and the price (Fixed cost / Assessment) or monthly fee (MSP). Duration is exact — a partial month counts by its days.
G45: =IF(OR($B$13<>"Y",D45=""),0,D45*IF(E45="Monthly",IF($B$10="",1,$B$10),1)) -> 0 | H45: =IF(UPPER(F45)="Y",G45,0) -> 0 | I45: =IF($B$13="N","Not counted (B13 = N)",IF(D45="","",IF($B$13="","Answer B13 first",IF(F45="","Pick Billed to client Y/N","OK")))) | V45: 2. Say Y or N to additional costs. If Y, every cost row needs Billed-to-client Y/N — the Check column tells you. Frequency blank = one-time.
G46: =IF(OR($B$13<>"Y",D46=""),0,D46*IF(E46="Monthly",IF($B$10="",1,$B$10),1)) -> 0 | H46: =IF(UPPER(F46)="Y",G46,0) -> 0 | I46: =IF($B$13="N","Not counted (B13 = N)",IF(D46="","",IF($B$13="","Answer B13 first",IF(F46="","Pick Billed to client Y/N","OK")))) | V46: 3. One staffing row per person: Role, Seniority, Location, Employment type (sets burden: US W-2 36%, US 1099 5%, India 8%), Utilization. Cost/hour pre-fills from the rate card; overwrite when you know better.
G47: =IF(OR($B$13<>"Y",D47=""),0,D47*IF(E47="Monthly",IF($B$10="",1,$B$10),1)) -> 0 | H47: =IF(UPPER(F47)="Y",G47,0) -> 0 | I47: =IF($B$13="N","Not counted (B13 = N)",IF(D47="","",IF($B$13="","Answer B13 first",IF(F47="","Pick Billed to client Y/N","OK")))) | V47: 3a. Dates: answer 'Same start/end for every resource?' in the project block. Y = everyone uses the project window and the row date columns grey out. N = each row pre-fills from the project dates and you change the ones who join late or leave early.
G48: =IF(OR($B$13<>"Y",D48=""),0,D48*IF(E48="Monthly",IF($B$10="",1,$B$10),1)) -> 0 | H48: =IF(UPPER(F48)="Y",G48,0) -> 0 | I48: =IF($B$13="N","Not counted (B13 = N)",IF(D48="","",IF($B$13="","Answer B13 first",IF(F48="","Pick Billed to client Y/N","OK")))) | V48: 4. Hours come from the dates (weekends and the location's holidays removed) × hours/day × utilization; type an override if the contract fixes hours.
G49: =IF(OR($B$13<>"Y",D49=""),0,D49*IF(E49="Monthly",IF($B$10="",1,$B$10),1)) -> 0 | H49: =IF(UPPER(F49)="Y",G49,0) -> 0 | I49: =IF($B$13="N","Not counted (B13 = N)",IF(D49="","",IF($B$13="","Answer B13 first",IF(F49="","Pick Billed to client Y/N","OK")))) | V49: 5. Bill rate matters for Time & materials and Staff augmentation only. For Fixed cost, Assessment and MSP the revenue is the price or fee.
G50: =IF(OR($B$13<>"Y",D50=""),0,D50*IF(E50="Monthly",IF($B$10="",1,$B$10),1)) -> 0 | H50: =IF(UPPER(F50)="Y",G50,0) -> 0 | I50: =IF($B$13="N","Not counted (B13 = N)",IF(D50="","",IF($B$13="","Answer B13 first",IF(F50="","Pick Billed to client Y/N","OK")))) | V50: 6. Staff augmentation: no project price. Each resource has their own bill rate, cost, dates and an Assignment name. A leaver = an End date; a re-hire or an added person = a new row with its own Start date. The Forecast tab shows every assignment month by month; the Monthly tab shows every person month by month.
G51: =IF(OR($B$13<>"Y",D51=""),0,D51*IF(E51="Monthly",IF($B$10="",1,$B$10),1)) -> 0 | H51: =IF(UPPER(F51)="Y",G51,0) -> 0 | I51: =IF($B$13="N","Not counted (B13 = N)",IF(D51="","",IF($B$13="","Answer B13 first",IF(F51="","Pick Billed to client Y/N","OK")))) | V51: 7. GM % = (revenue − labour − burden − additional costs) ÷ revenue. The project passes at or above the project floor (Settings, 35%). Row GM % shows each person's margin for hourly types and turns red under that location's resource floor.
G52: =IF(OR($B$13<>"Y",D52=""),0,D52*IF(E52="Monthly",IF($B$10="",1,$B$10),1)) -> 0 | H52: =IF(UPPER(F52)="Y",G52,0) -> 0 | I52: =IF($B$13="N","Not counted (B13 = N)",IF(D52="","",IF($B$13="","Answer B13 first",IF(F52="","Pick Billed to client Y/N","OK")))) | V52: 8. Sheets are unprotected while the form is being stabilised. Don't delete rows inside the staffing table — clear the yellow cells instead.
A53: Additional costs total | G53: =SUM(G41:G52) -> 0 | H53: =SUM(H41:H52) -> 0 | V53: 9. Settings: burden matrix and GM floors by location, the cost rate card (seniority × location × employment type — placeholders), lists, holidays.
A54: Frequency Monthly = repeats every month (× Duration). Blank or One-time = once. Billed to client Y = the client reimburses it (added to revenue and cost, zero margin); N = we absorb it. | V54: 10. Floors: the project must clear 35% overall. On hourly work, US resources should earn 35% and India resources 50% — the Location check shows each location against its own floor as a warning.

Sheet Settings
A1: Settings
A2: Yellow cells are yours to set. Everything on the Cost Margin, Monthly and Forecast tabs reads from here.
A4: 1 · General
A5: Hours per working day | B5: 8 | C5: Hours = working days (Mon–Fri minus the location's holidays) × hours/day × utilization.
A6: Project GM floor % | B6: 0.35 | C6: The project passes when its overall GM is at or above this. Each location also has its own resource-level floor below (US 35%, India 50%) — shown as a check, not a fail.
A7: 2 · Burden % and GM floor by location
A8: Location | B8: Burden % — W-2 / Employee | C8: Burden % — 1099 / Contractor | D8: Resource GM floor % | E8: Note
A9: US | B9: 0.36 | C9: 0.05 | D9: 0.35 | E9: US W-2 36%, US 1099 5% — per Kanna, 2026-10-11.
A10: India | B10: 0.08 | C10: 0.08 | D10: 0.5 | E10: All India resources 8% — per Kanna, 2026-10-11.
E11: Add a third location here; it appears in every dropdown, the rate card and the holiday table.
A13: Burden cost = labour cost × the burden % for the person's Location and Employment type. Resource GM floor = what each location's people should earn on hourly work (US 35%, India 50%).
A15: 3 · Cost rate card — OUR hourly cost per person before burden, by seniority, location and employment type (PLACEHOLDERS — set your real numbers)
A16: Seniority | B16: =IF($A$9="","",$A$9&" · "&"W-2 / Employee") -> US · W-2 / Employee | C16: =IF($A$9="","",$A$9&" · "&"1099 / Contractor") -> US · 1099 / Contractor | D16: =IF($A$10="","",$A$10&" · "&"W-2 / Employee") -> India · W-2 / Employee | E16: =IF($A$10="","",$A$10&" · "&"1099 / Contractor") -> India · 1099 / Contractor | F16: =IF($A$11="","",$A$11&" · "&"W-2 / Employee") | G16: =IF($A$11="","",$A$11&" · "&"1099 / Contractor") | H16: =IF($A$12="","",$A$12&" · "&"W-2 / Employee") | I16: =IF($A$12="","",$A$12&" · "&"1099 / Contractor")
A17: Junior | B17: 60 | C17: 65 | D17: 12 | E17: 14
A18: Mid | B18: 80 | C18: 88 | D18: 18 | E18: 20
A19: Senior | B19: 100 | C19: 110 | D19: 25 | E19: 28
A20: Principal | B20: 130 | C20: 145 | D20: 35 | E20: 40
A21: A staffing row's cost/hour is pre-filled from here by Seniority × Location × Employment type. Typing a value on the row overrides it.
A23: 4 · Lists
C24: Employment types | E24: Engagement types | G24: Cost categories
A25: Seniority levels are the rate-card rows above (A17:A20). | C25: W-2 / Employee | E25: Fixed cost | F25: Fixed cost / Assessment: one total price. MSP: fixed fee per month. Time & materials: hours × bill rate. Staff augmentation: pure staffing — each resource has their own bill rate, cost, dates and assignment. | G25: Travel
C26: 1099 / Contractor | E26: Assessment | G26: Lodging
E27: MSP | G27: Meals
E28: Time & materials | G28: Software / licences
E29: Staff augmentation | G29: Hardware
G30: Subcontractor
G31: Miscellaneous
A33: 5 · Holidays by location — weekday holidays only; the header is the location name
A34: =IF($A$9="","",$A$9) -> US | B34: =IF($A$10="","",$A$10) -> India | C34: =IF($A$11="","",$A$11) | D34: =IF($A$12="","",$A$12)
A35: 46023 | B35: 46023 | F35: US = federal holidays 2026–27 (observed). India = national days only (Republic Day, Independence Day, Gandhi Jayanti, Jan 1, Dec 25); add Holi, Diwali and state/company days from your HR calendar. Rows run to 74.
A36: 46041 | B36: 46048
A37: 46069 | B37: 46249
A38: 46167 | B38: 46297
A39: 46192 | B39: 46381
A40: 46206 | B40: 46388
A41: 46272 | B41: 46413
A42: 46307 | B42: 46614
A43: 46337 | B43: 46662
A44: 46352 | B44: 46746
A45: 46381
A46: 46388
A47: 46405
A48: 46433
A49: 46538
A50: 46556
A51: 46573
A52: 46636
A53: 46671
A54: 46702
A55: 46716
A56: 46745

Sheet Monthly
A1: Month by month — people, revenue, cost and margin
A2: Built from the Cost Margin tab. Up to 24 months. Partial months are prorated by days (row 4). MSP revenue = fee × share of month; Fixed cost / Assessment = price spread by share of month; T&M / Staff augmentation = each resource's hours that month × their bill rate (see the per-person grids). One-time costs land in month 1; monthly ones repeat, prorated.
A3: =IF('Cost Margin'!$B$10="","Fill engagement type and project dates on the Cost Margin tab.",IF('Cost Margin'!$B$10>2,"Monthly view REQUIRED — this engagement runs "&TEXT('Cost Margin'!$B$10,"0.0")&" months.","Not needed — this engagement is "&TEXT('Cost Margin'!$B$10,"0.0")&" month(s). Use the Cost Margin summary; everything below is greyed out.")) -> Fill engagement type and project dates on the Cost Margin tab.
A4: Share of month covered | C4: =IF(C5="","",(C6-C5+1)/DAY(EOMONTH(C5,0))) | D4: =IF(D5="","",(D6-D5+1)/DAY(EOMONTH(D5,0))) | E4: =IF(E5="","",(E6-E5+1)/DAY(EOMONTH(E5,0))) | F4: =IF(F5="","",(F6-F5+1)/DAY(EOMONTH(F5,0))) | G4: =IF(G5="","",(G6-G5+1)/DAY(EOMONTH(G5,0))) | H4: =IF(H5="","",(H6-H5+1)/DAY(EOMONTH(H5,0))) | I4: =IF(I5="","",(I6-I5+1)/DAY(EOMONTH(I5,0))) | J4: =IF(J5="","",(J6-J5+1)/DAY(EOMONTH(J5,0))) | ... Z4: =IF(Z5="","",(Z6-Z5+1)/DAY(EOMONTH(Z5,0)))
A5: Month start | B5: =IF(OR('Cost Margin'!$B$8="",'Cost Margin'!$B$9=""),"",(YEAR('Cost Margin'!$B$9)-YEAR('Cost Margin'!$B$8))*12+MONTH('Cost Margin'!$B$9)-MONTH('Cost Margin'!$B$8)+1) | C5: =IF('Cost Margin'!$B$8="","",'Cost Margin'!$B$8) | D5: =IF(OR($C$5="",$B$5="",1>=$B$5),"",EOMONTH($C$5,0)+1) | E5: =IF(OR($C$5="",$B$5="",2>=$B$5),"",EOMONTH($C$5,1)+1) | F5: =IF(OR($C$5="",$B$5="",3>=$B$5),"",EOMONTH($C$5,2)+1) | G5: =IF(OR($C$5="",$B$5="",4>=$B$5),"",EOMONTH($C$5,3)+1) | H5: =IF(OR($C$5="",$B$5="",5>=$B$5),"",EOMONTH($C$5,4)+1) | I5: =IF(OR($C$5="",$B$5="",6>=$B$5),"",EOMONTH($C$5,5)+1) | J5: =IF(OR($C$5="",$B$5="",7>=$B$5),"",EOMONTH($C$5,6)+1) | K5: =IF(OR($C$5="",$B$5="",8>=$B$5),"",EOMONTH($C$5,7)+1) | L5: =IF(OR($C$5="",$B$5="",9>=$B$5),"",EOMONTH($C$5,8)+1) | M5: =IF(OR($C$5="",$B$5="",10>=$B$5),"",EOMONTH($C$5,9)+1) | N5: =IF(OR($C$5="",$B$5="",11>=$B$5),"",EOMONTH($C$5,10)+1) | O5: =IF(OR($C$5="",$B$5="",12>=$B$5),"",EOMONTH($C$5,11)+1) | P5: =IF(OR($C$5="",$B$5="",13>=$B$5),"",EOMONTH($C$5,12)+1) | Q5: =IF(OR($C$5="",$B$5="",14>=$B$5),"",EOMONTH($C$5,13)+1) | R5: =IF(OR($C$5="",$B$5="",15>=$B$5),"",EOMONTH($C$5,14)+1) | S5: =IF(OR($C$5="",$B$5="",16>=$B$5),"",EOMONTH($C$5,15)+1) | T5: =IF(OR($C$5="",$B$5="",17>=$B$5),"",EOMONTH($C$5,16)+1) | U5: =IF(OR($C$5="",$B$5="",18>=$B$5),"",EOMONTH($C$5,17)+1) | V5: =IF(OR($C$5="",$B$5="",19>=$B$5),"",EOMONTH($C$5,18)+1) | W5: =IF(OR($C$5="",$B$5="",20>=$B$5),"",EOMONTH($C$5,19)+1) | X5: =IF(OR($C$5="",$B$5="",21>=$B$5),"",EOMONTH($C$5,20)+1) | Y5: =IF(OR($C$5="",$B$5="",22>=$B$5),"",EOMONTH($C$5,21)+1) | Z5: =IF(OR($C$5="",$B$5="",23>=$B$5),"",EOMONTH($C$5,22)+1)
A6: Month end | B6: ← calendar months in view | C6: =IF(C5="","",MIN(EOMONTH(C5,0),'Cost Margin'!$B$9)) | D6: =IF(D5="","",MIN(EOMONTH(D5,0),'Cost Margin'!$B$9)) | E6: =IF(E5="","",MIN(EOMONTH(E5,0),'Cost Margin'!$B$9)) | F6: =IF(F5="","",MIN(EOMONTH(F5,0),'Cost Margin'!$B$9)) | G6: =IF(G5="","",MIN(EOMONTH(G5,0),'Cost Margin'!$B$9)) | H6: =IF(H5="","",MIN(EOMONTH(H5,0),'Cost Margin'!$B$9)) | I6: =IF(I5="","",MIN(EOMONTH(I5,0),'Cost Margin'!$B$9)) | J6: =IF(J5="","",MIN(EOMONTH(J5,0),'Cost Margin'!$B$9)) | ... Z6: =IF(Z5="","",MIN(EOMONTH(Z5,0),'Cost Margin'!$B$9))
A7: Row | B7: Person / line | C7: =IF(C5="","",TEXT(C5,"mmm yyyy")) | D7: =IF(D5="","",TEXT(D5,"mmm yyyy")) | E7: =IF(E5="","",TEXT(E5,"mmm yyyy")) | F7: =IF(F5="","",TEXT(F5,"mmm yyyy")) | G7: =IF(G5="","",TEXT(G5,"mmm yyyy")) | H7: =IF(H5="","",TEXT(H5,"mmm yyyy")) | I7: =IF(I5="","",TEXT(I5,"mmm yyyy")) | J7: =IF(J5="","",TEXT(J5,"mmm yyyy")) | ... Z7: =IF(Z5="","",TEXT(Z5,"mmm yyyy")) | AA7: Project total
A8: Working days in month, per person | AB8: Assignment
A9: 1 | B9: =IF('Cost Margin'!A17="","",'Cost Margin'!A17&IF('Cost Margin'!E17="",""," · "&'Cost Margin'!E17)) | C9: =IF(OR(C$5="",'Cost Margin'!$A17="",IF(OR('Cost Margin'!$B$14="Y",'Cost Margin'!$J17=""),'Cost Margin'!$B$8,'Cost Margin'!$J17)="",IF(OR('Cost Margin'!$B$14="Y",'Cost Margin'!$K17=""),'Cost Margin'!$B$9,'Cost Margin'!$K17)=""),0,IF(MIN(IF(OR('Cost Margin'!$B$14="Y",'Cost Margin'!$K17=""),'Cost Margin'!$B$9,'Cost Margin'!$K17),C$6)<MAX(IF(OR('Cost Margin'!$B$14="Y",'Cost Margin'!$J17=""),'Cost Margin'!$B$8,'Cost Margin'!$J17),C$5),0,IFERROR(NETWORKDAYS(MAX(IF(OR('Cost Margin'!$B$14="Y",'Cost Margin'!$J17=""),'Cost Margin'!$B$8,'Cost Margin'!$J17),C$5),MIN(IF(OR('Cost Margin'!$B$14="Y",'Cost Margin'!$K17=""),'Cost Margin'!$B$9,'Cost Margin'!$K17),C$6),INDEX(Settings!$A$35:$D$74,0,MATCH('Cost Margin'!$C17,Settings!$A$34:$D$34,0))),NETWORKDAYS(MAX(IF(OR('Cost Margin'!$B$14="Y",'Cost Margin'!$J17=""),'Cost Margin'!$B$8,'Cost Margin'!$J17),C$5),MIN(IF(OR('Cost Margin'!$B$14="Y",'Cost Margin'!$K17=""),'Cost Margin'!$B$9,'Cost Margin'!$K17),C$6))))) -> 0 | D9: =IF(OR(D$5="",'Cost Margin'!$A17="",IF(OR('Cost Margin'!$B$14="Y",'Cost Margin'!$J17=""),'Cost Margin'!$B$8,'Cost Margin'!$J17)="",IF(OR('Cost Margin'!$B$14="Y",'Cost Margin'!$K17=""),'Cost Margin'!$B$9,'Cost Margin'!$K17)=""),0,IF(MIN(IF(OR('Cost Margin'!$B$14="Y",'Cost Margin'!$K17=""),'Cost Margin'!$B$9,'Cost Margin'!$K17),D$6)<MAX(IF(OR('Cost Margin'!$B$14="Y",'Cost Margin'!$J17=""),'Cost Margin'!$B$8,'Cost Margin'!$J17),D$5),0,IFERROR(NETWORKDAYS(MAX(IF(OR('Cost Margin'!$B$14="Y",'Cost Margin'!$J17=""),'Cost Margin'!$B$8,'Cost Margin'!$J17),D$5),MIN(IF(OR('Cost Margin'!$B$14="Y",'Cost Margin'!$K17=""),'Cost Margin'!$B$9,'Cost Margin'!$K17),D$6),INDEX(Settings!$A$35:$D$74,0,MATCH('Cost Margin'!$C17,Settings!$A$34:$D$34,0))),NETWORKDAYS(MAX(IF(OR('Cost Margin'!$B$14="Y",'Cost Margin'!$J17=""),'Cost Margin'!$B$8,'Cost Margin'!$J17),D$5),MIN(IF(OR('Cost Margin'!$B$14="Y",'Cost Margin'!$K17=""),'Cost Margin'!$B$9,'Cost Margin'!$K17),D$6))))) -> 0 | E9: =IF(OR(E$5="",'Cost Margin'!$A17="",IF(OR('Cost Margin'!$B$14="Y",'Cost Margin'!$J17=""),'Cost Margin'!$B$8,'Cost Margin'!$J17)="",IF(OR('Cost Margin'!$B$14="Y",'Cost Margin'!$K17=""),'Cost Margin'!$B$9,'Cost Margin'!$K17)=""),0,IF(MIN(IF(OR('Cost Margin'!$B$14="Y",'Cost Margin'!$K17=""),'Cost Margin'!$B$9,'Cost Margin'!$K17),E$6)<MAX(IF(OR('Cost Margin'!$B$14="Y",'Cost Margin'!$J17=""),'Cost Margin'!$B$8,'Cost Margin'!$J17),E$5),0,IFERROR(NETWORKDAYS(MAX(IF(OR('Cost Margin'!$B$14="Y",'Cost Margin'!$J17=""),'Cost Margin'!$B$8,'Cost Margin'!$J17),E$5),MIN(IF(OR('Cost Margin'!$B$14="Y",'Cost Margin'!$K17=""),'Cost Margin'!$B$9,'Cost Margin'!$K17),E$6),INDEX(Settings!$A$35:$D$74,0,MATCH('Cost Margin'!$C17,Settings!$A$34:$D$34,0))),NETWORKDAYS(MAX(IF(OR('Cost Margin'!$B$14="Y",'Cost Margin'!$J17=""),'Cost Margin'!$B$8,'Cost Margin'!$J17),E$5),MIN(IF(OR('Cost Margin'!$B$14="Y",'Cost Margin'!$K17=""),'Cost Margin'!$B$9,'Cost Margin'!$K17),E$6))))) -> 0 | F9: =IF(OR(F$5="",'Cost Margin'!$A17="",IF(OR('Cost Margin'!$B$14="Y",'Cost Margin'!$J17=""),'Cost Margin'!$B$8,'Cost Margin'!$J17)="",IF(OR('Cost Margin'!$B$14="Y",'Cost Margin'!$K17=""),'Cost Margin'!$B$9,'Cost Margin'!$K17)=""),0,IF(MIN(IF(OR('Cost Margin'!$B$14="Y",'Cost Margin'!$K17=""),'Cost Margin'!$B$9,'Cost Margin'!$K17),F$6)<MAX(IF(OR('Cost Margin'!$B$14="Y",'Cost Margin'!$J17=""),'Cost Margin'!$B$8,'Cost Margin'!$J17),F$5),0,IFERROR(NETWORKDAYS(MAX(IF(OR('Cost Margin'!$B$14="Y",'Cost Margin'!$J17=""),'Cost Margin'!$B$8,'Cost Margin'!$J17),F$5),MIN(IF(OR('Cost Margin'!$B$14="Y",'Cost Margin'!$K17=""),'Cost Margin'!$B$9,'Cost Margin'!$K17),F$6),INDEX(Settings!$A$35:$D$74,0,MATCH('Cost Margin'!$C17,Settings!$A$34:$D$34,0))),NETWORKDAYS(MAX(IF(OR('Cost Margin'!$B$14="Y",'Cost Margin'!$J17=""),'Cost Margin'!$B$8,'Cost Margin'!$J17),F$5),MIN(IF(OR('Cost Margin'!$B$14="Y",'Cost Margin'!$K17=""),'Cost Margin'!$B$9,'Cost Margin'!$K17),F$6))))) -> 0 | G9: =IF(OR(G$5="",'Cost Margin'!$A17="",IF(OR('Cost Margin'!$B$14="Y",'Cost Margin'!$J17=""),'Cost Margin'!$B$8,'Cost Margin'!$J17)="",IF(OR('Cost Margin'!$B$14="Y",'Cost Margin'!$K17=""),'Cost Margin'!$B$9,'Cost Margin'!$K17)=""),0,IF(MIN(IF(OR('Cost Margin'!$B$14="Y",'Cost Margin'!$K17=""),'Cost Margin'!$B$9,'Cost Margin'!$K17),G$6)<MAX(IF(OR('Cost Margin'!$B$14="Y",'Cost Margin'!$J17=""),'Cost Margin'!$B$8,'Cost Margin'!$J17),G$5),0,IFERROR(NETWORKDAYS(MAX(IF(OR('Cost Margin'!$B$14="Y",'Cost Margin'!$J17=""),'Cost Margin'!$B$8,'Cost Margin'!$J17),G$5),MIN(IF(OR('Cost Margin'!$B$14="Y",'Cost Margin'!$K17=""),'Cost Margin'!$B$9,'Cost Margin'!$K17),G$6),INDEX(Settings!$A$35:$D$74,0,MATCH('Cost Margin'!$C17,Settings!$A$34:$D$34,0))),NETWORKDAYS(MAX(IF(OR('Cost Margin'!$B$14="Y",'Cost Margin'!$J17=""),'Cost Margin'!$B$8,'Cost Margin'!$J17),G$5),MIN(IF(OR('Cost Margin'!$B$14="Y",'Cost Margin'!$K17=""),'Cost Margin'!$B$9,'Cost Margin'!$K17),G$6))))) -> 0 | H9: =IF(OR(H$5="",'Cost Margin'!$A17="",IF(OR('Cost Margin'!$B$14="Y",'Cost Margin'!$J17=""),'Cost Margin'!$B$8,'Cost Margin'!$J17)="",IF(OR('Cost Margin'!$B$14="Y",'Cost Margin'!$K17=""),'Cost Margin'!$B$9,'Cost Margin'!$K17)=""),0,IF(MIN(IF(OR('Cost Margin'!$B$14="Y",'Cost Margin'!$K17=""),'Cost Margin'!$B$9,'Cost Margin'!$K17),H$6)<MAX(IF(OR('Cost Margin'!$B$14="Y",'Cost Margin'!$J17=""),'Cost Margin'!$B$8,'Cost Margin'!$J17),H$5),0,IFERROR(NETWORKDAYS(MAX(IF(OR('Cost Margin'!$B$14="Y",'Cost Margin'!$J17=""),'Cost Margin'!$B$8,'Cost Margin'!$J17),H$5),MIN(IF(OR('Cost Margin'!$B$14="Y",'Cost Margin'!$K17=""),'Cost Margin'!$B$9,'Cost Margin'!$K17),H$6),INDEX(Settings!$A$35:$D$74,0,MATCH('Cost Margin'!$C17,Settings!$A$34:$D$34,0))),NETWORKDAYS(MAX(IF(OR('Cost Margin'!$B$14="Y",'Cost Margin'!$J17=""),'Cost Margin'!$B$8,'Cost Margin'!$J17),H$5),MIN(IF(OR('Cost Margin'!$B$14="Y",'Cost Margin'!$K17=""),'Cost Margin'!$B$9,'Cost Margin'!$K17),H$6))))) -> 0 | I9: =IF(OR(I$5="",'Cost Margin'!$A17="",IF(OR('Cost Margin'!$B$14="Y",'Cost Margin'!$J17=""),'Cost Margin'!$B$8,'Cost Margin'!$J17)="",IF(OR('Cost Margin'!$B$14="Y",'Cost Margin'!$K17=""),'Cost Margin'!$B$9,'Cost Margin'!$K17)=""),0,IF(MIN(IF(OR('Cost Margin'!$B$14="Y",'Cost Margin'!$K17=""),'Cost Margin'!$B$9,'Cost Margin'!$K17),I$6)<MAX(IF(OR('Cost Margin'!$B$14="Y",'Cost Margin'!$J17=""),'Cost Margin'!$B$8,'Cost Margin'!$J17),I$5),0,IFERROR(NETWORKDAYS(MAX(IF(OR('Cost Margin'!$B$14="Y",'Cost Margin'!$J17=""),'Cost Margin'!$B$8,'Cost Margin'!$J17),I$5),MIN(IF(OR('Cost Margin'!$B$14="Y",'Cost Margin'!$K17=""),'Cost Margin'!$B$9,'Cost Margin'!$K17),I$6),INDEX(Settings!$A$35:$D$74,0,MATCH('Cost Margin'!$C17,Settings!$A$34:$D$34,0))),NETWORKDAYS(MAX(IF(OR('Cost Margin'!$B$14="Y",'Cost Margin'!$J17=""),'Cost Margin'!$B$8,'Cost Margin'!$J17),I$5),MIN(IF(OR('Cost Margin'!$B$14="Y",'Cost Margin'!$K17=""),'Cost Margin'!$B$9,'Cost Margin'!$K17),I$6))))) -> 0 | J9: =IF(OR(J$5="",'Cost Margin'!$A17="",IF(OR('Cost Margin'!$B$14="Y",'Cost Margin'!$J17=""),'Cost Margin'!$B$8,'Cost Margin'!$J17)="",IF(OR('Cost Margin'!$B$14="Y",'Cost Margin'!$K17=""),'Cost Margin'!$B$9,'Cost Margin'!$K17)=""),0,IF(MIN(IF(OR('Cost Margin'!$B$14="Y",'Cost Margin'!$K17=""),'Cost Margin'!$B$9,'Cost Margin'!$K17),J$6)<MAX(IF(OR('Cost Margin'!$B$14="Y",'Cost Margin'!$J17=""),'Cost Margin'!$B$8,'Cost Margin'!$J17),J$5),0,IFERROR(NETWORKDAYS(MAX(IF(OR('Cost Margin'!$B$14="Y",'Cost Margin'!$J17=""),'Cost Margin'!$B$8,'Cost Margin'!$J17),J$5),MIN(IF(OR('Cost Margin'!$B$14="Y",'Cost Margin'!$K17=""),'Cost Margin'!$B$9,'Cost Margin'!$K17),J$6),INDEX(Settings!$A$35:$D$74,0,MATCH('Cost Margin'!$C17,Settings!$A$34:$D$34,0))),NETWORKDAYS(MAX(IF(OR('Cost Margin'!$B$14="Y",'Cost Margin'!$J17=""),'Cost Margin'!$B$8,'Cost Margin'!$J17),J$5),MIN(IF(OR('Cost Margin'!$B$14="Y",'Cost Margin'!$K17=""),'Cost Margin'!$B$9,'Cost Margin'!$K17),J$6))))) -> 0 | ... Z9: =IF(OR(Z$5="",'Cost Margin'!$A17="",IF(OR('Cost Margin'!$B$14="Y",'Cost Margin'!$J17=""),'Cost Margin'!$B$8,'Cost Margin'!$J17)="",IF(OR('Cost Margin'!$B$14="Y",'Cost Margin'!$K17=""),'Cost Margin'!$B$9,'Cost Margin'!$K17)=""),0,IF(MIN(IF(OR('Cost Margin'!$B$14="Y",'Cost Margin'!$K17=""),'Cost Margin'!$B$9,'Cost Margin'!$K17),Z$6)<MAX(IF(OR('Cost Margin'!$B$14="Y",'Cost Margin'!$J17=""),'Cost Margin'!$B$8,'Cost Margin'!$J17),Z$5),0,IFERROR(NETWORKDAYS(MAX(IF(OR('Cost Margin'!$B$14="Y",'Cost Margin'!$J17=""),'Cost Margin'!$B$8,'Cost Margin'!$J17),Z$5),MIN(IF(OR('Cost Margin'!$B$14="Y",'Cost Margin'!$K17=""),'Cost Margin'!$B$9,'Cost Margin'!$K17),Z$6),INDEX(Settings!$A$35:$D$74,0,MATCH('Cost Margin'!$C17,Settings!$A$34:$D$34,0))),NETWORKDAYS(MAX(IF(OR('Cost Margin'!$B$14="Y",'Cost Margin'!$J17=""),'Cost Margin'!$B$8,'Cost Margin'!$J17),Z$5),MIN(IF(OR('Cost Margin'!$B$14="Y",'Cost Margin'!$K17=""),'Cost Margin'!$B$9,'Cost Margin'!$K17),Z$6))))) -> 0 | AB9: =IF('Cost Margin'!A17="","",IF('Cost Margin'!E17="","(unassigned)",'Cost Margin'!E17))
A10: 2 | B10: =IF('Cost Margin'!A18="","",'Cost Margin'!A18&IF('Cost Margin'!E18="",""," · "&'Cost Margin'!E18)) | C10: =IF(OR(C$5="",'Cost Margin'!$A18="",IF(OR('Cost Margin'!$B$14="Y",'Cost Margin'!$J18=""),'Cost Margin'!$B$8,'Cost Margin'!$J18)="",IF(OR('Cost Margin'!$B$14="Y",'Cost Margin'!$K18=""),'Cost Margin'!$B$9,'Cost Margin'!$K18)=""),0,IF(MIN(IF(OR('Cost Margin'!$B$14="Y",'Cost Margin'!$K18=""),'Cost Margin'!$B$9,'Cost Margin'!$K18),C$6)<MAX(IF(OR('Cost Margin'!$B$14="Y",'Cost Margin'!$J18=""),'Cost Margin'!$B$8,'Cost Margin'!$J18),C$5),0,IFERROR(NETWORKDAYS(MAX(IF(OR('Cost Margin'!$B$14="Y",'Cost Margin'!$J18=""),'Cost Margin'!$B$8,'Cost Margin'!$J18),C$5),MIN(IF(OR('Cost Margin'!$B$14="Y",'Cost Margin'!$K18=""),'Cost Margin'!$B$9,'Cost Margin'!$K18),C$6),INDEX(Settings!$A$35:$D$74,0,MATCH('Cost Margin'!$C18,Settings!$A$34:$D$34,0))),NETWORKDAYS(MAX(IF(OR('Cost Margin'!$B$14="Y",'Cost Margin'!$J18=""),'Cost Margin'!$B$8,'Cost Margin'!$J18),C$5),MIN(IF(OR('Cost Margin'!$B$14="Y",'Cost Margin'!$K18=""),'Cost Margin'!$B$9,'Cost Margin'!$K18),C$6))))) -> 0 | D10: =IF(OR(D$5="",'Cost Margin'!$A18="",IF(OR('Cost Margin'!$B$14="Y",'Cost Margin'!$J18=""),'Cost Margin'!$B$8,'Cost Margin'!$J18)="",IF(OR('Cost Margin'!$B$14="Y",'Cost Margin'!$K18=""),'Cost Margin'!$B$9,'Cost Margin'!$K18)=""),0,IF(MIN(IF(OR('Cost Margin'!$B$14="Y",'Cost Margin'!$K18=""),'Cost Margin'!$B$9,'Cost Margin'!$K18),D$6)<MAX(IF(OR('Cost Margin'!$B$14="Y",'Cost Margin'!$J18=""),'Cost Margin'!$B$8,'Cost Margin'!$J18),D$5),0,IFERROR(NETWORKDAYS(MAX(IF(OR('Cost Margin'!$B$14="Y",'Cost Margin'!$J18=""),'Cost Margin'!$B$8,'Cost Margin'!$J18),D$5),MIN(IF(OR('Cost Margin'!$B$14="Y",'Cost Margin'!$K18=""),'Cost Margin'!$B$9,'Cost Margin'!$K18),D$6),INDEX(Settings!$A$35:$D$74,0,MATCH('Cost Margin'!$C18,Settings!$A$34:$D$34,0))),NETWORKDAYS(MAX(IF(OR('Cost Margin'!$B$14="Y",'Cost Margin'!$J18=""),'Cost Margin'!$B$8,'Cost Margin'!$J18),D$5),MIN(IF(OR('Cost Margin'!$B$14="Y",'Cost Margin'!$K18=""),'Cost Margin'!$B$9,'Cost Margin'!$K18),D$6))))) -> 0 | E10: =IF(OR(E$5="",'Cost Margin'!$A18="",IF(OR('Cost Margin'!$B$14="Y",'Cost Margin'!$J18=""),'Cost Margin'!$B$8,'Cost Margin'!$J18)="",IF(OR('Cost Margin'!$B$14="Y",'Cost Margin'!$K18=""),'Cost Margin'!$B$9,'Cost Margin'!$K18)=""),0,IF(MIN(IF(OR('Cost Margin'!$B$14="Y",'Cost Margin'!$K18=""),'Cost Margin'!$B$9,'Cost Margin'!$K18),E$6)<MAX(IF(OR('Cost Margin'!$B$14="Y",'Cost Margin'!$J18=""),'Cost Margin'!$B$8,'Cost Margin'!$J18),E$5),0,IFERROR(NETWORKDAYS(MAX(IF(OR('Cost Margin'!$B$14="Y",'Cost Margin'!$J18=""),'Cost Margin'!$B$8,'Cost Margin'!$J18),E$5),MIN(IF(OR('Cost Margin'!$B$14="Y",'Cost Margin'!$K18=""),'Cost Margin'!$B$9,'Cost Margin'!$K18),E$6),INDEX(Settings!$A$35:$D$74,0,MATCH('Cost Margin'!$C18,Settings!$A$34:$D$34,0))),NETWORKDAYS(MAX(IF(OR('Cost Margin'!$B$14="Y",'Cost Margin'!$J18=""),'Cost Margin'!$B$8,'Cost Margin'!$J18),E$5),MIN(IF(OR('Cost Margin'!$B$14="Y",'Cost Margin'!$K18=""),'Cost Margin'!$B$9,'Cost Margin'!$K18),E$6))))) -> 0 | F10: =IF(OR(F$5="",'Cost Margin'!$A18="",IF(OR('Cost Margin'!$B$14="Y",'Cost Margin'!$J18=""),'Cost Margin'!$B$8,'Cost Margin'!$J18)="",IF(OR('Cost Margin'!$B$14="Y",'Cost Margin'!$K18=""),'Cost Margin'!$B$9,'Cost Margin'!$K18)=""),0,IF(MIN(IF(OR('Cost Margin'!$B$14="Y",'Cost Margin'!$K18=""),'Cost Margin'!$B$9,'Cost Margin'!$K18),F$6)<MAX(IF(OR('Cost Margin'!$B$14="Y",'Cost Margin'!$J18=""),'Cost Margin'!$B$8,'Cost Margin'!$J18),F$5),0,IFERROR(NETWORKDAYS(MAX(IF(OR('Cost Margin'!$B$14="Y",'Cost Margin'!$J18=""),'Cost Margin'!$B$8,'Cost Margin'!$J18),F$5),MIN(IF(OR('Cost Margin'!$B$14="Y",'Cost Margin'!$K18=""),'Cost Margin'!$B$9,'Cost Margin'!$K18),F$6),INDEX(Settings!$A$35:$D$74,0,MATCH('Cost Margin'!$C18,Settings!$A$34:$D$34,0))),NETWORKDAYS(MAX(IF(OR('Cost Margin'!$B$14="Y",'Cost Margin'!$J18=""),'Cost Margin'!$B$8,'Cost Margin'!$J18),F$5),MIN(IF(OR('Cost Margin'!$B$14="Y",'Cost Margin'!$K18=""),'Cost Margin'!$B$9,'Cost Margin'!$K18),F$6))))) -> 0 | G10: =IF(OR(G$5="",'Cost Margin'!$A18="",IF(OR('Cost Margin'!$B$14="Y",'Cost Margin'!$J18=""),'Cost Margin'!$B$8,'Cost Margin'!$J18)="",IF(OR('Cost Margin'!$B$14="Y",'Cost Margin'!$K18=""),'Cost Margin'!$B$9,'Cost Margin'!$K18)=""),0,IF(MIN(IF(OR('Cost Margin'!$B$14="Y",'Cost Margin'!$K18=""),'Cost Margin'!$B$9,'Cost Margin'!$K18),G$6)<MAX(IF(OR('Cost Margin'!$B$14="Y",'Cost Margin'!$J18=""),'Cost Margin'!$B$8,'Cost Margin'!$J18),G$5),0,IFERROR(NETWORKDAYS(MAX(IF(OR('Cost Margin'!$B$14="Y",'Cost Margin'!$J18=""),'Cost Margin'!$B$8,'Cost Margin'!$J18),G$5),MIN(IF(OR('Cost Margin'!$B$14="Y",'Cost Margin'!$K18=""),'Cost Margin'!$B$9,'Cost Margin'!$K18),G$6),INDEX(Settings!$A$35:$D$74,0,MATCH('Cost Margin'!$C18,Settings!$A$34:$D$34,0))),NETWORKDAYS(MAX(IF(OR('Cost Margin'!$B$14="Y",'Cost Margin'!$J18=""),'Cost Margin'!$B$8,'Cost Margin'!$J18),G$5),MIN(IF(OR('Cost Margin'!$B$14="Y",'Cost Margin'!$K18=""),'Cost Margin'!$B$9,'Cost Margin'!$K18),G$6))))) -> 0 | H10: =IF(OR(H$5="",'Cost Margin'!$A18="",IF(OR('Cost Margin'!$B$14="Y",'Cost Margin'!$J18=""),'Cost Margin'!$B$8,'Cost Margin'!$J18)="",IF(OR('Cost Margin'!$B$14="Y",'Cost Margin'!$K18=""),'Cost Margin'!$B$9,'Cost Margin'!$K18)=""),0,IF(MIN(IF(OR('Cost Margin'!$B$14="Y",'Cost Margin'!$K18=""),'Cost Margin'!$B$9,'Cost Margin'!$K18),H$6)<MAX(IF(OR('Cost Margin'!$B$14="Y",'Cost Margin'!$J18=""),'Cost Margin'!$B$8,'Cost Margin'!$J18),H$5),0,IFERROR(NETWORKDAYS(MAX(IF(OR('Cost Margin'!$B$14="Y",'Cost Margin'!$J18=""),'Cost Margin'!$B$8,'Cost Margin'!$J18),H$5),MIN(IF(OR('Cost Margin'!$B$14="Y",'Cost Margin'!$K18=""),'Cost Margin'!$B$9,'Cost Margin'!$K18),H$6),INDEX(Settings!$A$35:$D$74,0,MATCH('Cost Margin'!$C18,Settings!$A$34:$D$34,0))),NETWORKDAYS(MAX(IF(OR('Cost Margin'!$B$14="Y",'Cost Margin'!$J18=""),'Cost Margin'!$B$8,'Cost Margin'!$J18),H$5),MIN(IF(OR('Cost Margin'!$B$14="Y",'Cost Margin'!$K18=""),'Cost Margin'!$B$9,'Cost Margin'!$K18),H$6))))) -> 0 | I10: =IF(OR(I$5="",'Cost Margin'!$A18="",IF(OR('Cost Margin'!$B$14="Y",'Cost Margin'!$J18=""),'Cost Margin'!$B$8,'Cost Margin'!$J18)="",IF(OR('Cost Margin'!$B$14="Y",'Cost Margin'!$K18=""),'Cost Margin'!$B$9,'Cost Margin'!$K18)=""),0,IF(MIN(IF(OR('Cost Margin'!$B$14="Y",'Cost Margin'!$K18=""),'Cost Margin'!$B$9,'Cost Margin'!$K18),I$6)<MAX(IF(OR('Cost Margin'!$B$14="Y",'Cost Margin'!$J18=""),'Cost Margin'!$B$8,'Cost Margin'!$J18),I$5),0,IFERROR(NETWORKDAYS(MAX(IF(OR('Cost Margin'!$B$14="Y",'Cost Margin'!$J18=""),'Cost Margin'!$B$8,'Cost Margin'!$J18),I$5),MIN(IF(OR('Cost Margin'!$B$14="Y",'Cost Margin'!$K18=""),'Cost Margin'!$B$9,'Cost Margin'!$K18),I$6),INDEX(Settings!$A$35:$D$74,0,MATCH('Cost Margin'!$C18,Settings!$A$34:$D$34,0))),NETWORKDAYS(MAX(IF(OR('Cost Margin'!$B$14="Y",'Cost Margin'!$J18=""),'Cost Margin'!$B$8,'Cost Margin'!$J18),I$5),MIN(IF(OR('Cost Margin'!$B$14="Y",'Cost Margin'!$K18=""),'Cost Margin'!$B$9,'Cost Margin'!$K18),I$6))))) -> 0 | J10: =IF(OR(J$5="",'Cost Margin'!$A18="",IF(OR('Cost Margin'!$B$14="Y",'Cost Margin'!$J18=""),'Cost Margin'!$B$8,'Cost Margin'!$J18)="",IF(OR('Cost Margin'!$B$14="Y",'Cost Margin'!$K18=""),'Cost Margin'!$B$9,'Cost Margin'!$K18)=""),0,IF(MIN(IF(OR('Cost Margin'!$B$14="Y",'Cost Margin'!$K18=""),'Cost Margin'!$B$9,'Cost Margin'!$K18),J$6)<MAX(IF(OR('Cost Margin'!$B$14="Y",'Cost Margin'!$J18=""),'Cost Margin'!$B$8,'Cost Margin'!$J18),J$5),0,IFERROR(NETWORKDAYS(MAX(IF(OR('Cost Margin'!$B$14="Y",'Cost Margin'!$J18=""),'Cost Margin'!$B$8,'Cost Margin'!$J18),J$5),MIN(IF(OR('Cost Margin'!$B$14="Y",'Cost Margin'!$K18=""),'Cost Margin'!$B$9,'Cost Margin'!$K18),J$6),INDEX(Settings!$A$35:$D$74,0,MATCH('Cost Margin'!$C18,Settings!$A$34:$D$34,0))),NETWORKDAYS(MAX(IF(OR('Cost Margin'!$B$14="Y",'Cost Margin'!$J18=""),'Cost Margin'!$B$8,'Cost Margin'!$J18),J$5),MIN(IF(OR('Cost Margin'!$B$14="Y",'Cost Margin'!$K18=""),'Cost Margin'!$B$9,'Cost Margin'!$K18),J$6))))) -> 0 | ... Z10: =IF(OR(Z$5="",'Cost Margin'!$A18="",IF(OR('Cost Margin'!$B$14="Y",'Cost Margin'!$J18=""),'Cost Margin'!$B$8,'Cost Margin'!$J18)="",IF(OR('Cost Margin'!$B$14="Y",'Cost Margin'!$K18=""),'Cost Margin'!$B$9,'Cost Margin'!$K18)=""),0,IF(MIN(IF(OR('Cost Margin'!$B$14="Y",'Cost Margin'!$K18=""),'Cost Margin'!$B$9,'Cost Margin'!$K18),Z$6)<MAX(IF(OR('Cost Margin'!$B$14="Y",'Cost Margin'!$J18=""),'Cost Margin'!$B$8,'Cost Margin'!$J18),Z$5),0,IFERROR(NETWORKDAYS(MAX(IF(OR('Cost Margin'!$B$14="Y",'Cost Margin'!$J18=""),'Cost Margin'!$B$8,'Cost Margin'!$J18),Z$5),MIN(IF(OR('Cost Margin'!$B$14="Y",'Cost Margin'!$K18=""),'Cost Margin'!$B$9,'Cost Margin'!$K18),Z$6),INDEX(Settings!$A$35:$D$74,0,MATCH('Cost Margin'!$C18,Settings!$A$34:$D$34,0))),NETWORKDAYS(MAX(IF(OR('Cost Margin'!$B$14="Y",'Cost Margin'!$J18=""),'Cost Margin'!$B$8,'Cost Margin'!$J18),Z$5),MIN(IF(OR('Cost Margin'!$B$14="Y",'Cost Margin'!$K18=""),'Cost Margin'!$B$9,'Cost Margin'!$K18),Z$6))))) -> 0 | AB10: =IF('Cost Margin'!A18="","",IF('Cost Margin'!E18="","(unassigned)",'Cost Margin'!E18))
A11: 3 | B11: =IF('Cost Margin'!A19="","",'Cost Margin'!A19&IF('Cost Margin'!E19="",""," · "&'Cost Margin'!E19)) | C11: =IF(OR(C$5="",'Cost Margin'!$A19="",IF(OR('Cost Margin'!$B$14="Y",'Cost Margin'!$J19=""),'Cost Margin'!$B$8,'Cost Margin'!$J19)="",IF(OR('Cost Margin'!$B$14="Y",'Cost Margin'!$K19=""),'Cost Margin'!$B$9,'Cost Margin'!$K19)=""),0,IF(MIN(IF(OR('Cost Margin'!$B$14="Y",'Cost Margin'!$K19=""),'Cost Margin'!$B$9,'Cost Margin'!$K19),C$6)<MAX(IF(OR('Cost Margin'!$B$14="Y",'Cost Margin'!$J19=""),'Cost Margin'!$B$8,'Cost Margin'!$J19),C$5),0,IFERROR(NETWORKDAYS(MAX(IF(OR('Cost Margin'!$B$14="Y",'Cost Margin'!$J19=""),'Cost Margin'!$B$8,'Cost Margin'!$J19),C$5),MIN(IF(OR('Cost Margin'!$B$14="Y",'Cost Margin'!$K19=""),'Cost Margin'!$B$9,'Cost Margin'!$K19),C$6),INDEX(Settings!$A$35:$D$74,0,MATCH('Cost Margin'!$C19,Settings!$A$34:$D$34,0))),NETWORKDAYS(MAX(IF(OR('Cost Margin'!$B$14="Y",'Cost Margin'!$J19=""),'Cost Margin'!$B$8,'Cost Margin'!$J19),C$5),MIN(IF(OR('Cost Margin'!$B$14="Y",'Cost Margin'!$K19=""),'Cost Margin'!$B$9,'Cost Margin'!$K19),C$6))))) -> 0 | D11: =IF(OR(D$5="",'Cost Margin'!$A19="",IF(OR('Cost Margin'!$B$14="Y",'Cost Margin'!$J19=""),'Cost Margin'!$B$8,'Cost Margin'!$J19)="",IF(OR('Cost Margin'!$B$14="Y",'Cost Margin'!$K19=""),'Cost Margin'!$B$9,'Cost Margin'!$K19)=""),0,IF(MIN(IF(OR('Cost Margin'!$B$14="Y",'Cost Margin'!$K19=""),'Cost Margin'!$B$9,'Cost Margin'!$K19),D$6)<MAX(IF(OR('Cost Margin'!$B$14="Y",'Cost Margin'!$J19=""),'Cost Margin'!$B$8,'Cost Margin'!$J19),D$5),0,IFERROR(NETWORKDAYS(MAX(IF(OR('Cost Margin'!$B$14="Y",'Cost Margin'!$J19=""),'Cost Margin'!$B$8,'Cost Margin'!$J19),D$5),MIN(IF(OR('Cost Margin'!$B$14="Y",'Cost Margin'!$K19=""),'Cost Margin'!$B$9,'Cost Margin'!$K19),D$6),INDEX(Settings!$A$35:$D$74,0,MATCH('Cost Margin'!$C19,Settings!$A$34:$D$34,0))),NETWORKDAYS(MAX(IF(OR('Cost Margin'!$B$14="Y",'Cost Margin'!$J19=""),'Cost Margin'!$B$8,'Cost Margin'!$J19),D$5),MIN(IF(OR('Cost Margin'!$B$14="Y",'Cost Margin'!$K19=""),'Cost Margin'!$B$9,'Cost Margin'!$K19),D$6))))) -> 0 | E11: =IF(OR(E$5="",'Cost Margin'!$A19="",IF(OR('Cost Margin'!$B$14="Y",'Cost Margin'!$J19=""),'Cost Margin'!$B$8,'Cost Margin'!$J19)="",IF(OR('Cost Margin'!$B$14="Y",'Cost Margin'!$K19=""),'Cost Margin'!$B$9,'Cost Margin'!$K19)=""),0,IF(MIN(IF(OR('Cost Margin'!$B$14="Y",'Cost Margin'!$K19=""),'Cost Margin'!$B$9,'Cost Margin'!$K19),E$6)<MAX(IF(OR('Cost Margin'!$B$14="Y",'Cost Margin'!$J19=""),'Cost Margin'!$B$8,'Cost Margin'!$J19),E$5),0,IFERROR(NETWORKDAYS(MAX(IF(OR('Cost Margin'!$B$14="Y",'Cost Margin'!$J19=""),'Cost Margin'!$B$8,'Cost Margin'!$J19),E$5),MIN(IF(OR('Cost Margin'!$B$14="Y",'Cost Margin'!$K19=""),'Cost Margin'!$B$9,'Cost Margin'!$K19),E$6),INDEX(Settings!$A$35:$D$74,0,MATCH('Cost Margin'!$C19,Settings!$A$34:$D$34,0))),NETWORKDAYS(MAX(IF(OR('Cost Margin'!$B$14="Y",'Cost Margin'!$J19=""),'Cost Margin'!$B$8,'Cost Margin'!$J19),E$5),MIN(IF(OR('Cost Margin'!$B$14="Y",'Cost Margin'!$K19=""),'Cost Margin'!$B$9,'Cost Margin'!$K19),E$6))))) -> 0 | F11: =IF(OR(F$5="",'Cost Margin'!$A19="",IF(OR('Cost Margin'!$B$14="Y",'Cost Margin'!$J19=""),'Cost Margin'!$B$8,'Cost Margin'!$J19)="",IF(OR('Cost Margin'!$B$14="Y",'Cost Margin'!$K19=""),'Cost Margin'!$B$9,'Cost Margin'!$K19)=""),0,IF(MIN(IF(OR('Cost Margin'!$B$14="Y",'Cost Margin'!$K19=""),'Cost Margin'!$B$9,'Cost Margin'!$K19),F$6)<MAX(IF(OR('Cost Margin'!$B$14="Y",'Cost Margin'!$J19=""),'Cost Margin'!$B$8,'Cost Margin'!$J19),F$5),0,IFERROR(NETWORKDAYS(MAX(IF(OR('Cost Margin'!$B$14="Y",'Cost Margin'!$J19=""),'Cost Margin'!$B$8,'Cost Margin'!$J19),F$5),MIN(IF(OR('Cost Margin'!$B$14="Y",'Cost Margin'!$K19=""),'Cost Margin'!$B$9,'Cost Margin'!$K19),F$6),INDEX(Settings!$A$35:$D$74,0,MATCH('Cost Margin'!$C19,Settings!$A$34:$D$34,0))),NETWORKDAYS(MAX(IF(OR('Cost Margin'!$B$14="Y",'Cost Margin'!$J19=""),'Cost Margin'!$B$8,'Cost Margin'!$J19),F$5),MIN(IF(OR('Cost Margin'!$B$14="Y",'Cost Margin'!$K19=""),'Cost Margin'!$B$9,'Cost Margin'!$K19),F$6))))) -> 0 | G11: =IF(OR(G$5="",'Cost Margin'!$A19="",IF(OR('Cost Margin'!$B$14="Y",'Cost Margin'!$J19=""),'Cost Margin'!$B$8,'Cost Margin'!$J19)="",IF(OR('Cost Margin'!$B$14="Y",'Cost Margin'!$K19=""),'Cost Margin'!$B$9,'Cost Margin'!$K19)=""),0,IF(MIN(IF(OR('Cost Margin'!$B$14="Y",'Cost Margin'!$K19=""),'Cost Margin'!$B$9,'Cost Margin'!$K19),G$6)<MAX(IF(OR('Cost Margin'!$B$14="Y",'Cost Margin'!$J19=""),'Cost Margin'!$B$8,'Cost Margin'!$J19),G$5),0,IFERROR(NETWORKDAYS(MAX(IF(OR('Cost Margin'!$B$14="Y",'Cost Margin'!$J19=""),'Cost Margin'!$B$8,'Cost Margin'!$J19),G$5),MIN(IF(OR('Cost Margin'!$B$14="Y",'Cost Margin'!$K19=""),'Cost Margin'!$B$9,'Cost Margin'!$K19),G$6),INDEX(Settings!$A$35:$D$74,0,MATCH('Cost Margin'!$C19,Settings!$A$34:$D$34,0))),NETWORKDAYS(MAX(IF(OR('Cost Margin'!$B$14="Y",'Cost Margin'!$J19=""),'Cost Margin'!$B$8,'Cost Margin'!$J19),G$5),MIN(IF(OR('Cost Margin'!$B$14="Y",'Cost Margin'!$K19=""),'Cost Margin'!$B$9,'Cost Margin'!$K19),G$6))))) -> 0 | H11: =IF(OR(H$5="",'Cost Margin'!$A19="",IF(OR('Cost Margin'!$B$14="Y",'Cost Margin'!$J19=""),'Cost Margin'!$B$8,'Cost Margin'!$J19)="",IF(OR('Cost Margin'!$B$14="Y",'Cost Margin'!$K19=""),'Cost Margin'!$B$9,'Cost Margin'!$K19)=""),0,IF(MIN(IF(OR('Cost Margin'!$B$14="Y",'Cost Margin'!$K19=""),'Cost Margin'!$B$9,'Cost Margin'!$K19),H$6)<MAX(IF(OR('Cost Margin'!$B$14="Y",'Cost Margin'!$J19=""),'Cost Margin'!$B$8,'Cost Margin'!$J19),H$5),0,IFERROR(NETWORKDAYS(MAX(IF(OR('Cost Margin'!$B$14="Y",'Cost Margin'!$J19=""),'Cost Margin'!$B$8,'Cost Margin'!$J19),H$5),MIN(IF(OR('Cost Margin'!$B$14="Y",'Cost Margin'!$K19=""),'Cost Margin'!$B$9,'Cost Margin'!$K19),H$6),INDEX(Settings!$A$35:$D$74,0,MATCH('Cost Margin'!$C19,Settings!$A$34:$D$34,0))),NETWORKDAYS(MAX(IF(OR('Cost Margin'!$B$14="Y",'Cost Margin'!$J19=""),'Cost Margin'!$B$8,'Cost Margin'!$J19),H$5),MIN(IF(OR('Cost Margin'!$B$14="Y",'Cost Margin'!$K19=""),'Cost Margin'!$B$9,'Cost Margin'!$K19),H$6))))) -> 0 | I11: =IF(OR(I$5="",'Cost Margin'!$A19="",IF(OR('Cost Margin'!$B$14="Y",'Cost Margin'!$J19=""),'Cost Margin'!$B$8,'Cost Margin'!$J19)="",IF(OR('Cost Margin'!$B$14="Y",'Cost Margin'!$K19=""),'Cost Margin'!$B$9,'Cost Margin'!$K19)=""),0,IF(MIN(IF(OR('Cost Margin'!$B$14="Y",'Cost Margin'!$K19=""),'Cost Margin'!$B$9,'Cost Margin'!$K19),I$6)<MAX(IF(OR('Cost Margin'!$B$14="Y",'Cost Margin'!$J19=""),'Cost Margin'!$B$8,'Cost Margin'!$J19),I$5),0,IFERROR(NETWORKDAYS(MAX(IF(OR('Cost Margin'!$B$14="Y",'Cost Margin'!$J19=""),'Cost Margin'!$B$8,'Cost Margin'!$J19),I$5),MIN(IF(OR('Cost Margin'!$B$14="Y",'Cost Margin'!$K19=""),'Cost Margin'!$B$9,'Cost Margin'!$K19),I$6),INDEX(Settings!$A$35:$D$74,0,MATCH('Cost Margin'!$C19,Settings!$A$34:$D$34,0))),NETWORKDAYS(MAX(IF(OR('Cost Margin'!$B$14="Y",'Cost Margin'!$J19=""),'Cost Margin'!$B$8,'Cost Margin'!$J19),I$5),MIN(IF(OR('Cost Margin'!$B$14="Y",'Cost Margin'!$K19=""),'Cost Margin'!$B$9,'Cost Margin'!$K19),I$6))))) -> 0 | J11: =IF(OR(J$5="",'Cost Margin'!$A19="",IF(OR('Cost Margin'!$B$14="Y",'Cost Margin'!$J19=""),'Cost Margin'!$B$8,'Cost Margin'!$J19)="",IF(OR('Cost Margin'!$B$14="Y",'Cost Margin'!$K19=""),'Cost Margin'!$B$9,'Cost Margin'!$K19)=""),0,IF(MIN(IF(OR('Cost Margin'!$B$14="Y",'Cost Margin'!$K19=""),'Cost Margin'!$B$9,'Cost Margin'!$K19),J$6)<MAX(IF(OR('Cost Margin'!$B$14="Y",'Cost Margin'!$J19=""),'Cost Margin'!$B$8,'Cost Margin'!$J19),J$5),0,IFERROR(NETWORKDAYS(MAX(IF(OR('Cost Margin'!$B$14="Y",'Cost Margin'!$J19=""),'Cost Margin'!$B$8,'Cost Margin'!$J19),J$5),MIN(IF(OR('Cost Margin'!$B$14="Y",'Cost Margin'!$K19=""),'Cost Margin'!$B$9,'Cost Margin'!$K19),J$6),INDEX(Settings!$A$35:$D$74,0,MATCH('Cost Margin'!$C19,Settings!$A$34:$D$34,0))),NETWORKDAYS(MAX(IF(OR('Cost Margin'!$B$14="Y",'Cost Margin'!$J19=""),'Cost Margin'!$B$8,'Cost Margin'!$J19),J$5),MIN(IF(OR('Cost Margin'!$B$14="Y",'Cost Margin'!$K19=""),'Cost Margin'!$B$9,'Cost Margin'!$K19),J$6))))) -> 0 | ... Z11: =IF(OR(Z$5="",'Cost Margin'!$A19="",IF(OR('Cost Margin'!$B$14="Y",'Cost Margin'!$J19=""),'Cost Margin'!$B$8,'Cost Margin'!$J19)="",IF(OR('Cost Margin'!$B$14="Y",'Cost Margin'!$K19=""),'Cost Margin'!$B$9,'Cost Margin'!$K19)=""),0,IF(MIN(IF(OR('Cost Margin'!$B$14="Y",'Cost Margin'!$K19=""),'Cost Margin'!$B$9,'Cost Margin'!$K19),Z$6)<MAX(IF(OR('Cost Margin'!$B$14="Y",'Cost Margin'!$J19=""),'Cost Margin'!$B$8,'Cost Margin'!$J19),Z$5),0,IFERROR(NETWORKDAYS(MAX(IF(OR('Cost Margin'!$B$14="Y",'Cost Margin'!$J19=""),'Cost Margin'!$B$8,'Cost Margin'!$J19),Z$5),MIN(IF(OR('Cost Margin'!$B$14="Y",'Cost Margin'!$K19=""),'Cost Margin'!$B$9,'Cost Margin'!$K19),Z$6),INDEX(Settings!$A$35:$D$74,0,MATCH('Cost Margin'!$C19,Settings!$A$34:$D$34,0))),NETWORKDAYS(MAX(IF(OR('Cost Margin'!$B$14="Y",'Cost Margin'!$J19=""),'Cost Margin'!$B$8,'Cost Margin'!$J19),Z$5),MIN(IF(OR('Cost Margin'!$B$14="Y",'Cost Margin'!$K19=""),'Cost Margin'!$B$9,'Cost Margin'!$K19),Z$6))))) -> 0 | AB11: =IF('Cost Margin'!A19="","",IF('Cost Margin'!E19="","(unassigned)",'Cost Margin'!E19))
A12: 4 | B12: =IF('Cost Margin'!A20="","",'Cost Margin'!A20&IF('Cost Margin'!E20="",""," · "&'Cost Margin'!E20)) | C12: =IF(OR(C$5="",'Cost Margin'!$A20="",IF(OR('Cost Margin'!$B$14="Y",'Cost Margin'!$J20=""),'Cost Margin'!$B$8,'Cost Margin'!$J20)="",IF(OR('Cost Margin'!$B$14="Y",'Cost Margin'!$K20=""),'Cost Margin'!$B$9,'Cost Margin'!$K20)=""),0,IF(MIN(IF(OR('Cost Margin'!$B$14="Y",'Cost Margin'!$K20=""),'Cost Margin'!$B$9,'Cost Margin'!$K20),C$6)<MAX(IF(OR('Cost Margin'!$B$14="Y",'Cost Margin'!$J20=""),'Cost Margin'!$B$8,'Cost Margin'!$J20),C$5),0,IFERROR(NETWORKDAYS(MAX(IF(OR('Cost Margin'!$B$14="Y",'Cost Margin'!$J20=""),'Cost Margin'!$B$8,'Cost Margin'!$J20),C$5),MIN(IF(OR('Cost Margin'!$B$14="Y",'Cost Margin'!$K20=""),'Cost Margin'!$B$9,'Cost Margin'!$K20),C$6),INDEX(Settings!$A$35:$D$74,0,MATCH('Cost Margin'!$C20,Settings!$A$34:$D$34,0))),NETWORKDAYS(MAX(IF(OR('Cost Margin'!$B$14="Y",'Cost Margin'!$J20=""),'Cost Margin'!$B$8,'Cost Margin'!$J20),C$5),MIN(IF(OR('Cost Margin'!$B$14="Y",'Cost Margin'!$K20=""),'Cost Margin'!$B$9,'Cost Margin'!$K20),C$6))))) -> 0 | D12: =IF(OR(D$5="",'Cost Margin'!$A20="",IF(OR('Cost Margin'!$B$14="Y",'Cost Margin'!$J20=""),'Cost Margin'!$B$8,'Cost Margin'!$J20)="",IF(OR('Cost Margin'!$B$14="Y",'Cost Margin'!$K20=""),'Cost Margin'!$B$9,'Cost Margin'!$K20)=""),0,IF(MIN(IF(OR('Cost Margin'!$B$14="Y",'Cost Margin'!$K20=""),'Cost Margin'!$B$9,'Cost Margin'!$K20),D$6)<MAX(IF(OR('Cost Margin'!$B$14="Y",'Cost Margin'!$J20=""),'Cost Margin'!$B$8,'Cost Margin'!$J20),D$5),0,IFERROR(NETWORKDAYS(MAX(IF(OR('Cost Margin'!$B$14="Y",'Cost Margin'!$J20=""),'Cost Margin'!$B$8,'Cost Margin'!$J20),D$5),MIN(IF(OR('Cost Margin'!$B$14="Y",'Cost Margin'!$K20=""),'Cost Margin'!$B$9,'Cost Margin'!$K20),D$6),INDEX(Settings!$A$35:$D$74,0,MATCH('Cost Margin'!$C20,Settings!$A$34:$D$34,0))),NETWORKDAYS(MAX(IF(OR('Cost Margin'!$B$14="Y",'Cost Margin'!$J20=""),'Cost Margin'!$B$8,'Cost Margin'!$J20),D$5),MIN(IF(OR('Cost Margin'!$B$14="Y",'Cost Margin'!$K20=""),'Cost Margin'!$B$9,'Cost Margin'!$K20),D$6))))) -> 0 | E12: =IF(OR(E$5="",'Cost Margin'!$A20="",IF(OR('Cost Margin'!$B$14="Y",'Cost Margin'!$J20=""),'Cost Margin'!$B$8,'Cost Margin'!$J20)="",IF(OR('Cost Margin'!$B$14="Y",'Cost Margin'!$K20=""),'Cost Margin'!$B$9,'Cost Margin'!$K20)=""),0,IF(MIN(IF(OR('Cost Margin'!$B$14="Y",'Cost Margin'!$K20=""),'Cost Margin'!$B$9,'Cost Margin'!$K20),E$6)<MAX(IF(OR('Cost Margin'!$B$14="Y",'Cost Margin'!$J20=""),'Cost Margin'!$B$8,'Cost Margin'!$J20),E$5),0,IFERROR(NETWORKDAYS(MAX(IF(OR('Cost Margin'!$B$14="Y",'Cost Margin'!$J20=""),'Cost Margin'!$B$8,'Cost Margin'!$J20),E$5),MIN(IF(OR('Cost Margin'!$B$14="Y",'Cost Margin'!$K20=""),'Cost Margin'!$B$9,'Cost Margin'!$K20),E$6),INDEX(Settings!$A$35:$D$74,0,MATCH('Cost Margin'!$C20,Settings!$A$34:$D$34,0))),NETWORKDAYS(MAX(IF(OR('Cost Margin'!$B$14="Y",'Cost Margin'!$J20=""),'Cost Margin'!$B$8,'Cost Margin'!$J20),E$5),MIN(IF(OR('Cost Margin'!$B$14="Y",'Cost Margin'!$K20=""),'Cost Margin'!$B$9,'Cost Margin'!$K20),E$6))))) -> 0 | F12: =IF(OR(F$5="",'Cost Margin'!$A20="",IF(OR('Cost Margin'!$B$14="Y",'Cost Margin'!$J20=""),'Cost Margin'!$B$8,'Cost Margin'!$J20)="",IF(OR('Cost Margin'!$B$14="Y",'Cost Margin'!$K20=""),'Cost Margin'!$B$9,'Cost Margin'!$K20)=""),0,IF(MIN(IF(OR('Cost Margin'!$B$14="Y",'Cost Margin'!$K20=""),'Cost Margin'!$B$9,'Cost Margin'!$K20),F$6)<MAX(IF(OR('Cost Margin'!$B$14="Y",'Cost Margin'!$J20=""),'Cost Margin'!$B$8,'Cost Margin'!$J20),F$5),0,IFERROR(NETWORKDAYS(MAX(IF(OR('Cost Margin'!$B$14="Y",'Cost Margin'!$J20=""),'Cost Margin'!$B$8,'Cost Margin'!$J20),F$5),MIN(IF(OR('Cost Margin'!$B$14="Y",'Cost Margin'!$K20=""),'Cost Margin'!$B$9,'Cost Margin'!$K20),F$6),INDEX(Settings!$A$35:$D$74,0,MATCH('Cost Margin'!$C20,Settings!$A$34:$D$34,0))),NETWORKDAYS(MAX(IF(OR('Cost Margin'!$B$14="Y",'Cost Margin'!$J20=""),'Cost Margin'!$B$8,'Cost Margin'!$J20),F$5),MIN(IF(OR('Cost Margin'!$B$14="Y",'Cost Margin'!$K20=""),'Cost Margin'!$B$9,'Cost Margin'!$K20),F$6))))) -> 0 | G12: =IF(OR(G$5="",'Cost Margin'!$A20="",IF(OR('Cost Margin'!$B$14="Y",'Cost Margin'!$J20=""),'Cost Margin'!$B$8,'Cost Margin'!$J20)="",IF(OR('Cost Margin'!$B$14="Y",'Cost Margin'!$K20=""),'Cost Margin'!$B$9,'Cost Margin'!$K20)=""),0,IF(MIN(IF(OR('Cost Margin'!$B$14="Y",'Cost Margin'!$K20=""),'Cost Margin'!$B$9,'Cost Margin'!$K20),G$6)<MAX(IF(OR('Cost Margin'!$B$14="Y",'Cost Margin'!$J20=""),'Cost Margin'!$B$8,'Cost Margin'!$J20),G$5),0,IFERROR(NETWORKDAYS(MAX(IF(OR('Cost Margin'!$B$14="Y",'Cost Margin'!$J20=""),'Cost Margin'!$B$8,'Cost Margin'!$J20),G$5),MIN(IF(OR('Cost Margin'!$B$14="Y",'Cost Margin'!$K20=""),'Cost Margin'!$B$9,'Cost Margin'!$K20),G$6),INDEX(Settings!$A$35:$D$74,0,MATCH('Cost Margin'!$C20,Settings!$A$34:$D$34,0))),NETWORKDAYS(MAX(IF(OR('Cost Margin'!$B$14="Y",'Cost Margin'!$J20=""),'Cost Margin'!$B$8,'Cost Margin'!$J20),G$5),MIN(IF(OR('Cost Margin'!$B$14="Y",'Cost Margin'!$K20=""),'Cost Margin'!$B$9,'Cost Margin'!$K20),G$6))))) -> 0 | H12: =IF(OR(H$5="",'Cost Margin'!$A20="",IF(OR('Cost Margin'!$B$14="Y",'Cost Margin'!$J20=""),'Cost Margin'!$B$8,'Cost Margin'!$J20)="",IF(OR('Cost Margin'!$B$14="Y",'Cost Margin'!$K20=""),'Cost Margin'!$B$9,'Cost Margin'!$K20)=""),0,IF(MIN(IF(OR('Cost Margin'!$B$14="Y",'Cost Margin'!$K20=""),'Cost Margin'!$B$9,'Cost Margin'!$K20),H$6)<MAX(IF(OR('Cost Margin'!$B$14="Y",'Cost Margin'!$J20=""),'Cost Margin'!$B$8,'Cost Margin'!$J20),H$5),0,IFERROR(NETWORKDAYS(MAX(IF(OR('Cost Margin'!$B$14="Y",'Cost Margin'!$J20=""),'Cost Margin'!$B$8,'Cost Margin'!$J20),H$5),MIN(IF(OR('Cost Margin'!$B$14="Y",'Cost Margin'!$K20=""),'Cost Margin'!$B$9,'Cost Margin'!$K20),H$6),INDEX(Settings!$A$35:$D$74,0,MATCH('Cost Margin'!$C20,Settings!$A$34:$D$34,0))),NETWORKDAYS(MAX(IF(OR('Cost Margin'!$B$14="Y",'Cost Margin'!$J20=""),'Cost Margin'!$B$8,'Cost Margin'!$J20),H$5),MIN(IF(OR('Cost Margin'!$B$14="Y",'Cost Margin'!$K20=""),'Cost Margin'!$B$9,'Cost Margin'!$K20),H$6))))) -> 0 | I12: =IF(OR(I$5="",'Cost Margin'!$A20="",IF(OR('Cost Margin'!$B$14="Y",'Cost Margin'!$J20=""),'Cost Margin'!$B$8,'Cost Margin'!$J20)="",IF(OR('Cost Margin'!$B$14="Y",'Cost Margin'!$K20=""),'Cost Margin'!$B$9,'Cost Margin'!$K20)=""),0,IF(MIN(IF(OR('Cost Margin'!$B$14="Y",'Cost Margin'!$K20=""),'Cost Margin'!$B$9,'Cost Margin'!$K20),I$6)<MAX(IF(OR('Cost Margin'!$B$14="Y",'Cost Margin'!$J20=""),'Cost Margin'!$B$8,'Cost Margin'!$J20),I$5),0,IFERROR(NETWORKDAYS(MAX(IF(OR('Cost Margin'!$B$14="Y",'Cost Margin'!$J20=""),'Cost Margin'!$B$8,'Cost Margin'!$J20),I$5),MIN(IF(OR('Cost Margin'!$B$14="Y",'Cost Margin'!$K20=""),'Cost Margin'!$B$9,'Cost Margin'!$K20),I$6),INDEX(Settings!$A$35:$D$74,0,MATCH('Cost Margin'!$C20,Settings!$A$34:$D$34,0))),NETWORKDAYS(MAX(IF(OR('Cost Margin'!$B$14="Y",'Cost Margin'!$J20=""),'Cost Margin'!$B$8,'Cost Margin'!$J20),I$5),MIN(IF(OR('Cost Margin'!$B$14="Y",'Cost Margin'!$K20=""),'Cost Margin'!$B$9,'Cost Margin'!$K20),I$6))))) -> 0 | J12: =IF(OR(J$5="",'Cost Margin'!$A20="",IF(OR('Cost Margin'!$B$14="Y",'Cost Margin'!$J20=""),'Cost Margin'!$B$8,'Cost Margin'!$J20)="",IF(OR('Cost Margin'!$B$14="Y",'Cost Margin'!$K20=""),'Cost Margin'!$B$9,'Cost Margin'!$K20)=""),0,IF(MIN(IF(OR('Cost Margin'!$B$14="Y",'Cost Margin'!$K20=""),'Cost Margin'!$B$9,'Cost Margin'!$K20),J$6)<MAX(IF(OR('Cost Margin'!$B$14="Y",'Cost Margin'!$J20=""),'Cost Margin'!$B$8,'Cost Margin'!$J20),J$5),0,IFERROR(NETWORKDAYS(MAX(IF(OR('Cost Margin'!$B$14="Y",'Cost Margin'!$J20=""),'Cost Margin'!$B$8,'Cost Margin'!$J20),J$5),MIN(IF(OR('Cost Margin'!$B$14="Y",'Cost Margin'!$K20=""),'Cost Margin'!$B$9,'Cost Margin'!$K20),J$6),INDEX(Settings!$A$35:$D$74,0,MATCH('Cost Margin'!$C20,Settings!$A$34:$D$34,0))),NETWORKDAYS(MAX(IF(OR('Cost Margin'!$B$14="Y",'Cost Margin'!$J20=""),'Cost Margin'!$B$8,'Cost Margin'!$J20),J$5),MIN(IF(OR('Cost Margin'!$B$14="Y",'Cost Margin'!$K20=""),'Cost Margin'!$B$9,'Cost Margin'!$K20),J$6))))) -> 0 | ... Z12: =IF(OR(Z$5="",'Cost Margin'!$A20="",IF(OR('Cost Margin'!$B$14="Y",'Cost Margin'!$J20=""),'Cost Margin'!$B$8,'Cost Margin'!$J20)="",IF(OR('Cost Margin'!$B$14="Y",'Cost Margin'!$K20=""),'Cost Margin'!$B$9,'Cost Margin'!$K20)=""),0,IF(MIN(IF(OR('Cost Margin'!$B$14="Y",'Cost Margin'!$K20=""),'Cost Margin'!$B$9,'Cost Margin'!$K20),Z$6)<MAX(IF(OR('Cost Margin'!$B$14="Y",'Cost Margin'!$J20=""),'Cost Margin'!$B$8,'Cost Margin'!$J20),Z$5),0,IFERROR(NETWORKDAYS(MAX(IF(OR('Cost Margin'!$B$14="Y",'Cost Margin'!$J20=""),'Cost Margin'!$B$8,'Cost Margin'!$J20),Z$5),MIN(IF(OR('Cost Margin'!$B$14="Y",'Cost Margin'!$K20=""),'Cost Margin'!$B$9,'Cost Margin'!$K20),Z$6),INDEX(Settings!$A$35:$D$74,0,MATCH('Cost Margin'!$C20,Settings!$A$34:$D$34,0))),NETWORKDAYS(MAX(IF(OR('Cost Margin'!$B$14="Y",'Cost Margin'!$J20=""),'Cost Margin'!$B$8,'Cost Margin'!$J20),Z$5),MIN(IF(OR('Cost Margin'!$B$14="Y",'Cost Margin'!$K20=""),'Cost Margin'!$B$9,'Cost Margin'!$K20),Z$6))))) -> 0 | AB12: =IF('Cost Margin'!A20="","",IF('Cost Margin'!E20="","(unassigned)",'Cost Margin'!E20))
A13: 5 | B13: =IF('Cost Margin'!A21="","",'Cost Margin'!A21&IF('Cost Margin'!E21="",""," · "&'Cost Margin'!E21)) | C13: =IF(OR(C$5="",'Cost Margin'!$A21="",IF(OR('Cost Margin'!$B$14="Y",'Cost Margin'!$J21=""),'Cost Margin'!$B$8,'Cost Margin'!$J21)="",IF(OR('Cost Margin'!$B$14="Y",'Cost Margin'!$K21=""),'Cost Margin'!$B$9,'Cost Margin'!$K21)=""),0,IF(MIN(IF(OR('Cost Margin'!$B$14="Y",'Cost Margin'!$K21=""),'Cost Margin'!$B$9,'Cost Margin'!$K21),C$6)<MAX(IF(OR('Cost Margin'!$B$14="Y",'Cost Margin'!$J21=""),'Cost Margin'!$B$8,'Cost Margin'!$J21),C$5),0,IFERROR(NETWORKDAYS(MAX(IF(OR('Cost Margin'!$B$14="Y",'Cost Margin'!$J21=""),'Cost Margin'!$B$8,'Cost Margin'!$J21),C$5),MIN(IF(OR('Cost Margin'!$B$14="Y",'Cost Margin'!$K21=""),'Cost Margin'!$B$9,'Cost Margin'!$K21),C$6),INDEX(Settings!$A$35:$D$74,0,MATCH('Cost Margin'!$C21,Settings!$A$34:$D$34,0))),NETWORKDAYS(MAX(IF(OR('Cost Margin'!$B$14="Y",'Cost Margin'!$J21=""),'Cost Margin'!$B$8,'Cost Margin'!$J21),C$5),MIN(IF(OR('Cost Margin'!$B$14="Y",'Cost Margin'!$K21=""),'Cost Margin'!$B$9,'Cost Margin'!$K21),C$6))))) -> 0 | D13: =IF(OR(D$5="",'Cost Margin'!$A21="",IF(OR('Cost Margin'!$B$14="Y",'Cost Margin'!$J21=""),'Cost Margin'!$B$8,'Cost Margin'!$J21)="",IF(OR('Cost Margin'!$B$14="Y",'Cost Margin'!$K21=""),'Cost Margin'!$B$9,'Cost Margin'!$K21)=""),0,IF(MIN(IF(OR('Cost Margin'!$B$14="Y",'Cost Margin'!$K21=""),'Cost Margin'!$B$9,'Cost Margin'!$K21),D$6)<MAX(IF(OR('Cost Margin'!$B$14="Y",'Cost Margin'!$J21=""),'Cost Margin'!$B$8,'Cost Margin'!$J21),D$5),0,IFERROR(NETWORKDAYS(MAX(IF(OR('Cost Margin'!$B$14="Y",'Cost Margin'!$J21=""),'Cost Margin'!$B$8,'Cost Margin'!$J21),D$5),MIN(IF(OR('Cost Margin'!$B$14="Y",'Cost Margin'!$K21=""),'Cost Margin'!$B$9,'Cost Margin'!$K21),D$6),INDEX(Settings!$A$35:$D$74,0,MATCH('Cost Margin'!$C21,Settings!$A$34:$D$34,0))),NETWORKDAYS(MAX(IF(OR('Cost Margin'!$B$14="Y",'Cost Margin'!$J21=""),'Cost Margin'!$B$8,'Cost Margin'!$J21),D$5),MIN(IF(OR('Cost Margin'!$B$14="Y",'Cost Margin'!$K21=""),'Cost Margin'!$B$9,'Cost Margin'!$K21),D$6))))) -> 0 | E13: =IF(OR(E$5="",'Cost Margin'!$A21="",IF(OR('Cost Margin'!$B$14="Y",'Cost Margin'!$J21=""),'Cost Margin'!$B$8,'Cost Margin'!$J21)="",IF(OR('Cost Margin'!$B$14="Y",'Cost Margin'!$K21=""),'Cost Margin'!$B$9,'Cost Margin'!$K21)=""),0,IF(MIN(IF(OR('Cost Margin'!$B$14="Y",'Cost Margin'!$K21=""),'Cost Margin'!$B$9,'Cost Margin'!$K21),E$6)<MAX(IF(OR('Cost Margin'!$B$14="Y",'Cost Margin'!$J21=""),'Cost Margin'!$B$8,'Cost Margin'!$J21),E$5),0,IFERROR(NETWORKDAYS(MAX(IF(OR('Cost Margin'!$B$14="Y",'Cost Margin'!$J21=""),'Cost Margin'!$B$8,'Cost Margin'!$J21),E$5),MIN(IF(OR('Cost Margin'!$B$14="Y",'Cost Margin'!$K21=""),'Cost Margin'!$B$9,'Cost Margin'!$K21),E$6),INDEX(Settings!$A$35:$D$74,0,MATCH('Cost Margin'!$C21,Settings!$A$34:$D$34,0))),NETWORKDAYS(MAX(IF(OR('Cost Margin'!$B$14="Y",'Cost Margin'!$J21=""),'Cost Margin'!$B$8,'Cost Margin'!$J21),E$5),MIN(IF(OR('Cost Margin'!$B$14="Y",'Cost Margin'!$K21=""),'Cost Margin'!$B$9,'Cost Margin'!$K21),E$6))))) -> 0 | F13: =IF(OR(F$5="",'Cost Margin'!$A21="",IF(OR('Cost Margin'!$B$14="Y",'Cost Margin'!$J21=""),'Cost Margin'!$B$8,'Cost Margin'!$J21)="",IF(OR('Cost Margin'!$B$14="Y",'Cost Margin'!$K21=""),'Cost Margin'!$B$9,'Cost Margin'!$K21)=""),0,IF(MIN(IF(OR('Cost Margin'!$B$14="Y",'Cost Margin'!$K21=""),'Cost Margin'!$B$9,'Cost Margin'!$K21),F$6)<MAX(IF(OR('Cost Margin'!$B$14="Y",'Cost Margin'!$J21=""),'Cost Margin'!$B$8,'Cost Margin'!$J21),F$5),0,IFERROR(NETWORKDAYS(MAX(IF(OR('Cost Margin'!$B$14="Y",'Cost Margin'!$J21=""),'Cost Margin'!$B$8,'Cost Margin'!$J21),F$5),MIN(IF(OR('Cost Margin'!$B$14="Y",'Cost Margin'!$K21=""),'Cost Margin'!$B$9,'Cost Margin'!$K21),F$6),INDEX(Settings!$A$35:$D$74,0,MATCH('Cost Margin'!$C21,Settings!$A$34:$D$34,0))),NETWORKDAYS(MAX(IF(OR('Cost Margin'!$B$14="Y",'Cost Margin'!$J21=""),'Cost Margin'!$B$8,'Cost Margin'!$J21),F$5),MIN(IF(OR('Cost Margin'!$B$14="Y",'Cost Margin'!$K21=""),'Cost Margin'!$B$9,'Cost Margin'!$K21),F$6))))) -> 0 | G13: =IF(OR(G$5="",'Cost Margin'!$A21="",IF(OR('Cost Margin'!$B$14="Y",'Cost Margin'!$J21=""),'Cost Margin'!$B$8,'Cost Margin'!$J21)="",IF(OR('Cost Margin'!$B$14="Y",'Cost Margin'!$K21=""),'Cost Margin'!$B$9,'Cost Margin'!$K21)=""),0,IF(MIN(IF(OR('Cost Margin'!$B$14="Y",'Cost Margin'!$K21=""),'Cost Margin'!$B$9,'Cost Margin'!$K21),G$6)<MAX(IF(OR('Cost Margin'!$B$14="Y",'Cost Margin'!$J21=""),'Cost Margin'!$B$8,'Cost Margin'!$J21),G$5),0,IFERROR(NETWORKDAYS(MAX(IF(OR('Cost Margin'!$B$14="Y",'Cost Margin'!$J21=""),'Cost Margin'!$B$8,'Cost Margin'!$J21),G$5),MIN(IF(OR('Cost Margin'!$B$14="Y",'Cost Margin'!$K21=""),'Cost Margin'!$B$9,'Cost Margin'!$K21),G$6),INDEX(Settings!$A$35:$D$74,0,MATCH('Cost Margin'!$C21,Settings!$A$34:$D$34,0))),NETWORKDAYS(MAX(IF(OR('Cost Margin'!$B$14="Y",'Cost Margin'!$J21=""),'Cost Margin'!$B$8,'Cost Margin'!$J21),G$5),MIN(IF(OR('Cost Margin'!$B$14="Y",'Cost Margin'!$K21=""),'Cost Margin'!$B$9,'Cost Margin'!$K21),G$6))))) -> 0 | H13: =IF(OR(H$5="",'Cost Margin'!$A21="",IF(OR('Cost Margin'!$B$14="Y",'Cost Margin'!$J21=""),'Cost Margin'!$B$8,'Cost Margin'!$J21)="",IF(OR('Cost Margin'!$B$14="Y",'Cost Margin'!$K21=""),'Cost Margin'!$B$9,'Cost Margin'!$K21)=""),0,IF(MIN(IF(OR('Cost Margin'!$B$14="Y",'Cost Margin'!$K21=""),'Cost Margin'!$B$9,'Cost Margin'!$K21),H$6)<MAX(IF(OR('Cost Margin'!$B$14="Y",'Cost Margin'!$J21=""),'Cost Margin'!$B$8,'Cost Margin'!$J21),H$5),0,IFERROR(NETWORKDAYS(MAX(IF(OR('Cost Margin'!$B$14="Y",'Cost Margin'!$J21=""),'Cost Margin'!$B$8,'Cost Margin'!$J21),H$5),MIN(IF(OR('Cost Margin'!$B$14="Y",'Cost Margin'!$K21=""),'Cost Margin'!$B$9,'Cost Margin'!$K21),H$6),INDEX(Settings!$A$35:$D$74,0,MATCH('Cost Margin'!$C21,Settings!$A$34:$D$34,0))),NETWORKDAYS(MAX(IF(OR('Cost Margin'!$B$14="Y",'Cost Margin'!$J21=""),'Cost Margin'!$B$8,'Cost Margin'!$J21),H$5),MIN(IF(OR('Cost Margin'!$B$14="Y",'Cost Margin'!$K21=""),'Cost Margin'!$B$9,'Cost Margin'!$K21),H$6))))) -> 0 | I13: =IF(OR(I$5="",'Cost Margin'!$A21="",IF(OR('Cost Margin'!$B$14="Y",'Cost Margin'!$J21=""),'Cost Margin'!$B$8,'Cost Margin'!$J21)="",IF(OR('Cost Margin'!$B$14="Y",'Cost Margin'!$K21=""),'Cost Margin'!$B$9,'Cost Margin'!$K21)=""),0,IF(MIN(IF(OR('Cost Margin'!$B$14="Y",'Cost Margin'!$K21=""),'Cost Margin'!$B$9,'Cost Margin'!$K21),I$6)<MAX(IF(OR('Cost Margin'!$B$14="Y",'Cost Margin'!$J21=""),'Cost Margin'!$B$8,'Cost Margin'!$J21),I$5),0,IFERROR(NETWORKDAYS(MAX(IF(OR('Cost Margin'!$B$14="Y",'Cost Margin'!$J21=""),'Cost Margin'!$B$8,'Cost Margin'!$J21),I$5),MIN(IF(OR('Cost Margin'!$B$14="Y",'Cost Margin'!$K21=""),'Cost Margin'!$B$9,'Cost Margin'!$K21),I$6),INDEX(Settings!$A$35:$D$74,0,MATCH('Cost Margin'!$C21,Settings!$A$34:$D$34,0))),NETWORKDAYS(MAX(IF(OR('Cost Margin'!$B$14="Y",'Cost Margin'!$J21=""),'Cost Margin'!$B$8,'Cost Margin'!$J21),I$5),MIN(IF(OR('Cost Margin'!$B$14="Y",'Cost Margin'!$K21=""),'Cost Margin'!$B$9,'Cost Margin'!$K21),I$6))))) -> 0 | J13: =IF(OR(J$5="",'Cost Margin'!$A21="",IF(OR('Cost Margin'!$B$14="Y",'Cost Margin'!$J21=""),'Cost Margin'!$B$8,'Cost Margin'!$J21)="",IF(OR('Cost Margin'!$B$14="Y",'Cost Margin'!$K21=""),'Cost Margin'!$B$9,'Cost Margin'!$K21)=""),0,IF(MIN(IF(OR('Cost Margin'!$B$14="Y",'Cost Margin'!$K21=""),'Cost Margin'!$B$9,'Cost Margin'!$K21),J$6)<MAX(IF(OR('Cost Margin'!$B$14="Y",'Cost Margin'!$J21=""),'Cost Margin'!$B$8,'Cost Margin'!$J21),J$5),0,IFERROR(NETWORKDAYS(MAX(IF(OR('Cost Margin'!$B$14="Y",'Cost Margin'!$J21=""),'Cost Margin'!$B$8,'Cost Margin'!$J21),J$5),MIN(IF(OR('Cost Margin'!$B$14="Y",'Cost Margin'!$K21=""),'Cost Margin'!$B$9,'Cost Margin'!$K21),J$6),INDEX(Settings!$A$35:$D$74,0,MATCH('Cost Margin'!$C21,Settings!$A$34:$D$34,0))),NETWORKDAYS(MAX(IF(OR('Cost Margin'!$B$14="Y",'Cost Margin'!$J21=""),'Cost Margin'!$B$8,'Cost Margin'!$J21),J$5),MIN(IF(OR('Cost Margin'!$B$14="Y",'Cost Margin'!$K21=""),'Cost Margin'!$B$9,'Cost Margin'!$K21),J$6))))) -> 0 | ... Z13: =IF(OR(Z$5="",'Cost Margin'!$A21="",IF(OR('Cost Margin'!$B$14="Y",'Cost Margin'!$J21=""),'Cost Margin'!$B$8,'Cost Margin'!$J21)="",IF(OR('Cost Margin'!$B$14="Y",'Cost Margin'!$K21=""),'Cost Margin'!$B$9,'Cost Margin'!$K21)=""),0,IF(MIN(IF(OR('Cost Margin'!$B$14="Y",'Cost Margin'!$K21=""),'Cost Margin'!$B$9,'Cost Margin'!$K21),Z$6)<MAX(IF(OR('Cost Margin'!$B$14="Y",'Cost Margin'!$J21=""),'Cost Margin'!$B$8,'Cost Margin'!$J21),Z$5),0,IFERROR(NETWORKDAYS(MAX(IF(OR('Cost Margin'!$B$14="Y",'Cost Margin'!$J21=""),'Cost Margin'!$B$8,'Cost Margin'!$J21),Z$5),MIN(IF(OR('Cost Margin'!$B$14="Y",'Cost Margin'!$K21=""),'Cost Margin'!$B$9,'Cost Margin'!$K21),Z$6),INDEX(Settings!$A$35:$D$74,0,MATCH('Cost Margin'!$C21,Settings!$A$34:$D$34,0))),NETWORKDAYS(MAX(IF(OR('Cost Margin'!$B$14="Y",'Cost Margin'!$J21=""),'Cost Margin'!$B$8,'Cost Margin'!$J21),Z$5),MIN(IF(OR('Cost Margin'!$B$14="Y",'Cost Margin'!$K21=""),'Cost Margin'!$B$9,'Cost Margin'!$K21),Z$6))))) -> 0 | AB13: =IF('Cost Margin'!A21="","",IF('Cost Margin'!E21="","(unassigned)",'Cost Margin'!E21))
A14: 6 | B14: =IF('Cost Margin'!A22="","",'Cost Margin'!A22&IF('Cost Margin'!E22="",""," · "&'Cost Margin'!E22)) | C14: =IF(OR(C$5="",'Cost Margin'!$A22="",IF(OR('Cost Margin'!$B$14="Y",'Cost Margin'!$J22=""),'Cost Margin'!$B$8,'Cost Margin'!$J22)="",IF(OR('Cost Margin'!$B$14="Y",'Cost Margin'!$K22=""),'Cost Margin'!$B$9,'Cost Margin'!$K22)=""),0,IF(MIN(IF(OR('Cost Margin'!$B$14="Y",'Cost Margin'!$K22=""),'Cost Margin'!$B$9,'Cost Margin'!$K22),C$6)<MAX(IF(OR('Cost Margin'!$B$14="Y",'Cost Margin'!$J22=""),'Cost Margin'!$B$8,'Cost Margin'!$J22),C$5),0,IFERROR(NETWORKDAYS(MAX(IF(OR('Cost Margin'!$B$14="Y",'Cost Margin'!$J22=""),'Cost Margin'!$B$8,'Cost Margin'!$J22),C$5),MIN(IF(OR('Cost Margin'!$B$14="Y",'Cost Margin'!$K22=""),'Cost Margin'!$B$9,'Cost Margin'!$K22),C$6),INDEX(Settings!$A$35:$D$74,0,MATCH('Cost Margin'!$C22,Settings!$A$34:$D$34,0))),NETWORKDAYS(MAX(IF(OR('Cost Margin'!$B$14="Y",'Cost Margin'!$J22=""),'Cost Margin'!$B$8,'Cost Margin'!$J22),C$5),MIN(IF(OR('Cost Margin'!$B$14="Y",'Cost Margin'!$K22=""),'Cost Margin'!$B$9,'Cost Margin'!$K22),C$6))))) -> 0 | D14: =IF(OR(D$5="",'Cost Margin'!$A22="",IF(OR('Cost Margin'!$B$14="Y",'Cost Margin'!$J22=""),'Cost Margin'!$B$8,'Cost Margin'!$J22)="",IF(OR('Cost Margin'!$B$14="Y",'Cost Margin'!$K22=""),'Cost Margin'!$B$9,'Cost Margin'!$K22)=""),0,IF(MIN(IF(OR('Cost Margin'!$B$14="Y",'Cost Margin'!$K22=""),'Cost Margin'!$B$9,'Cost Margin'!$K22),D$6)<MAX(IF(OR('Cost Margin'!$B$14="Y",'Cost Margin'!$J22=""),'Cost Margin'!$B$8,'Cost Margin'!$J22),D$5),0,IFERROR(NETWORKDAYS(MAX(IF(OR('Cost Margin'!$B$14="Y",'Cost Margin'!$J22=""),'Cost Margin'!$B$8,'Cost Margin'!$J22),D$5),MIN(IF(OR('Cost Margin'!$B$14="Y",'Cost Margin'!$K22=""),'Cost Margin'!$B$9,'Cost Margin'!$K22),D$6),INDEX(Settings!$A$35:$D$74,0,MATCH('Cost Margin'!$C22,Settings!$A$34:$D$34,0))),NETWORKDAYS(MAX(IF(OR('Cost Margin'!$B$14="Y",'Cost Margin'!$J22=""),'Cost Margin'!$B$8,'Cost Margin'!$J22),D$5),MIN(IF(OR('Cost Margin'!$B$14="Y",'Cost Margin'!$K22=""),'Cost Margin'!$B$9,'Cost Margin'!$K22),D$6))))) -> 0 | E14: =IF(OR(E$5="",'Cost Margin'!$A22="",IF(OR('Cost Margin'!$B$14="Y",'Cost Margin'!$J22=""),'Cost Margin'!$B$8,'Cost Margin'!$J22)="",IF(OR('Cost Margin'!$B$14="Y",'Cost Margin'!$K22=""),'Cost Margin'!$B$9,'Cost Margin'!$K22)=""),0,IF(MIN(IF(OR('Cost Margin'!$B$14="Y",'Cost Margin'!$K22=""),'Cost Margin'!$B$9,'Cost Margin'!$K22),E$6)<MAX(IF(OR('Cost Margin'!$B$14="Y",'Cost Margin'!$J22=""),'Cost Margin'!$B$8,'Cost Margin'!$J22),E$5),0,IFERROR(NETWORKDAYS(MAX(IF(OR('Cost Margin'!$B$14="Y",'Cost Margin'!$J22=""),'Cost Margin'!$B$8,'Cost Margin'!$J22),E$5),MIN(IF(OR('Cost Margin'!$B$14="Y",'Cost Margin'!$K22=""),'Cost Margin'!$B$9,'Cost Margin'!$K22),E$6),INDEX(Settings!$A$35:$D$74,0,MATCH('Cost Margin'!$C22,Settings!$A$34:$D$34,0))),NETWORKDAYS(MAX(IF(OR('Cost Margin'!$B$14="Y",'Cost Margin'!$J22=""),'Cost Margin'!$B$8,'Cost Margin'!$J22),E$5),MIN(IF(OR('Cost Margin'!$B$14="Y",'Cost Margin'!$K22=""),'Cost Margin'!$B$9,'Cost Margin'!$K22),E$6))))) -> 0 | F14: =IF(OR(F$5="",'Cost Margin'!$A22="",IF(OR('Cost Margin'!$B$14="Y",'Cost Margin'!$J22=""),'Cost Margin'!$B$8,'Cost Margin'!$J22)="",IF(OR('Cost Margin'!$B$14="Y",'Cost Margin'!$K22=""),'Cost Margin'!$B$9,'Cost Margin'!$K22)=""),0,IF(MIN(IF(OR('Cost Margin'!$B$14="Y",'Cost Margin'!$K22=""),'Cost Margin'!$B$9,'Cost Margin'!$K22),F$6)<MAX(IF(OR('Cost Margin'!$B$14="Y",'Cost Margin'!$J22=""),'Cost Margin'!$B$8,'Cost Margin'!$J22),F$5),0,IFERROR(NETWORKDAYS(MAX(IF(OR('Cost Margin'!$B$14="Y",'Cost Margin'!$J22=""),'Cost Margin'!$B$8,'Cost Margin'!$J22),F$5),MIN(IF(OR('Cost Margin'!$B$14="Y",'Cost Margin'!$K22=""),'Cost Margin'!$B$9,'Cost Margin'!$K22),F$6),INDEX(Settings!$A$35:$D$74,0,MATCH('Cost Margin'!$C22,Settings!$A$34:$D$34,0))),NETWORKDAYS(MAX(IF(OR('Cost Margin'!$B$14="Y",'Cost Margin'!$J22=""),'Cost Margin'!$B$8,'Cost Margin'!$J22),F$5),MIN(IF(OR('Cost Margin'!$B$14="Y",'Cost Margin'!$K22=""),'Cost Margin'!$B$9,'Cost Margin'!$K22),F$6))))) -> 0 | G14: =IF(OR(G$5="",'Cost Margin'!$A22="",IF(OR('Cost Margin'!$B$14="Y",'Cost Margin'!$J22=""),'Cost Margin'!$B$8,'Cost Margin'!$J22)="",IF(OR('Cost Margin'!$B$14="Y",'Cost Margin'!$K22=""),'Cost Margin'!$B$9,'Cost Margin'!$K22)=""),0,IF(MIN(IF(OR('Cost Margin'!$B$14="Y",'Cost Margin'!$K22=""),'Cost Margin'!$B$9,'Cost Margin'!$K22),G$6)<MAX(IF(OR('Cost Margin'!$B$14="Y",'Cost Margin'!$J22=""),'Cost Margin'!$B$8,'Cost Margin'!$J22),G$5),0,IFERROR(NETWORKDAYS(MAX(IF(OR('Cost Margin'!$B$14="Y",'Cost Margin'!$J22=""),'Cost Margin'!$B$8,'Cost Margin'!$J22),G$5),MIN(IF(OR('Cost Margin'!$B$14="Y",'Cost Margin'!$K22=""),'Cost Margin'!$B$9,'Cost Margin'!$K22),G$6),INDEX(Settings!$A$35:$D$74,0,MATCH('Cost Margin'!$C22,Settings!$A$34:$D$34,0))),NETWORKDAYS(MAX(IF(OR('Cost Margin'!$B$14="Y",'Cost Margin'!$J22=""),'Cost Margin'!$B$8,'Cost Margin'!$J22),G$5),MIN(IF(OR('Cost Margin'!$B$14="Y",'Cost Margin'!$K22=""),'Cost Margin'!$B$9,'Cost Margin'!$K22),G$6))))) -> 0 | H14: =IF(OR(H$5="",'Cost Margin'!$A22="",IF(OR('Cost Margin'!$B$14="Y",'Cost Margin'!$J22=""),'Cost Margin'!$B$8,'Cost Margin'!$J22)="",IF(OR('Cost Margin'!$B$14="Y",'Cost Margin'!$K22=""),'Cost Margin'!$B$9,'Cost Margin'!$K22)=""),0,IF(MIN(IF(OR('Cost Margin'!$B$14="Y",'Cost Margin'!$K22=""),'Cost Margin'!$B$9,'Cost Margin'!$K22),H$6)<MAX(IF(OR('Cost Margin'!$B$14="Y",'Cost Margin'!$J22=""),'Cost Margin'!$B$8,'Cost Margin'!$J22),H$5),0,IFERROR(NETWORKDAYS(MAX(IF(OR('Cost Margin'!$B$14="Y",'Cost Margin'!$J22=""),'Cost Margin'!$B$8,'Cost Margin'!$J22),H$5),MIN(IF(OR('Cost Margin'!$B$14="Y",'Cost Margin'!$K22=""),'Cost Margin'!$B$9,'Cost Margin'!$K22),H$6),INDEX(Settings!$A$35:$D$74,0,MATCH('Cost Margin'!$C22,Settings!$A$34:$D$34,0))),NETWORKDAYS(MAX(IF(OR('Cost Margin'!$B$14="Y",'Cost Margin'!$J22=""),'Cost Margin'!$B$8,'Cost Margin'!$J22),H$5),MIN(IF(OR('Cost Margin'!$B$14="Y",'Cost Margin'!$K22=""),'Cost Margin'!$B$9,'Cost Margin'!$K22),H$6))))) -> 0 | I14: =IF(OR(I$5="",'Cost Margin'!$A22="",IF(OR('Cost Margin'!$B$14="Y",'Cost Margin'!$J22=""),'Cost Margin'!$B$8,'Cost Margin'!$J22)="",IF(OR('Cost Margin'!$B$14="Y",'Cost Margin'!$K22=""),'Cost Margin'!$B$9,'Cost Margin'!$K22)=""),0,IF(MIN(IF(OR('Cost Margin'!$B$14="Y",'Cost Margin'!$K22=""),'Cost Margin'!$B$9,'Cost Margin'!$K22),I$6)<MAX(IF(OR('Cost Margin'!$B$14="Y",'Cost Margin'!$J22=""),'Cost Margin'!$B$8,'Cost Margin'!$J22),I$5),0,IFERROR(NETWORKDAYS(MAX(IF(OR('Cost Margin'!$B$14="Y",'Cost Margin'!$J22=""),'Cost Margin'!$B$8,'Cost Margin'!$J22),I$5),MIN(IF(OR('Cost Margin'!$B$14="Y",'Cost Margin'!$K22=""),'Cost Margin'!$B$9,'Cost Margin'!$K22),I$6),INDEX(Settings!$A$35:$D$74,0,MATCH('Cost Margin'!$C22,Settings!$A$34:$D$34,0))),NETWORKDAYS(MAX(IF(OR('Cost Margin'!$B$14="Y",'Cost Margin'!$J22=""),'Cost Margin'!$B$8,'Cost Margin'!$J22),I$5),MIN(IF(OR('Cost Margin'!$B$14="Y",'Cost Margin'!$K22=""),'Cost Margin'!$B$9,'Cost Margin'!$K22),I$6))))) -> 0 | J14: =IF(OR(J$5="",'Cost Margin'!$A22="",IF(OR('Cost Margin'!$B$14="Y",'Cost Margin'!$J22=""),'Cost Margin'!$B$8,'Cost Margin'!$J22)="",IF(OR('Cost Margin'!$B$14="Y",'Cost Margin'!$K22=""),'Cost Margin'!$B$9,'Cost Margin'!$K22)=""),0,IF(MIN(IF(OR('Cost Margin'!$B$14="Y",'Cost Margin'!$K22=""),'Cost Margin'!$B$9,'Cost Margin'!$K22),J$6)<MAX(IF(OR('Cost Margin'!$B$14="Y",'Cost Margin'!$J22=""),'Cost Margin'!$B$8,'Cost Margin'!$J22),J$5),0,IFERROR(NETWORKDAYS(MAX(IF(OR('Cost Margin'!$B$14="Y",'Cost Margin'!$J22=""),'Cost Margin'!$B$8,'Cost Margin'!$J22),J$5),MIN(IF(OR('Cost Margin'!$B$14="Y",'Cost Margin'!$K22=""),'Cost Margin'!$B$9,'Cost Margin'!$K22),J$6),INDEX(Settings!$A$35:$D$74,0,MATCH('Cost Margin'!$C22,Settings!$A$34:$D$34,0))),NETWORKDAYS(MAX(IF(OR('Cost Margin'!$B$14="Y",'Cost Margin'!$J22=""),'Cost Margin'!$B$8,'Cost Margin'!$J22),J$5),MIN(IF(OR('Cost Margin'!$B$14="Y",'Cost Margin'!$K22=""),'Cost Margin'!$B$9,'Cost Margin'!$K22),J$6))))) -> 0 | ... Z14: =IF(OR(Z$5="",'Cost Margin'!$A22="",IF(OR('Cost Margin'!$B$14="Y",'Cost Margin'!$J22=""),'Cost Margin'!$B$8,'Cost Margin'!$J22)="",IF(OR('Cost Margin'!$B$14="Y",'Cost Margin'!$K22=""),'Cost Margin'!$B$9,'Cost Margin'!$K22)=""),0,IF(MIN(IF(OR('Cost Margin'!$B$14="Y",'Cost Margin'!$K22=""),'Cost Margin'!$B$9,'Cost Margin'!$K22),Z$6)<MAX(IF(OR('Cost Margin'!$B$14="Y",'Cost Margin'!$J22=""),'Cost Margin'!$B$8,'Cost Margin'!$J22),Z$5),0,IFERROR(NETWORKDAYS(MAX(IF(OR('Cost Margin'!$B$14="Y",'Cost Margin'!$J22=""),'Cost Margin'!$B$8,'Cost Margin'!$J22),Z$5),MIN(IF(OR('Cost Margin'!$B$14="Y",'Cost Margin'!$K22=""),'Cost Margin'!$B$9,'Cost Margin'!$K22),Z$6),INDEX(Settings!$A$35:$D$74,0,MATCH('Cost Margin'!$C22,Settings!$A$34:$D$34,0))),NETWORKDAYS(MAX(IF(OR('Cost Margin'!$B$14="Y",'Cost Margin'!$J22=""),'Cost Margin'!$B$8,'Cost Margin'!$J22),Z$5),MIN(IF(OR('Cost Margin'!$B$14="Y",'Cost Margin'!$K22=""),'Cost Margin'!$B$9,'Cost Margin'!$K22),Z$6))))) -> 0 | AB14: =IF('Cost Margin'!A22="","",IF('Cost Margin'!E22="","(unassigned)",'Cost Margin'!E22))
A15: 7 | B15: =IF('Cost Margin'!A23="","",'Cost Margin'!A23&IF('Cost Margin'!E23="",""," · "&'Cost Margin'!E23)) | C15: =IF(OR(C$5="",'Cost Margin'!$A23="",IF(OR('Cost Margin'!$B$14="Y",'Cost Margin'!$J23=""),'Cost Margin'!$B$8,'Cost Margin'!$J23)="",IF(OR('Cost Margin'!$B$14="Y",'Cost Margin'!$K23=""),'Cost Margin'!$B$9,'Cost Margin'!$K23)=""),0,IF(MIN(IF(OR('Cost Margin'!$B$14="Y",'Cost Margin'!$K23=""),'Cost Margin'!$B$9,'Cost Margin'!$K23),C$6)<MAX(IF(OR('Cost Margin'!$B$14="Y",'Cost Margin'!$J23=""),'Cost Margin'!$B$8,'Cost Margin'!$J23),C$5),0,IFERROR(NETWORKDAYS(MAX(IF(OR('Cost Margin'!$B$14="Y",'Cost Margin'!$J23=""),'Cost Margin'!$B$8,'Cost Margin'!$J23),C$5),MIN(IF(OR('Cost Margin'!$B$14="Y",'Cost Margin'!$K23=""),'Cost Margin'!$B$9,'Cost Margin'!$K23),C$6),INDEX(Settings!$A$35:$D$74,0,MATCH('Cost Margin'!$C23,Settings!$A$34:$D$34,0))),NETWORKDAYS(MAX(IF(OR('Cost Margin'!$B$14="Y",'Cost Margin'!$J23=""),'Cost Margin'!$B$8,'Cost Margin'!$J23),C$5),MIN(IF(OR('Cost Margin'!$B$14="Y",'Cost Margin'!$K23=""),'Cost Margin'!$B$9,'Cost Margin'!$K23),C$6))))) -> 0 | D15: =IF(OR(D$5="",'Cost Margin'!$A23="",IF(OR('Cost Margin'!$B$14="Y",'Cost Margin'!$J23=""),'Cost Margin'!$B$8,'Cost Margin'!$J23)="",IF(OR('Cost Margin'!$B$14="Y",'Cost Margin'!$K23=""),'Cost Margin'!$B$9,'Cost Margin'!$K23)=""),0,IF(MIN(IF(OR('Cost Margin'!$B$14="Y",'Cost Margin'!$K23=""),'Cost Margin'!$B$9,'Cost Margin'!$K23),D$6)<MAX(IF(OR('Cost Margin'!$B$14="Y",'Cost Margin'!$J23=""),'Cost Margin'!$B$8,'Cost Margin'!$J23),D$5),0,IFERROR(NETWORKDAYS(MAX(IF(OR('Cost Margin'!$B$14="Y",'Cost Margin'!$J23=""),'Cost Margin'!$B$8,'Cost Margin'!$J23),D$5),MIN(IF(OR('Cost Margin'!$B$14="Y",'Cost Margin'!$K23=""),'Cost Margin'!$B$9,'Cost Margin'!$K23),D$6),INDEX(Settings!$A$35:$D$74,0,MATCH('Cost Margin'!$C23,Settings!$A$34:$D$34,0))),NETWORKDAYS(MAX(IF(OR('Cost Margin'!$B$14="Y",'Cost Margin'!$J23=""),'Cost Margin'!$B$8,'Cost Margin'!$J23),D$5),MIN(IF(OR('Cost Margin'!$B$14="Y",'Cost Margin'!$K23=""),'Cost Margin'!$B$9,'Cost Margin'!$K23),D$6))))) -> 0 | E15: =IF(OR(E$5="",'Cost Margin'!$A23="",IF(OR('Cost Margin'!$B$14="Y",'Cost Margin'!$J23=""),'Cost Margin'!$B$8,'Cost Margin'!$J23)="",IF(OR('Cost Margin'!$B$14="Y",'Cost Margin'!$K23=""),'Cost Margin'!$B$9,'Cost Margin'!$K23)=""),0,IF(MIN(IF(OR('Cost Margin'!$B$14="Y",'Cost Margin'!$K23=""),'Cost Margin'!$B$9,'Cost Margin'!$K23),E$6)<MAX(IF(OR('Cost Margin'!$B$14="Y",'Cost Margin'!$J23=""),'Cost Margin'!$B$8,'Cost Margin'!$J23),E$5),0,IFERROR(NETWORKDAYS(MAX(IF(OR('Cost Margin'!$B$14="Y",'Cost Margin'!$J23=""),'Cost Margin'!$B$8,'Cost Margin'!$J23),E$5),MIN(IF(OR('Cost Margin'!$B$14="Y",'Cost Margin'!$K23=""),'Cost Margin'!$B$9,'Cost Margin'!$K23),E$6),INDEX(Settings!$A$35:$D$74,0,MATCH('Cost Margin'!$C23,Settings!$A$34:$D$34,0))),NETWORKDAYS(MAX(IF(OR('Cost Margin'!$B$14="Y",'Cost Margin'!$J23=""),'Cost Margin'!$B$8,'Cost Margin'!$J23),E$5),MIN(IF(OR('Cost Margin'!$B$14="Y",'Cost Margin'!$K23=""),'Cost Margin'!$B$9,'Cost Margin'!$K23),E$6))))) -> 0 | F15: =IF(OR(F$5="",'Cost Margin'!$A23="",IF(OR('Cost Margin'!$B$14="Y",'Cost Margin'!$J23=""),'Cost Margin'!$B$8,'Cost Margin'!$J23)="",IF(OR('Cost Margin'!$B$14="Y",'Cost Margin'!$K23=""),'Cost Margin'!$B$9,'Cost Margin'!$K23)=""),0,IF(MIN(IF(OR('Cost Margin'!$B$14="Y",'Cost Margin'!$K23=""),'Cost Margin'!$B$9,'Cost Margin'!$K23),F$6)<MAX(IF(OR('Cost Margin'!$B$14="Y",'Cost Margin'!$J23=""),'Cost Margin'!$B$8,'Cost Margin'!$J23),F$5),0,IFERROR(NETWORKDAYS(MAX(IF(OR('Cost Margin'!$B$14="Y",'Cost Margin'!$J23=""),'Cost Margin'!$B$8,'Cost Margin'!$J23),F$5),MIN(IF(OR('Cost Margin'!$B$14="Y",'Cost Margin'!$K23=""),'Cost Margin'!$B$9,'Cost Margin'!$K23),F$6),INDEX(Settings!$A$35:$D$74,0,MATCH('Cost Margin'!$C23,Settings!$A$34:$D$34,0))),NETWORKDAYS(MAX(IF(OR('Cost Margin'!$B$14="Y",'Cost Margin'!$J23=""),'Cost Margin'!$B$8,'Cost Margin'!$J23),F$5),MIN(IF(OR('Cost Margin'!$B$14="Y",'Cost Margin'!$K23=""),'Cost Margin'!$B$9,'Cost Margin'!$K23),F$6))))) -> 0 | G15: =IF(OR(G$5="",'Cost Margin'!$A23="",IF(OR('Cost Margin'!$B$14="Y",'Cost Margin'!$J23=""),'Cost Margin'!$B$8,'Cost Margin'!$J23)="",IF(OR('Cost Margin'!$B$14="Y",'Cost Margin'!$K23=""),'Cost Margin'!$B$9,'Cost Margin'!$K23)=""),0,IF(MIN(IF(OR('Cost Margin'!$B$14="Y",'Cost Margin'!$K23=""),'Cost Margin'!$B$9,'Cost Margin'!$K23),G$6)<MAX(IF(OR('Cost Margin'!$B$14="Y",'Cost Margin'!$J23=""),'Cost Margin'!$B$8,'Cost Margin'!$J23),G$5),0,IFERROR(NETWORKDAYS(MAX(IF(OR('Cost Margin'!$B$14="Y",'Cost Margin'!$J23=""),'Cost Margin'!$B$8,'Cost Margin'!$J23),G$5),MIN(IF(OR('Cost Margin'!$B$14="Y",'Cost Margin'!$K23=""),'Cost Margin'!$B$9,'Cost Margin'!$K23),G$6),INDEX(Settings!$A$35:$D$74,0,MATCH('Cost Margin'!$C23,Settings!$A$34:$D$34,0))),NETWORKDAYS(MAX(IF(OR('Cost Margin'!$B$14="Y",'Cost Margin'!$J23=""),'Cost Margin'!$B$8,'Cost Margin'!$J23),G$5),MIN(IF(OR('Cost Margin'!$B$14="Y",'Cost Margin'!$K23=""),'Cost Margin'!$B$9,'Cost Margin'!$K23),G$6))))) -> 0 | H15: =IF(OR(H$5="",'Cost Margin'!$A23="",IF(OR('Cost Margin'!$B$14="Y",'Cost Margin'!$J23=""),'Cost Margin'!$B$8,'Cost Margin'!$J23)="",IF(OR('Cost Margin'!$B$14="Y",'Cost Margin'!$K23=""),'Cost Margin'!$B$9,'Cost Margin'!$K23)=""),0,IF(MIN(IF(OR('Cost Margin'!$B$14="Y",'Cost Margin'!$K23=""),'Cost Margin'!$B$9,'Cost Margin'!$K23),H$6)<MAX(IF(OR('Cost Margin'!$B$14="Y",'Cost Margin'!$J23=""),'Cost Margin'!$B$8,'Cost Margin'!$J23),H$5),0,IFERROR(NETWORKDAYS(MAX(IF(OR('Cost Margin'!$B$14="Y",'Cost Margin'!$J23=""),'Cost Margin'!$B$8,'Cost Margin'!$J23),H$5),MIN(IF(OR('Cost Margin'!$B$14="Y",'Cost Margin'!$K23=""),'Cost Margin'!$B$9,'Cost Margin'!$K23),H$6),INDEX(Settings!$A$35:$D$74,0,MATCH('Cost Margin'!$C23,Settings!$A$34:$D$34,0))),NETWORKDAYS(MAX(IF(OR('Cost Margin'!$B$14="Y",'Cost Margin'!$J23=""),'Cost Margin'!$B$8,'Cost Margin'!$J23),H$5),MIN(IF(OR('Cost Margin'!$B$14="Y",'Cost Margin'!$K23=""),'Cost Margin'!$B$9,'Cost Margin'!$K23),H$6))))) -> 0 | I15: =IF(OR(I$5="",'Cost Margin'!$A23="",IF(OR('Cost Margin'!$B$14="Y",'Cost Margin'!$J23=""),'Cost Margin'!$B$8,'Cost Margin'!$J23)="",IF(OR('Cost Margin'!$B$14="Y",'Cost Margin'!$K23=""),'Cost Margin'!$B$9,'Cost Margin'!$K23)=""),0,IF(MIN(IF(OR('Cost Margin'!$B$14="Y",'Cost Margin'!$K23=""),'Cost Margin'!$B$9,'Cost Margin'!$K23),I$6)<MAX(IF(OR('Cost Margin'!$B$14="Y",'Cost Margin'!$J23=""),'Cost Margin'!$B$8,'Cost Margin'!$J23),I$5),0,IFERROR(NETWORKDAYS(MAX(IF(OR('Cost Margin'!$B$14="Y",'Cost Margin'!$J23=""),'Cost Margin'!$B$8,'Cost Margin'!$J23),I$5),MIN(IF(OR('Cost Margin'!$B$14="Y",'Cost Margin'!$K23=""),'Cost Margin'!$B$9,'Cost Margin'!$K23),I$6),INDEX(Settings!$A$35:$D$74,0,MATCH('Cost Margin'!$C23,Settings!$A$34:$D$34,0))),NETWORKDAYS(MAX(IF(OR('Cost Margin'!$B$14="Y",'Cost Margin'!$J23=""),'Cost Margin'!$B$8,'Cost Margin'!$J23),I$5),MIN(IF(OR('Cost Margin'!$B$14="Y",'Cost Margin'!$K23=""),'Cost Margin'!$B$9,'Cost Margin'!$K23),I$6))))) -> 0 | J15: =IF(OR(J$5="",'Cost Margin'!$A23="",IF(OR('Cost Margin'!$B$14="Y",'Cost Margin'!$J23=""),'Cost Margin'!$B$8,'Cost Margin'!$J23)="",IF(OR('Cost Margin'!$B$14="Y",'Cost Margin'!$K23=""),'Cost Margin'!$B$9,'Cost Margin'!$K23)=""),0,IF(MIN(IF(OR('Cost Margin'!$B$14="Y",'Cost Margin'!$K23=""),'Cost Margin'!$B$9,'Cost Margin'!$K23),J$6)<MAX(IF(OR('Cost Margin'!$B$14="Y",'Cost Margin'!$J23=""),'Cost Margin'!$B$8,'Cost Margin'!$J23),J$5),0,IFERROR(NETWORKDAYS(MAX(IF(OR('Cost Margin'!$B$14="Y",'Cost Margin'!$J23=""),'Cost Margin'!$B$8,'Cost Margin'!$J23),J$5),MIN(IF(OR('Cost Margin'!$B$14="Y",'Cost Margin'!$K23=""),'Cost Margin'!$B$9,'Cost Margin'!$K23),J$6),INDEX(Settings!$A$35:$D$74,0,MATCH('Cost Margin'!$C23,Settings!$A$34:$D$34,0))),NETWORKDAYS(MAX(IF(OR('Cost Margin'!$B$14="Y",'Cost Margin'!$J23=""),'Cost Margin'!$B$8,'Cost Margin'!$J23),J$5),MIN(IF(OR('Cost Margin'!$B$14="Y",'Cost Margin'!$K23=""),'Cost Margin'!$B$9,'Cost Margin'!$K23),J$6))))) -> 0 | ... Z15: =IF(OR(Z$5="",'Cost Margin'!$A23="",IF(OR('Cost Margin'!$B$14="Y",'Cost Margin'!$J23=""),'Cost Margin'!$B$8,'Cost Margin'!$J23)="",IF(OR('Cost Margin'!$B$14="Y",'Cost Margin'!$K23=""),'Cost Margin'!$B$9,'Cost Margin'!$K23)=""),0,IF(MIN(IF(OR('Cost Margin'!$B$14="Y",'Cost Margin'!$K23=""),'Cost Margin'!$B$9,'Cost Margin'!$K23),Z$6)<MAX(IF(OR('Cost Margin'!$B$14="Y",'Cost Margin'!$J23=""),'Cost Margin'!$B$8,'Cost Margin'!$J23),Z$5),0,IFERROR(NETWORKDAYS(MAX(IF(OR('Cost Margin'!$B$14="Y",'Cost Margin'!$J23=""),'Cost Margin'!$B$8,'Cost Margin'!$J23),Z$5),MIN(IF(OR('Cost Margin'!$B$14="Y",'Cost Margin'!$K23=""),'Cost Margin'!$B$9,'Cost Margin'!$K23),Z$6),INDEX(Settings!$A$35:$D$74,0,MATCH('Cost Margin'!$C23,Settings!$A$34:$D$34,0))),NETWORKDAYS(MAX(IF(OR('Cost Margin'!$B$14="Y",'Cost Margin'!$J23=""),'Cost Margin'!$B$8,'Cost Margin'!$J23),Z$5),MIN(IF(OR('Cost Margin'!$B$14="Y",'Cost Margin'!$K23=""),'Cost Margin'!$B$9,'Cost Margin'!$K23),Z$6))))) -> 0 | AB15: =IF('Cost Margin'!A23="","",IF('Cost Margin'!E23="","(unassigned)",'Cost Margin'!E23))
A16: 8 | B16: =IF('Cost Margin'!A24="","",'Cost Margin'!A24&IF('Cost Margin'!E24="",""," · "&'Cost Margin'!E24)) | C16: =IF(OR(C$5="",'Cost Margin'!$A24="",IF(OR('Cost Margin'!$B$14="Y",'Cost Margin'!$J24=""),'Cost Margin'!$B$8,'Cost Margin'!$J24)="",IF(OR('Cost Margin'!$B$14="Y",'Cost Margin'!$K24=""),'Cost Margin'!$B$9,'Cost Margin'!$K24)=""),0,IF(MIN(IF(OR('Cost Margin'!$B$14="Y",'Cost Margin'!$K24=""),'Cost Margin'!$B$9,'Cost Margin'!$K24),C$6)<MAX(IF(OR('Cost Margin'!$B$14="Y",'Cost Margin'!$J24=""),'Cost Margin'!$B$8,'Cost Margin'!$J24),C$5),0,IFERROR(NETWORKDAYS(MAX(IF(OR('Cost Margin'!$B$14="Y",'Cost Margin'!$J24=""),'Cost Margin'!$B$8,'Cost Margin'!$J24),C$5),MIN(IF(OR('Cost Margin'!$B$14="Y",'Cost Margin'!$K24=""),'Cost Margin'!$B$9,'Cost Margin'!$K24),C$6),INDEX(Settings!$A$35:$D$74,0,MATCH('Cost Margin'!$C24,Settings!$A$34:$D$34,0))),NETWORKDAYS(MAX(IF(OR('Cost Margin'!$B$14="Y",'Cost Margin'!$J24=""),'Cost Margin'!$B$8,'Cost Margin'!$J24),C$5),MIN(IF(OR('Cost Margin'!$B$14="Y",'Cost Margin'!$K24=""),'Cost Margin'!$B$9,'Cost Margin'!$K24),C$6))))) -> 0 | D16: =IF(OR(D$5="",'Cost Margin'!$A24="",IF(OR('Cost Margin'!$B$14="Y",'Cost Margin'!$J24=""),'Cost Margin'!$B$8,'Cost Margin'!$J24)="",IF(OR('Cost Margin'!$B$14="Y",'Cost Margin'!$K24=""),'Cost Margin'!$B$9,'Cost Margin'!$K24)=""),0,IF(MIN(IF(OR('Cost Margin'!$B$14="Y",'Cost Margin'!$K24=""),'Cost Margin'!$B$9,'Cost Margin'!$K24),D$6)<MAX(IF(OR('Cost Margin'!$B$14="Y",'Cost Margin'!$J24=""),'Cost Margin'!$B$8,'Cost Margin'!$J24),D$5),0,IFERROR(NETWORKDAYS(MAX(IF(OR('Cost Margin'!$B$14="Y",'Cost Margin'!$J24=""),'Cost Margin'!$B$8,'Cost Margin'!$J24),D$5),MIN(IF(OR('Cost Margin'!$B$14="Y",'Cost Margin'!$K24=""),'Cost Margin'!$B$9,'Cost Margin'!$K24),D$6),INDEX(Settings!$A$35:$D$74,0,MATCH('Cost Margin'!$C24,Settings!$A$34:$D$34,0))),NETWORKDAYS(MAX(IF(OR('Cost Margin'!$B$14="Y",'Cost Margin'!$J24=""),'Cost Margin'!$B$8,'Cost Margin'!$J24),D$5),MIN(IF(OR('Cost Margin'!$B$14="Y",'Cost Margin'!$K24=""),'Cost Margin'!$B$9,'Cost Margin'!$K24),D$6))))) -> 0 | E16: =IF(OR(E$5="",'Cost Margin'!$A24="",IF(OR('Cost Margin'!$B$14="Y",'Cost Margin'!$J24=""),'Cost Margin'!$B$8,'Cost Margin'!$J24)="",IF(OR('Cost Margin'!$B$14="Y",'Cost Margin'!$K24=""),'Cost Margin'!$B$9,'Cost Margin'!$K24)=""),0,IF(MIN(IF(OR('Cost Margin'!$B$14="Y",'Cost Margin'!$K24=""),'Cost Margin'!$B$9,'Cost Margin'!$K24),E$6)<MAX(IF(OR('Cost Margin'!$B$14="Y",'Cost Margin'!$J24=""),'Cost Margin'!$B$8,'Cost Margin'!$J24),E$5),0,IFERROR(NETWORKDAYS(MAX(IF(OR('Cost Margin'!$B$14="Y",'Cost Margin'!$J24=""),'Cost Margin'!$B$8,'Cost Margin'!$J24),E$5),MIN(IF(OR('Cost Margin'!$B$14="Y",'Cost Margin'!$K24=""),'Cost Margin'!$B$9,'Cost Margin'!$K24),E$6),INDEX(Settings!$A$35:$D$74,0,MATCH('Cost Margin'!$C24,Settings!$A$34:$D$34,0))),NETWORKDAYS(MAX(IF(OR('Cost Margin'!$B$14="Y",'Cost Margin'!$J24=""),'Cost Margin'!$B$8,'Cost Margin'!$J24),E$5),MIN(IF(OR('Cost Margin'!$B$14="Y",'Cost Margin'!$K24=""),'Cost Margin'!$B$9,'Cost Margin'!$K24),E$6))))) -> 0 | F16: =IF(OR(F$5="",'Cost Margin'!$A24="",IF(OR('Cost Margin'!$B$14="Y",'Cost Margin'!$J24=""),'Cost Margin'!$B$8,'Cost Margin'!$J24)="",IF(OR('Cost Margin'!$B$14="Y",'Cost Margin'!$K24=""),'Cost Margin'!$B$9,'Cost Margin'!$K24)=""),0,IF(MIN(IF(OR('Cost Margin'!$B$14="Y",'Cost Margin'!$K24=""),'Cost Margin'!$B$9,'Cost Margin'!$K24),F$6)<MAX(IF(OR('Cost Margin'!$B$14="Y",'Cost Margin'!$J24=""),'Cost Margin'!$B$8,'Cost Margin'!$J24),F$5),0,IFERROR(NETWORKDAYS(MAX(IF(OR('Cost Margin'!$B$14="Y",'Cost Margin'!$J24=""),'Cost Margin'!$B$8,'Cost Margin'!$J24),F$5),MIN(IF(OR('Cost Margin'!$B$14="Y",'Cost Margin'!$K24=""),'Cost Margin'!$B$9,'Cost Margin'!$K24),F$6),INDEX(Settings!$A$35:$D$74,0,MATCH('Cost Margin'!$C24,Settings!$A$34:$D$34,0))),NETWORKDAYS(MAX(IF(OR('Cost Margin'!$B$14="Y",'Cost Margin'!$J24=""),'Cost Margin'!$B$8,'Cost Margin'!$J24),F$5),MIN(IF(OR('Cost Margin'!$B$14="Y",'Cost Margin'!$K24=""),'Cost Margin'!$B$9,'Cost Margin'!$K24),F$6))))) -> 0 | G16: =IF(OR(G$5="",'Cost Margin'!$A24="",IF(OR('Cost Margin'!$B$14="Y",'Cost Margin'!$J24=""),'Cost Margin'!$B$8,'Cost Margin'!$J24)="",IF(OR('Cost Margin'!$B$14="Y",'Cost Margin'!$K24=""),'Cost Margin'!$B$9,'Cost Margin'!$K24)=""),0,IF(MIN(IF(OR('Cost Margin'!$B$14="Y",'Cost Margin'!$K24=""),'Cost Margin'!$B$9,'Cost Margin'!$K24),G$6)<MAX(IF(OR('Cost Margin'!$B$14="Y",'Cost Margin'!$J24=""),'Cost Margin'!$B$8,'Cost Margin'!$J24),G$5),0,IFERROR(NETWORKDAYS(MAX(IF(OR('Cost Margin'!$B$14="Y",'Cost Margin'!$J24=""),'Cost Margin'!$B$8,'Cost Margin'!$J24),G$5),MIN(IF(OR('Cost Margin'!$B$14="Y",'Cost Margin'!$K24=""),'Cost Margin'!$B$9,'Cost Margin'!$K24),G$6),INDEX(Settings!$A$35:$D$74,0,MATCH('Cost Margin'!$C24,Settings!$A$34:$D$34,0))),NETWORKDAYS(MAX(IF(OR('Cost Margin'!$B$14="Y",'Cost Margin'!$J24=""),'Cost Margin'!$B$8,'Cost Margin'!$J24),G$5),MIN(IF(OR('Cost Margin'!$B$14="Y",'Cost Margin'!$K24=""),'Cost Margin'!$B$9,'Cost Margin'!$K24),G$6))))) -> 0 | H16: =IF(OR(H$5="",'Cost Margin'!$A24="",IF(OR('Cost Margin'!$B$14="Y",'Cost Margin'!$J24=""),'Cost Margin'!$B$8,'Cost Margin'!$J24)="",IF(OR('Cost Margin'!$B$14="Y",'Cost Margin'!$K24=""),'Cost Margin'!$B$9,'Cost Margin'!$K24)=""),0,IF(MIN(IF(OR('Cost Margin'!$B$14="Y",'Cost Margin'!$K24=""),'Cost Margin'!$B$9,'Cost Margin'!$K24),H$6)<MAX(IF(OR('Cost Margin'!$B$14="Y",'Cost Margin'!$J24=""),'Cost Margin'!$B$8,'Cost Margin'!$J24),H$5),0,IFERROR(NETWORKDAYS(MAX(IF(OR('Cost Margin'!$B$14="Y",'Cost Margin'!$J24=""),'Cost Margin'!$B$8,'Cost Margin'!$J24),H$5),MIN(IF(OR('Cost Margin'!$B$14="Y",'Cost Margin'!$K24=""),'Cost Margin'!$B$9,'Cost Margin'!$K24),H$6),INDEX(Settings!$A$35:$D$74,0,MATCH('Cost Margin'!$C24,Settings!$A$34:$D$34,0))),NETWORKDAYS(MAX(IF(OR('Cost Margin'!$B$14="Y",'Cost Margin'!$J24=""),'Cost Margin'!$B$8,'Cost Margin'!$J24),H$5),MIN(IF(OR('Cost Margin'!$B$14="Y",'Cost Margin'!$K24=""),'Cost Margin'!$B$9,'Cost Margin'!$K24),H$6))))) -> 0 | I16: =IF(OR(I$5="",'Cost Margin'!$A24="",IF(OR('Cost Margin'!$B$14="Y",'Cost Margin'!$J24=""),'Cost Margin'!$B$8,'Cost Margin'!$J24)="",IF(OR('Cost Margin'!$B$14="Y",'Cost Margin'!$K24=""),'Cost Margin'!$B$9,'Cost Margin'!$K24)=""),0,IF(MIN(IF(OR('Cost Margin'!$B$14="Y",'Cost Margin'!$K24=""),'Cost Margin'!$B$9,'Cost Margin'!$K24),I$6)<MAX(IF(OR('Cost Margin'!$B$14="Y",'Cost Margin'!$J24=""),'Cost Margin'!$B$8,'Cost Margin'!$J24),I$5),0,IFERROR(NETWORKDAYS(MAX(IF(OR('Cost Margin'!$B$14="Y",'Cost Margin'!$J24=""),'Cost Margin'!$B$8,'Cost Margin'!$J24),I$5),MIN(IF(OR('Cost Margin'!$B$14="Y",'Cost Margin'!$K24=""),'Cost Margin'!$B$9,'Cost Margin'!$K24),I$6),INDEX(Settings!$A$35:$D$74,0,MATCH('Cost Margin'!$C24,Settings!$A$34:$D$34,0))),NETWORKDAYS(MAX(IF(OR('Cost Margin'!$B$14="Y",'Cost Margin'!$J24=""),'Cost Margin'!$B$8,'Cost Margin'!$J24),I$5),MIN(IF(OR('Cost Margin'!$B$14="Y",'Cost Margin'!$K24=""),'Cost Margin'!$B$9,'Cost Margin'!$K24),I$6))))) -> 0 | J16: =IF(OR(J$5="",'Cost Margin'!$A24="",IF(OR('Cost Margin'!$B$14="Y",'Cost Margin'!$J24=""),'Cost Margin'!$B$8,'Cost Margin'!$J24)="",IF(OR('Cost Margin'!$B$14="Y",'Cost Margin'!$K24=""),'Cost Margin'!$B$9,'Cost Margin'!$K24)=""),0,IF(MIN(IF(OR('Cost Margin'!$B$14="Y",'Cost Margin'!$K24=""),'Cost Margin'!$B$9,'Cost Margin'!$K24),J$6)<MAX(IF(OR('Cost Margin'!$B$14="Y",'Cost Margin'!$J24=""),'Cost Margin'!$B$8,'Cost Margin'!$J24),J$5),0,IFERROR(NETWORKDAYS(MAX(IF(OR('Cost Margin'!$B$14="Y",'Cost Margin'!$J24=""),'Cost Margin'!$B$8,'Cost Margin'!$J24),J$5),MIN(IF(OR('Cost Margin'!$B$14="Y",'Cost Margin'!$K24=""),'Cost Margin'!$B$9,'Cost Margin'!$K24),J$6),INDEX(Settings!$A$35:$D$74,0,MATCH('Cost Margin'!$C24,Settings!$A$34:$D$34,0))),NETWORKDAYS(MAX(IF(OR('Cost Margin'!$B$14="Y",'Cost Margin'!$J24=""),'Cost Margin'!$B$8,'Cost Margin'!$J24),J$5),MIN(IF(OR('Cost Margin'!$B$14="Y",'Cost Margin'!$K24=""),'Cost Margin'!$B$9,'Cost Margin'!$K24),J$6))))) -> 0 | ... Z16: =IF(OR(Z$5="",'Cost Margin'!$A24="",IF(OR('Cost Margin'!$B$14="Y",'Cost Margin'!$J24=""),'Cost Margin'!$B$8,'Cost Margin'!$J24)="",IF(OR('Cost Margin'!$B$14="Y",'Cost Margin'!$K24=""),'Cost Margin'!$B$9,'Cost Margin'!$K24)=""),0,IF(MIN(IF(OR('Cost Margin'!$B$14="Y",'Cost Margin'!$K24=""),'Cost Margin'!$B$9,'Cost Margin'!$K24),Z$6)<MAX(IF(OR('Cost Margin'!$B$14="Y",'Cost Margin'!$J24=""),'Cost Margin'!$B$8,'Cost Margin'!$J24),Z$5),0,IFERROR(NETWORKDAYS(MAX(IF(OR('Cost Margin'!$B$14="Y",'Cost Margin'!$J24=""),'Cost Margin'!$B$8,'Cost Margin'!$J24),Z$5),MIN(IF(OR('Cost Margin'!$B$14="Y",'Cost Margin'!$K24=""),'Cost Margin'!$B$9,'Cost Margin'!$K24),Z$6),INDEX(Settings!$A$35:$D$74,0,MATCH('Cost Margin'!$C24,Settings!$A$34:$D$34,0))),NETWORKDAYS(MAX(IF(OR('Cost Margin'!$B$14="Y",'Cost Margin'!$J24=""),'Cost Margin'!$B$8,'Cost Margin'!$J24),Z$5),MIN(IF(OR('Cost Margin'!$B$14="Y",'Cost Margin'!$K24=""),'Cost Margin'!$B$9,'Cost Margin'!$K24),Z$6))))) -> 0 | AB16: =IF('Cost Margin'!A24="","",IF('Cost Margin'!E24="","(unassigned)",'Cost Margin'!E24))
A17: 9 | B17: =IF('Cost Margin'!A25="","",'Cost Margin'!A25&IF('Cost Margin'!E25="",""," · "&'Cost Margin'!E25)) | C17: =IF(OR(C$5="",'Cost Margin'!$A25="",IF(OR('Cost Margin'!$B$14="Y",'Cost Margin'!$J25=""),'Cost Margin'!$B$8,'Cost Margin'!$J25)="",IF(OR('Cost Margin'!$B$14="Y",'Cost Margin'!$K25=""),'Cost Margin'!$B$9,'Cost Margin'!$K25)=""),0,IF(MIN(IF(OR('Cost Margin'!$B$14="Y",'Cost Margin'!$K25=""),'Cost Margin'!$B$9,'Cost Margin'!$K25),C$6)<MAX(IF(OR('Cost Margin'!$B$14="Y",'Cost Margin'!$J25=""),'Cost Margin'!$B$8,'Cost Margin'!$J25),C$5),0,IFERROR(NETWORKDAYS(MAX(IF(OR('Cost Margin'!$B$14="Y",'Cost Margin'!$J25=""),'Cost Margin'!$B$8,'Cost Margin'!$J25),C$5),MIN(IF(OR('Cost Margin'!$B$14="Y",'Cost Margin'!$K25=""),'Cost Margin'!$B$9,'Cost Margin'!$K25),C$6),INDEX(Settings!$A$35:$D$74,0,MATCH('Cost Margin'!$C25,Settings!$A$34:$D$34,0))),NETWORKDAYS(MAX(IF(OR('Cost Margin'!$B$14="Y",'Cost Margin'!$J25=""),'Cost Margin'!$B$8,'Cost Margin'!$J25),C$5),MIN(IF(OR('Cost Margin'!$B$14="Y",'Cost Margin'!$K25=""),'Cost Margin'!$B$9,'Cost Margin'!$K25),C$6))))) -> 0 | D17: =IF(OR(D$5="",'Cost Margin'!$A25="",IF(OR('Cost Margin'!$B$14="Y",'Cost Margin'!$J25=""),'Cost Margin'!$B$8,'Cost Margin'!$J25)="",IF(OR('Cost Margin'!$B$14="Y",'Cost Margin'!$K25=""),'Cost Margin'!$B$9,'Cost Margin'!$K25)=""),0,IF(MIN(IF(OR('Cost Margin'!$B$14="Y",'Cost Margin'!$K25=""),'Cost Margin'!$B$9,'Cost Margin'!$K25),D$6)<MAX(IF(OR('Cost Margin'!$B$14="Y",'Cost Margin'!$J25=""),'Cost Margin'!$B$8,'Cost Margin'!$J25),D$5),0,IFERROR(NETWORKDAYS(MAX(IF(OR('Cost Margin'!$B$14="Y",'Cost Margin'!$J25=""),'Cost Margin'!$B$8,'Cost Margin'!$J25),D$5),MIN(IF(OR('Cost Margin'!$B$14="Y",'Cost Margin'!$K25=""),'Cost Margin'!$B$9,'Cost Margin'!$K25),D$6),INDEX(Settings!$A$35:$D$74,0,MATCH('Cost Margin'!$C25,Settings!$A$34:$D$34,0))),NETWORKDAYS(MAX(IF(OR('Cost Margin'!$B$14="Y",'Cost Margin'!$J25=""),'Cost Margin'!$B$8,'Cost Margin'!$J25),D$5),MIN(IF(OR('Cost Margin'!$B$14="Y",'Cost Margin'!$K25=""),'Cost Margin'!$B$9,'Cost Margin'!$K25),D$6))))) -> 0 | E17: =IF(OR(E$5="",'Cost Margin'!$A25="",IF(OR('Cost Margin'!$B$14="Y",'Cost Margin'!$J25=""),'Cost Margin'!$B$8,'Cost Margin'!$J25)="",IF(OR('Cost Margin'!$B$14="Y",'Cost Margin'!$K25=""),'Cost Margin'!$B$9,'Cost Margin'!$K25)=""),0,IF(MIN(IF(OR('Cost Margin'!$B$14="Y",'Cost Margin'!$K25=""),'Cost Margin'!$B$9,'Cost Margin'!$K25),E$6)<MAX(IF(OR('Cost Margin'!$B$14="Y",'Cost Margin'!$J25=""),'Cost Margin'!$B$8,'Cost Margin'!$J25),E$5),0,IFERROR(NETWORKDAYS(MAX(IF(OR('Cost Margin'!$B$14="Y",'Cost Margin'!$J25=""),'Cost Margin'!$B$8,'Cost Margin'!$J25),E$5),MIN(IF(OR('Cost Margin'!$B$14="Y",'Cost Margin'!$K25=""),'Cost Margin'!$B$9,'Cost Margin'!$K25),E$6),INDEX(Settings!$A$35:$D$74,0,MATCH('Cost Margin'!$C25,Settings!$A$34:$D$34,0))),NETWORKDAYS(MAX(IF(OR('Cost Margin'!$B$14="Y",'Cost Margin'!$J25=""),'Cost Margin'!$B$8,'Cost Margin'!$J25),E$5),MIN(IF(OR('Cost Margin'!$B$14="Y",'Cost Margin'!$K25=""),'Cost Margin'!$B$9,'Cost Margin'!$K25),E$6))))) -> 0 | F17: =IF(OR(F$5="",'Cost Margin'!$A25="",IF(OR('Cost Margin'!$B$14="Y",'Cost Margin'!$J25=""),'Cost Margin'!$B$8,'Cost Margin'!$J25)="",IF(OR('Cost Margin'!$B$14="Y",'Cost Margin'!$K25=""),'Cost Margin'!$B$9,'Cost Margin'!$K25)=""),0,IF(MIN(IF(OR('Cost Margin'!$B$14="Y",'Cost Margin'!$K25=""),'Cost Margin'!$B$9,'Cost Margin'!$K25),F$6)<MAX(IF(OR('Cost Margin'!$B$14="Y",'Cost Margin'!$J25=""),'Cost Margin'!$B$8,'Cost Margin'!$J25),F$5),0,IFERROR(NETWORKDAYS(MAX(IF(OR('Cost Margin'!$B$14="Y",'Cost Margin'!$J25=""),'Cost Margin'!$B$8,'Cost Margin'!$J25),F$5),MIN(IF(OR('Cost Margin'!$B$14="Y",'Cost Margin'!$K25=""),'Cost Margin'!$B$9,'Cost Margin'!$K25),F$6),INDEX(Settings!$A$35:$D$74,0,MATCH('Cost Margin'!$C25,Settings!$A$34:$D$34,0))),NETWORKDAYS(MAX(IF(OR('Cost Margin'!$B$14="Y",'Cost Margin'!$J25=""),'Cost Margin'!$B$8,'Cost Margin'!$J25),F$5),MIN(IF(OR('Cost Margin'!$B$14="Y",'Cost Margin'!$K25=""),'Cost Margin'!$B$9,'Cost Margin'!$K25),F$6))))) -> 0 | G17: =IF(OR(G$5="",'Cost Margin'!$A25="",IF(OR('Cost Margin'!$B$14="Y",'Cost Margin'!$J25=""),'Cost Margin'!$B$8,'Cost Margin'!$J25)="",IF(OR('Cost Margin'!$B$14="Y",'Cost Margin'!$K25=""),'Cost Margin'!$B$9,'Cost Margin'!$K25)=""),0,IF(MIN(IF(OR('Cost Margin'!$B$14="Y",'Cost Margin'!$K25=""),'Cost Margin'!$B$9,'Cost Margin'!$K25),G$6)<MAX(IF(OR('Cost Margin'!$B$14="Y",'Cost Margin'!$J25=""),'Cost Margin'!$B$8,'Cost Margin'!$J25),G$5),0,IFERROR(NETWORKDAYS(MAX(IF(OR('Cost Margin'!$B$14="Y",'Cost Margin'!$J25=""),'Cost Margin'!$B$8,'Cost Margin'!$J25),G$5),MIN(IF(OR('Cost Margin'!$B$14="Y",'Cost Margin'!$K25=""),'Cost Margin'!$B$9,'Cost Margin'!$K25),G$6),INDEX(Settings!$A$35:$D$74,0,MATCH('Cost Margin'!$C25,Settings!$A$34:$D$34,0))),NETWORKDAYS(MAX(IF(OR('Cost Margin'!$B$14="Y",'Cost Margin'!$J25=""),'Cost Margin'!$B$8,'Cost Margin'!$J25),G$5),MIN(IF(OR('Cost Margin'!$B$14="Y",'Cost Margin'!$K25=""),'Cost Margin'!$B$9,'Cost Margin'!$K25),G$6))))) -> 0 | H17: =IF(OR(H$5="",'Cost Margin'!$A25="",IF(OR('Cost Margin'!$B$14="Y",'Cost Margin'!$J25=""),'Cost Margin'!$B$8,'Cost Margin'!$J25)="",IF(OR('Cost Margin'!$B$14="Y",'Cost Margin'!$K25=""),'Cost Margin'!$B$9,'Cost Margin'!$K25)=""),0,IF(MIN(IF(OR('Cost Margin'!$B$14="Y",'Cost Margin'!$K25=""),'Cost Margin'!$B$9,'Cost Margin'!$K25),H$6)<MAX(IF(OR('Cost Margin'!$B$14="Y",'Cost Margin'!$J25=""),'Cost Margin'!$B$8,'Cost Margin'!$J25),H$5),0,IFERROR(NETWORKDAYS(MAX(IF(OR('Cost Margin'!$B$14="Y",'Cost Margin'!$J25=""),'Cost Margin'!$B$8,'Cost Margin'!$J25),H$5),MIN(IF(OR('Cost Margin'!$B$14="Y",'Cost Margin'!$K25=""),'Cost Margin'!$B$9,'Cost Margin'!$K25),H$6),INDEX(Settings!$A$35:$D$74,0,MATCH('Cost Margin'!$C25,Settings!$A$34:$D$34,0))),NETWORKDAYS(MAX(IF(OR('Cost Margin'!$B$14="Y",'Cost Margin'!$J25=""),'Cost Margin'!$B$8,'Cost Margin'!$J25),H$5),MIN(IF(OR('Cost Margin'!$B$14="Y",'Cost Margin'!$K25=""),'Cost Margin'!$B$9,'Cost Margin'!$K25),H$6))))) -> 0 | I17: =IF(OR(I$5="",'Cost Margin'!$A25="",IF(OR('Cost Margin'!$B$14="Y",'Cost Margin'!$J25=""),'Cost Margin'!$B$8,'Cost Margin'!$J25)="",IF(OR('Cost Margin'!$B$14="Y",'Cost Margin'!$K25=""),'Cost Margin'!$B$9,'Cost Margin'!$K25)=""),0,IF(MIN(IF(OR('Cost Margin'!$B$14="Y",'Cost Margin'!$K25=""),'Cost Margin'!$B$9,'Cost Margin'!$K25),I$6)<MAX(IF(OR('Cost Margin'!$B$14="Y",'Cost Margin'!$J25=""),'Cost Margin'!$B$8,'Cost Margin'!$J25),I$5),0,IFERROR(NETWORKDAYS(MAX(IF(OR('Cost Margin'!$B$14="Y",'Cost Margin'!$J25=""),'Cost Margin'!$B$8,'Cost Margin'!$J25),I$5),MIN(IF(OR('Cost Margin'!$B$14="Y",'Cost Margin'!$K25=""),'Cost Margin'!$B$9,'Cost Margin'!$K25),I$6),INDEX(Settings!$A$35:$D$74,0,MATCH('Cost Margin'!$C25,Settings!$A$34:$D$34,0))),NETWORKDAYS(MAX(IF(OR('Cost Margin'!$B$14="Y",'Cost Margin'!$J25=""),'Cost Margin'!$B$8,'Cost Margin'!$J25),I$5),MIN(IF(OR('Cost Margin'!$B$14="Y",'Cost Margin'!$K25=""),'Cost Margin'!$B$9,'Cost Margin'!$K25),I$6))))) -> 0 | J17: =IF(OR(J$5="",'Cost Margin'!$A25="",IF(OR('Cost Margin'!$B$14="Y",'Cost Margin'!$J25=""),'Cost Margin'!$B$8,'Cost Margin'!$J25)="",IF(OR('Cost Margin'!$B$14="Y",'Cost Margin'!$K25=""),'Cost Margin'!$B$9,'Cost Margin'!$K25)=""),0,IF(MIN(IF(OR('Cost Margin'!$B$14="Y",'Cost Margin'!$K25=""),'Cost Margin'!$B$9,'Cost Margin'!$K25),J$6)<MAX(IF(OR('Cost Margin'!$B$14="Y",'Cost Margin'!$J25=""),'Cost Margin'!$B$8,'Cost Margin'!$J25),J$5),0,IFERROR(NETWORKDAYS(MAX(IF(OR('Cost Margin'!$B$14="Y",'Cost Margin'!$J25=""),'Cost Margin'!$B$8,'Cost Margin'!$J25),J$5),MIN(IF(OR('Cost Margin'!$B$14="Y",'Cost Margin'!$K25=""),'Cost Margin'!$B$9,'Cost Margin'!$K25),J$6),INDEX(Settings!$A$35:$D$74,0,MATCH('Cost Margin'!$C25,Settings!$A$34:$D$34,0))),NETWORKDAYS(MAX(IF(OR('Cost Margin'!$B$14="Y",'Cost Margin'!$J25=""),'Cost Margin'!$B$8,'Cost Margin'!$J25),J$5),MIN(IF(OR('Cost Margin'!$B$14="Y",'Cost Margin'!$K25=""),'Cost Margin'!$B$9,'Cost Margin'!$K25),J$6))))) -> 0 | ... Z17: =IF(OR(Z$5="",'Cost Margin'!$A25="",IF(OR('Cost Margin'!$B$14="Y",'Cost Margin'!$J25=""),'Cost Margin'!$B$8,'Cost Margin'!$J25)="",IF(OR('Cost Margin'!$B$14="Y",'Cost Margin'!$K25=""),'Cost Margin'!$B$9,'Cost Margin'!$K25)=""),0,IF(MIN(IF(OR('Cost Margin'!$B$14="Y",'Cost Margin'!$K25=""),'Cost Margin'!$B$9,'Cost Margin'!$K25),Z$6)<MAX(IF(OR('Cost Margin'!$B$14="Y",'Cost Margin'!$J25=""),'Cost Margin'!$B$8,'Cost Margin'!$J25),Z$5),0,IFERROR(NETWORKDAYS(MAX(IF(OR('Cost Margin'!$B$14="Y",'Cost Margin'!$J25=""),'Cost Margin'!$B$8,'Cost Margin'!$J25),Z$5),MIN(IF(OR('Cost Margin'!$B$14="Y",'Cost Margin'!$K25=""),'Cost Margin'!$B$9,'Cost Margin'!$K25),Z$6),INDEX(Settings!$A$35:$D$74,0,MATCH('Cost Margin'!$C25,Settings!$A$34:$D$34,0))),NETWORKDAYS(MAX(IF(OR('Cost Margin'!$B$14="Y",'Cost Margin'!$J25=""),'Cost Margin'!$B$8,'Cost Margin'!$J25),Z$5),MIN(IF(OR('Cost Margin'!$B$14="Y",'Cost Margin'!$K25=""),'Cost Margin'!$B$9,'Cost Margin'!$K25),Z$6))))) -> 0 | AB17: =IF('Cost Margin'!A25="","",IF('Cost Margin'!E25="","(unassigned)",'Cost Margin'!E25))
A18: 10 | B18: =IF('Cost Margin'!A26="","",'Cost Margin'!A26&IF('Cost Margin'!E26="",""," · "&'Cost Margin'!E26)) | C18: =IF(OR(C$5="",'Cost Margin'!$A26="",IF(OR('Cost Margin'!$B$14="Y",'Cost Margin'!$J26=""),'Cost Margin'!$B$8,'Cost Margin'!$J26)="",IF(OR('Cost Margin'!$B$14="Y",'Cost Margin'!$K26=""),'Cost Margin'!$B$9,'Cost Margin'!$K26)=""),0,IF(MIN(IF(OR('Cost Margin'!$B$14="Y",'Cost Margin'!$K26=""),'Cost Margin'!$B$9,'Cost Margin'!$K26),C$6)<MAX(IF(OR('Cost Margin'!$B$14="Y",'Cost Margin'!$J26=""),'Cost Margin'!$B$8,'Cost Margin'!$J26),C$5),0,IFERROR(NETWORKDAYS(MAX(IF(OR('Cost Margin'!$B$14="Y",'Cost Margin'!$J26=""),'Cost Margin'!$B$8,'Cost Margin'!$J26),C$5),MIN(IF(OR('Cost Margin'!$B$14="Y",'Cost Margin'!$K26=""),'Cost Margin'!$B$9,'Cost Margin'!$K26),C$6),INDEX(Settings!$A$35:$D$74,0,MATCH('Cost Margin'!$C26,Settings!$A$34:$D$34,0))),NETWORKDAYS(MAX(IF(OR('Cost Margin'!$B$14="Y",'Cost Margin'!$J26=""),'Cost Margin'!$B$8,'Cost Margin'!$J26),C$5),MIN(IF(OR('Cost Margin'!$B$14="Y",'Cost Margin'!$K26=""),'Cost Margin'!$B$9,'Cost Margin'!$K26),C$6))))) -> 0 | D18: =IF(OR(D$5="",'Cost Margin'!$A26="",IF(OR('Cost Margin'!$B$14="Y",'Cost Margin'!$J26=""),'Cost Margin'!$B$8,'Cost Margin'!$J26)="",IF(OR('Cost Margin'!$B$14="Y",'Cost Margin'!$K26=""),'Cost Margin'!$B$9,'Cost Margin'!$K26)=""),0,IF(MIN(IF(OR('Cost Margin'!$B$14="Y",'Cost Margin'!$K26=""),'Cost Margin'!$B$9,'Cost Margin'!$K26),D$6)<MAX(IF(OR('Cost Margin'!$B$14="Y",'Cost Margin'!$J26=""),'Cost Margin'!$B$8,'Cost Margin'!$J26),D$5),0,IFERROR(NETWORKDAYS(MAX(IF(OR('Cost Margin'!$B$14="Y",'Cost Margin'!$J26=""),'Cost Margin'!$B$8,'Cost Margin'!$J26),D$5),MIN(IF(OR('Cost Margin'!$B$14="Y",'Cost Margin'!$K26=""),'Cost Margin'!$B$9,'Cost Margin'!$K26),D$6),INDEX(Settings!$A$35:$D$74,0,MATCH('Cost Margin'!$C26,Settings!$A$34:$D$34,0))),NETWORKDAYS(MAX(IF(OR('Cost Margin'!$B$14="Y",'Cost Margin'!$J26=""),'Cost Margin'!$B$8,'Cost Margin'!$J26),D$5),MIN(IF(OR('Cost Margin'!$B$14="Y",'Cost Margin'!$K26=""),'Cost Margin'!$B$9,'Cost Margin'!$K26),D$6))))) -> 0 | E18: =IF(OR(E$5="",'Cost Margin'!$A26="",IF(OR('Cost Margin'!$B$14="Y",'Cost Margin'!$J26=""),'Cost Margin'!$B$8,'Cost Margin'!$J26)="",IF(OR('Cost Margin'!$B$14="Y",'Cost Margin'!$K26=""),'Cost Margin'!$B$9,'Cost Margin'!$K26)=""),0,IF(MIN(IF(OR('Cost Margin'!$B$14="Y",'Cost Margin'!$K26=""),'Cost Margin'!$B$9,'Cost Margin'!$K26),E$6)<MAX(IF(OR('Cost Margin'!$B$14="Y",'Cost Margin'!$J26=""),'Cost Margin'!$B$8,'Cost Margin'!$J26),E$5),0,IFERROR(NETWORKDAYS(MAX(IF(OR('Cost Margin'!$B$14="Y",'Cost Margin'!$J26=""),'Cost Margin'!$B$8,'Cost Margin'!$J26),E$5),MIN(IF(OR('Cost Margin'!$B$14="Y",'Cost Margin'!$K26=""),'Cost Margin'!$B$9,'Cost Margin'!$K26),E$6),INDEX(Settings!$A$35:$D$74,0,MATCH('Cost Margin'!$C26,Settings!$A$34:$D$34,0))),NETWORKDAYS(MAX(IF(OR('Cost Margin'!$B$14="Y",'Cost Margin'!$J26=""),'Cost Margin'!$B$8,'Cost Margin'!$J26),E$5),MIN(IF(OR('Cost Margin'!$B$14="Y",'Cost Margin'!$K26=""),'Cost Margin'!$B$9,'Cost Margin'!$K26),E$6))))) -> 0 | F18: =IF(OR(F$5="",'Cost Margin'!$A26="",IF(OR('Cost Margin'!$B$14="Y",'Cost Margin'!$J26=""),'Cost Margin'!$B$8,'Cost Margin'!$J26)="",IF(OR('Cost Margin'!$B$14="Y",'Cost Margin'!$K26=""),'Cost Margin'!$B$9,'Cost Margin'!$K26)=""),0,IF(MIN(IF(OR('Cost Margin'!$B$14="Y",'Cost Margin'!$K26=""),'Cost Margin'!$B$9,'Cost Margin'!$K26),F$6)<MAX(IF(OR('Cost Margin'!$B$14="Y",'Cost Margin'!$J26=""),'Cost Margin'!$B$8,'Cost Margin'!$J26),F$5),0,IFERROR(NETWORKDAYS(MAX(IF(OR('Cost Margin'!$B$14="Y",'Cost Margin'!$J26=""),'Cost Margin'!$B$8,'Cost Margin'!$J26),F$5),MIN(IF(OR('Cost Margin'!$B$14="Y",'Cost Margin'!$K26=""),'Cost Margin'!$B$9,'Cost Margin'!$K26),F$6),INDEX(Settings!$A$35:$D$74,0,MATCH('Cost Margin'!$C26,Settings!$A$34:$D$34,0))),NETWORKDAYS(MAX(IF(OR('Cost Margin'!$B$14="Y",'Cost Margin'!$J26=""),'Cost Margin'!$B$8,'Cost Margin'!$J26),F$5),MIN(IF(OR('Cost Margin'!$B$14="Y",'Cost Margin'!$K26=""),'Cost Margin'!$B$9,'Cost Margin'!$K26),F$6))))) -> 0 | G18: =IF(OR(G$5="",'Cost Margin'!$A26="",IF(OR('Cost Margin'!$B$14="Y",'Cost Margin'!$J26=""),'Cost Margin'!$B$8,'Cost Margin'!$J26)="",IF(OR('Cost Margin'!$B$14="Y",'Cost Margin'!$K26=""),'Cost Margin'!$B$9,'Cost Margin'!$K26)=""),0,IF(MIN(IF(OR('Cost Margin'!$B$14="Y",'Cost Margin'!$K26=""),'Cost Margin'!$B$9,'Cost Margin'!$K26),G$6)<MAX(IF(OR('Cost Margin'!$B$14="Y",'Cost Margin'!$J26=""),'Cost Margin'!$B$8,'Cost Margin'!$J26),G$5),0,IFERROR(NETWORKDAYS(MAX(IF(OR('Cost Margin'!$B$14="Y",'Cost Margin'!$J26=""),'Cost Margin'!$B$8,'Cost Margin'!$J26),G$5),MIN(IF(OR('Cost Margin'!$B$14="Y",'Cost Margin'!$K26=""),'Cost Margin'!$B$9,'Cost Margin'!$K26),G$6),INDEX(Settings!$A$35:$D$74,0,MATCH('Cost Margin'!$C26,Settings!$A$34:$D$34,0))),NETWORKDAYS(MAX(IF(OR('Cost Margin'!$B$14="Y",'Cost Margin'!$J26=""),'Cost Margin'!$B$8,'Cost Margin'!$J26),G$5),MIN(IF(OR('Cost Margin'!$B$14="Y",'Cost Margin'!$K26=""),'Cost Margin'!$B$9,'Cost Margin'!$K26),G$6))))) -> 0 | H18: =IF(OR(H$5="",'Cost Margin'!$A26="",IF(OR('Cost Margin'!$B$14="Y",'Cost Margin'!$J26=""),'Cost Margin'!$B$8,'Cost Margin'!$J26)="",IF(OR('Cost Margin'!$B$14="Y",'Cost Margin'!$K26=""),'Cost Margin'!$B$9,'Cost Margin'!$K26)=""),0,IF(MIN(IF(OR('Cost Margin'!$B$14="Y",'Cost Margin'!$K26=""),'Cost Margin'!$B$9,'Cost Margin'!$K26),H$6)<MAX(IF(OR('Cost Margin'!$B$14="Y",'Cost Margin'!$J26=""),'Cost Margin'!$B$8,'Cost Margin'!$J26),H$5),0,IFERROR(NETWORKDAYS(MAX(IF(OR('Cost Margin'!$B$14="Y",'Cost Margin'!$J26=""),'Cost Margin'!$B$8,'Cost Margin'!$J26),H$5),MIN(IF(OR('Cost Margin'!$B$14="Y",'Cost Margin'!$K26=""),'Cost Margin'!$B$9,'Cost Margin'!$K26),H$6),INDEX(Settings!$A$35:$D$74,0,MATCH('Cost Margin'!$C26,Settings!$A$34:$D$34,0))),NETWORKDAYS(MAX(IF(OR('Cost Margin'!$B$14="Y",'Cost Margin'!$J26=""),'Cost Margin'!$B$8,'Cost Margin'!$J26),H$5),MIN(IF(OR('Cost Margin'!$B$14="Y",'Cost Margin'!$K26=""),'Cost Margin'!$B$9,'Cost Margin'!$K26),H$6))))) -> 0 | I18: =IF(OR(I$5="",'Cost Margin'!$A26="",IF(OR('Cost Margin'!$B$14="Y",'Cost Margin'!$J26=""),'Cost Margin'!$B$8,'Cost Margin'!$J26)="",IF(OR('Cost Margin'!$B$14="Y",'Cost Margin'!$K26=""),'Cost Margin'!$B$9,'Cost Margin'!$K26)=""),0,IF(MIN(IF(OR('Cost Margin'!$B$14="Y",'Cost Margin'!$K26=""),'Cost Margin'!$B$9,'Cost Margin'!$K26),I$6)<MAX(IF(OR('Cost Margin'!$B$14="Y",'Cost Margin'!$J26=""),'Cost Margin'!$B$8,'Cost Margin'!$J26),I$5),0,IFERROR(NETWORKDAYS(MAX(IF(OR('Cost Margin'!$B$14="Y",'Cost Margin'!$J26=""),'Cost Margin'!$B$8,'Cost Margin'!$J26),I$5),MIN(IF(OR('Cost Margin'!$B$14="Y",'Cost Margin'!$K26=""),'Cost Margin'!$B$9,'Cost Margin'!$K26),I$6),INDEX(Settings!$A$35:$D$74,0,MATCH('Cost Margin'!$C26,Settings!$A$34:$D$34,0))),NETWORKDAYS(MAX(IF(OR('Cost Margin'!$B$14="Y",'Cost Margin'!$J26=""),'Cost Margin'!$B$8,'Cost Margin'!$J26),I$5),MIN(IF(OR('Cost Margin'!$B$14="Y",'Cost Margin'!$K26=""),'Cost Margin'!$B$9,'Cost Margin'!$K26),I$6))))) -> 0 | J18: =IF(OR(J$5="",'Cost Margin'!$A26="",IF(OR('Cost Margin'!$B$14="Y",'Cost Margin'!$J26=""),'Cost Margin'!$B$8,'Cost Margin'!$J26)="",IF(OR('Cost Margin'!$B$14="Y",'Cost Margin'!$K26=""),'Cost Margin'!$B$9,'Cost Margin'!$K26)=""),0,IF(MIN(IF(OR('Cost Margin'!$B$14="Y",'Cost Margin'!$K26=""),'Cost Margin'!$B$9,'Cost Margin'!$K26),J$6)<MAX(IF(OR('Cost Margin'!$B$14="Y",'Cost Margin'!$J26=""),'Cost Margin'!$B$8,'Cost Margin'!$J26),J$5),0,IFERROR(NETWORKDAYS(MAX(IF(OR('Cost Margin'!$B$14="Y",'Cost Margin'!$J26=""),'Cost Margin'!$B$8,'Cost Margin'!$J26),J$5),MIN(IF(OR('Cost Margin'!$B$14="Y",'Cost Margin'!$K26=""),'Cost Margin'!$B$9,'Cost Margin'!$K26),J$6),INDEX(Settings!$A$35:$D$74,0,MATCH('Cost Margin'!$C26,Settings!$A$34:$D$34,0))),NETWORKDAYS(MAX(IF(OR('Cost Margin'!$B$14="Y",'Cost Margin'!$J26=""),'Cost Margin'!$B$8,'Cost Margin'!$J26),J$5),MIN(IF(OR('Cost Margin'!$B$14="Y",'Cost Margin'!$K26=""),'Cost Margin'!$B$9,'Cost Margin'!$K26),J$6))))) -> 0 | ... Z18: =IF(OR(Z$5="",'Cost Margin'!$A26="",IF(OR('Cost Margin'!$B$14="Y",'Cost Margin'!$J26=""),'Cost Margin'!$B$8,'Cost Margin'!$J26)="",IF(OR('Cost Margin'!$B$14="Y",'Cost Margin'!$K26=""),'Cost Margin'!$B$9,'Cost Margin'!$K26)=""),0,IF(MIN(IF(OR('Cost Margin'!$B$14="Y",'Cost Margin'!$K26=""),'Cost Margin'!$B$9,'Cost Margin'!$K26),Z$6)<MAX(IF(OR('Cost Margin'!$B$14="Y",'Cost Margin'!$J26=""),'Cost Margin'!$B$8,'Cost Margin'!$J26),Z$5),0,IFERROR(NETWORKDAYS(MAX(IF(OR('Cost Margin'!$B$14="Y",'Cost Margin'!$J26=""),'Cost Margin'!$B$8,'Cost Margin'!$J26),Z$5),MIN(IF(OR('Cost Margin'!$B$14="Y",'Cost Margin'!$K26=""),'Cost Margin'!$B$9,'Cost Margin'!$K26),Z$6),INDEX(Settings!$A$35:$D$74,0,MATCH('Cost Margin'!$C26,Settings!$A$34:$D$34,0))),NETWORKDAYS(MAX(IF(OR('Cost Margin'!$B$14="Y",'Cost Margin'!$J26=""),'Cost Margin'!$B$8,'Cost Margin'!$J26),Z$5),MIN(IF(OR('Cost Margin'!$B$14="Y",'Cost Margin'!$K26=""),'Cost Margin'!$B$9,'Cost Margin'!$K26),Z$6))))) -> 0 | AB18: =IF('Cost Margin'!A26="","",IF('Cost Margin'!E26="","(unassigned)",'Cost Margin'!E26))
A19: 11 | B19: =IF('Cost Margin'!A27="","",'Cost Margin'!A27&IF('Cost Margin'!E27="",""," · "&'Cost Margin'!E27)) | C19: =IF(OR(C$5="",'Cost Margin'!$A27="",IF(OR('Cost Margin'!$B$14="Y",'Cost Margin'!$J27=""),'Cost Margin'!$B$8,'Cost Margin'!$J27)="",IF(OR('Cost Margin'!$B$14="Y",'Cost Margin'!$K27=""),'Cost Margin'!$B$9,'Cost Margin'!$K27)=""),0,IF(MIN(IF(OR('Cost Margin'!$B$14="Y",'Cost Margin'!$K27=""),'Cost Margin'!$B$9,'Cost Margin'!$K27),C$6)<MAX(IF(OR('Cost Margin'!$B$14="Y",'Cost Margin'!$J27=""),'Cost Margin'!$B$8,'Cost Margin'!$J27),C$5),0,IFERROR(NETWORKDAYS(MAX(IF(OR('Cost Margin'!$B$14="Y",'Cost Margin'!$J27=""),'Cost Margin'!$B$8,'Cost Margin'!$J27),C$5),MIN(IF(OR('Cost Margin'!$B$14="Y",'Cost Margin'!$K27=""),'Cost Margin'!$B$9,'Cost Margin'!$K27),C$6),INDEX(Settings!$A$35:$D$74,0,MATCH('Cost Margin'!$C27,Settings!$A$34:$D$34,0))),NETWORKDAYS(MAX(IF(OR('Cost Margin'!$B$14="Y",'Cost Margin'!$J27=""),'Cost Margin'!$B$8,'Cost Margin'!$J27),C$5),MIN(IF(OR('Cost Margin'!$B$14="Y",'Cost Margin'!$K27=""),'Cost Margin'!$B$9,'Cost Margin'!$K27),C$6))))) -> 0 | D19: =IF(OR(D$5="",'Cost Margin'!$A27="",IF(OR('Cost Margin'!$B$14="Y",'Cost Margin'!$J27=""),'Cost Margin'!$B$8,'Cost Margin'!$J27)="",IF(OR('Cost Margin'!$B$14="Y",'Cost Margin'!$K27=""),'Cost Margin'!$B$9,'Cost Margin'!$K27)=""),0,IF(MIN(IF(OR('Cost Margin'!$B$14="Y",'Cost Margin'!$K27=""),'Cost Margin'!$B$9,'Cost Margin'!$K27),D$6)<MAX(IF(OR('Cost Margin'!$B$14="Y",'Cost Margin'!$J27=""),'Cost Margin'!$B$8,'Cost Margin'!$J27),D$5),0,IFERROR(NETWORKDAYS(MAX(IF(OR('Cost Margin'!$B$14="Y",'Cost Margin'!$J27=""),'Cost Margin'!$B$8,'Cost Margin'!$J27),D$5),MIN(IF(OR('Cost Margin'!$B$14="Y",'Cost Margin'!$K27=""),'Cost Margin'!$B$9,'Cost Margin'!$K27),D$6),INDEX(Settings!$A$35:$D$74,0,MATCH('Cost Margin'!$C27,Settings!$A$34:$D$34,0))),NETWORKDAYS(MAX(IF(OR('Cost Margin'!$B$14="Y",'Cost Margin'!$J27=""),'Cost Margin'!$B$8,'Cost Margin'!$J27),D$5),MIN(IF(OR('Cost Margin'!$B$14="Y",'Cost Margin'!$K27=""),'Cost Margin'!$B$9,'Cost Margin'!$K27),D$6))))) -> 0 | E19: =IF(OR(E$5="",'Cost Margin'!$A27="",IF(OR('Cost Margin'!$B$14="Y",'Cost Margin'!$J27=""),'Cost Margin'!$B$8,'Cost Margin'!$J27)="",IF(OR('Cost Margin'!$B$14="Y",'Cost Margin'!$K27=""),'Cost Margin'!$B$9,'Cost Margin'!$K27)=""),0,IF(MIN(IF(OR('Cost Margin'!$B$14="Y",'Cost Margin'!$K27=""),'Cost Margin'!$B$9,'Cost Margin'!$K27),E$6)<MAX(IF(OR('Cost Margin'!$B$14="Y",'Cost Margin'!$J27=""),'Cost Margin'!$B$8,'Cost Margin'!$J27),E$5),0,IFERROR(NETWORKDAYS(MAX(IF(OR('Cost Margin'!$B$14="Y",'Cost Margin'!$J27=""),'Cost Margin'!$B$8,'Cost Margin'!$J27),E$5),MIN(IF(OR('Cost Margin'!$B$14="Y",'Cost Margin'!$K27=""),'Cost Margin'!$B$9,'Cost Margin'!$K27),E$6),INDEX(Settings!$A$35:$D$74,0,MATCH('Cost Margin'!$C27,Settings!$A$34:$D$34,0))),NETWORKDAYS(MAX(IF(OR('Cost Margin'!$B$14="Y",'Cost Margin'!$J27=""),'Cost Margin'!$B$8,'Cost Margin'!$J27),E$5),MIN(IF(OR('Cost Margin'!$B$14="Y",'Cost Margin'!$K27=""),'Cost Margin'!$B$9,'Cost Margin'!$K27),E$6))))) -> 0 | F19: =IF(OR(F$5="",'Cost Margin'!$A27="",IF(OR('Cost Margin'!$B$14="Y",'Cost Margin'!$J27=""),'Cost Margin'!$B$8,'Cost Margin'!$J27)="",IF(OR('Cost Margin'!$B$14="Y",'Cost Margin'!$K27=""),'Cost Margin'!$B$9,'Cost Margin'!$K27)=""),0,IF(MIN(IF(OR('Cost Margin'!$B$14="Y",'Cost Margin'!$K27=""),'Cost Margin'!$B$9,'Cost Margin'!$K27),F$6)<MAX(IF(OR('Cost Margin'!$B$14="Y",'Cost Margin'!$J27=""),'Cost Margin'!$B$8,'Cost Margin'!$J27),F$5),0,IFERROR(NETWORKDAYS(MAX(IF(OR('Cost Margin'!$B$14="Y",'Cost Margin'!$J27=""),'Cost Margin'!$B$8,'Cost Margin'!$J27),F$5),MIN(IF(OR('Cost Margin'!$B$14="Y",'Cost Margin'!$K27=""),'Cost Margin'!$B$9,'Cost Margin'!$K27),F$6),INDEX(Settings!$A$35:$D$74,0,MATCH('Cost Margin'!$C27,Settings!$A$34:$D$34,0))),NETWORKDAYS(MAX(IF(OR('Cost Margin'!$B$14="Y",'Cost Margin'!$J27=""),'Cost Margin'!$B$8,'Cost Margin'!$J27),F$5),MIN(IF(OR('Cost Margin'!$B$14="Y",'Cost Margin'!$K27=""),'Cost Margin'!$B$9,'Cost Margin'!$K27),F$6))))) -> 0 | G19: =IF(OR(G$5="",'Cost Margin'!$A27="",IF(OR('Cost Margin'!$B$14="Y",'Cost Margin'!$J27=""),'Cost Margin'!$B$8,'Cost Margin'!$J27)="",IF(OR('Cost Margin'!$B$14="Y",'Cost Margin'!$K27=""),'Cost Margin'!$B$9,'Cost Margin'!$K27)=""),0,IF(MIN(IF(OR('Cost Margin'!$B$14="Y",'Cost Margin'!$K27=""),'Cost Margin'!$B$9,'Cost Margin'!$K27),G$6)<MAX(IF(OR('Cost Margin'!$B$14="Y",'Cost Margin'!$J27=""),'Cost Margin'!$B$8,'Cost Margin'!$J27),G$5),0,IFERROR(NETWORKDAYS(MAX(IF(OR('Cost Margin'!$B$14="Y",'Cost Margin'!$J27=""),'Cost Margin'!$B$8,'Cost Margin'!$J27),G$5),MIN(IF(OR('Cost Margin'!$B$14="Y",'Cost Margin'!$K27=""),'Cost Margin'!$B$9,'Cost Margin'!$K27),G$6),INDEX(Settings!$A$35:$D$74,0,MATCH('Cost Margin'!$C27,Settings!$A$34:$D$34,0))),NETWORKDAYS(MAX(IF(OR('Cost Margin'!$B$14="Y",'Cost Margin'!$J27=""),'Cost Margin'!$B$8,'Cost Margin'!$J27),G$5),MIN(IF(OR('Cost Margin'!$B$14="Y",'Cost Margin'!$K27=""),'Cost Margin'!$B$9,'Cost Margin'!$K27),G$6))))) -> 0 | H19: =IF(OR(H$5="",'Cost Margin'!$A27="",IF(OR('Cost Margin'!$B$14="Y",'Cost Margin'!$J27=""),'Cost Margin'!$B$8,'Cost Margin'!$J27)="",IF(OR('Cost Margin'!$B$14="Y",'Cost Margin'!$K27=""),'Cost Margin'!$B$9,'Cost Margin'!$K27)=""),0,IF(MIN(IF(OR('Cost Margin'!$B$14="Y",'Cost Margin'!$K27=""),'Cost Margin'!$B$9,'Cost Margin'!$K27),H$6)<MAX(IF(OR('Cost Margin'!$B$14="Y",'Cost Margin'!$J27=""),'Cost Margin'!$B$8,'Cost Margin'!$J27),H$5),0,IFERROR(NETWORKDAYS(MAX(IF(OR('Cost Margin'!$B$14="Y",'Cost Margin'!$J27=""),'Cost Margin'!$B$8,'Cost Margin'!$J27),H$5),MIN(IF(OR('Cost Margin'!$B$14="Y",'Cost Margin'!$K27=""),'Cost Margin'!$B$9,'Cost Margin'!$K27),H$6),INDEX(Settings!$A$35:$D$74,0,MATCH('Cost Margin'!$C27,Settings!$A$34:$D$34,0))),NETWORKDAYS(MAX(IF(OR('Cost Margin'!$B$14="Y",'Cost Margin'!$J27=""),'Cost Margin'!$B$8,'Cost Margin'!$J27),H$5),MIN(IF(OR('Cost Margin'!$B$14="Y",'Cost Margin'!$K27=""),'Cost Margin'!$B$9,'Cost Margin'!$K27),H$6))))) -> 0 | I19: =IF(OR(I$5="",'Cost Margin'!$A27="",IF(OR('Cost Margin'!$B$14="Y",'Cost Margin'!$J27=""),'Cost Margin'!$B$8,'Cost Margin'!$J27)="",IF(OR('Cost Margin'!$B$14="Y",'Cost Margin'!$K27=""),'Cost Margin'!$B$9,'Cost Margin'!$K27)=""),0,IF(MIN(IF(OR('Cost Margin'!$B$14="Y",'Cost Margin'!$K27=""),'Cost Margin'!$B$9,'Cost Margin'!$K27),I$6)<MAX(IF(OR('Cost Margin'!$B$14="Y",'Cost Margin'!$J27=""),'Cost Margin'!$B$8,'Cost Margin'!$J27),I$5),0,IFERROR(NETWORKDAYS(MAX(IF(OR('Cost Margin'!$B$14="Y",'Cost Margin'!$J27=""),'Cost Margin'!$B$8,'Cost Margin'!$J27),I$5),MIN(IF(OR('Cost Margin'!$B$14="Y",'Cost Margin'!$K27=""),'Cost Margin'!$B$9,'Cost Margin'!$K27),I$6),INDEX(Settings!$A$35:$D$74,0,MATCH('Cost Margin'!$C27,Settings!$A$34:$D$34,0))),NETWORKDAYS(MAX(IF(OR('Cost Margin'!$B$14="Y",'Cost Margin'!$J27=""),'Cost Margin'!$B$8,'Cost Margin'!$J27),I$5),MIN(IF(OR('Cost Margin'!$B$14="Y",'Cost Margin'!$K27=""),'Cost Margin'!$B$9,'Cost Margin'!$K27),I$6))))) -> 0 | J19: =IF(OR(J$5="",'Cost Margin'!$A27="",IF(OR('Cost Margin'!$B$14="Y",'Cost Margin'!$J27=""),'Cost Margin'!$B$8,'Cost Margin'!$J27)="",IF(OR('Cost Margin'!$B$14="Y",'Cost Margin'!$K27=""),'Cost Margin'!$B$9,'Cost Margin'!$K27)=""),0,IF(MIN(IF(OR('Cost Margin'!$B$14="Y",'Cost Margin'!$K27=""),'Cost Margin'!$B$9,'Cost Margin'!$K27),J$6)<MAX(IF(OR('Cost Margin'!$B$14="Y",'Cost Margin'!$J27=""),'Cost Margin'!$B$8,'Cost Margin'!$J27),J$5),0,IFERROR(NETWORKDAYS(MAX(IF(OR('Cost Margin'!$B$14="Y",'Cost Margin'!$J27=""),'Cost Margin'!$B$8,'Cost Margin'!$J27),J$5),MIN(IF(OR('Cost Margin'!$B$14="Y",'Cost Margin'!$K27=""),'Cost Margin'!$B$9,'Cost Margin'!$K27),J$6),INDEX(Settings!$A$35:$D$74,0,MATCH('Cost Margin'!$C27,Settings!$A$34:$D$34,0))),NETWORKDAYS(MAX(IF(OR('Cost Margin'!$B$14="Y",'Cost Margin'!$J27=""),'Cost Margin'!$B$8,'Cost Margin'!$J27),J$5),MIN(IF(OR('Cost Margin'!$B$14="Y",'Cost Margin'!$K27=""),'Cost Margin'!$B$9,'Cost Margin'!$K27),J$6))))) -> 0 | ... Z19: =IF(OR(Z$5="",'Cost Margin'!$A27="",IF(OR('Cost Margin'!$B$14="Y",'Cost Margin'!$J27=""),'Cost Margin'!$B$8,'Cost Margin'!$J27)="",IF(OR('Cost Margin'!$B$14="Y",'Cost Margin'!$K27=""),'Cost Margin'!$B$9,'Cost Margin'!$K27)=""),0,IF(MIN(IF(OR('Cost Margin'!$B$14="Y",'Cost Margin'!$K27=""),'Cost Margin'!$B$9,'Cost Margin'!$K27),Z$6)<MAX(IF(OR('Cost Margin'!$B$14="Y",'Cost Margin'!$J27=""),'Cost Margin'!$B$8,'Cost Margin'!$J27),Z$5),0,IFERROR(NETWORKDAYS(MAX(IF(OR('Cost Margin'!$B$14="Y",'Cost Margin'!$J27=""),'Cost Margin'!$B$8,'Cost Margin'!$J27),Z$5),MIN(IF(OR('Cost Margin'!$B$14="Y",'Cost Margin'!$K27=""),'Cost Margin'!$B$9,'Cost Margin'!$K27),Z$6),INDEX(Settings!$A$35:$D$74,0,MATCH('Cost Margin'!$C27,Settings!$A$34:$D$34,0))),NETWORKDAYS(MAX(IF(OR('Cost Margin'!$B$14="Y",'Cost Margin'!$J27=""),'Cost Margin'!$B$8,'Cost Margin'!$J27),Z$5),MIN(IF(OR('Cost Margin'!$B$14="Y",'Cost Margin'!$K27=""),'Cost Margin'!$B$9,'Cost Margin'!$K27),Z$6))))) -> 0 | AB19: =IF('Cost Margin'!A27="","",IF('Cost Margin'!E27="","(unassigned)",'Cost Margin'!E27))
A20: 12 | B20: =IF('Cost Margin'!A28="","",'Cost Margin'!A28&IF('Cost Margin'!E28="",""," · "&'Cost Margin'!E28)) | C20: =IF(OR(C$5="",'Cost Margin'!$A28="",IF(OR('Cost Margin'!$B$14="Y",'Cost Margin'!$J28=""),'Cost Margin'!$B$8,'Cost Margin'!$J28)="",IF(OR('Cost Margin'!$B$14="Y",'Cost Margin'!$K28=""),'Cost Margin'!$B$9,'Cost Margin'!$K28)=""),0,IF(MIN(IF(OR('Cost Margin'!$B$14="Y",'Cost Margin'!$K28=""),'Cost Margin'!$B$9,'Cost Margin'!$K28),C$6)<MAX(IF(OR('Cost Margin'!$B$14="Y",'Cost Margin'!$J28=""),'Cost Margin'!$B$8,'Cost Margin'!$J28),C$5),0,IFERROR(NETWORKDAYS(MAX(IF(OR('Cost Margin'!$B$14="Y",'Cost Margin'!$J28=""),'Cost Margin'!$B$8,'Cost Margin'!$J28),C$5),MIN(IF(OR('Cost Margin'!$B$14="Y",'Cost Margin'!$K28=""),'Cost Margin'!$B$9,'Cost Margin'!$K28),C$6),INDEX(Settings!$A$35:$D$74,0,MATCH('Cost Margin'!$C28,Settings!$A$34:$D$34,0))),NETWORKDAYS(MAX(IF(OR('Cost Margin'!$B$14="Y",'Cost Margin'!$J28=""),'Cost Margin'!$B$8,'Cost Margin'!$J28),C$5),MIN(IF(OR('Cost Margin'!$B$14="Y",'Cost Margin'!$K28=""),'Cost Margin'!$B$9,'Cost Margin'!$K28),C$6))))) -> 0 | D20: =IF(OR(D$5="",'Cost Margin'!$A28="",IF(OR('Cost Margin'!$B$14="Y",'Cost Margin'!$J28=""),'Cost Margin'!$B$8,'Cost Margin'!$J28)="",IF(OR('Cost Margin'!$B$14="Y",'Cost Margin'!$K28=""),'Cost Margin'!$B$9,'Cost Margin'!$K28)=""),0,IF(MIN(IF(OR('Cost Margin'!$B$14="Y",'Cost Margin'!$K28=""),'Cost Margin'!$B$9,'Cost Margin'!$K28),D$6)<MAX(IF(OR('Cost Margin'!$B$14="Y",'Cost Margin'!$J28=""),'Cost Margin'!$B$8,'Cost Margin'!$J28),D$5),0,IFERROR(NETWORKDAYS(MAX(IF(OR('Cost Margin'!$B$14="Y",'Cost Margin'!$J28=""),'Cost Margin'!$B$8,'Cost Margin'!$J28),D$5),MIN(IF(OR('Cost Margin'!$B$14="Y",'Cost Margin'!$K28=""),'Cost Margin'!$B$9,'Cost Margin'!$K28),D$6),INDEX(Settings!$A$35:$D$74,0,MATCH('Cost Margin'!$C28,Settings!$A$34:$D$34,0))),NETWORKDAYS(MAX(IF(OR('Cost Margin'!$B$14="Y",'Cost Margin'!$J28=""),'Cost Margin'!$B$8,'Cost Margin'!$J28),D$5),MIN(IF(OR('Cost Margin'!$B$14="Y",'Cost Margin'!$K28=""),'Cost Margin'!$B$9,'Cost Margin'!$K28),D$6))))) -> 0 | E20: =IF(OR(E$5="",'Cost Margin'!$A28="",IF(OR('Cost Margin'!$B$14="Y",'Cost Margin'!$J28=""),'Cost Margin'!$B$8,'Cost Margin'!$J28)="",IF(OR('Cost Margin'!$B$14="Y",'Cost Margin'!$K28=""),'Cost Margin'!$B$9,'Cost Margin'!$K28)=""),0,IF(MIN(IF(OR('Cost Margin'!$B$14="Y",'Cost Margin'!$K28=""),'Cost Margin'!$B$9,'Cost Margin'!$K28),E$6)<MAX(IF(OR('Cost Margin'!$B$14="Y",'Cost Margin'!$J28=""),'Cost Margin'!$B$8,'Cost Margin'!$J28),E$5),0,IFERROR(NETWORKDAYS(MAX(IF(OR('Cost Margin'!$B$14="Y",'Cost Margin'!$J28=""),'Cost Margin'!$B$8,'Cost Margin'!$J28),E$5),MIN(IF(OR('Cost Margin'!$B$14="Y",'Cost Margin'!$K28=""),'Cost Margin'!$B$9,'Cost Margin'!$K28),E$6),INDEX(Settings!$A$35:$D$74,0,MATCH('Cost Margin'!$C28,Settings!$A$34:$D$34,0))),NETWORKDAYS(MAX(IF(OR('Cost Margin'!$B$14="Y",'Cost Margin'!$J28=""),'Cost Margin'!$B$8,'Cost Margin'!$J28),E$5),MIN(IF(OR('Cost Margin'!$B$14="Y",'Cost Margin'!$K28=""),'Cost Margin'!$B$9,'Cost Margin'!$K28),E$6))))) -> 0 | F20: =IF(OR(F$5="",'Cost Margin'!$A28="",IF(OR('Cost Margin'!$B$14="Y",'Cost Margin'!$J28=""),'Cost Margin'!$B$8,'Cost Margin'!$J28)="",IF(OR('Cost Margin'!$B$14="Y",'Cost Margin'!$K28=""),'Cost Margin'!$B$9,'Cost Margin'!$K28)=""),0,IF(MIN(IF(OR('Cost Margin'!$B$14="Y",'Cost Margin'!$K28=""),'Cost Margin'!$B$9,'Cost Margin'!$K28),F$6)<MAX(IF(OR('Cost Margin'!$B$14="Y",'Cost Margin'!$J28=""),'Cost Margin'!$B$8,'Cost Margin'!$J28),F$5),0,IFERROR(NETWORKDAYS(MAX(IF(OR('Cost Margin'!$B$14="Y",'Cost Margin'!$J28=""),'Cost Margin'!$B$8,'Cost Margin'!$J28),F$5),MIN(IF(OR('Cost Margin'!$B$14="Y",'Cost Margin'!$K28=""),'Cost Margin'!$B$9,'Cost Margin'!$K28),F$6),INDEX(Settings!$A$35:$D$74,0,MATCH('Cost Margin'!$C28,Settings!$A$34:$D$34,0))),NETWORKDAYS(MAX(IF(OR('Cost Margin'!$B$14="Y",'Cost Margin'!$J28=""),'Cost Margin'!$B$8,'Cost Margin'!$J28),F$5),MIN(IF(OR('Cost Margin'!$B$14="Y",'Cost Margin'!$K28=""),'Cost Margin'!$B$9,'Cost Margin'!$K28),F$6))))) -> 0 | G20: =IF(OR(G$5="",'Cost Margin'!$A28="",IF(OR('Cost Margin'!$B$14="Y",'Cost Margin'!$J28=""),'Cost Margin'!$B$8,'Cost Margin'!$J28)="",IF(OR('Cost Margin'!$B$14="Y",'Cost Margin'!$K28=""),'Cost Margin'!$B$9,'Cost Margin'!$K28)=""),0,IF(MIN(IF(OR('Cost Margin'!$B$14="Y",'Cost Margin'!$K28=""),'Cost Margin'!$B$9,'Cost Margin'!$K28),G$6)<MAX(IF(OR('Cost Margin'!$B$14="Y",'Cost Margin'!$J28=""),'Cost Margin'!$B$8,'Cost Margin'!$J28),G$5),0,IFERROR(NETWORKDAYS(MAX(IF(OR('Cost Margin'!$B$14="Y",'Cost Margin'!$J28=""),'Cost Margin'!$B$8,'Cost Margin'!$J28),G$5),MIN(IF(OR('Cost Margin'!$B$14="Y",'Cost Margin'!$K28=""),'Cost Margin'!$B$9,'Cost Margin'!$K28),G$6),INDEX(Settings!$A$35:$D$74,0,MATCH('Cost Margin'!$C28,Settings!$A$34:$D$34,0))),NETWORKDAYS(MAX(IF(OR('Cost Margin'!$B$14="Y",'Cost Margin'!$J28=""),'Cost Margin'!$B$8,'Cost Margin'!$J28),G$5),MIN(IF(OR('Cost Margin'!$B$14="Y",'Cost Margin'!$K28=""),'Cost Margin'!$B$9,'Cost Margin'!$K28),G$6))))) -> 0 | H20: =IF(OR(H$5="",'Cost Margin'!$A28="",IF(OR('Cost Margin'!$B$14="Y",'Cost Margin'!$J28=""),'Cost Margin'!$B$8,'Cost Margin'!$J28)="",IF(OR('Cost Margin'!$B$14="Y",'Cost Margin'!$K28=""),'Cost Margin'!$B$9,'Cost Margin'!$K28)=""),0,IF(MIN(IF(OR('Cost Margin'!$B$14="Y",'Cost Margin'!$K28=""),'Cost Margin'!$B$9,'Cost Margin'!$K28),H$6)<MAX(IF(OR('Cost Margin'!$B$14="Y",'Cost Margin'!$J28=""),'Cost Margin'!$B$8,'Cost Margin'!$J28),H$5),0,IFERROR(NETWORKDAYS(MAX(IF(OR('Cost Margin'!$B$14="Y",'Cost Margin'!$J28=""),'Cost Margin'!$B$8,'Cost Margin'!$J28),H$5),MIN(IF(OR('Cost Margin'!$B$14="Y",'Cost Margin'!$K28=""),'Cost Margin'!$B$9,'Cost Margin'!$K28),H$6),INDEX(Settings!$A$35:$D$74,0,MATCH('Cost Margin'!$C28,Settings!$A$34:$D$34,0))),NETWORKDAYS(MAX(IF(OR('Cost Margin'!$B$14="Y",'Cost Margin'!$J28=""),'Cost Margin'!$B$8,'Cost Margin'!$J28),H$5),MIN(IF(OR('Cost Margin'!$B$14="Y",'Cost Margin'!$K28=""),'Cost Margin'!$B$9,'Cost Margin'!$K28),H$6))))) -> 0 | I20: =IF(OR(I$5="",'Cost Margin'!$A28="",IF(OR('Cost Margin'!$B$14="Y",'Cost Margin'!$J28=""),'Cost Margin'!$B$8,'Cost Margin'!$J28)="",IF(OR('Cost Margin'!$B$14="Y",'Cost Margin'!$K28=""),'Cost Margin'!$B$9,'Cost Margin'!$K28)=""),0,IF(MIN(IF(OR('Cost Margin'!$B$14="Y",'Cost Margin'!$K28=""),'Cost Margin'!$B$9,'Cost Margin'!$K28),I$6)<MAX(IF(OR('Cost Margin'!$B$14="Y",'Cost Margin'!$J28=""),'Cost Margin'!$B$8,'Cost Margin'!$J28),I$5),0,IFERROR(NETWORKDAYS(MAX(IF(OR('Cost Margin'!$B$14="Y",'Cost Margin'!$J28=""),'Cost Margin'!$B$8,'Cost Margin'!$J28),I$5),MIN(IF(OR('Cost Margin'!$B$14="Y",'Cost Margin'!$K28=""),'Cost Margin'!$B$9,'Cost Margin'!$K28),I$6),INDEX(Settings!$A$35:$D$74,0,MATCH('Cost Margin'!$C28,Settings!$A$34:$D$34,0))),NETWORKDAYS(MAX(IF(OR('Cost Margin'!$B$14="Y",'Cost Margin'!$J28=""),'Cost Margin'!$B$8,'Cost Margin'!$J28),I$5),MIN(IF(OR('Cost Margin'!$B$14="Y",'Cost Margin'!$K28=""),'Cost Margin'!$B$9,'Cost Margin'!$K28),I$6))))) -> 0 | J20: =IF(OR(J$5="",'Cost Margin'!$A28="",IF(OR('Cost Margin'!$B$14="Y",'Cost Margin'!$J28=""),'Cost Margin'!$B$8,'Cost Margin'!$J28)="",IF(OR('Cost Margin'!$B$14="Y",'Cost Margin'!$K28=""),'Cost Margin'!$B$9,'Cost Margin'!$K28)=""),0,IF(MIN(IF(OR('Cost Margin'!$B$14="Y",'Cost Margin'!$K28=""),'Cost Margin'!$B$9,'Cost Margin'!$K28),J$6)<MAX(IF(OR('Cost Margin'!$B$14="Y",'Cost Margin'!$J28=""),'Cost Margin'!$B$8,'Cost Margin'!$J28),J$5),0,IFERROR(NETWORKDAYS(MAX(IF(OR('Cost Margin'!$B$14="Y",'Cost Margin'!$J28=""),'Cost Margin'!$B$8,'Cost Margin'!$J28),J$5),MIN(IF(OR('Cost Margin'!$B$14="Y",'Cost Margin'!$K28=""),'Cost Margin'!$B$9,'Cost Margin'!$K28),J$6),INDEX(Settings!$A$35:$D$74,0,MATCH('Cost Margin'!$C28,Settings!$A$34:$D$34,0))),NETWORKDAYS(MAX(IF(OR('Cost Margin'!$B$14="Y",'Cost Margin'!$J28=""),'Cost Margin'!$B$8,'Cost Margin'!$J28),J$5),MIN(IF(OR('Cost Margin'!$B$14="Y",'Cost Margin'!$K28=""),'Cost Margin'!$B$9,'Cost Margin'!$K28),J$6))))) -> 0 | ... Z20: =IF(OR(Z$5="",'Cost Margin'!$A28="",IF(OR('Cost Margin'!$B$14="Y",'Cost Margin'!$J28=""),'Cost Margin'!$B$8,'Cost Margin'!$J28)="",IF(OR('Cost Margin'!$B$14="Y",'Cost Margin'!$K28=""),'Cost Margin'!$B$9,'Cost Margin'!$K28)=""),0,IF(MIN(IF(OR('Cost Margin'!$B$14="Y",'Cost Margin'!$K28=""),'Cost Margin'!$B$9,'Cost Margin'!$K28),Z$6)<MAX(IF(OR('Cost Margin'!$B$14="Y",'Cost Margin'!$J28=""),'Cost Margin'!$B$8,'Cost Margin'!$J28),Z$5),0,IFERROR(NETWORKDAYS(MAX(IF(OR('Cost Margin'!$B$14="Y",'Cost Margin'!$J28=""),'Cost Margin'!$B$8,'Cost Margin'!$J28),Z$5),MIN(IF(OR('Cost Margin'!$B$14="Y",'Cost Margin'!$K28=""),'Cost Margin'!$B$9,'Cost Margin'!$K28),Z$6),INDEX(Settings!$A$35:$D$74,0,MATCH('Cost Margin'!$C28,Settings!$A$34:$D$34,0))),NETWORKDAYS(MAX(IF(OR('Cost Margin'!$B$14="Y",'Cost Margin'!$J28=""),'Cost Margin'!$B$8,'Cost Margin'!$J28),Z$5),MIN(IF(OR('Cost Margin'!$B$14="Y",'Cost Margin'!$K28=""),'Cost Margin'!$B$9,'Cost Margin'!$K28),Z$6))))) -> 0 | AB20: =IF('Cost Margin'!A28="","",IF('Cost Margin'!E28="","(unassigned)",'Cost Margin'!E28))
... A28: 20 | B28: =IF('Cost Margin'!A36="","",'Cost Margin'!A36&IF('Cost Margin'!E36="",""," · "&'Cost Margin'!E36)) | C28: =IF(OR(C$5="",'Cost Margin'!$A36="",IF(OR('Cost Margin'!$B$14="Y",'Cost Margin'!$J36=""),'Cost Margin'!$B$8,'Cost Margin'!$J36)="",IF(OR('Cost Margin'!$B$14="Y",'Cost Margin'!$K36=""),'Cost Margin'!$B$9,'Cost Margin'!$K36)=""),0,IF(MIN(IF(OR('Cost Margin'!$B$14="Y",'Cost Margin'!$K36=""),'Cost Margin'!$B$9,'Cost Margin'!$K36),C$6)<MAX(IF(OR('Cost Margin'!$B$14="Y",'Cost Margin'!$J36=""),'Cost Margin'!$B$8,'Cost Margin'!$J36),C$5),0,IFERROR(NETWORKDAYS(MAX(IF(OR('Cost Margin'!$B$14="Y",'Cost Margin'!$J36=""),'Cost Margin'!$B$8,'Cost Margin'!$J36),C$5),MIN(IF(OR('Cost Margin'!$B$14="Y",'Cost Margin'!$K36=""),'Cost Margin'!$B$9,'Cost Margin'!$K36),C$6),INDEX(Settings!$A$35:$D$74,0,MATCH('Cost Margin'!$C36,Settings!$A$34:$D$34,0))),NETWORKDAYS(MAX(IF(OR('Cost Margin'!$B$14="Y",'Cost Margin'!$J36=""),'Cost Margin'!$B$8,'Cost Margin'!$J36),C$5),MIN(IF(OR('Cost Margin'!$B$14="Y",'Cost Margin'!$K36=""),'Cost Margin'!$B$9,'Cost Margin'!$K36),C$6))))) -> 0 | D28: =IF(OR(D$5="",'Cost Margin'!$A36="",IF(OR('Cost Margin'!$B$14="Y",'Cost Margin'!$J36=""),'Cost Margin'!$B$8,'Cost Margin'!$J36)="",IF(OR('Cost Margin'!$B$14="Y",'Cost Margin'!$K36=""),'Cost Margin'!$B$9,'Cost Margin'!$K36)=""),0,IF(MIN(IF(OR('Cost Margin'!$B$14="Y",'Cost Margin'!$K36=""),'Cost Margin'!$B$9,'Cost Margin'!$K36),D$6)<MAX(IF(OR('Cost Margin'!$B$14="Y",'Cost Margin'!$J36=""),'Cost Margin'!$B$8,'Cost Margin'!$J36),D$5),0,IFERROR(NETWORKDAYS(MAX(IF(OR('Cost Margin'!$B$14="Y",'Cost Margin'!$J36=""),'Cost Margin'!$B$8,'Cost Margin'!$J36),D$5),MIN(IF(OR('Cost Margin'!$B$14="Y",'Cost Margin'!$K36=""),'Cost Margin'!$B$9,'Cost Margin'!$K36),D$6),INDEX(Settings!$A$35:$D$74,0,MATCH('Cost Margin'!$C36,Settings!$A$34:$D$34,0))),NETWORKDAYS(MAX(IF(OR('Cost Margin'!$B$14="Y",'Cost Margin'!$J36=""),'Cost Margin'!$B$8,'Cost Margin'!$J36),D$5),MIN(IF(OR('Cost Margin'!$B$14="Y",'Cost Margin'!$K36=""),'Cost Margin'!$B$9,'Cost Margin'!$K36),D$6))))) -> 0 | E28: =IF(OR(E$5="",'Cost Margin'!$A36="",IF(OR('Cost Margin'!$B$14="Y",'Cost Margin'!$J36=""),'Cost Margin'!$B$8,'Cost Margin'!$J36)="",IF(OR('Cost Margin'!$B$14="Y",'Cost Margin'!$K36=""),'Cost Margin'!$B$9,'Cost Margin'!$K36)=""),0,IF(MIN(IF(OR('Cost Margin'!$B$14="Y",'Cost Margin'!$K36=""),'Cost Margin'!$B$9,'Cost Margin'!$K36),E$6)<MAX(IF(OR('Cost Margin'!$B$14="Y",'Cost Margin'!$J36=""),'Cost Margin'!$B$8,'Cost Margin'!$J36),E$5),0,IFERROR(NETWORKDAYS(MAX(IF(OR('Cost Margin'!$B$14="Y",'Cost Margin'!$J36=""),'Cost Margin'!$B$8,'Cost Margin'!$J36),E$5),MIN(IF(OR('Cost Margin'!$B$14="Y",'Cost Margin'!$K36=""),'Cost Margin'!$B$9,'Cost Margin'!$K36),E$6),INDEX(Settings!$A$35:$D$74,0,MATCH('Cost Margin'!$C36,Settings!$A$34:$D$34,0))),NETWORKDAYS(MAX(IF(OR('Cost Margin'!$B$14="Y",'Cost Margin'!$J36=""),'Cost Margin'!$B$8,'Cost Margin'!$J36),E$5),MIN(IF(OR('Cost Margin'!$B$14="Y",'Cost Margin'!$K36=""),'Cost Margin'!$B$9,'Cost Margin'!$K36),E$6))))) -> 0 | F28: =IF(OR(F$5="",'Cost Margin'!$A36="",IF(OR('Cost Margin'!$B$14="Y",'Cost Margin'!$J36=""),'Cost Margin'!$B$8,'Cost Margin'!$J36)="",IF(OR('Cost Margin'!$B$14="Y",'Cost Margin'!$K36=""),'Cost Margin'!$B$9,'Cost Margin'!$K36)=""),0,IF(MIN(IF(OR('Cost Margin'!$B$14="Y",'Cost Margin'!$K36=""),'Cost Margin'!$B$9,'Cost Margin'!$K36),F$6)<MAX(IF(OR('Cost Margin'!$B$14="Y",'Cost Margin'!$J36=""),'Cost Margin'!$B$8,'Cost Margin'!$J36),F$5),0,IFERROR(NETWORKDAYS(MAX(IF(OR('Cost Margin'!$B$14="Y",'Cost Margin'!$J36=""),'Cost Margin'!$B$8,'Cost Margin'!$J36),F$5),MIN(IF(OR('Cost Margin'!$B$14="Y",'Cost Margin'!$K36=""),'Cost Margin'!$B$9,'Cost Margin'!$K36),F$6),INDEX(Settings!$A$35:$D$74,0,MATCH('Cost Margin'!$C36,Settings!$A$34:$D$34,0))),NETWORKDAYS(MAX(IF(OR('Cost Margin'!$B$14="Y",'Cost Margin'!$J36=""),'Cost Margin'!$B$8,'Cost Margin'!$J36),F$5),MIN(IF(OR('Cost Margin'!$B$14="Y",'Cost Margin'!$K36=""),'Cost Margin'!$B$9,'Cost Margin'!$K36),F$6))))) -> 0 | G28: =IF(OR(G$5="",'Cost Margin'!$A36="",IF(OR('Cost Margin'!$B$14="Y",'Cost Margin'!$J36=""),'Cost Margin'!$B$8,'Cost Margin'!$J36)="",IF(OR('Cost Margin'!$B$14="Y",'Cost Margin'!$K36=""),'Cost Margin'!$B$9,'Cost Margin'!$K36)=""),0,IF(MIN(IF(OR('Cost Margin'!$B$14="Y",'Cost Margin'!$K36=""),'Cost Margin'!$B$9,'Cost Margin'!$K36),G$6)<MAX(IF(OR('Cost Margin'!$B$14="Y",'Cost Margin'!$J36=""),'Cost Margin'!$B$8,'Cost Margin'!$J36),G$5),0,IFERROR(NETWORKDAYS(MAX(IF(OR('Cost Margin'!$B$14="Y",'Cost Margin'!$J36=""),'Cost Margin'!$B$8,'Cost Margin'!$J36),G$5),MIN(IF(OR('Cost Margin'!$B$14="Y",'Cost Margin'!$K36=""),'Cost Margin'!$B$9,'Cost Margin'!$K36),G$6),INDEX(Settings!$A$35:$D$74,0,MATCH('Cost Margin'!$C36,Settings!$A$34:$D$34,0))),NETWORKDAYS(MAX(IF(OR('Cost Margin'!$B$14="Y",'Cost Margin'!$J36=""),'Cost Margin'!$B$8,'Cost Margin'!$J36),G$5),MIN(IF(OR('Cost Margin'!$B$14="Y",'Cost Margin'!$K36=""),'Cost Margin'!$B$9,'Cost Margin'!$K36),G$6))))) -> 0 | H28: =IF(OR(H$5="",'Cost Margin'!$A36="",IF(OR('Cost Margin'!$B$14="Y",'Cost Margin'!$J36=""),'Cost Margin'!$B$8,'Cost Margin'!$J36)="",IF(OR('Cost Margin'!$B$14="Y",'Cost Margin'!$K36=""),'Cost Margin'!$B$9,'Cost Margin'!$K36)=""),0,IF(MIN(IF(OR('Cost Margin'!$B$14="Y",'Cost Margin'!$K36=""),'Cost Margin'!$B$9,'Cost Margin'!$K36),H$6)<MAX(IF(OR('Cost Margin'!$B$14="Y",'Cost Margin'!$J36=""),'Cost Margin'!$B$8,'Cost Margin'!$J36),H$5),0,IFERROR(NETWORKDAYS(MAX(IF(OR('Cost Margin'!$B$14="Y",'Cost Margin'!$J36=""),'Cost Margin'!$B$8,'Cost Margin'!$J36),H$5),MIN(IF(OR('Cost Margin'!$B$14="Y",'Cost Margin'!$K36=""),'Cost Margin'!$B$9,'Cost Margin'!$K36),H$6),INDEX(Settings!$A$35:$D$74,0,MATCH('Cost Margin'!$C36,Settings!$A$34:$D$34,0))),NETWORKDAYS(MAX(IF(OR('Cost Margin'!$B$14="Y",'Cost Margin'!$J36=""),'Cost Margin'!$B$8,'Cost Margin'!$J36),H$5),MIN(IF(OR('Cost Margin'!$B$14="Y",'Cost Margin'!$K36=""),'Cost Margin'!$B$9,'Cost Margin'!$K36),H$6))))) -> 0 | I28: =IF(OR(I$5="",'Cost Margin'!$A36="",IF(OR('Cost Margin'!$B$14="Y",'Cost Margin'!$J36=""),'Cost Margin'!$B$8,'Cost Margin'!$J36)="",IF(OR('Cost Margin'!$B$14="Y",'Cost Margin'!$K36=""),'Cost Margin'!$B$9,'Cost Margin'!$K36)=""),0,IF(MIN(IF(OR('Cost Margin'!$B$14="Y",'Cost Margin'!$K36=""),'Cost Margin'!$B$9,'Cost Margin'!$K36),I$6)<MAX(IF(OR('Cost Margin'!$B$14="Y",'Cost Margin'!$J36=""),'Cost Margin'!$B$8,'Cost Margin'!$J36),I$5),0,IFERROR(NETWORKDAYS(MAX(IF(OR('Cost Margin'!$B$14="Y",'Cost Margin'!$J36=""),'Cost Margin'!$B$8,'Cost Margin'!$J36),I$5),MIN(IF(OR('Cost Margin'!$B$14="Y",'Cost Margin'!$K36=""),'Cost Margin'!$B$9,'Cost Margin'!$K36),I$6),INDEX(Settings!$A$35:$D$74,0,MATCH('Cost Margin'!$C36,Settings!$A$34:$D$34,0))),NETWORKDAYS(MAX(IF(OR('Cost Margin'!$B$14="Y",'Cost Margin'!$J36=""),'Cost Margin'!$B$8,'Cost Margin'!$J36),I$5),MIN(IF(OR('Cost Margin'!$B$14="Y",'Cost Margin'!$K36=""),'Cost Margin'!$B$9,'Cost Margin'!$K36),I$6))))) -> 0 | J28: =IF(OR(J$5="",'Cost Margin'!$A36="",IF(OR('Cost Margin'!$B$14="Y",'Cost Margin'!$J36=""),'Cost Margin'!$B$8,'Cost Margin'!$J36)="",IF(OR('Cost Margin'!$B$14="Y",'Cost Margin'!$K36=""),'Cost Margin'!$B$9,'Cost Margin'!$K36)=""),0,IF(MIN(IF(OR('Cost Margin'!$B$14="Y",'Cost Margin'!$K36=""),'Cost Margin'!$B$9,'Cost Margin'!$K36),J$6)<MAX(IF(OR('Cost Margin'!$B$14="Y",'Cost Margin'!$J36=""),'Cost Margin'!$B$8,'Cost Margin'!$J36),J$5),0,IFERROR(NETWORKDAYS(MAX(IF(OR('Cost Margin'!$B$14="Y",'Cost Margin'!$J36=""),'Cost Margin'!$B$8,'Cost Margin'!$J36),J$5),MIN(IF(OR('Cost Margin'!$B$14="Y",'Cost Margin'!$K36=""),'Cost Margin'!$B$9,'Cost Margin'!$K36),J$6),INDEX(Settings!$A$35:$D$74,0,MATCH('Cost Margin'!$C36,Settings!$A$34:$D$34,0))),NETWORKDAYS(MAX(IF(OR('Cost Margin'!$B$14="Y",'Cost Margin'!$J36=""),'Cost Margin'!$B$8,'Cost Margin'!$J36),J$5),MIN(IF(OR('Cost Margin'!$B$14="Y",'Cost Margin'!$K36=""),'Cost Margin'!$B$9,'Cost Margin'!$K36),J$6))))) -> 0 | ... Z28: =IF(OR(Z$5="",'Cost Margin'!$A36="",IF(OR('Cost Margin'!$B$14="Y",'Cost Margin'!$J36=""),'Cost Margin'!$B$8,'Cost Margin'!$J36)="",IF(OR('Cost Margin'!$B$14="Y",'Cost Margin'!$K36=""),'Cost Margin'!$B$9,'Cost Margin'!$K36)=""),0,IF(MIN(IF(OR('Cost Margin'!$B$14="Y",'Cost Margin'!$K36=""),'Cost Margin'!$B$9,'Cost Margin'!$K36),Z$6)<MAX(IF(OR('Cost Margin'!$B$14="Y",'Cost Margin'!$J36=""),'Cost Margin'!$B$8,'Cost Margin'!$J36),Z$5),0,IFERROR(NETWORKDAYS(MAX(IF(OR('Cost Margin'!$B$14="Y",'Cost Margin'!$J36=""),'Cost Margin'!$B$8,'Cost Margin'!$J36),Z$5),MIN(IF(OR('Cost Margin'!$B$14="Y",'Cost Margin'!$K36=""),'Cost Margin'!$B$9,'Cost Margin'!$K36),Z$6),INDEX(Settings!$A$35:$D$74,0,MATCH('Cost Margin'!$C36,Settings!$A$34:$D$34,0))),NETWORKDAYS(MAX(IF(OR('Cost Margin'!$B$14="Y",'Cost Margin'!$J36=""),'Cost Margin'!$B$8,'Cost Margin'!$J36),Z$5),MIN(IF(OR('Cost Margin'!$B$14="Y",'Cost Margin'!$K36=""),'Cost Margin'!$B$9,'Cost Margin'!$K36),Z$6))))) -> 0 | AB28: =IF('Cost Margin'!A36="","",IF('Cost Margin'!E36="","(unassigned)",'Cost Margin'!E36))
A30: Hours in month, per person (override hours are spread by working-day share) | AB30: Assignment
A31: 1 | B31: =IF('Cost Margin'!A17="","",'Cost Margin'!A17&IF('Cost Margin'!E17="",""," · "&'Cost Margin'!E17)) | C31: =IF(C9=0,0,IF('Cost Margin'!$M17<>"",'Cost Margin'!$M17*C9/'Cost Margin'!$L17,C9*Settings!$B$5*IF('Cost Margin'!$F17="",1,'Cost Margin'!$F17))) -> 0 | D31: =IF(D9=0,0,IF('Cost Margin'!$M17<>"",'Cost Margin'!$M17*D9/'Cost Margin'!$L17,D9*Settings!$B$5*IF('Cost Margin'!$F17="",1,'Cost Margin'!$F17))) -> 0 | E31: =IF(E9=0,0,IF('Cost Margin'!$M17<>"",'Cost Margin'!$M17*E9/'Cost Margin'!$L17,E9*Settings!$B$5*IF('Cost Margin'!$F17="",1,'Cost Margin'!$F17))) -> 0 | F31: =IF(F9=0,0,IF('Cost Margin'!$M17<>"",'Cost Margin'!$M17*F9/'Cost Margin'!$L17,F9*Settings!$B$5*IF('Cost Margin'!$F17="",1,'Cost Margin'!$F17))) -> 0 | G31: =IF(G9=0,0,IF('Cost Margin'!$M17<>"",'Cost Margin'!$M17*G9/'Cost Margin'!$L17,G9*Settings!$B$5*IF('Cost Margin'!$F17="",1,'Cost Margin'!$F17))) -> 0 | H31: =IF(H9=0,0,IF('Cost Margin'!$M17<>"",'Cost Margin'!$M17*H9/'Cost Margin'!$L17,H9*Settings!$B$5*IF('Cost Margin'!$F17="",1,'Cost Margin'!$F17))) -> 0 | I31: =IF(I9=0,0,IF('Cost Margin'!$M17<>"",'Cost Margin'!$M17*I9/'Cost Margin'!$L17,I9*Settings!$B$5*IF('Cost Margin'!$F17="",1,'Cost Margin'!$F17))) -> 0 | J31: =IF(J9=0,0,IF('Cost Margin'!$M17<>"",'Cost Margin'!$M17*J9/'Cost Margin'!$L17,J9*Settings!$B$5*IF('Cost Margin'!$F17="",1,'Cost Margin'!$F17))) -> 0 | ... Z31: =IF(Z9=0,0,IF('Cost Margin'!$M17<>"",'Cost Margin'!$M17*Z9/'Cost Margin'!$L17,Z9*Settings!$B$5*IF('Cost Margin'!$F17="",1,'Cost Margin'!$F17))) -> 0 | AB31: =IF('Cost Margin'!A17="","",IF('Cost Margin'!E17="","(unassigned)",'Cost Margin'!E17))
A32: 2 | B32: =IF('Cost Margin'!A18="","",'Cost Margin'!A18&IF('Cost Margin'!E18="",""," · "&'Cost Margin'!E18)) | C32: =IF(C10=0,0,IF('Cost Margin'!$M18<>"",'Cost Margin'!$M18*C10/'Cost Margin'!$L18,C10*Settings!$B$5*IF('Cost Margin'!$F18="",1,'Cost Margin'!$F18))) -> 0 | D32: =IF(D10=0,0,IF('Cost Margin'!$M18<>"",'Cost Margin'!$M18*D10/'Cost Margin'!$L18,D10*Settings!$B$5*IF('Cost Margin'!$F18="",1,'Cost Margin'!$F18))) -> 0 | E32: =IF(E10=0,0,IF('Cost Margin'!$M18<>"",'Cost Margin'!$M18*E10/'Cost Margin'!$L18,E10*Settings!$B$5*IF('Cost Margin'!$F18="",1,'Cost Margin'!$F18))) -> 0 | F32: =IF(F10=0,0,IF('Cost Margin'!$M18<>"",'Cost Margin'!$M18*F10/'Cost Margin'!$L18,F10*Settings!$B$5*IF('Cost Margin'!$F18="",1,'Cost Margin'!$F18))) -> 0 | G32: =IF(G10=0,0,IF('Cost Margin'!$M18<>"",'Cost Margin'!$M18*G10/'Cost Margin'!$L18,G10*Settings!$B$5*IF('Cost Margin'!$F18="",1,'Cost Margin'!$F18))) -> 0 | H32: =IF(H10=0,0,IF('Cost Margin'!$M18<>"",'Cost Margin'!$M18*H10/'Cost Margin'!$L18,H10*Settings!$B$5*IF('Cost Margin'!$F18="",1,'Cost Margin'!$F18))) -> 0 | I32: =IF(I10=0,0,IF('Cost Margin'!$M18<>"",'Cost Margin'!$M18*I10/'Cost Margin'!$L18,I10*Settings!$B$5*IF('Cost Margin'!$F18="",1,'Cost Margin'!$F18))) -> 0 | J32: =IF(J10=0,0,IF('Cost Margin'!$M18<>"",'Cost Margin'!$M18*J10/'Cost Margin'!$L18,J10*Settings!$B$5*IF('Cost Margin'!$F18="",1,'Cost Margin'!$F18))) -> 0 | ... Z32: =IF(Z10=0,0,IF('Cost Margin'!$M18<>"",'Cost Margin'!$M18*Z10/'Cost Margin'!$L18,Z10*Settings!$B$5*IF('Cost Margin'!$F18="",1,'Cost Margin'!$F18))) -> 0 | AB32: =IF('Cost Margin'!A18="","",IF('Cost Margin'!E18="","(unassigned)",'Cost Margin'!E18))
A33: 3 | B33: =IF('Cost Margin'!A19="","",'Cost Margin'!A19&IF('Cost Margin'!E19="",""," · "&'Cost Margin'!E19)) | C33: =IF(C11=0,0,IF('Cost Margin'!$M19<>"",'Cost Margin'!$M19*C11/'Cost Margin'!$L19,C11*Settings!$B$5*IF('Cost Margin'!$F19="",1,'Cost Margin'!$F19))) -> 0 | D33: =IF(D11=0,0,IF('Cost Margin'!$M19<>"",'Cost Margin'!$M19*D11/'Cost Margin'!$L19,D11*Settings!$B$5*IF('Cost Margin'!$F19="",1,'Cost Margin'!$F19))) -> 0 | E33: =IF(E11=0,0,IF('Cost Margin'!$M19<>"",'Cost Margin'!$M19*E11/'Cost Margin'!$L19,E11*Settings!$B$5*IF('Cost Margin'!$F19="",1,'Cost Margin'!$F19))) -> 0 | F33: =IF(F11=0,0,IF('Cost Margin'!$M19<>"",'Cost Margin'!$M19*F11/'Cost Margin'!$L19,F11*Settings!$B$5*IF('Cost Margin'!$F19="",1,'Cost Margin'!$F19))) -> 0 | G33: =IF(G11=0,0,IF('Cost Margin'!$M19<>"",'Cost Margin'!$M19*G11/'Cost Margin'!$L19,G11*Settings!$B$5*IF('Cost Margin'!$F19="",1,'Cost Margin'!$F19))) -> 0 | H33: =IF(H11=0,0,IF('Cost Margin'!$M19<>"",'Cost Margin'!$M19*H11/'Cost Margin'!$L19,H11*Settings!$B$5*IF('Cost Margin'!$F19="",1,'Cost Margin'!$F19))) -> 0 | I33: =IF(I11=0,0,IF('Cost Margin'!$M19<>"",'Cost Margin'!$M19*I11/'Cost Margin'!$L19,I11*Settings!$B$5*IF('Cost Margin'!$F19="",1,'Cost Margin'!$F19))) -> 0 | J33: =IF(J11=0,0,IF('Cost Margin'!$M19<>"",'Cost Margin'!$M19*J11/'Cost Margin'!$L19,J11*Settings!$B$5*IF('Cost Margin'!$F19="",1,'Cost Margin'!$F19))) -> 0 | ... Z33: =IF(Z11=0,0,IF('Cost Margin'!$M19<>"",'Cost Margin'!$M19*Z11/'Cost Margin'!$L19,Z11*Settings!$B$5*IF('Cost Margin'!$F19="",1,'Cost Margin'!$F19))) -> 0 | AB33: =IF('Cost Margin'!A19="","",IF('Cost Margin'!E19="","(unassigned)",'Cost Margin'!E19))
A34: 4 | B34: =IF('Cost Margin'!A20="","",'Cost Margin'!A20&IF('Cost Margin'!E20="",""," · "&'Cost Margin'!E20)) | C34: =IF(C12=0,0,IF('Cost Margin'!$M20<>"",'Cost Margin'!$M20*C12/'Cost Margin'!$L20,C12*Settings!$B$5*IF('Cost Margin'!$F20="",1,'Cost Margin'!$F20))) -> 0 | D34: =IF(D12=0,0,IF('Cost Margin'!$M20<>"",'Cost Margin'!$M20*D12/'Cost Margin'!$L20,D12*Settings!$B$5*IF('Cost Margin'!$F20="",1,'Cost Margin'!$F20))) -> 0 | E34: =IF(E12=0,0,IF('Cost Margin'!$M20<>"",'Cost Margin'!$M20*E12/'Cost Margin'!$L20,E12*Settings!$B$5*IF('Cost Margin'!$F20="",1,'Cost Margin'!$F20))) -> 0 | F34: =IF(F12=0,0,IF('Cost Margin'!$M20<>"",'Cost Margin'!$M20*F12/'Cost Margin'!$L20,F12*Settings!$B$5*IF('Cost Margin'!$F20="",1,'Cost Margin'!$F20))) -> 0 | G34: =IF(G12=0,0,IF('Cost Margin'!$M20<>"",'Cost Margin'!$M20*G12/'Cost Margin'!$L20,G12*Settings!$B$5*IF('Cost Margin'!$F20="",1,'Cost Margin'!$F20))) -> 0 | H34: =IF(H12=0,0,IF('Cost Margin'!$M20<>"",'Cost Margin'!$M20*H12/'Cost Margin'!$L20,H12*Settings!$B$5*IF('Cost Margin'!$F20="",1,'Cost Margin'!$F20))) -> 0 | I34: =IF(I12=0,0,IF('Cost Margin'!$M20<>"",'Cost Margin'!$M20*I12/'Cost Margin'!$L20,I12*Settings!$B$5*IF('Cost Margin'!$F20="",1,'Cost Margin'!$F20))) -> 0 | J34: =IF(J12=0,0,IF('Cost Margin'!$M20<>"",'Cost Margin'!$M20*J12/'Cost Margin'!$L20,J12*Settings!$B$5*IF('Cost Margin'!$F20="",1,'Cost Margin'!$F20))) -> 0 | ... Z34: =IF(Z12=0,0,IF('Cost Margin'!$M20<>"",'Cost Margin'!$M20*Z12/'Cost Margin'!$L20,Z12*Settings!$B$5*IF('Cost Margin'!$F20="",1,'Cost Margin'!$F20))) -> 0 | AB34: =IF('Cost Margin'!A20="","",IF('Cost Margin'!E20="","(unassigned)",'Cost Margin'!E20))
A35: 5 | B35: =IF('Cost Margin'!A21="","",'Cost Margin'!A21&IF('Cost Margin'!E21="",""," · "&'Cost Margin'!E21)) | C35: =IF(C13=0,0,IF('Cost Margin'!$M21<>"",'Cost Margin'!$M21*C13/'Cost Margin'!$L21,C13*Settings!$B$5*IF('Cost Margin'!$F21="",1,'Cost Margin'!$F21))) -> 0 | D35: =IF(D13=0,0,IF('Cost Margin'!$M21<>"",'Cost Margin'!$M21*D13/'Cost Margin'!$L21,D13*Settings!$B$5*IF('Cost Margin'!$F21="",1,'Cost Margin'!$F21))) -> 0 | E35: =IF(E13=0,0,IF('Cost Margin'!$M21<>"",'Cost Margin'!$M21*E13/'Cost Margin'!$L21,E13*Settings!$B$5*IF('Cost Margin'!$F21="",1,'Cost Margin'!$F21))) -> 0 | F35: =IF(F13=0,0,IF('Cost Margin'!$M21<>"",'Cost Margin'!$M21*F13/'Cost Margin'!$L21,F13*Settings!$B$5*IF('Cost Margin'!$F21="",1,'Cost Margin'!$F21))) -> 0 | G35: =IF(G13=0,0,IF('Cost Margin'!$M21<>"",'Cost Margin'!$M21*G13/'Cost Margin'!$L21,G13*Settings!$B$5*IF('Cost Margin'!$F21="",1,'Cost Margin'!$F21))) -> 0 | H35: =IF(H13=0,0,IF('Cost Margin'!$M21<>"",'Cost Margin'!$M21*H13/'Cost Margin'!$L21,H13*Settings!$B$5*IF('Cost Margin'!$F21="",1,'Cost Margin'!$F21))) -> 0 | I35: =IF(I13=0,0,IF('Cost Margin'!$M21<>"",'Cost Margin'!$M21*I13/'Cost Margin'!$L21,I13*Settings!$B$5*IF('Cost Margin'!$F21="",1,'Cost Margin'!$F21))) -> 0 | J35: =IF(J13=0,0,IF('Cost Margin'!$M21<>"",'Cost Margin'!$M21*J13/'Cost Margin'!$L21,J13*Settings!$B$5*IF('Cost Margin'!$F21="",1,'Cost Margin'!$F21))) -> 0 | ... Z35: =IF(Z13=0,0,IF('Cost Margin'!$M21<>"",'Cost Margin'!$M21*Z13/'Cost Margin'!$L21,Z13*Settings!$B$5*IF('Cost Margin'!$F21="",1,'Cost Margin'!$F21))) -> 0 | AB35: =IF('Cost Margin'!A21="","",IF('Cost Margin'!E21="","(unassigned)",'Cost Margin'!E21))
A36: 6 | B36: =IF('Cost Margin'!A22="","",'Cost Margin'!A22&IF('Cost Margin'!E22="",""," · "&'Cost Margin'!E22)) | C36: =IF(C14=0,0,IF('Cost Margin'!$M22<>"",'Cost Margin'!$M22*C14/'Cost Margin'!$L22,C14*Settings!$B$5*IF('Cost Margin'!$F22="",1,'Cost Margin'!$F22))) -> 0 | D36: =IF(D14=0,0,IF('Cost Margin'!$M22<>"",'Cost Margin'!$M22*D14/'Cost Margin'!$L22,D14*Settings!$B$5*IF('Cost Margin'!$F22="",1,'Cost Margin'!$F22))) -> 0 | E36: =IF(E14=0,0,IF('Cost Margin'!$M22<>"",'Cost Margin'!$M22*E14/'Cost Margin'!$L22,E14*Settings!$B$5*IF('Cost Margin'!$F22="",1,'Cost Margin'!$F22))) -> 0 | F36: =IF(F14=0,0,IF('Cost Margin'!$M22<>"",'Cost Margin'!$M22*F14/'Cost Margin'!$L22,F14*Settings!$B$5*IF('Cost Margin'!$F22="",1,'Cost Margin'!$F22))) -> 0 | G36: =IF(G14=0,0,IF('Cost Margin'!$M22<>"",'Cost Margin'!$M22*G14/'Cost Margin'!$L22,G14*Settings!$B$5*IF('Cost Margin'!$F22="",1,'Cost Margin'!$F22))) -> 0 | H36: =IF(H14=0,0,IF('Cost Margin'!$M22<>"",'Cost Margin'!$M22*H14/'Cost Margin'!$L22,H14*Settings!$B$5*IF('Cost Margin'!$F22="",1,'Cost Margin'!$F22))) -> 0 | I36: =IF(I14=0,0,IF('Cost Margin'!$M22<>"",'Cost Margin'!$M22*I14/'Cost Margin'!$L22,I14*Settings!$B$5*IF('Cost Margin'!$F22="",1,'Cost Margin'!$F22))) -> 0 | J36: =IF(J14=0,0,IF('Cost Margin'!$M22<>"",'Cost Margin'!$M22*J14/'Cost Margin'!$L22,J14*Settings!$B$5*IF('Cost Margin'!$F22="",1,'Cost Margin'!$F22))) -> 0 | ... Z36: =IF(Z14=0,0,IF('Cost Margin'!$M22<>"",'Cost Margin'!$M22*Z14/'Cost Margin'!$L22,Z14*Settings!$B$5*IF('Cost Margin'!$F22="",1,'Cost Margin'!$F22))) -> 0 | AB36: =IF('Cost Margin'!A22="","",IF('Cost Margin'!E22="","(unassigned)",'Cost Margin'!E22))
A37: 7 | B37: =IF('Cost Margin'!A23="","",'Cost Margin'!A23&IF('Cost Margin'!E23="",""," · "&'Cost Margin'!E23)) | C37: =IF(C15=0,0,IF('Cost Margin'!$M23<>"",'Cost Margin'!$M23*C15/'Cost Margin'!$L23,C15*Settings!$B$5*IF('Cost Margin'!$F23="",1,'Cost Margin'!$F23))) -> 0 | D37: =IF(D15=0,0,IF('Cost Margin'!$M23<>"",'Cost Margin'!$M23*D15/'Cost Margin'!$L23,D15*Settings!$B$5*IF('Cost Margin'!$F23="",1,'Cost Margin'!$F23))) -> 0 | E37: =IF(E15=0,0,IF('Cost Margin'!$M23<>"",'Cost Margin'!$M23*E15/'Cost Margin'!$L23,E15*Settings!$B$5*IF('Cost Margin'!$F23="",1,'Cost Margin'!$F23))) -> 0 | F37: =IF(F15=0,0,IF('Cost Margin'!$M23<>"",'Cost Margin'!$M23*F15/'Cost Margin'!$L23,F15*Settings!$B$5*IF('Cost Margin'!$F23="",1,'Cost Margin'!$F23))) -> 0 | G37: =IF(G15=0,0,IF('Cost Margin'!$M23<>"",'Cost Margin'!$M23*G15/'Cost Margin'!$L23,G15*Settings!$B$5*IF('Cost Margin'!$F23="",1,'Cost Margin'!$F23))) -> 0 | H37: =IF(H15=0,0,IF('Cost Margin'!$M23<>"",'Cost Margin'!$M23*H15/'Cost Margin'!$L23,H15*Settings!$B$5*IF('Cost Margin'!$F23="",1,'Cost Margin'!$F23))) -> 0 | I37: =IF(I15=0,0,IF('Cost Margin'!$M23<>"",'Cost Margin'!$M23*I15/'Cost Margin'!$L23,I15*Settings!$B$5*IF('Cost Margin'!$F23="",1,'Cost Margin'!$F23))) -> 0 | J37: =IF(J15=0,0,IF('Cost Margin'!$M23<>"",'Cost Margin'!$M23*J15/'Cost Margin'!$L23,J15*Settings!$B$5*IF('Cost Margin'!$F23="",1,'Cost Margin'!$F23))) -> 0 | ... Z37: =IF(Z15=0,0,IF('Cost Margin'!$M23<>"",'Cost Margin'!$M23*Z15/'Cost Margin'!$L23,Z15*Settings!$B$5*IF('Cost Margin'!$F23="",1,'Cost Margin'!$F23))) -> 0 | AB37: =IF('Cost Margin'!A23="","",IF('Cost Margin'!E23="","(unassigned)",'Cost Margin'!E23))
A38: 8 | B38: =IF('Cost Margin'!A24="","",'Cost Margin'!A24&IF('Cost Margin'!E24="",""," · "&'Cost Margin'!E24)) | C38: =IF(C16=0,0,IF('Cost Margin'!$M24<>"",'Cost Margin'!$M24*C16/'Cost Margin'!$L24,C16*Settings!$B$5*IF('Cost Margin'!$F24="",1,'Cost Margin'!$F24))) -> 0 | D38: =IF(D16=0,0,IF('Cost Margin'!$M24<>"",'Cost Margin'!$M24*D16/'Cost Margin'!$L24,D16*Settings!$B$5*IF('Cost Margin'!$F24="",1,'Cost Margin'!$F24))) -> 0 | E38: =IF(E16=0,0,IF('Cost Margin'!$M24<>"",'Cost Margin'!$M24*E16/'Cost Margin'!$L24,E16*Settings!$B$5*IF('Cost Margin'!$F24="",1,'Cost Margin'!$F24))) -> 0 | F38: =IF(F16=0,0,IF('Cost Margin'!$M24<>"",'Cost Margin'!$M24*F16/'Cost Margin'!$L24,F16*Settings!$B$5*IF('Cost Margin'!$F24="",1,'Cost Margin'!$F24))) -> 0 | G38: =IF(G16=0,0,IF('Cost Margin'!$M24<>"",'Cost Margin'!$M24*G16/'Cost Margin'!$L24,G16*Settings!$B$5*IF('Cost Margin'!$F24="",1,'Cost Margin'!$F24))) -> 0 | H38: =IF(H16=0,0,IF('Cost Margin'!$M24<>"",'Cost Margin'!$M24*H16/'Cost Margin'!$L24,H16*Settings!$B$5*IF('Cost Margin'!$F24="",1,'Cost Margin'!$F24))) -> 0 | I38: =IF(I16=0,0,IF('Cost Margin'!$M24<>"",'Cost Margin'!$M24*I16/'Cost Margin'!$L24,I16*Settings!$B$5*IF('Cost Margin'!$F24="",1,'Cost Margin'!$F24))) -> 0 | J38: =IF(J16=0,0,IF('Cost Margin'!$M24<>"",'Cost Margin'!$M24*J16/'Cost Margin'!$L24,J16*Settings!$B$5*IF('Cost Margin'!$F24="",1,'Cost Margin'!$F24))) -> 0 | ... Z38: =IF(Z16=0,0,IF('Cost Margin'!$M24<>"",'Cost Margin'!$M24*Z16/'Cost Margin'!$L24,Z16*Settings!$B$5*IF('Cost Margin'!$F24="",1,'Cost Margin'!$F24))) -> 0 | AB38: =IF('Cost Margin'!A24="","",IF('Cost Margin'!E24="","(unassigned)",'Cost Margin'!E24))
A39: 9 | B39: =IF('Cost Margin'!A25="","",'Cost Margin'!A25&IF('Cost Margin'!E25="",""," · "&'Cost Margin'!E25)) | C39: =IF(C17=0,0,IF('Cost Margin'!$M25<>"",'Cost Margin'!$M25*C17/'Cost Margin'!$L25,C17*Settings!$B$5*IF('Cost Margin'!$F25="",1,'Cost Margin'!$F25))) -> 0 | D39: =IF(D17=0,0,IF('Cost Margin'!$M25<>"",'Cost Margin'!$M25*D17/'Cost Margin'!$L25,D17*Settings!$B$5*IF('Cost Margin'!$F25="",1,'Cost Margin'!$F25))) -> 0 | E39: =IF(E17=0,0,IF('Cost Margin'!$M25<>"",'Cost Margin'!$M25*E17/'Cost Margin'!$L25,E17*Settings!$B$5*IF('Cost Margin'!$F25="",1,'Cost Margin'!$F25))) -> 0 | F39: =IF(F17=0,0,IF('Cost Margin'!$M25<>"",'Cost Margin'!$M25*F17/'Cost Margin'!$L25,F17*Settings!$B$5*IF('Cost Margin'!$F25="",1,'Cost Margin'!$F25))) -> 0 | G39: =IF(G17=0,0,IF('Cost Margin'!$M25<>"",'Cost Margin'!$M25*G17/'Cost Margin'!$L25,G17*Settings!$B$5*IF('Cost Margin'!$F25="",1,'Cost Margin'!$F25))) -> 0 | H39: =IF(H17=0,0,IF('Cost Margin'!$M25<>"",'Cost Margin'!$M25*H17/'Cost Margin'!$L25,H17*Settings!$B$5*IF('Cost Margin'!$F25="",1,'Cost Margin'!$F25))) -> 0 | I39: =IF(I17=0,0,IF('Cost Margin'!$M25<>"",'Cost Margin'!$M25*I17/'Cost Margin'!$L25,I17*Settings!$B$5*IF('Cost Margin'!$F25="",1,'Cost Margin'!$F25))) -> 0 | J39: =IF(J17=0,0,IF('Cost Margin'!$M25<>"",'Cost Margin'!$M25*J17/'Cost Margin'!$L25,J17*Settings!$B$5*IF('Cost Margin'!$F25="",1,'Cost Margin'!$F25))) -> 0 | ... Z39: =IF(Z17=0,0,IF('Cost Margin'!$M25<>"",'Cost Margin'!$M25*Z17/'Cost Margin'!$L25,Z17*Settings!$B$5*IF('Cost Margin'!$F25="",1,'Cost Margin'!$F25))) -> 0 | AB39: =IF('Cost Margin'!A25="","",IF('Cost Margin'!E25="","(unassigned)",'Cost Margin'!E25))
A40: 10 | B40: =IF('Cost Margin'!A26="","",'Cost Margin'!A26&IF('Cost Margin'!E26="",""," · "&'Cost Margin'!E26)) | C40: =IF(C18=0,0,IF('Cost Margin'!$M26<>"",'Cost Margin'!$M26*C18/'Cost Margin'!$L26,C18*Settings!$B$5*IF('Cost Margin'!$F26="",1,'Cost Margin'!$F26))) -> 0 | D40: =IF(D18=0,0,IF('Cost Margin'!$M26<>"",'Cost Margin'!$M26*D18/'Cost Margin'!$L26,D18*Settings!$B$5*IF('Cost Margin'!$F26="",1,'Cost Margin'!$F26))) -> 0 | E40: =IF(E18=0,0,IF('Cost Margin'!$M26<>"",'Cost Margin'!$M26*E18/'Cost Margin'!$L26,E18*Settings!$B$5*IF('Cost Margin'!$F26="",1,'Cost Margin'!$F26))) -> 0 | F40: =IF(F18=0,0,IF('Cost Margin'!$M26<>"",'Cost Margin'!$M26*F18/'Cost Margin'!$L26,F18*Settings!$B$5*IF('Cost Margin'!$F26="",1,'Cost Margin'!$F26))) -> 0 | G40: =IF(G18=0,0,IF('Cost Margin'!$M26<>"",'Cost Margin'!$M26*G18/'Cost Margin'!$L26,G18*Settings!$B$5*IF('Cost Margin'!$F26="",1,'Cost Margin'!$F26))) -> 0 | H40: =IF(H18=0,0,IF('Cost Margin'!$M26<>"",'Cost Margin'!$M26*H18/'Cost Margin'!$L26,H18*Settings!$B$5*IF('Cost Margin'!$F26="",1,'Cost Margin'!$F26))) -> 0 | I40: =IF(I18=0,0,IF('Cost Margin'!$M26<>"",'Cost Margin'!$M26*I18/'Cost Margin'!$L26,I18*Settings!$B$5*IF('Cost Margin'!$F26="",1,'Cost Margin'!$F26))) -> 0 | J40: =IF(J18=0,0,IF('Cost Margin'!$M26<>"",'Cost Margin'!$M26*J18/'Cost Margin'!$L26,J18*Settings!$B$5*IF('Cost Margin'!$F26="",1,'Cost Margin'!$F26))) -> 0 | ... Z40: =IF(Z18=0,0,IF('Cost Margin'!$M26<>"",'Cost Margin'!$M26*Z18/'Cost Margin'!$L26,Z18*Settings!$B$5*IF('Cost Margin'!$F26="",1,'Cost Margin'!$F26))) -> 0 | AB40: =IF('Cost Margin'!A26="","",IF('Cost Margin'!E26="","(unassigned)",'Cost Margin'!E26))
A41: 11 | B41: =IF('Cost Margin'!A27="","",'Cost Margin'!A27&IF('Cost Margin'!E27="",""," · "&'Cost Margin'!E27)) | C41: =IF(C19=0,0,IF('Cost Margin'!$M27<>"",'Cost Margin'!$M27*C19/'Cost Margin'!$L27,C19*Settings!$B$5*IF('Cost Margin'!$F27="",1,'Cost Margin'!$F27))) -> 0 | D41: =IF(D19=0,0,IF('Cost Margin'!$M27<>"",'Cost Margin'!$M27*D19/'Cost Margin'!$L27,D19*Settings!$B$5*IF('Cost Margin'!$F27="",1,'Cost Margin'!$F27))) -> 0 | E41: =IF(E19=0,0,IF('Cost Margin'!$M27<>"",'Cost Margin'!$M27*E19/'Cost Margin'!$L27,E19*Settings!$B$5*IF('Cost Margin'!$F27="",1,'Cost Margin'!$F27))) -> 0 | F41: =IF(F19=0,0,IF('Cost Margin'!$M27<>"",'Cost Margin'!$M27*F19/'Cost Margin'!$L27,F19*Settings!$B$5*IF('Cost Margin'!$F27="",1,'Cost Margin'!$F27))) -> 0 | G41: =IF(G19=0,0,IF('Cost Margin'!$M27<>"",'Cost Margin'!$M27*G19/'Cost Margin'!$L27,G19*Settings!$B$5*IF('Cost Margin'!$F27="",1,'Cost Margin'!$F27))) -> 0 | H41: =IF(H19=0,0,IF('Cost Margin'!$M27<>"",'Cost Margin'!$M27*H19/'Cost Margin'!$L27,H19*Settings!$B$5*IF('Cost Margin'!$F27="",1,'Cost Margin'!$F27))) -> 0 | I41: =IF(I19=0,0,IF('Cost Margin'!$M27<>"",'Cost Margin'!$M27*I19/'Cost Margin'!$L27,I19*Settings!$B$5*IF('Cost Margin'!$F27="",1,'Cost Margin'!$F27))) -> 0 | J41: =IF(J19=0,0,IF('Cost Margin'!$M27<>"",'Cost Margin'!$M27*J19/'Cost Margin'!$L27,J19*Settings!$B$5*IF('Cost Margin'!$F27="",1,'Cost Margin'!$F27))) -> 0 | ... Z41: =IF(Z19=0,0,IF('Cost Margin'!$M27<>"",'Cost Margin'!$M27*Z19/'Cost Margin'!$L27,Z19*Settings!$B$5*IF('Cost Margin'!$F27="",1,'Cost Margin'!$F27))) -> 0 | AB41: =IF('Cost Margin'!A27="","",IF('Cost Margin'!E27="","(unassigned)",'Cost Margin'!E27))
A42: 12 | B42: =IF('Cost Margin'!A28="","",'Cost Margin'!A28&IF('Cost Margin'!E28="",""," · "&'Cost Margin'!E28)) | C42: =IF(C20=0,0,IF('Cost Margin'!$M28<>"",'Cost Margin'!$M28*C20/'Cost Margin'!$L28,C20*Settings!$B$5*IF('Cost Margin'!$F28="",1,'Cost Margin'!$F28))) -> 0 | D42: =IF(D20=0,0,IF('Cost Margin'!$M28<>"",'Cost Margin'!$M28*D20/'Cost Margin'!$L28,D20*Settings!$B$5*IF('Cost Margin'!$F28="",1,'Cost Margin'!$F28))) -> 0 | E42: =IF(E20=0,0,IF('Cost Margin'!$M28<>"",'Cost Margin'!$M28*E20/'Cost Margin'!$L28,E20*Settings!$B$5*IF('Cost Margin'!$F28="",1,'Cost Margin'!$F28))) -> 0 | F42: =IF(F20=0,0,IF('Cost Margin'!$M28<>"",'Cost Margin'!$M28*F20/'Cost Margin'!$L28,F20*Settings!$B$5*IF('Cost Margin'!$F28="",1,'Cost Margin'!$F28))) -> 0 | G42: =IF(G20=0,0,IF('Cost Margin'!$M28<>"",'Cost Margin'!$M28*G20/'Cost Margin'!$L28,G20*Settings!$B$5*IF('Cost Margin'!$F28="",1,'Cost Margin'!$F28))) -> 0 | H42: =IF(H20=0,0,IF('Cost Margin'!$M28<>"",'Cost Margin'!$M28*H20/'Cost Margin'!$L28,H20*Settings!$B$5*IF('Cost Margin'!$F28="",1,'Cost Margin'!$F28))) -> 0 | I42: =IF(I20=0,0,IF('Cost Margin'!$M28<>"",'Cost Margin'!$M28*I20/'Cost Margin'!$L28,I20*Settings!$B$5*IF('Cost Margin'!$F28="",1,'Cost Margin'!$F28))) -> 0 | J42: =IF(J20=0,0,IF('Cost Margin'!$M28<>"",'Cost Margin'!$M28*J20/'Cost Margin'!$L28,J20*Settings!$B$5*IF('Cost Margin'!$F28="",1,'Cost Margin'!$F28))) -> 0 | ... Z42: =IF(Z20=0,0,IF('Cost Margin'!$M28<>"",'Cost Margin'!$M28*Z20/'Cost Margin'!$L28,Z20*Settings!$B$5*IF('Cost Margin'!$F28="",1,'Cost Margin'!$F28))) -> 0 | AB42: =IF('Cost Margin'!A28="","",IF('Cost Margin'!E28="","(unassigned)",'Cost Margin'!E28))
... A50: 20 | B50: =IF('Cost Margin'!A36="","",'Cost Margin'!A36&IF('Cost Margin'!E36="",""," · "&'Cost Margin'!E36)) | C50: =IF(C28=0,0,IF('Cost Margin'!$M36<>"",'Cost Margin'!$M36*C28/'Cost Margin'!$L36,C28*Settings!$B$5*IF('Cost Margin'!$F36="",1,'Cost Margin'!$F36))) -> 0 | D50: =IF(D28=0,0,IF('Cost Margin'!$M36<>"",'Cost Margin'!$M36*D28/'Cost Margin'!$L36,D28*Settings!$B$5*IF('Cost Margin'!$F36="",1,'Cost Margin'!$F36))) -> 0 | E50: =IF(E28=0,0,IF('Cost Margin'!$M36<>"",'Cost Margin'!$M36*E28/'Cost Margin'!$L36,E28*Settings!$B$5*IF('Cost Margin'!$F36="",1,'Cost Margin'!$F36))) -> 0 | F50: =IF(F28=0,0,IF('Cost Margin'!$M36<>"",'Cost Margin'!$M36*F28/'Cost Margin'!$L36,F28*Settings!$B$5*IF('Cost Margin'!$F36="",1,'Cost Margin'!$F36))) -> 0 | G50: =IF(G28=0,0,IF('Cost Margin'!$M36<>"",'Cost Margin'!$M36*G28/'Cost Margin'!$L36,G28*Settings!$B$5*IF('Cost Margin'!$F36="",1,'Cost Margin'!$F36))) -> 0 | H50: =IF(H28=0,0,IF('Cost Margin'!$M36<>"",'Cost Margin'!$M36*H28/'Cost Margin'!$L36,H28*Settings!$B$5*IF('Cost Margin'!$F36="",1,'Cost Margin'!$F36))) -> 0 | I50: =IF(I28=0,0,IF('Cost Margin'!$M36<>"",'Cost Margin'!$M36*I28/'Cost Margin'!$L36,I28*Settings!$B$5*IF('Cost Margin'!$F36="",1,'Cost Margin'!$F36))) -> 0 | J50: =IF(J28=0,0,IF('Cost Margin'!$M36<>"",'Cost Margin'!$M36*J28/'Cost Margin'!$L36,J28*Settings!$B$5*IF('Cost Margin'!$F36="",1,'Cost Margin'!$F36))) -> 0 | ... Z50: =IF(Z28=0,0,IF('Cost Margin'!$M36<>"",'Cost Margin'!$M36*Z28/'Cost Margin'!$L36,Z28*Settings!$B$5*IF('Cost Margin'!$F36="",1,'Cost Margin'!$F36))) -> 0 | AB50: =IF('Cost Margin'!A36="","",IF('Cost Margin'!E36="","(unassigned)",'Cost Margin'!E36))
A52: Revenue in month, per person (hours × bill rate — T&M / Staff augmentation) | AB52: Assignment
A53: 1 | B53: =IF('Cost Margin'!A17="","",'Cost Margin'!A17&IF('Cost Margin'!E17="",""," · "&'Cost Margin'!E17)) | C53: =IF(OR('Cost Margin'!$B$4="Time & materials",'Cost Margin'!$B$4="Staff augmentation"),C31*IF('Cost Margin'!$H17="",0,'Cost Margin'!$H17),0) -> 0 | D53: =IF(OR('Cost Margin'!$B$4="Time & materials",'Cost Margin'!$B$4="Staff augmentation"),D31*IF('Cost Margin'!$H17="",0,'Cost Margin'!$H17),0) -> 0 | E53: =IF(OR('Cost Margin'!$B$4="Time & materials",'Cost Margin'!$B$4="Staff augmentation"),E31*IF('Cost Margin'!$H17="",0,'Cost Margin'!$H17),0) -> 0 | F53: =IF(OR('Cost Margin'!$B$4="Time & materials",'Cost Margin'!$B$4="Staff augmentation"),F31*IF('Cost Margin'!$H17="",0,'Cost Margin'!$H17),0) -> 0 | G53: =IF(OR('Cost Margin'!$B$4="Time & materials",'Cost Margin'!$B$4="Staff augmentation"),G31*IF('Cost Margin'!$H17="",0,'Cost Margin'!$H17),0) -> 0 | H53: =IF(OR('Cost Margin'!$B$4="Time & materials",'Cost Margin'!$B$4="Staff augmentation"),H31*IF('Cost Margin'!$H17="",0,'Cost Margin'!$H17),0) -> 0 | I53: =IF(OR('Cost Margin'!$B$4="Time & materials",'Cost Margin'!$B$4="Staff augmentation"),I31*IF('Cost Margin'!$H17="",0,'Cost Margin'!$H17),0) -> 0 | J53: =IF(OR('Cost Margin'!$B$4="Time & materials",'Cost Margin'!$B$4="Staff augmentation"),J31*IF('Cost Margin'!$H17="",0,'Cost Margin'!$H17),0) -> 0 | ... Z53: =IF(OR('Cost Margin'!$B$4="Time & materials",'Cost Margin'!$B$4="Staff augmentation"),Z31*IF('Cost Margin'!$H17="",0,'Cost Margin'!$H17),0) -> 0 | AB53: =IF('Cost Margin'!A17="","",IF('Cost Margin'!E17="","(unassigned)",'Cost Margin'!E17))
A54: 2 | B54: =IF('Cost Margin'!A18="","",'Cost Margin'!A18&IF('Cost Margin'!E18="",""," · "&'Cost Margin'!E18)) | C54: =IF(OR('Cost Margin'!$B$4="Time & materials",'Cost Margin'!$B$4="Staff augmentation"),C32*IF('Cost Margin'!$H18="",0,'Cost Margin'!$H18),0) -> 0 | D54: =IF(OR('Cost Margin'!$B$4="Time & materials",'Cost Margin'!$B$4="Staff augmentation"),D32*IF('Cost Margin'!$H18="",0,'Cost Margin'!$H18),0) -> 0 | E54: =IF(OR('Cost Margin'!$B$4="Time & materials",'Cost Margin'!$B$4="Staff augmentation"),E32*IF('Cost Margin'!$H18="",0,'Cost Margin'!$H18),0) -> 0 | F54: =IF(OR('Cost Margin'!$B$4="Time & materials",'Cost Margin'!$B$4="Staff augmentation"),F32*IF('Cost Margin'!$H18="",0,'Cost Margin'!$H18),0) -> 0 | G54: =IF(OR('Cost Margin'!$B$4="Time & materials",'Cost Margin'!$B$4="Staff augmentation"),G32*IF('Cost Margin'!$H18="",0,'Cost Margin'!$H18),0) -> 0 | H54: =IF(OR('Cost Margin'!$B$4="Time & materials",'Cost Margin'!$B$4="Staff augmentation"),H32*IF('Cost Margin'!$H18="",0,'Cost Margin'!$H18),0) -> 0 | I54: =IF(OR('Cost Margin'!$B$4="Time & materials",'Cost Margin'!$B$4="Staff augmentation"),I32*IF('Cost Margin'!$H18="",0,'Cost Margin'!$H18),0) -> 0 | J54: =IF(OR('Cost Margin'!$B$4="Time & materials",'Cost Margin'!$B$4="Staff augmentation"),J32*IF('Cost Margin'!$H18="",0,'Cost Margin'!$H18),0) -> 0 | ... Z54: =IF(OR('Cost Margin'!$B$4="Time & materials",'Cost Margin'!$B$4="Staff augmentation"),Z32*IF('Cost Margin'!$H18="",0,'Cost Margin'!$H18),0) -> 0 | AB54: =IF('Cost Margin'!A18="","",IF('Cost Margin'!E18="","(unassigned)",'Cost Margin'!E18))
A55: 3 | B55: =IF('Cost Margin'!A19="","",'Cost Margin'!A19&IF('Cost Margin'!E19="",""," · "&'Cost Margin'!E19)) | C55: =IF(OR('Cost Margin'!$B$4="Time & materials",'Cost Margin'!$B$4="Staff augmentation"),C33*IF('Cost Margin'!$H19="",0,'Cost Margin'!$H19),0) -> 0 | D55: =IF(OR('Cost Margin'!$B$4="Time & materials",'Cost Margin'!$B$4="Staff augmentation"),D33*IF('Cost Margin'!$H19="",0,'Cost Margin'!$H19),0) -> 0 | E55: =IF(OR('Cost Margin'!$B$4="Time & materials",'Cost Margin'!$B$4="Staff augmentation"),E33*IF('Cost Margin'!$H19="",0,'Cost Margin'!$H19),0) -> 0 | F55: =IF(OR('Cost Margin'!$B$4="Time & materials",'Cost Margin'!$B$4="Staff augmentation"),F33*IF('Cost Margin'!$H19="",0,'Cost Margin'!$H19),0) -> 0 | G55: =IF(OR('Cost Margin'!$B$4="Time & materials",'Cost Margin'!$B$4="Staff augmentation"),G33*IF('Cost Margin'!$H19="",0,'Cost Margin'!$H19),0) -> 0 | H55: =IF(OR('Cost Margin'!$B$4="Time & materials",'Cost Margin'!$B$4="Staff augmentation"),H33*IF('Cost Margin'!$H19="",0,'Cost Margin'!$H19),0) -> 0 | I55: =IF(OR('Cost Margin'!$B$4="Time & materials",'Cost Margin'!$B$4="Staff augmentation"),I33*IF('Cost Margin'!$H19="",0,'Cost Margin'!$H19),0) -> 0 | J55: =IF(OR('Cost Margin'!$B$4="Time & materials",'Cost Margin'!$B$4="Staff augmentation"),J33*IF('Cost Margin'!$H19="",0,'Cost Margin'!$H19),0) -> 0 | ... Z55: =IF(OR('Cost Margin'!$B$4="Time & materials",'Cost Margin'!$B$4="Staff augmentation"),Z33*IF('Cost Margin'!$H19="",0,'Cost Margin'!$H19),0) -> 0 | AB55: =IF('Cost Margin'!A19="","",IF('Cost Margin'!E19="","(unassigned)",'Cost Margin'!E19))
A56: 4 | B56: =IF('Cost Margin'!A20="","",'Cost Margin'!A20&IF('Cost Margin'!E20="",""," · "&'Cost Margin'!E20)) | C56: =IF(OR('Cost Margin'!$B$4="Time & materials",'Cost Margin'!$B$4="Staff augmentation"),C34*IF('Cost Margin'!$H20="",0,'Cost Margin'!$H20),0) -> 0 | D56: =IF(OR('Cost Margin'!$B$4="Time & materials",'Cost Margin'!$B$4="Staff augmentation"),D34*IF('Cost Margin'!$H20="",0,'Cost Margin'!$H20),0) -> 0 | E56: =IF(OR('Cost Margin'!$B$4="Time & materials",'Cost Margin'!$B$4="Staff augmentation"),E34*IF('Cost Margin'!$H20="",0,'Cost Margin'!$H20),0) -> 0 | F56: =IF(OR('Cost Margin'!$B$4="Time & materials",'Cost Margin'!$B$4="Staff augmentation"),F34*IF('Cost Margin'!$H20="",0,'Cost Margin'!$H20),0) -> 0 | G56: =IF(OR('Cost Margin'!$B$4="Time & materials",'Cost Margin'!$B$4="Staff augmentation"),G34*IF('Cost Margin'!$H20="",0,'Cost Margin'!$H20),0) -> 0 | H56: =IF(OR('Cost Margin'!$B$4="Time & materials",'Cost Margin'!$B$4="Staff augmentation"),H34*IF('Cost Margin'!$H20="",0,'Cost Margin'!$H20),0) -> 0 | I56: =IF(OR('Cost Margin'!$B$4="Time & materials",'Cost Margin'!$B$4="Staff augmentation"),I34*IF('Cost Margin'!$H20="",0,'Cost Margin'!$H20),0) -> 0 | J56: =IF(OR('Cost Margin'!$B$4="Time & materials",'Cost Margin'!$B$4="Staff augmentation"),J34*IF('Cost Margin'!$H20="",0,'Cost Margin'!$H20),0) -> 0 | ... Z56: =IF(OR('Cost Margin'!$B$4="Time & materials",'Cost Margin'!$B$4="Staff augmentation"),Z34*IF('Cost Margin'!$H20="",0,'Cost Margin'!$H20),0) -> 0 | AB56: =IF('Cost Margin'!A20="","",IF('Cost Margin'!E20="","(unassigned)",'Cost Margin'!E20))
A57: 5 | B57: =IF('Cost Margin'!A21="","",'Cost Margin'!A21&IF('Cost Margin'!E21="",""," · "&'Cost Margin'!E21)) | C57: =IF(OR('Cost Margin'!$B$4="Time & materials",'Cost Margin'!$B$4="Staff augmentation"),C35*IF('Cost Margin'!$H21="",0,'Cost Margin'!$H21),0) -> 0 | D57: =IF(OR('Cost Margin'!$B$4="Time & materials",'Cost Margin'!$B$4="Staff augmentation"),D35*IF('Cost Margin'!$H21="",0,'Cost Margin'!$H21),0) -> 0 | E57: =IF(OR('Cost Margin'!$B$4="Time & materials",'Cost Margin'!$B$4="Staff augmentation"),E35*IF('Cost Margin'!$H21="",0,'Cost Margin'!$H21),0) -> 0 | F57: =IF(OR('Cost Margin'!$B$4="Time & materials",'Cost Margin'!$B$4="Staff augmentation"),F35*IF('Cost Margin'!$H21="",0,'Cost Margin'!$H21),0) -> 0 | G57: =IF(OR('Cost Margin'!$B$4="Time & materials",'Cost Margin'!$B$4="Staff augmentation"),G35*IF('Cost Margin'!$H21="",0,'Cost Margin'!$H21),0) -> 0 | H57: =IF(OR('Cost Margin'!$B$4="Time & materials",'Cost Margin'!$B$4="Staff augmentation"),H35*IF('Cost Margin'!$H21="",0,'Cost Margin'!$H21),0) -> 0 | I57: =IF(OR('Cost Margin'!$B$4="Time & materials",'Cost Margin'!$B$4="Staff augmentation"),I35*IF('Cost Margin'!$H21="",0,'Cost Margin'!$H21),0) -> 0 | J57: =IF(OR('Cost Margin'!$B$4="Time & materials",'Cost Margin'!$B$4="Staff augmentation"),J35*IF('Cost Margin'!$H21="",0,'Cost Margin'!$H21),0) -> 0 | ... Z57: =IF(OR('Cost Margin'!$B$4="Time & materials",'Cost Margin'!$B$4="Staff augmentation"),Z35*IF('Cost Margin'!$H21="",0,'Cost Margin'!$H21),0) -> 0 | AB57: =IF('Cost Margin'!A21="","",IF('Cost Margin'!E21="","(unassigned)",'Cost Margin'!E21))
A58: 6 | B58: =IF('Cost Margin'!A22="","",'Cost Margin'!A22&IF('Cost Margin'!E22="",""," · "&'Cost Margin'!E22)) | C58: =IF(OR('Cost Margin'!$B$4="Time & materials",'Cost Margin'!$B$4="Staff augmentation"),C36*IF('Cost Margin'!$H22="",0,'Cost Margin'!$H22),0) -> 0 | D58: =IF(OR('Cost Margin'!$B$4="Time & materials",'Cost Margin'!$B$4="Staff augmentation"),D36*IF('Cost Margin'!$H22="",0,'Cost Margin'!$H22),0) -> 0 | E58: =IF(OR('Cost Margin'!$B$4="Time & materials",'Cost Margin'!$B$4="Staff augmentation"),E36*IF('Cost Margin'!$H22="",0,'Cost Margin'!$H22),0) -> 0 | F58: =IF(OR('Cost Margin'!$B$4="Time & materials",'Cost Margin'!$B$4="Staff augmentation"),F36*IF('Cost Margin'!$H22="",0,'Cost Margin'!$H22),0) -> 0 | G58: =IF(OR('Cost Margin'!$B$4="Time & materials",'Cost Margin'!$B$4="Staff augmentation"),G36*IF('Cost Margin'!$H22="",0,'Cost Margin'!$H22),0) -> 0 | H58: =IF(OR('Cost Margin'!$B$4="Time & materials",'Cost Margin'!$B$4="Staff augmentation"),H36*IF('Cost Margin'!$H22="",0,'Cost Margin'!$H22),0) -> 0 | I58: =IF(OR('Cost Margin'!$B$4="Time & materials",'Cost Margin'!$B$4="Staff augmentation"),I36*IF('Cost Margin'!$H22="",0,'Cost Margin'!$H22),0) -> 0 | J58: =IF(OR('Cost Margin'!$B$4="Time & materials",'Cost Margin'!$B$4="Staff augmentation"),J36*IF('Cost Margin'!$H22="",0,'Cost Margin'!$H22),0) -> 0 | ... Z58: =IF(OR('Cost Margin'!$B$4="Time & materials",'Cost Margin'!$B$4="Staff augmentation"),Z36*IF('Cost Margin'!$H22="",0,'Cost Margin'!$H22),0) -> 0 | AB58: =IF('Cost Margin'!A22="","",IF('Cost Margin'!E22="","(unassigned)",'Cost Margin'!E22))
A59: 7 | B59: =IF('Cost Margin'!A23="","",'Cost Margin'!A23&IF('Cost Margin'!E23="",""," · "&'Cost Margin'!E23)) | C59: =IF(OR('Cost Margin'!$B$4="Time & materials",'Cost Margin'!$B$4="Staff augmentation"),C37*IF('Cost Margin'!$H23="",0,'Cost Margin'!$H23),0) -> 0 | D59: =IF(OR('Cost Margin'!$B$4="Time & materials",'Cost Margin'!$B$4="Staff augmentation"),D37*IF('Cost Margin'!$H23="",0,'Cost Margin'!$H23),0) -> 0 | E59: =IF(OR('Cost Margin'!$B$4="Time & materials",'Cost Margin'!$B$4="Staff augmentation"),E37*IF('Cost Margin'!$H23="",0,'Cost Margin'!$H23),0) -> 0 | F59: =IF(OR('Cost Margin'!$B$4="Time & materials",'Cost Margin'!$B$4="Staff augmentation"),F37*IF('Cost Margin'!$H23="",0,'Cost Margin'!$H23),0) -> 0 | G59: =IF(OR('Cost Margin'!$B$4="Time & materials",'Cost Margin'!$B$4="Staff augmentation"),G37*IF('Cost Margin'!$H23="",0,'Cost Margin'!$H23),0) -> 0 | H59: =IF(OR('Cost Margin'!$B$4="Time & materials",'Cost Margin'!$B$4="Staff augmentation"),H37*IF('Cost Margin'!$H23="",0,'Cost Margin'!$H23),0) -> 0 | I59: =IF(OR('Cost Margin'!$B$4="Time & materials",'Cost Margin'!$B$4="Staff augmentation"),I37*IF('Cost Margin'!$H23="",0,'Cost Margin'!$H23),0) -> 0 | J59: =IF(OR('Cost Margin'!$B$4="Time & materials",'Cost Margin'!$B$4="Staff augmentation"),J37*IF('Cost Margin'!$H23="",0,'Cost Margin'!$H23),0) -> 0 | ... Z59: =IF(OR('Cost Margin'!$B$4="Time & materials",'Cost Margin'!$B$4="Staff augmentation"),Z37*IF('Cost Margin'!$H23="",0,'Cost Margin'!$H23),0) -> 0 | AB59: =IF('Cost Margin'!A23="","",IF('Cost Margin'!E23="","(unassigned)",'Cost Margin'!E23))
A60: 8 | B60: =IF('Cost Margin'!A24="","",'Cost Margin'!A24&IF('Cost Margin'!E24="",""," · "&'Cost Margin'!E24)) | C60: =IF(OR('Cost Margin'!$B$4="Time & materials",'Cost Margin'!$B$4="Staff augmentation"),C38*IF('Cost Margin'!$H24="",0,'Cost Margin'!$H24),0) -> 0 | D60: =IF(OR('Cost Margin'!$B$4="Time & materials",'Cost Margin'!$B$4="Staff augmentation"),D38*IF('Cost Margin'!$H24="",0,'Cost Margin'!$H24),0) -> 0 | E60: =IF(OR('Cost Margin'!$B$4="Time & materials",'Cost Margin'!$B$4="Staff augmentation"),E38*IF('Cost Margin'!$H24="",0,'Cost Margin'!$H24),0) -> 0 | F60: =IF(OR('Cost Margin'!$B$4="Time & materials",'Cost Margin'!$B$4="Staff augmentation"),F38*IF('Cost Margin'!$H24="",0,'Cost Margin'!$H24),0) -> 0 | G60: =IF(OR('Cost Margin'!$B$4="Time & materials",'Cost Margin'!$B$4="Staff augmentation"),G38*IF('Cost Margin'!$H24="",0,'Cost Margin'!$H24),0) -> 0 | H60: =IF(OR('Cost Margin'!$B$4="Time & materials",'Cost Margin'!$B$4="Staff augmentation"),H38*IF('Cost Margin'!$H24="",0,'Cost Margin'!$H24),0) -> 0 | I60: =IF(OR('Cost Margin'!$B$4="Time & materials",'Cost Margin'!$B$4="Staff augmentation"),I38*IF('Cost Margin'!$H24="",0,'Cost Margin'!$H24),0) -> 0 | J60: =IF(OR('Cost Margin'!$B$4="Time & materials",'Cost Margin'!$B$4="Staff augmentation"),J38*IF('Cost Margin'!$H24="",0,'Cost Margin'!$H24),0) -> 0 | ... Z60: =IF(OR('Cost Margin'!$B$4="Time & materials",'Cost Margin'!$B$4="Staff augmentation"),Z38*IF('Cost Margin'!$H24="",0,'Cost Margin'!$H24),0) -> 0 | AB60: =IF('Cost Margin'!A24="","",IF('Cost Margin'!E24="","(unassigned)",'Cost Margin'!E24))
A61: 9 | B61: =IF('Cost Margin'!A25="","",'Cost Margin'!A25&IF('Cost Margin'!E25="",""," · "&'Cost Margin'!E25)) | C61: =IF(OR('Cost Margin'!$B$4="Time & materials",'Cost Margin'!$B$4="Staff augmentation"),C39*IF('Cost Margin'!$H25="",0,'Cost Margin'!$H25),0) -> 0 | D61: =IF(OR('Cost Margin'!$B$4="Time & materials",'Cost Margin'!$B$4="Staff augmentation"),D39*IF('Cost Margin'!$H25="",0,'Cost Margin'!$H25),0) -> 0 | E61: =IF(OR('Cost Margin'!$B$4="Time & materials",'Cost Margin'!$B$4="Staff augmentation"),E39*IF('Cost Margin'!$H25="",0,'Cost Margin'!$H25),0) -> 0 | F61: =IF(OR('Cost Margin'!$B$4="Time & materials",'Cost Margin'!$B$4="Staff augmentation"),F39*IF('Cost Margin'!$H25="",0,'Cost Margin'!$H25),0) -> 0 | G61: =IF(OR('Cost Margin'!$B$4="Time & materials",'Cost Margin'!$B$4="Staff augmentation"),G39*IF('Cost Margin'!$H25="",0,'Cost Margin'!$H25),0) -> 0 | H61: =IF(OR('Cost Margin'!$B$4="Time & materials",'Cost Margin'!$B$4="Staff augmentation"),H39*IF('Cost Margin'!$H25="",0,'Cost Margin'!$H25),0) -> 0 | I61: =IF(OR('Cost Margin'!$B$4="Time & materials",'Cost Margin'!$B$4="Staff augmentation"),I39*IF('Cost Margin'!$H25="",0,'Cost Margin'!$H25),0) -> 0 | J61: =IF(OR('Cost Margin'!$B$4="Time & materials",'Cost Margin'!$B$4="Staff augmentation"),J39*IF('Cost Margin'!$H25="",0,'Cost Margin'!$H25),0) -> 0 | ... Z61: =IF(OR('Cost Margin'!$B$4="Time & materials",'Cost Margin'!$B$4="Staff augmentation"),Z39*IF('Cost Margin'!$H25="",0,'Cost Margin'!$H25),0) -> 0 | AB61: =IF('Cost Margin'!A25="","",IF('Cost Margin'!E25="","(unassigned)",'Cost Margin'!E25))
A62: 10 | B62: =IF('Cost Margin'!A26="","",'Cost Margin'!A26&IF('Cost Margin'!E26="",""," · "&'Cost Margin'!E26)) | C62: =IF(OR('Cost Margin'!$B$4="Time & materials",'Cost Margin'!$B$4="Staff augmentation"),C40*IF('Cost Margin'!$H26="",0,'Cost Margin'!$H26),0) -> 0 | D62: =IF(OR('Cost Margin'!$B$4="Time & materials",'Cost Margin'!$B$4="Staff augmentation"),D40*IF('Cost Margin'!$H26="",0,'Cost Margin'!$H26),0) -> 0 | E62: =IF(OR('Cost Margin'!$B$4="Time & materials",'Cost Margin'!$B$4="Staff augmentation"),E40*IF('Cost Margin'!$H26="",0,'Cost Margin'!$H26),0) -> 0 | F62: =IF(OR('Cost Margin'!$B$4="Time & materials",'Cost Margin'!$B$4="Staff augmentation"),F40*IF('Cost Margin'!$H26="",0,'Cost Margin'!$H26),0) -> 0 | G62: =IF(OR('Cost Margin'!$B$4="Time & materials",'Cost Margin'!$B$4="Staff augmentation"),G40*IF('Cost Margin'!$H26="",0,'Cost Margin'!$H26),0) -> 0 | H62: =IF(OR('Cost Margin'!$B$4="Time & materials",'Cost Margin'!$B$4="Staff augmentation"),H40*IF('Cost Margin'!$H26="",0,'Cost Margin'!$H26),0) -> 0 | I62: =IF(OR('Cost Margin'!$B$4="Time & materials",'Cost Margin'!$B$4="Staff augmentation"),I40*IF('Cost Margin'!$H26="",0,'Cost Margin'!$H26),0) -> 0 | J62: =IF(OR('Cost Margin'!$B$4="Time & materials",'Cost Margin'!$B$4="Staff augmentation"),J40*IF('Cost Margin'!$H26="",0,'Cost Margin'!$H26),0) -> 0 | ... Z62: =IF(OR('Cost Margin'!$B$4="Time & materials",'Cost Margin'!$B$4="Staff augmentation"),Z40*IF('Cost Margin'!$H26="",0,'Cost Margin'!$H26),0) -> 0 | AB62: =IF('Cost Margin'!A26="","",IF('Cost Margin'!E26="","(unassigned)",'Cost Margin'!E26))
A63: 11 | B63: =IF('Cost Margin'!A27="","",'Cost Margin'!A27&IF('Cost Margin'!E27="",""," · "&'Cost Margin'!E27)) | C63: =IF(OR('Cost Margin'!$B$4="Time & materials",'Cost Margin'!$B$4="Staff augmentation"),C41*IF('Cost Margin'!$H27="",0,'Cost Margin'!$H27),0) -> 0 | D63: =IF(OR('Cost Margin'!$B$4="Time & materials",'Cost Margin'!$B$4="Staff augmentation"),D41*IF('Cost Margin'!$H27="",0,'Cost Margin'!$H27),0) -> 0 | E63: =IF(OR('Cost Margin'!$B$4="Time & materials",'Cost Margin'!$B$4="Staff augmentation"),E41*IF('Cost Margin'!$H27="",0,'Cost Margin'!$H27),0) -> 0 | F63: =IF(OR('Cost Margin'!$B$4="Time & materials",'Cost Margin'!$B$4="Staff augmentation"),F41*IF('Cost Margin'!$H27="",0,'Cost Margin'!$H27),0) -> 0 | G63: =IF(OR('Cost Margin'!$B$4="Time & materials",'Cost Margin'!$B$4="Staff augmentation"),G41*IF('Cost Margin'!$H27="",0,'Cost Margin'!$H27),0) -> 0 | H63: =IF(OR('Cost Margin'!$B$4="Time & materials",'Cost Margin'!$B$4="Staff augmentation"),H41*IF('Cost Margin'!$H27="",0,'Cost Margin'!$H27),0) -> 0 | I63: =IF(OR('Cost Margin'!$B$4="Time & materials",'Cost Margin'!$B$4="Staff augmentation"),I41*IF('Cost Margin'!$H27="",0,'Cost Margin'!$H27),0) -> 0 | J63: =IF(OR('Cost Margin'!$B$4="Time & materials",'Cost Margin'!$B$4="Staff augmentation"),J41*IF('Cost Margin'!$H27="",0,'Cost Margin'!$H27),0) -> 0 | ... Z63: =IF(OR('Cost Margin'!$B$4="Time & materials",'Cost Margin'!$B$4="Staff augmentation"),Z41*IF('Cost Margin'!$H27="",0,'Cost Margin'!$H27),0) -> 0 | AB63: =IF('Cost Margin'!A27="","",IF('Cost Margin'!E27="","(unassigned)",'Cost Margin'!E27))
A64: 12 | B64: =IF('Cost Margin'!A28="","",'Cost Margin'!A28&IF('Cost Margin'!E28="",""," · "&'Cost Margin'!E28)) | C64: =IF(OR('Cost Margin'!$B$4="Time & materials",'Cost Margin'!$B$4="Staff augmentation"),C42*IF('Cost Margin'!$H28="",0,'Cost Margin'!$H28),0) -> 0 | D64: =IF(OR('Cost Margin'!$B$4="Time & materials",'Cost Margin'!$B$4="Staff augmentation"),D42*IF('Cost Margin'!$H28="",0,'Cost Margin'!$H28),0) -> 0 | E64: =IF(OR('Cost Margin'!$B$4="Time & materials",'Cost Margin'!$B$4="Staff augmentation"),E42*IF('Cost Margin'!$H28="",0,'Cost Margin'!$H28),0) -> 0 | F64: =IF(OR('Cost Margin'!$B$4="Time & materials",'Cost Margin'!$B$4="Staff augmentation"),F42*IF('Cost Margin'!$H28="",0,'Cost Margin'!$H28),0) -> 0 | G64: =IF(OR('Cost Margin'!$B$4="Time & materials",'Cost Margin'!$B$4="Staff augmentation"),G42*IF('Cost Margin'!$H28="",0,'Cost Margin'!$H28),0) -> 0 | H64: =IF(OR('Cost Margin'!$B$4="Time & materials",'Cost Margin'!$B$4="Staff augmentation"),H42*IF('Cost Margin'!$H28="",0,'Cost Margin'!$H28),0) -> 0 | I64: =IF(OR('Cost Margin'!$B$4="Time & materials",'Cost Margin'!$B$4="Staff augmentation"),I42*IF('Cost Margin'!$H28="",0,'Cost Margin'!$H28),0) -> 0 | J64: =IF(OR('Cost Margin'!$B$4="Time & materials",'Cost Margin'!$B$4="Staff augmentation"),J42*IF('Cost Margin'!$H28="",0,'Cost Margin'!$H28),0) -> 0 | ... Z64: =IF(OR('Cost Margin'!$B$4="Time & materials",'Cost Margin'!$B$4="Staff augmentation"),Z42*IF('Cost Margin'!$H28="",0,'Cost Margin'!$H28),0) -> 0 | AB64: =IF('Cost Margin'!A28="","",IF('Cost Margin'!E28="","(unassigned)",'Cost Margin'!E28))
